Workbook

Sheet 🏠 Accueil
A1: TECHNOLOGIE 5e Progression annuelle 2026-2027 · Académie de Martinique
A5: Programme 2024 (BO n°9 du 29/02/2024) · 1 h 30 / semaine · cahier Nathan 5e (éd. 2024) · ressources en ligne du dépôt « En ligne pour le cycle 4 »
B7: 📊 L'année en un coup d'œil
B8: 37 | D8: ='🧭 Progression'!G11 -> 29 | F8: 8
B9: Semaines de cours | D9: Séances planifiées | F9: Semaines tampon (aléas)
B11: 7 | D11: 38 | F11: 2 (+1 partielle)
B12: Séquences | D12: Codes 5e travaillés | F12: Séquences déjà en ligne
B14: 🧭 Naviguer dans le classeur (cliquer)
B15: ▸ 📅 Calendrier | C15: 37 semaines, vacances, fériés, tampons, aléas | E15: ▸ 🗓 Frise de l'année | F15: les 7 séquences posées sur l'année (vue gantt)
B16: ▸ 📚 Référentiel Cycle 4 | C16: C1 → C9 : les 114 sous-compétences du cycle | E16: ▸ 📗 Référentiel 5e | F16: les 38 sous-compétences du niveau
B17: ▸ 🧭 Progression | C17: les 7 séquences : codes, répartition 🏫🏠🔁, ressources | E17: ▸ S1 | F17: Environnement numérique — IA Thème 1 (canevas)
B18: ▸ S2 | C18: Comparer pour choisir — IA Thème 1 (canevas) | E18: ▸ S3 | F18: Chaîne d'énergie — IA Th.1 + Fable (canevas + lampadaire)
B19: ▸ S4 | C19: Lampadaire (1) : information, données, programmes — ✅ rempli | E19: ▸ S5 | F19: Lampadaire (2) : réseau local — ✅ rempli
B20: ▸ S6 | C20: SOS panne — pré-rempli (ressources 🔜) | E20: ▸ S7 | F20: Mini-projet — IA Thème 3 (canevas)
B22: 📖 Mode d'emploi express
B23: 🏫 / 🏠 / 🔁 | C23: En classe (matériel, collectif, évaluations) · À la maison (QCM, synthèses, simulateurs — corrections intégrées, faisables sur téléphone) · Hybride/classe inversée (lancement en classe, simulateur à la maison, exploitation au retour).
B24: ⏳ Tampons | C24: 8 semaines NON planifiées absorbent les aléas. NOUVEAU — moteur automatique : dans 📅 Calendrier, colonne « ⚠ Imprévu ? », choisis l'imprévu dans le menu de la semaine touchée (absence, sortie, Fête de la science, ERASMUS…) : toutes les séances se décalent d'une semaine, la frise et la progression se recalculent, et la réserve de fin d'année absorbe le décalage. Au-delà de 8 imprévus, une alerte 🛑 s'affiche.
B25: 📋 Cahier de texte | C25: Dans chaque générateur, les blocs jaunes sont prêts à copier-coller dans Pronote : « Contenu de la séance » + « Travail à faire » (lien direct, durée estimée, mention téléphone).
B26: ✅ 🔜 📘 | C26: Ressource en ligne · à produire · cahier Nathan (filet de sécurité sans connexion). Chaque IA de thème remplit les générateurs de SES séquences — canevas à entériner au Conseil du 28/07.
B27: 📆 Calendrier | C27: Rectorat de Martinique 2026-2027 : rentrée mar. 1/09 · Toussaint 20/10→3/11 · Noël 19/12→4/01 · Carnaval 6→22/02 · Pâques 20/04→3/05 · fin des cours 3/07. À confirmer sur ac-martinique.fr.
B29: Classeur généré par Fable (IA du Thème 2) — dépôt : https://pll-process.github.io/en-ligne-pour-le-cycle-4/

Sheet 📅 Calendrier
A1: CALENDRIER 5e — année scolaire 2026-2027 (académie de Martinique) — 1 séance de 1 h 30 par semaine
D2: =IF(COUNTIF($G$4:$G$44,"<>")>8,"🛑 "&COUNTIF($G$4:$G$44,"<>")&" imprévus : la réserve (8) est dépassée — des séances sortent de l'année, arbitrage nécessaire !","✔ Réserve d'aléas : "&(8-COUNTIF($G$4:$G$44,"<>"))&" semaine(s) tampon restante(s) sur 8") -> ✔ Réserve d'aléas : 8 semaine(s) tampon restante(s) sur 8 | F2: ◀ Accueil
A3: Sem. | B3: Lundi de la semaine | C3: Période | D3: Affectation (séquence · séance) | E3: Repères / jours fériés | F3: Aléas / notes (à remplir) | G3: ⚠ Imprévu ? (menu déroulant) | H3: n° créneau (auto)
A4: S01 | B4: 31/08/2026 | C4: P1 | D4: =IF($G4<>"",$G4&" — les séances suivantes se décalent d'une semaine",INDEX('⚙ Moteur'!$B$5:$B$41,$H4)) -> S1 · séance 1 | E4: Rentrée des élèves mardi 1er septembre. | H4: =IF($G4<>"",0,0+1) -> 1
A5: S02 | B5: 07/09/2026 | C5: P1 | D5: =IF($G5<>"",$G5&" — les séances suivantes se décalent d'une semaine",INDEX('⚙ Moteur'!$B$5:$B$41,$H5)) -> S1 · séance 2 | H5: =IF($G5<>"",H4,H4+1) -> 2
A6: S03 | B6: 14/09/2026 | C6: P1 | D6: =IF($G6<>"",$G6&" — les séances suivantes se décalent d'une semaine",INDEX('⚙ Moteur'!$B$5:$B$41,$H6)) -> S1 · séance 3 | H6: =IF($G6<>"",H5,H5+1) -> 3
A7: S04 | B7: 21/09/2026 | C7: P1 | D7: =IF($G7<>"",$G7&" — les séances suivantes se décalent d'une semaine",INDEX('⚙ Moteur'!$B$5:$B$41,$H7)) -> S2 · séance 1 | H7: =IF($G7<>"",H6,H6+1) -> 4
A8: S05 | B8: 28/09/2026 | C8: P1 | D8: =IF($G8<>"",$G8&" — les séances suivantes se décalent d'une semaine",INDEX('⚙ Moteur'!$B$5:$B$41,$H8)) -> S2 · séance 2 | H8: =IF($G8<>"",H7,H7+1) -> 5
A9: S06 | B9: 05/10/2026 | C9: P1 | D9: =IF($G9<>"",$G9&" — les séances suivantes se décalent d'une semaine",INDEX('⚙ Moteur'!$B$5:$B$41,$H9)) -> S2 · séance 3 | H9: =IF($G9<>"",H8,H8+1) -> 6
A10: S07 | B10: 12/10/2026 | C10: P1 | D10: =IF($G10<>"",$G10&" — les séances suivantes se décalent d'une semaine",INDEX('⚙ Moteur'!$B$5:$B$41,$H10)) -> S2 · séance 4 | H10: =IF($G10<>"",H9,H9+1) -> 7
A11: S08 | B11: 19/10/2026 | C11: P1 | D11: =IF($G11<>"",$G11&" — les séances suivantes se décalent d'une semaine",INDEX('⚙ Moteur'!$B$5:$B$41,$H11)) -> ⏳ TAMPON P1 — rattrapage / remédiation | H11: =IF($G11<>"",H10,H10+1) -> 8
A12: 🏖 Vacances de la Toussaint : 20/10 → 3/11
A13: S09 | B13: 02/11/2026 | C13: P2 | D13: =IF($G13<>"",$G13&" — les séances suivantes se décalent d'une semaine",INDEX('⚙ Moteur'!$B$5:$B$41,$H13)) -> S3 · séance 1 | H13: =IF($G13<>"",H11,H11+1) -> 9
A14: S10 | B14: 09/11/2026 | C14: P2 | D14: =IF($G14<>"",$G14&" — les séances suivantes se décalent d'une semaine",INDEX('⚙ Moteur'!$B$5:$B$41,$H14)) -> S3 · séance 2 | E14: Mer. 11/11 férié (Armistice) | H14: =IF($G14<>"",H13,H13+1) -> 10
A15: S11 | B15: 16/11/2026 | C15: P2 | D15: =IF($G15<>"",$G15&" — les séances suivantes se décalent d'une semaine",INDEX('⚙ Moteur'!$B$5:$B$41,$H15)) -> S3 · séance 3 | H15: =IF($G15<>"",H14,H14+1) -> 11
A16: S12 | B16: 23/11/2026 | C16: P2 | D16: =IF($G16<>"",$G16&" — les séances suivantes se décalent d'une semaine",INDEX('⚙ Moteur'!$B$5:$B$41,$H16)) -> S3 · séance 4 | H16: =IF($G16<>"",H15,H15+1) -> 12
A17: S13 | B17: 30/11/2026 | C17: P2 | D17: =IF($G17<>"",$G17&" — les séances suivantes se décalent d'une semaine",INDEX('⚙ Moteur'!$B$5:$B$41,$H17)) -> S4 · séance 1 | H17: =IF($G17<>"",H16,H16+1) -> 13
A18: S14 | B18: 07/12/2026 | C18: P2 | D18: =IF($G18<>"",$G18&" — les séances suivantes se décalent d'une semaine",INDEX('⚙ Moteur'!$B$5:$B$41,$H18)) -> S4 · séance 2 | H18: =IF($G18<>"",H17,H17+1) -> 14
A19: S15 | B19: 14/12/2026 | C19: P2 | D19: =IF($G19<>"",$G19&" — les séances suivantes se décalent d'une semaine",INDEX('⚙ Moteur'!$B$5:$B$41,$H19)) -> ⏳ TAMPON P2 — rattrapage / remédiation | H19: =IF($G19<>"",H18,H18+1) -> 15
A20: 🏖 Vacances de Noël : 19/12 → 4/01
A21: S16 | B21: 04/01/2027 | C21: P3 | D21: =IF($G21<>"",$G21&" — les séances suivantes se décalent d'une semaine",INDEX('⚙ Moteur'!$B$5:$B$41,$H21)) -> S4 · séance 3 | H21: =IF($G21<>"",H19,H19+1) -> 16
A22: S17 | B22: 11/01/2027 | C22: P3 | D22: =IF($G22<>"",$G22&" — les séances suivantes se décalent d'une semaine",INDEX('⚙ Moteur'!$B$5:$B$41,$H22)) -> S4 · séance 4 | H22: =IF($G22<>"",H21,H21+1) -> 17
A23: S18 | B23: 18/01/2027 | C23: P3 | D23: =IF($G23<>"",$G23&" — les séances suivantes se décalent d'une semaine",INDEX('⚙ Moteur'!$B$5:$B$41,$H23)) -> S4 · séance 5 | H23: =IF($G23<>"",H22,H22+1) -> 18
A24: S19 | B24: 25/01/2027 | C24: P3 | D24: =IF($G24<>"",$G24&" — les séances suivantes se décalent d'une semaine",INDEX('⚙ Moteur'!$B$5:$B$41,$H24)) -> S5 · séance 1 | H24: =IF($G24<>"",H23,H23+1) -> 19
A25: S20 | B25: 01/02/2027 | C25: P3 | D25: =IF($G25<>"",$G25&" — les séances suivantes se décalent d'une semaine",INDEX('⚙ Moteur'!$B$5:$B$41,$H25)) -> ⏳ TAMPON P3 — rattrapage / remédiation | H25: =IF($G25<>"",H24,H24+1) -> 20
A26: 🏖 Vacances de Carnaval : 6/02 → 22/02
A27: S21 | B27: 22/02/2027 | C27: P4 | D27: =IF($G27<>"",$G27&" — les séances suivantes se décalent d'une semaine",INDEX('⚙ Moteur'!$B$5:$B$41,$H27)) -> S5 · séance 2 | H27: =IF($G27<>"",H25,H25+1) -> 21
A28: S22 | B28: 01/03/2027 | C28: P4 | D28: =IF($G28<>"",$G28&" — les séances suivantes se décalent d'une semaine",INDEX('⚙ Moteur'!$B$5:$B$41,$H28)) -> S5 · séance 3 | H28: =IF($G28<>"",H27,H27+1) -> 22
A29: S23 | B29: 08/03/2027 | C29: P4 | D29: =IF($G29<>"",$G29&" — les séances suivantes se décalent d'une semaine",INDEX('⚙ Moteur'!$B$5:$B$41,$H29)) -> S6 · séance 1 | H29: =IF($G29<>"",H28,H28+1) -> 23
A30: S24 | B30: 15/03/2027 | C30: P4 | D30: =IF($G30<>"",$G30&" — les séances suivantes se décalent d'une semaine",INDEX('⚙ Moteur'!$B$5:$B$41,$H30)) -> S6 · séance 2 | H30: =IF($G30<>"",H29,H29+1) -> 24
A31: S25 | B31: 22/03/2027 | C31: P4 | D31: =IF($G31<>"",$G31&" — les séances suivantes se décalent d'une semaine",INDEX('⚙ Moteur'!$B$5:$B$41,$H31)) -> S6 · séance 3 | E31: Ven. 26/03 férié (Vendredi saint, Martinique) | H31: =IF($G31<>"",H30,H30+1) -> 25
A32: S26 | B32: 29/03/2027 | C32: P4 | D32: =IF($G32<>"",$G32&" — les séances suivantes se décalent d'une semaine",INDEX('⚙ Moteur'!$B$5:$B$41,$H32)) -> S6 · séance 4 | E32: Lun. 29/03 férié (lundi de Pâques) | H32: =IF($G32<>"",H31,H31+1) -> 26
A33: S27 | B33: 05/04/2027 | C33: P4 | D33: =IF($G33<>"",$G33&" — les séances suivantes se décalent d'une semaine",INDEX('⚙ Moteur'!$B$5:$B$41,$H33)) -> S7 · séance 1 | H33: =IF($G33<>"",H32,H32+1) -> 27
A34: S28 | B34: 12/04/2027 | C34: P4 | D34: =IF($G34<>"",$G34&" — les séances suivantes se décalent d'une semaine",INDEX('⚙ Moteur'!$B$5:$B$41,$H34)) -> ⏳ TAMPON P4 — rattrapage / remédiation | H34: =IF($G34<>"",H33,H33+1) -> 28
A35: 🏖 Vacances de Pâques : 20/04 → 3/05
A36: S29 | B36: 03/05/2027 | C36: P5 | D36: =IF($G36<>"",$G36&" — les séances suivantes se décalent d'une semaine",INDEX('⚙ Moteur'!$B$5:$B$41,$H36)) -> S7 · séance 2 | E36: Jeu. 6/05 férié (Ascension) — pont probable ven. 7/05 | H36: =IF($G36<>"",H34,H34+1) -> 29
A37: S30 | B37: 10/05/2027 | C37: P5 | D37: =IF($G37<>"",$G37&" — les séances suivantes se décalent d'une semaine",INDEX('⚙ Moteur'!$B$5:$B$41,$H37)) -> S7 · séance 3 | H37: =IF($G37<>"",H36,H36+1) -> 30
A38: S31 | B38: 17/05/2027 | C38: P5 | D38: =IF($G38<>"",$G38&" — les séances suivantes se décalent d'une semaine",INDEX('⚙ Moteur'!$B$5:$B$41,$H38)) -> S7 · séance 4 | E38: Lun. 17/05 férié (Pentecôte); Ven. 21/05 : veille du 22 mai (abolition, samedi) — commémorations | H38: =IF($G38<>"",H37,H37+1) -> 31
A39: S32 | B39: 24/05/2027 | C39: P5 | D39: =IF($G39<>"",$G39&" — les séances suivantes se décalent d'une semaine",INDEX('⚙ Moteur'!$B$5:$B$41,$H39)) -> S7 · séance 5 | H39: =IF($G39<>"",H38,H38+1) -> 32
A40: S33 | B40: 31/05/2027 | C40: P5 | D40: =IF($G40<>"",$G40&" — les séances suivantes se décalent d'une semaine",INDEX('⚙ Moteur'!$B$5:$B$41,$H40)) -> S7 · séance 6 | H40: =IF($G40<>"",H39,H39+1) -> 33
A41: S34 | B41: 07/06/2027 | C41: P5 | D41: =IF($G41<>"",$G41&" — les séances suivantes se décalent d'une semaine",INDEX('⚙ Moteur'!$B$5:$B$41,$H41)) -> ⏳ TAMPON P5 — réserve a | H41: =IF($G41<>"",H40,H40+1) -> 34
A42: S35 | B42: 14/06/2027 | C42: P5 | D42: =IF($G42<>"",$G42&" — les séances suivantes se décalent d'une semaine",INDEX('⚙ Moteur'!$B$5:$B$41,$H42)) -> ⏳ TAMPON P5 — réserve b (revue de projet de secours) | H42: =IF($G42<>"",H41,H41+1) -> 35
A43: S36 | B43: 21/06/2027 | C43: P5 | D43: =IF($G43<>"",$G43&" — les séances suivantes se décalent d'une semaine",INDEX('⚙ Moteur'!$B$5:$B$41,$H43)) -> ⏳ TAMPON P5 — réserve c (bilan de l'année) | H43: =IF($G43<>"",H42,H42+1) -> 36
A44: S37 | B44: 28/06/2027 | C44: P5 | D44: =IF($G44<>"",$G44&" — les séances suivantes se décalent d'une semaine",INDEX('⚙ Moteur'!$B$5:$B$41,$H44)) -> ⏳ TAMPON P5 — réserve d (fin des cours) | H44: =IF($G44<>"",H43,H43+1) -> 37
A45: 🏖 Fin des cours : 3 juillet 2027
A47: Synthèse
B48: Semaines de cours au total | C48: =COUNTIF(C4:C45,"P1")+COUNTIF(C4:C45,"P2")+COUNTIF(C4:C45,"P3")+COUNTIF(C4:C45,"P4")+COUNTIF(C4:C45,"P5") -> 37
B49: … dont semaines tampon | C49: =COUNTIF(D4:D44,"⏳*") -> 8
B50: … dont semaines avec séance planifiée | C50: =COUNTIF(D4:D44,"S*") -> 29
B51: Moteur automatique : marquer un ⚠ imprévu en colonne G décale toutes les séances suivantes (calendrier, frise et progression se recalculent). Un jour férié sur ton créneau = un imprévu à marquer aussi.

Sheet 🗓 Frise de l'année
A1: FRISE DE L'ANNÉE 5e — se recalcule automatiquement selon les imprévus du Calendrier
B2: ='📅 Calendrier'!D2 -> ✔ Réserve d'aléas : 8 semaine(s) tampon restante(s) sur 8 | P2: ◀ Accueil
C3: P1 (8 sem.) | K3: P2 (7 sem.) | R3: P3 (5 sem.) | W3: P4 (8 sem.) | AE3: P5 (9 sem.)
C4: S01 | D4: S02 | E4: S03 | F4: S04 | G4: S05 | H4: S06 | I4: S07 | J4: S08 | K4: S09 | L4: S10 | M4: S11 | N4: S12 | O4: S13 | P4: S14 | Q4: S15 | R4: S16 | S4: S17 | T4: S18 | U4: S19 | V4: S20 | W4: S21 | X4: S22 | Y4: S23 | Z4: S24 | AA4: S25 | AB4: S26 | AC4: S27 | AD4: S28 | AE4: S29 | AF4: S30 | AG4: S31 | AH4: S32 | AI4: S33 | AJ4: S34 | AK4: S35 | AL4: S36 | AM4: S37
C5: 31/08 | D5: 07/09 | E5: 14/09 | F5: 21/09 | G5: 28/09 | H5: 05/10 | I5: 12/10 | J5: 19/10 | K5: 02/11 | L5: 09/11 | M5: 16/11 | N5: 23/11 | O5: 30/11 | P5: 07/12 | Q5: 14/12 | R5: 04/01 | S5: 11/01 | T5: 18/01 | U5: 25/01 | V5: 01/02 | W5: 22/02 | X5: 01/03 | Y5: 08/03 | Z5: 15/03 | AA5: 22/03 | AB5: 29/03 | AC5: 05/04 | AD5: 12/04 | AE5: 03/05 | AF5: 10/05 | AG5: 17/05 | AH5: 24/05 | AI5: 31/05 | AJ5: 07/06 | AK5: 14/06 | AL5: 21/06 | AM5: 28/06
B6: S1 · Environnement numérique | C6: =IF(LEFT('📅 Calendrier'!$D4,2)="S1",MID('📅 Calendrier'!$D4,SEARCH("séance",'📅 Calendrier'!$D4)+7,2),"") -> 1 | D6: =IF(LEFT('📅 Calendrier'!$D5,2)="S1",MID('📅 Calendrier'!$D5,SEARCH("séance",'📅 Calendrier'!$D5)+7,2),"") -> 2 | E6: =IF(LEFT('📅 Calendrier'!$D6,2)="S1",MID('📅 Calendrier'!$D6,SEARCH("séance",'📅 Calendrier'!$D6)+7,2),"") -> 3 | F6: =IF(LEFT('📅 Calendrier'!$D7,2)="S1",MID('📅 Calendrier'!$D7,SEARCH("séance",'📅 Calendrier'!$D7)+7,2),"") | G6: =IF(LEFT('📅 Calendrier'!$D8,2)="S1",MID('📅 Calendrier'!$D8,SEARCH("séance",'📅 Calendrier'!$D8)+7,2),"") | H6: =IF(LEFT('📅 Calendrier'!$D9,2)="S1",MID('📅 Calendrier'!$D9,SEARCH("séance",'📅 Calendrier'!$D9)+7,2),"") | I6: =IF(LEFT('📅 Calendrier'!$D10,2)="S1",MID('📅 Calendrier'!$D10,SEARCH("séance",'📅 Calendrier'!$D10)+7,2),"") | J6: =IF(LEFT('📅 Calendrier'!$D11,2)="S1",MID('📅 Calendrier'!$D11,SEARCH("séance",'📅 Calendrier'!$D11)+7,2),"") | K6: =IF(LEFT('📅 Calendrier'!$D13,2)="S1",MID('📅 Calendrier'!$D13,SEARCH("séance",'📅 Calendrier'!$D13)+7,2),"") | L6: =IF(LEFT('📅 Calendrier'!$D14,2)="S1",MID('📅 Calendrier'!$D14,SEARCH("séance",'📅 Calendrier'!$D14)+7,2),"") | M6: =IF(LEFT('📅 Calendrier'!$D15,2)="S1",MID('📅 Calendrier'!$D15,SEARCH("séance",'📅 Calendrier'!$D15)+7,2),"") | N6: =IF(LEFT('📅 Calendrier'!$D16,2)="S1",MID('📅 Calendrier'!$D16,SEARCH("séance",'📅 Calendrier'!$D16)+7,2),"") | O6: =IF(LEFT('📅 Calendrier'!$D17,2)="S1",MID('📅 Calendrier'!$D17,SEARCH("séance",'📅 Calendrier'!$D17)+7,2),"") | P6: =IF(LEFT('📅 Calendrier'!$D18,2)="S1",MID('📅 Calendrier'!$D18,SEARCH("séance",'📅 Calendrier'!$D18)+7,2),"") | Q6: =IF(LEFT('📅 Calendrier'!$D19,2)="S1",MID('📅 Calendrier'!$D19,SEARCH("séance",'📅 Calendrier'!$D19)+7,2),"") | R6: =IF(LEFT('📅 Calendrier'!$D21,2)="S1",MID('📅 Calendrier'!$D21,SEARCH("séance",'📅 Calendrier'!$D21)+7,2),"") | S6: =IF(LEFT('📅 Calendrier'!$D22,2)="S1",MID('📅 Calendrier'!$D22,SEARCH("séance",'📅 Calendrier'!$D22)+7,2),"") | T6: =IF(LEFT('📅 Calendrier'!$D23,2)="S1",MID('📅 Calendrier'!$D23,SEARCH("séance",'📅 Calendrier'!$D23)+7,2),"") | U6: =IF(LEFT('📅 Calendrier'!$D24,2)="S1",MID('📅 Calendrier'!$D24,SEARCH("séance",'📅 Calendrier'!$D24)+7,2),"") | V6: =IF(LEFT('📅 Calendrier'!$D25,2)="S1",MID('📅 Calendrier'!$D25,SEARCH("séance",'📅 Calendrier'!$D25)+7,2),"") | W6: =IF(LEFT('📅 Calendrier'!$D27,2)="S1",MID('📅 Calendrier'!$D27,SEARCH("séance",'📅 Calendrier'!$D27)+7,2),"") | X6: =IF(LEFT('📅 Calendrier'!$D28,2)="S1",MID('📅 Calendrier'!$D28,SEARCH("séance",'📅 Calendrier'!$D28)+7,2),"") | Y6: =IF(LEFT('📅 Calendrier'!$D29,2)="S1",MID('📅 Calendrier'!$D29,SEARCH("séance",'📅 Calendrier'!$D29)+7,2),"") | Z6: =IF(LEFT('📅 Calendrier'!$D30,2)="S1",MID('📅 Calendrier'!$D30,SEARCH("séance",'📅 Calendrier'!$D30)+7,2),"") | AA6: =IF(LEFT('📅 Calendrier'!$D31,2)="S1",MID('📅 Calendrier'!$D31,SEARCH("séance",'📅 Calendrier'!$D31)+7,2),"") | AB6: =IF(LEFT('📅 Calendrier'!$D32,2)="S1",MID('📅 Calendrier'!$D32,SEARCH("séance",'📅 Calendrier'!$D32)+7,2),"") | AC6: =IF(LEFT('📅 Calendrier'!$D33,2)="S1",MID('📅 Calendrier'!$D33,SEARCH("séance",'📅 Calendrier'!$D33)+7,2),"") | AD6: =IF(LEFT('📅 Calendrier'!$D34,2)="S1",MID('📅 Calendrier'!$D34,SEARCH("séance",'📅 Calendrier'!$D34)+7,2),"") | AE6: =IF(LEFT('📅 Calendrier'!$D36,2)="S1",MID('📅 Calendrier'!$D36,SEARCH("séance",'📅 Calendrier'!$D36)+7,2),"") | AF6: =IF(LEFT('📅 Calendrier'!$D37,2)="S1",MID('📅 Calendrier'!$D37,SEARCH("séance",'📅 Calendrier'!$D37)+7,2),"") | AG6: =IF(LEFT('📅 Calendrier'!$D38,2)="S1",MID('📅 Calendrier'!$D38,SEARCH("séance",'📅 Calendrier'!$D38)+7,2),"") | AH6: =IF(LEFT('📅 Calendrier'!$D39,2)="S1",MID('📅 Calendrier'!$D39,SEARCH("séance",'📅 Calendrier'!$D39)+7,2),"") | AI6: =IF(LEFT('📅 Calendrier'!$D40,2)="S1",MID('📅 Calendrier'!$D40,SEARCH("séance",'📅 Calendrier'!$D40)+7,2),"") | AJ6: =IF(LEFT('📅 Calendrier'!$D41,2)="S1",MID('📅 Calendrier'!$D41,SEARCH("séance",'📅 Calendrier'!$D41)+7,2),"") | AK6: =IF(LEFT('📅 Calendrier'!$D42,2)="S1",MID('📅 Calendrier'!$D42,SEARCH("séance",'📅 Calendrier'!$D42)+7,2),"") | AL6: =IF(LEFT('📅 Calendrier'!$D43,2)="S1",MID('📅 Calendrier'!$D43,SEARCH("séance",'📅 Calendrier'!$D43)+7,2),"") | AM6: =IF(LEFT('📅 Calendrier'!$D44,2)="S1",MID('📅 Calendrier'!$D44,SEARCH("séance",'📅 Calendrier'!$D44)+7,2),"")
B7: S2 · Comparer pour choisir | C7: =IF(LEFT('📅 Calendrier'!$D4,2)="S2",MID('📅 Calendrier'!$D4,SEARCH("séance",'📅 Calendrier'!$D4)+7,2),"") | D7: =IF(LEFT('📅 Calendrier'!$D5,2)="S2",MID('📅 Calendrier'!$D5,SEARCH("séance",'📅 Calendrier'!$D5)+7,2),"") | E7: =IF(LEFT('📅 Calendrier'!$D6,2)="S2",MID('📅 Calendrier'!$D6,SEARCH("séance",'📅 Calendrier'!$D6)+7,2),"") | F7: =IF(LEFT('📅 Calendrier'!$D7,2)="S2",MID('📅 Calendrier'!$D7,SEARCH("séance",'📅 Calendrier'!$D7)+7,2),"") -> 1 | G7: =IF(LEFT('📅 Calendrier'!$D8,2)="S2",MID('📅 Calendrier'!$D8,SEARCH("séance",'📅 Calendrier'!$D8)+7,2),"") -> 2 | H7: =IF(LEFT('📅 Calendrier'!$D9,2)="S2",MID('📅 Calendrier'!$D9,SEARCH("séance",'📅 Calendrier'!$D9)+7,2),"") -> 3 | I7: =IF(LEFT('📅 Calendrier'!$D10,2)="S2",MID('📅 Calendrier'!$D10,SEARCH("séance",'📅 Calendrier'!$D10)+7,2),"") -> 4 | J7: =IF(LEFT('📅 Calendrier'!$D11,2)="S2",MID('📅 Calendrier'!$D11,SEARCH("séance",'📅 Calendrier'!$D11)+7,2),"") | K7: =IF(LEFT('📅 Calendrier'!$D13,2)="S2",MID('📅 Calendrier'!$D13,SEARCH("séance",'📅 Calendrier'!$D13)+7,2),"") | L7: =IF(LEFT('📅 Calendrier'!$D14,2)="S2",MID('📅 Calendrier'!$D14,SEARCH("séance",'📅 Calendrier'!$D14)+7,2),"") | M7: =IF(LEFT('📅 Calendrier'!$D15,2)="S2",MID('📅 Calendrier'!$D15,SEARCH("séance",'📅 Calendrier'!$D15)+7,2),"") | N7: =IF(LEFT('📅 Calendrier'!$D16,2)="S2",MID('📅 Calendrier'!$D16,SEARCH("séance",'📅 Calendrier'!$D16)+7,2),"") | O7: =IF(LEFT('📅 Calendrier'!$D17,2)="S2",MID('📅 Calendrier'!$D17,SEARCH("séance",'📅 Calendrier'!$D17)+7,2),"") | P7: =IF(LEFT('📅 Calendrier'!$D18,2)="S2",MID('📅 Calendrier'!$D18,SEARCH("séance",'📅 Calendrier'!$D18)+7,2),"") | Q7: =IF(LEFT('📅 Calendrier'!$D19,2)="S2",MID('📅 Calendrier'!$D19,SEARCH("séance",'📅 Calendrier'!$D19)+7,2),"") | R7: =IF(LEFT('📅 Calendrier'!$D21,2)="S2",MID('📅 Calendrier'!$D21,SEARCH("séance",'📅 Calendrier'!$D21)+7,2),"") | S7: =IF(LEFT('📅 Calendrier'!$D22,2)="S2",MID('📅 Calendrier'!$D22,SEARCH("séance",'📅 Calendrier'!$D22)+7,2),"") | T7: =IF(LEFT('📅 Calendrier'!$D23,2)="S2",MID('📅 Calendrier'!$D23,SEARCH("séance",'📅 Calendrier'!$D23)+7,2),"") | U7: =IF(LEFT('📅 Calendrier'!$D24,2)="S2",MID('📅 Calendrier'!$D24,SEARCH("séance",'📅 Calendrier'!$D24)+7,2),"") | V7: =IF(LEFT('📅 Calendrier'!$D25,2)="S2",MID('📅 Calendrier'!$D25,SEARCH("séance",'📅 Calendrier'!$D25)+7,2),"") | W7: =IF(LEFT('📅 Calendrier'!$D27,2)="S2",MID('📅 Calendrier'!$D27,SEARCH("séance",'📅 Calendrier'!$D27)+7,2),"") | X7: =IF(LEFT('📅 Calendrier'!$D28,2)="S2",MID('📅 Calendrier'!$D28,SEARCH("séance",'📅 Calendrier'!$D28)+7,2),"") | Y7: =IF(LEFT('📅 Calendrier'!$D29,2)="S2",MID('📅 Calendrier'!$D29,SEARCH("séance",'📅 Calendrier'!$D29)+7,2),"") | Z7: =IF(LEFT('📅 Calendrier'!$D30,2)="S2",MID('📅 Calendrier'!$D30,SEARCH("séance",'📅 Calendrier'!$D30)+7,2),"") | AA7: =IF(LEFT('📅 Calendrier'!$D31,2)="S2",MID('📅 Calendrier'!$D31,SEARCH("séance",'📅 Calendrier'!$D31)+7,2),"") | AB7: =IF(LEFT('📅 Calendrier'!$D32,2)="S2",MID('📅 Calendrier'!$D32,SEARCH("séance",'📅 Calendrier'!$D32)+7,2),"") | AC7: =IF(LEFT('📅 Calendrier'!$D33,2)="S2",MID('📅 Calendrier'!$D33,SEARCH("séance",'📅 Calendrier'!$D33)+7,2),"") | AD7: =IF(LEFT('📅 Calendrier'!$D34,2)="S2",MID('📅 Calendrier'!$D34,SEARCH("séance",'📅 Calendrier'!$D34)+7,2),"") | AE7: =IF(LEFT('📅 Calendrier'!$D36,2)="S2",MID('📅 Calendrier'!$D36,SEARCH("séance",'📅 Calendrier'!$D36)+7,2),"") | AF7: =IF(LEFT('📅 Calendrier'!$D37,2)="S2",MID('📅 Calendrier'!$D37,SEARCH("séance",'📅 Calendrier'!$D37)+7,2),"") | AG7: =IF(LEFT('📅 Calendrier'!$D38,2)="S2",MID('📅 Calendrier'!$D38,SEARCH("séance",'📅 Calendrier'!$D38)+7,2),"") | AH7: =IF(LEFT('📅 Calendrier'!$D39,2)="S2",MID('📅 Calendrier'!$D39,SEARCH("séance",'📅 Calendrier'!$D39)+7,2),"") | AI7: =IF(LEFT('📅 Calendrier'!$D40,2)="S2",MID('📅 Calendrier'!$D40,SEARCH("séance",'📅 Calendrier'!$D40)+7,2),"") | AJ7: =IF(LEFT('📅 Calendrier'!$D41,2)="S2",MID('📅 Calendrier'!$D41,SEARCH("séance",'📅 Calendrier'!$D41)+7,2),"") | AK7: =IF(LEFT('📅 Calendrier'!$D42,2)="S2",MID('📅 Calendrier'!$D42,SEARCH("séance",'📅 Calendrier'!$D42)+7,2),"") | AL7: =IF(LEFT('📅 Calendrier'!$D43,2)="S2",MID('📅 Calendrier'!$D43,SEARCH("séance",'📅 Calendrier'!$D43)+7,2),"") | AM7: =IF(LEFT('📅 Calendrier'!$D44,2)="S2",MID('📅 Calendrier'!$D44,SEARCH("séance",'📅 Calendrier'!$D44)+7,2),"")
B8: S3 · Chaîne d'énergie | C8: =IF(LEFT('📅 Calendrier'!$D4,2)="S3",MID('📅 Calendrier'!$D4,SEARCH("séance",'📅 Calendrier'!$D4)+7,2),"") | D8: =IF(LEFT('📅 Calendrier'!$D5,2)="S3",MID('📅 Calendrier'!$D5,SEARCH("séance",'📅 Calendrier'!$D5)+7,2),"") | E8: =IF(LEFT('📅 Calendrier'!$D6,2)="S3",MID('📅 Calendrier'!$D6,SEARCH("séance",'📅 Calendrier'!$D6)+7,2),"") | F8: =IF(LEFT('📅 Calendrier'!$D7,2)="S3",MID('📅 Calendrier'!$D7,SEARCH("séance",'📅 Calendrier'!$D7)+7,2),"") | G8: =IF(LEFT('📅 Calendrier'!$D8,2)="S3",MID('📅 Calendrier'!$D8,SEARCH("séance",'📅 Calendrier'!$D8)+7,2),"") | H8: =IF(LEFT('📅 Calendrier'!$D9,2)="S3",MID('📅 Calendrier'!$D9,SEARCH("séance",'📅 Calendrier'!$D9)+7,2),"") | I8: =IF(LEFT('📅 Calendrier'!$D10,2)="S3",MID('📅 Calendrier'!$D10,SEARCH("séance",'📅 Calendrier'!$D10)+7,2),"") | J8: =IF(LEFT('📅 Calendrier'!$D11,2)="S3",MID('📅 Calendrier'!$D11,SEARCH("séance",'📅 Calendrier'!$D11)+7,2),"") | K8: =IF(LEFT('📅 Calendrier'!$D13,2)="S3",MID('📅 Calendrier'!$D13,SEARCH("séance",'📅 Calendrier'!$D13)+7,2),"") -> 1 | L8: =IF(LEFT('📅 Calendrier'!$D14,2)="S3",MID('📅 Calendrier'!$D14,SEARCH("séance",'📅 Calendrier'!$D14)+7,2),"") -> 2 | M8: =IF(LEFT('📅 Calendrier'!$D15,2)="S3",MID('📅 Calendrier'!$D15,SEARCH("séance",'📅 Calendrier'!$D15)+7,2),"") -> 3 | N8: =IF(LEFT('📅 Calendrier'!$D16,2)="S3",MID('📅 Calendrier'!$D16,SEARCH("séance",'📅 Calendrier'!$D16)+7,2),"") -> 4 | O8: =IF(LEFT('📅 Calendrier'!$D17,2)="S3",MID('📅 Calendrier'!$D17,SEARCH("séance",'📅 Calendrier'!$D17)+7,2),"") | P8: =IF(LEFT('📅 Calendrier'!$D18,2)="S3",MID('📅 Calendrier'!$D18,SEARCH("séance",'📅 Calendrier'!$D18)+7,2),"") | Q8: =IF(LEFT('📅 Calendrier'!$D19,2)="S3",MID('📅 Calendrier'!$D19,SEARCH("séance",'📅 Calendrier'!$D19)+7,2),"") | R8: =IF(LEFT('📅 Calendrier'!$D21,2)="S3",MID('📅 Calendrier'!$D21,SEARCH("séance",'📅 Calendrier'!$D21)+7,2),"") | S8: =IF(LEFT('📅 Calendrier'!$D22,2)="S3",MID('📅 Calendrier'!$D22,SEARCH("séance",'📅 Calendrier'!$D22)+7,2),"") | T8: =IF(LEFT('📅 Calendrier'!$D23,2)="S3",MID('📅 Calendrier'!$D23,SEARCH("séance",'📅 Calendrier'!$D23)+7,2),"") | U8: =IF(LEFT('📅 Calendrier'!$D24,2)="S3",MID('📅 Calendrier'!$D24,SEARCH("séance",'📅 Calendrier'!$D24)+7,2),"") | V8: =IF(LEFT('📅 Calendrier'!$D25,2)="S3",MID('📅 Calendrier'!$D25,SEARCH("séance",'📅 Calendrier'!$D25)+7,2),"") | W8: =IF(LEFT('📅 Calendrier'!$D27,2)="S3",MID('📅 Calendrier'!$D27,SEARCH("séance",'📅 Calendrier'!$D27)+7,2),"") | X8: =IF(LEFT('📅 Calendrier'!$D28,2)="S3",MID('📅 Calendrier'!$D28,SEARCH("séance",'📅 Calendrier'!$D28)+7,2),"") | Y8: =IF(LEFT('📅 Calendrier'!$D29,2)="S3",MID('📅 Calendrier'!$D29,SEARCH("séance",'📅 Calendrier'!$D29)+7,2),"") | Z8: =IF(LEFT('📅 Calendrier'!$D30,2)="S3",MID('📅 Calendrier'!$D30,SEARCH("séance",'📅 Calendrier'!$D30)+7,2),"") | AA8: =IF(LEFT('📅 Calendrier'!$D31,2)="S3",MID('📅 Calendrier'!$D31,SEARCH("séance",'📅 Calendrier'!$D31)+7,2),"") | AB8: =IF(LEFT('📅 Calendrier'!$D32,2)="S3",MID('📅 Calendrier'!$D32,SEARCH("séance",'📅 Calendrier'!$D32)+7,2),"") | AC8: =IF(LEFT('📅 Calendrier'!$D33,2)="S3",MID('📅 Calendrier'!$D33,SEARCH("séance",'📅 Calendrier'!$D33)+7,2),"") | AD8: =IF(LEFT('📅 Calendrier'!$D34,2)="S3",MID('📅 Calendrier'!$D34,SEARCH("séance",'📅 Calendrier'!$D34)+7,2),"") | AE8: =IF(LEFT('📅 Calendrier'!$D36,2)="S3",MID('📅 Calendrier'!$D36,SEARCH("séance",'📅 Calendrier'!$D36)+7,2),"") | AF8: =IF(LEFT('📅 Calendrier'!$D37,2)="S3",MID('📅 Calendrier'!$D37,SEARCH("séance",'📅 Calendrier'!$D37)+7,2),"") | AG8: =IF(LEFT('📅 Calendrier'!$D38,2)="S3",MID('📅 Calendrier'!$D38,SEARCH("séance",'📅 Calendrier'!$D38)+7,2),"") | AH8: =IF(LEFT('📅 Calendrier'!$D39,2)="S3",MID('📅 Calendrier'!$D39,SEARCH("séance",'📅 Calendrier'!$D39)+7,2),"") | AI8: =IF(LEFT('📅 Calendrier'!$D40,2)="S3",MID('📅 Calendrier'!$D40,SEARCH("séance",'📅 Calendrier'!$D40)+7,2),"") | AJ8: =IF(LEFT('📅 Calendrier'!$D41,2)="S3",MID('📅 Calendrier'!$D41,SEARCH("séance",'📅 Calendrier'!$D41)+7,2),"") | AK8: =IF(LEFT('📅 Calendrier'!$D42,2)="S3",MID('📅 Calendrier'!$D42,SEARCH("séance",'📅 Calendrier'!$D42)+7,2),"") | AL8: =IF(LEFT('📅 Calendrier'!$D43,2)="S3",MID('📅 Calendrier'!$D43,SEARCH("séance",'📅 Calendrier'!$D43)+7,2),"") | AM8: =IF(LEFT('📅 Calendrier'!$D44,2)="S3",MID('📅 Calendrier'!$D44,SEARCH("séance",'📅 Calendrier'!$D44)+7,2),"")
B9: S4 · Lampadaire (1) : information & programmes | C9: =IF(LEFT('📅 Calendrier'!$D4,2)="S4",MID('📅 Calendrier'!$D4,SEARCH("séance",'📅 Calendrier'!$D4)+7,2),"") | D9: =IF(LEFT('📅 Calendrier'!$D5,2)="S4",MID('📅 Calendrier'!$D5,SEARCH("séance",'📅 Calendrier'!$D5)+7,2),"") | E9: =IF(LEFT('📅 Calendrier'!$D6,2)="S4",MID('📅 Calendrier'!$D6,SEARCH("séance",'📅 Calendrier'!$D6)+7,2),"") | F9: =IF(LEFT('📅 Calendrier'!$D7,2)="S4",MID('📅 Calendrier'!$D7,SEARCH("séance",'📅 Calendrier'!$D7)+7,2),"") | G9: =IF(LEFT('📅 Calendrier'!$D8,2)="S4",MID('📅 Calendrier'!$D8,SEARCH("séance",'📅 Calendrier'!$D8)+7,2),"") | H9: =IF(LEFT('📅 Calendrier'!$D9,2)="S4",MID('📅 Calendrier'!$D9,SEARCH("séance",'📅 Calendrier'!$D9)+7,2),"") | I9: =IF(LEFT('📅 Calendrier'!$D10,2)="S4",MID('📅 Calendrier'!$D10,SEARCH("séance",'📅 Calendrier'!$D10)+7,2),"") | J9: =IF(LEFT('📅 Calendrier'!$D11,2)="S4",MID('📅 Calendrier'!$D11,SEARCH("séance",'📅 Calendrier'!$D11)+7,2),"") | K9: =IF(LEFT('📅 Calendrier'!$D13,2)="S4",MID('📅 Calendrier'!$D13,SEARCH("séance",'📅 Calendrier'!$D13)+7,2),"") | L9: =IF(LEFT('📅 Calendrier'!$D14,2)="S4",MID('📅 Calendrier'!$D14,SEARCH("séance",'📅 Calendrier'!$D14)+7,2),"") | M9: =IF(LEFT('📅 Calendrier'!$D15,2)="S4",MID('📅 Calendrier'!$D15,SEARCH("séance",'📅 Calendrier'!$D15)+7,2),"") | N9: =IF(LEFT('📅 Calendrier'!$D16,2)="S4",MID('📅 Calendrier'!$D16,SEARCH("séance",'📅 Calendrier'!$D16)+7,2),"") | O9: =IF(LEFT('📅 Calendrier'!$D17,2)="S4",MID('📅 Calendrier'!$D17,SEARCH("séance",'📅 Calendrier'!$D17)+7,2),"") -> 1 | P9: =IF(LEFT('📅 Calendrier'!$D18,2)="S4",MID('📅 Calendrier'!$D18,SEARCH("séance",'📅 Calendrier'!$D18)+7,2),"") -> 2 | Q9: =IF(LEFT('📅 Calendrier'!$D19,2)="S4",MID('📅 Calendrier'!$D19,SEARCH("séance",'📅 Calendrier'!$D19)+7,2),"") | R9: =IF(LEFT('📅 Calendrier'!$D21,2)="S4",MID('📅 Calendrier'!$D21,SEARCH("séance",'📅 Calendrier'!$D21)+7,2),"") -> 3 | S9: =IF(LEFT('📅 Calendrier'!$D22,2)="S4",MID('📅 Calendrier'!$D22,SEARCH("séance",'📅 Calendrier'!$D22)+7,2),"") -> 4 | T9: =IF(LEFT('📅 Calendrier'!$D23,2)="S4",MID('📅 Calendrier'!$D23,SEARCH("séance",'📅 Calendrier'!$D23)+7,2),"") -> 5 | U9: =IF(LEFT('📅 Calendrier'!$D24,2)="S4",MID('📅 Calendrier'!$D24,SEARCH("séance",'📅 Calendrier'!$D24)+7,2),"") | V9: =IF(LEFT('📅 Calendrier'!$D25,2)="S4",MID('📅 Calendrier'!$D25,SEARCH("séance",'📅 Calendrier'!$D25)+7,2),"") | W9: =IF(LEFT('📅 Calendrier'!$D27,2)="S4",MID('📅 Calendrier'!$D27,SEARCH("séance",'📅 Calendrier'!$D27)+7,2),"") | X9: =IF(LEFT('📅 Calendrier'!$D28,2)="S4",MID('📅 Calendrier'!$D28,SEARCH("séance",'📅 Calendrier'!$D28)+7,2),"") | Y9: =IF(LEFT('📅 Calendrier'!$D29,2)="S4",MID('📅 Calendrier'!$D29,SEARCH("séance",'📅 Calendrier'!$D29)+7,2),"") | Z9: =IF(LEFT('📅 Calendrier'!$D30,2)="S4",MID('📅 Calendrier'!$D30,SEARCH("séance",'📅 Calendrier'!$D30)+7,2),"") | AA9: =IF(LEFT('📅 Calendrier'!$D31,2)="S4",MID('📅 Calendrier'!$D31,SEARCH("séance",'📅 Calendrier'!$D31)+7,2),"") | AB9: =IF(LEFT('📅 Calendrier'!$D32,2)="S4",MID('📅 Calendrier'!$D32,SEARCH("séance",'📅 Calendrier'!$D32)+7,2),"") | AC9: =IF(LEFT('📅 Calendrier'!$D33,2)="S4",MID('📅 Calendrier'!$D33,SEARCH("séance",'📅 Calendrier'!$D33)+7,2),"") | AD9: =IF(LEFT('📅 Calendrier'!$D34,2)="S4",MID('📅 Calendrier'!$D34,SEARCH("séance",'📅 Calendrier'!$D34)+7,2),"") | AE9: =IF(LEFT('📅 Calendrier'!$D36,2)="S4",MID('📅 Calendrier'!$D36,SEARCH("séance",'📅 Calendrier'!$D36)+7,2),"") | AF9: =IF(LEFT('📅 Calendrier'!$D37,2)="S4",MID('📅 Calendrier'!$D37,SEARCH("séance",'📅 Calendrier'!$D37)+7,2),"") | AG9: =IF(LEFT('📅 Calendrier'!$D38,2)="S4",MID('📅 Calendrier'!$D38,SEARCH("séance",'📅 Calendrier'!$D38)+7,2),"") | AH9: =IF(LEFT('📅 Calendrier'!$D39,2)="S4",MID('📅 Calendrier'!$D39,SEARCH("séance",'📅 Calendrier'!$D39)+7,2),"") | AI9: =IF(LEFT('📅 Calendrier'!$D40,2)="S4",MID('📅 Calendrier'!$D40,SEARCH("séance",'📅 Calendrier'!$D40)+7,2),"") | AJ9: =IF(LEFT('📅 Calendrier'!$D41,2)="S4",MID('📅 Calendrier'!$D41,SEARCH("séance",'📅 Calendrier'!$D41)+7,2),"") | AK9: =IF(LEFT('📅 Calendrier'!$D42,2)="S4",MID('📅 Calendrier'!$D42,SEARCH("séance",'📅 Calendrier'!$D42)+7,2),"") | AL9: =IF(LEFT('📅 Calendrier'!$D43,2)="S4",MID('📅 Calendrier'!$D43,SEARCH("séance",'📅 Calendrier'!$D43)+7,2),"") | AM9: =IF(LEFT('📅 Calendrier'!$D44,2)="S4",MID('📅 Calendrier'!$D44,SEARCH("séance",'📅 Calendrier'!$D44)+7,2),"")
B10: S5 · Lampadaire (2) : réseau local | C10: =IF(LEFT('📅 Calendrier'!$D4,2)="S5",MID('📅 Calendrier'!$D4,SEARCH("séance",'📅 Calendrier'!$D4)+7,2),"") | D10: =IF(LEFT('📅 Calendrier'!$D5,2)="S5",MID('📅 Calendrier'!$D5,SEARCH("séance",'📅 Calendrier'!$D5)+7,2),"") | E10: =IF(LEFT('📅 Calendrier'!$D6,2)="S5",MID('📅 Calendrier'!$D6,SEARCH("séance",'📅 Calendrier'!$D6)+7,2),"") | F10: =IF(LEFT('📅 Calendrier'!$D7,2)="S5",MID('📅 Calendrier'!$D7,SEARCH("séance",'📅 Calendrier'!$D7)+7,2),"") | G10: =IF(LEFT('📅 Calendrier'!$D8,2)="S5",MID('📅 Calendrier'!$D8,SEARCH("séance",'📅 Calendrier'!$D8)+7,2),"") | H10: =IF(LEFT('📅 Calendrier'!$D9,2)="S5",MID('📅 Calendrier'!$D9,SEARCH("séance",'📅 Calendrier'!$D9)+7,2),"") | I10: =IF(LEFT('📅 Calendrier'!$D10,2)="S5",MID('📅 Calendrier'!$D10,SEARCH("séance",'📅 Calendrier'!$D10)+7,2),"") | J10: =IF(LEFT('📅 Calendrier'!$D11,2)="S5",MID('📅 Calendrier'!$D11,SEARCH("séance",'📅 Calendrier'!$D11)+7,2),"") | K10: =IF(LEFT('📅 Calendrier'!$D13,2)="S5",MID('📅 Calendrier'!$D13,SEARCH("séance",'📅 Calendrier'!$D13)+7,2),"") | L10: =IF(LEFT('📅 Calendrier'!$D14,2)="S5",MID('📅 Calendrier'!$D14,SEARCH("séance",'📅 Calendrier'!$D14)+7,2),"") | M10: =IF(LEFT('📅 Calendrier'!$D15,2)="S5",MID('📅 Calendrier'!$D15,SEARCH("séance",'📅 Calendrier'!$D15)+7,2),"") | N10: =IF(LEFT('📅 Calendrier'!$D16,2)="S5",MID('📅 Calendrier'!$D16,SEARCH("séance",'📅 Calendrier'!$D16)+7,2),"") | O10: =IF(LEFT('📅 Calendrier'!$D17,2)="S5",MID('📅 Calendrier'!$D17,SEARCH("séance",'📅 Calendrier'!$D17)+7,2),"") | P10: =IF(LEFT('📅 Calendrier'!$D18,2)="S5",MID('📅 Calendrier'!$D18,SEARCH("séance",'📅 Calendrier'!$D18)+7,2),"") | Q10: =IF(LEFT('📅 Calendrier'!$D19,2)="S5",MID('📅 Calendrier'!$D19,SEARCH("séance",'📅 Calendrier'!$D19)+7,2),"") | R10: =IF(LEFT('📅 Calendrier'!$D21,2)="S5",MID('📅 Calendrier'!$D21,SEARCH("séance",'📅 Calendrier'!$D21)+7,2),"") | S10: =IF(LEFT('📅 Calendrier'!$D22,2)="S5",MID('📅 Calendrier'!$D22,SEARCH("séance",'📅 Calendrier'!$D22)+7,2),"") | T10: =IF(LEFT('📅 Calendrier'!$D23,2)="S5",MID('📅 Calendrier'!$D23,SEARCH("séance",'📅 Calendrier'!$D23)+7,2),"") | U10: =IF(LEFT('📅 Calendrier'!$D24,2)="S5",MID('📅 Calendrier'!$D24,SEARCH("séance",'📅 Calendrier'!$D24)+7,2),"") -> 1 | V10: =IF(LEFT('📅 Calendrier'!$D25,2)="S5",MID('📅 Calendrier'!$D25,SEARCH("séance",'📅 Calendrier'!$D25)+7,2),"") | W10: =IF(LEFT('📅 Calendrier'!$D27,2)="S5",MID('📅 Calendrier'!$D27,SEARCH("séance",'📅 Calendrier'!$D27)+7,2),"") -> 2 | X10: =IF(LEFT('📅 Calendrier'!$D28,2)="S5",MID('📅 Calendrier'!$D28,SEARCH("séance",'📅 Calendrier'!$D28)+7,2),"") -> 3 | Y10: =IF(LEFT('📅 Calendrier'!$D29,2)="S5",MID('📅 Calendrier'!$D29,SEARCH("séance",'📅 Calendrier'!$D29)+7,2),"") | Z10: =IF(LEFT('📅 Calendrier'!$D30,2)="S5",MID('📅 Calendrier'!$D30,SEARCH("séance",'📅 Calendrier'!$D30)+7,2),"") | AA10: =IF(LEFT('📅 Calendrier'!$D31,2)="S5",MID('📅 Calendrier'!$D31,SEARCH("séance",'📅 Calendrier'!$D31)+7,2),"") | AB10: =IF(LEFT('📅 Calendrier'!$D32,2)="S5",MID('📅 Calendrier'!$D32,SEARCH("séance",'📅 Calendrier'!$D32)+7,2),"") | AC10: =IF(LEFT('📅 Calendrier'!$D33,2)="S5",MID('📅 Calendrier'!$D33,SEARCH("séance",'📅 Calendrier'!$D33)+7,2),"") | AD10: =IF(LEFT('📅 Calendrier'!$D34,2)="S5",MID('📅 Calendrier'!$D34,SEARCH("séance",'📅 Calendrier'!$D34)+7,2),"") | AE10: =IF(LEFT('📅 Calendrier'!$D36,2)="S5",MID('📅 Calendrier'!$D36,SEARCH("séance",'📅 Calendrier'!$D36)+7,2),"") | AF10: =IF(LEFT('📅 Calendrier'!$D37,2)="S5",MID('📅 Calendrier'!$D37,SEARCH("séance",'📅 Calendrier'!$D37)+7,2),"") | AG10: =IF(LEFT('📅 Calendrier'!$D38,2)="S5",MID('📅 Calendrier'!$D38,SEARCH("séance",'📅 Calendrier'!$D38)+7,2),"") | AH10: =IF(LEFT('📅 Calendrier'!$D39,2)="S5",MID('📅 Calendrier'!$D39,SEARCH("séance",'📅 Calendrier'!$D39)+7,2),"") | AI10: =IF(LEFT('📅 Calendrier'!$D40,2)="S5",MID('📅 Calendrier'!$D40,SEARCH("séance",'📅 Calendrier'!$D40)+7,2),"") | AJ10: =IF(LEFT('📅 Calendrier'!$D41,2)="S5",MID('📅 Calendrier'!$D41,SEARCH("séance",'📅 Calendrier'!$D41)+7,2),"") | AK10: =IF(LEFT('📅 Calendrier'!$D42,2)="S5",MID('📅 Calendrier'!$D42,SEARCH("séance",'📅 Calendrier'!$D42)+7,2),"") | AL10: =IF(LEFT('📅 Calendrier'!$D43,2)="S5",MID('📅 Calendrier'!$D43,SEARCH("séance",'📅 Calendrier'!$D43)+7,2),"") | AM10: =IF(LEFT('📅 Calendrier'!$D44,2)="S5",MID('📅 Calendrier'!$D44,SEARCH("séance",'📅 Calendrier'!$D44)+7,2),"")
B11: S6 · SOS panne | C11: =IF(LEFT('📅 Calendrier'!$D4,2)="S6",MID('📅 Calendrier'!$D4,SEARCH("séance",'📅 Calendrier'!$D4)+7,2),"") | D11: =IF(LEFT('📅 Calendrier'!$D5,2)="S6",MID('📅 Calendrier'!$D5,SEARCH("séance",'📅 Calendrier'!$D5)+7,2),"") | E11: =IF(LEFT('📅 Calendrier'!$D6,2)="S6",MID('📅 Calendrier'!$D6,SEARCH("séance",'📅 Calendrier'!$D6)+7,2),"") | F11: =IF(LEFT('📅 Calendrier'!$D7,2)="S6",MID('📅 Calendrier'!$D7,SEARCH("séance",'📅 Calendrier'!$D7)+7,2),"") | G11: =IF(LEFT('📅 Calendrier'!$D8,2)="S6",MID('📅 Calendrier'!$D8,SEARCH("séance",'📅 Calendrier'!$D8)+7,2),"") | H11: =IF(LEFT('📅 Calendrier'!$D9,2)="S6",MID('📅 Calendrier'!$D9,SEARCH("séance",'📅 Calendrier'!$D9)+7,2),"") | I11: =IF(LEFT('📅 Calendrier'!$D10,2)="S6",MID('📅 Calendrier'!$D10,SEARCH("séance",'📅 Calendrier'!$D10)+7,2),"") | J11: =IF(LEFT('📅 Calendrier'!$D11,2)="S6",MID('📅 Calendrier'!$D11,SEARCH("séance",'📅 Calendrier'!$D11)+7,2),"") | K11: =IF(LEFT('📅 Calendrier'!$D13,2)="S6",MID('📅 Calendrier'!$D13,SEARCH("séance",'📅 Calendrier'!$D13)+7,2),"") | L11: =IF(LEFT('📅 Calendrier'!$D14,2)="S6",MID('📅 Calendrier'!$D14,SEARCH("séance",'📅 Calendrier'!$D14)+7,2),"") | M11: =IF(LEFT('📅 Calendrier'!$D15,2)="S6",MID('📅 Calendrier'!$D15,SEARCH("séance",'📅 Calendrier'!$D15)+7,2),"") | N11: =IF(LEFT('📅 Calendrier'!$D16,2)="S6",MID('📅 Calendrier'!$D16,SEARCH("séance",'📅 Calendrier'!$D16)+7,2),"") | O11: =IF(LEFT('📅 Calendrier'!$D17,2)="S6",MID('📅 Calendrier'!$D17,SEARCH("séance",'📅 Calendrier'!$D17)+7,2),"") | P11: =IF(LEFT('📅 Calendrier'!$D18,2)="S6",MID('📅 Calendrier'!$D18,SEARCH("séance",'📅 Calendrier'!$D18)+7,2),"") | Q11: =IF(LEFT('📅 Calendrier'!$D19,2)="S6",MID('📅 Calendrier'!$D19,SEARCH("séance",'📅 Calendrier'!$D19)+7,2),"") | R11: =IF(LEFT('📅 Calendrier'!$D21,2)="S6",MID('📅 Calendrier'!$D21,SEARCH("séance",'📅 Calendrier'!$D21)+7,2),"") | S11: =IF(LEFT('📅 Calendrier'!$D22,2)="S6",MID('📅 Calendrier'!$D22,SEARCH("séance",'📅 Calendrier'!$D22)+7,2),"") | T11: =IF(LEFT('📅 Calendrier'!$D23,2)="S6",MID('📅 Calendrier'!$D23,SEARCH("séance",'📅 Calendrier'!$D23)+7,2),"") | U11: =IF(LEFT('📅 Calendrier'!$D24,2)="S6",MID('📅 Calendrier'!$D24,SEARCH("séance",'📅 Calendrier'!$D24)+7,2),"") | V11: =IF(LEFT('📅 Calendrier'!$D25,2)="S6",MID('📅 Calendrier'!$D25,SEARCH("séance",'📅 Calendrier'!$D25)+7,2),"") | W11: =IF(LEFT('📅 Calendrier'!$D27,2)="S6",MID('📅 Calendrier'!$D27,SEARCH("séance",'📅 Calendrier'!$D27)+7,2),"") | X11: =IF(LEFT('📅 Calendrier'!$D28,2)="S6",MID('📅 Calendrier'!$D28,SEARCH("séance",'📅 Calendrier'!$D28)+7,2),"") | Y11: =IF(LEFT('📅 Calendrier'!$D29,2)="S6",MID('📅 Calendrier'!$D29,SEARCH("séance",'📅 Calendrier'!$D29)+7,2),"") -> 1 | Z11: =IF(LEFT('📅 Calendrier'!$D30,2)="S6",MID('📅 Calendrier'!$D30,SEARCH("séance",'📅 Calendrier'!$D30)+7,2),"") -> 2 | AA11: =IF(LEFT('📅 Calendrier'!$D31,2)="S6",MID('📅 Calendrier'!$D31,SEARCH("séance",'📅 Calendrier'!$D31)+7,2),"") -> 3 | AB11: =IF(LEFT('📅 Calendrier'!$D32,2)="S6",MID('📅 Calendrier'!$D32,SEARCH("séance",'📅 Calendrier'!$D32)+7,2),"") -> 4 | AC11: =IF(LEFT('📅 Calendrier'!$D33,2)="S6",MID('📅 Calendrier'!$D33,SEARCH("séance",'📅 Calendrier'!$D33)+7,2),"") | AD11: =IF(LEFT('📅 Calendrier'!$D34,2)="S6",MID('📅 Calendrier'!$D34,SEARCH("séance",'📅 Calendrier'!$D34)+7,2),"") | AE11: =IF(LEFT('📅 Calendrier'!$D36,2)="S6",MID('📅 Calendrier'!$D36,SEARCH("séance",'📅 Calendrier'!$D36)+7,2),"") | AF11: =IF(LEFT('📅 Calendrier'!$D37,2)="S6",MID('📅 Calendrier'!$D37,SEARCH("séance",'📅 Calendrier'!$D37)+7,2),"") | AG11: =IF(LEFT('📅 Calendrier'!$D38,2)="S6",MID('📅 Calendrier'!$D38,SEARCH("séance",'📅 Calendrier'!$D38)+7,2),"") | AH11: =IF(LEFT('📅 Calendrier'!$D39,2)="S6",MID('📅 Calendrier'!$D39,SEARCH("séance",'📅 Calendrier'!$D39)+7,2),"") | AI11: =IF(LEFT('📅 Calendrier'!$D40,2)="S6",MID('📅 Calendrier'!$D40,SEARCH("séance",'📅 Calendrier'!$D40)+7,2),"") | AJ11: =IF(LEFT('📅 Calendrier'!$D41,2)="S6",MID('📅 Calendrier'!$D41,SEARCH("séance",'📅 Calendrier'!$D41)+7,2),"") | AK11: =IF(LEFT('📅 Calendrier'!$D42,2)="S6",MID('📅 Calendrier'!$D42,SEARCH("séance",'📅 Calendrier'!$D42)+7,2),"") | AL11: =IF(LEFT('📅 Calendrier'!$D43,2)="S6",MID('📅 Calendrier'!$D43,SEARCH("séance",'📅 Calendrier'!$D43)+7,2),"") | AM11: =IF(LEFT('📅 Calendrier'!$D44,2)="S6",MID('📅 Calendrier'!$D44,SEARCH("séance",'📅 Calendrier'!$D44)+7,2),"")
B12: S7 · Mini-projet | C12: =IF(LEFT('📅 Calendrier'!$D4,2)="S7",MID('📅 Calendrier'!$D4,SEARCH("séance",'📅 Calendrier'!$D4)+7,2),"") | D12: =IF(LEFT('📅 Calendrier'!$D5,2)="S7",MID('📅 Calendrier'!$D5,SEARCH("séance",'📅 Calendrier'!$D5)+7,2),"") | E12: =IF(LEFT('📅 Calendrier'!$D6,2)="S7",MID('📅 Calendrier'!$D6,SEARCH("séance",'📅 Calendrier'!$D6)+7,2),"") | F12: =IF(LEFT('📅 Calendrier'!$D7,2)="S7",MID('📅 Calendrier'!$D7,SEARCH("séance",'📅 Calendrier'!$D7)+7,2),"") | G12: =IF(LEFT('📅 Calendrier'!$D8,2)="S7",MID('📅 Calendrier'!$D8,SEARCH("séance",'📅 Calendrier'!$D8)+7,2),"") | H12: =IF(LEFT('📅 Calendrier'!$D9,2)="S7",MID('📅 Calendrier'!$D9,SEARCH("séance",'📅 Calendrier'!$D9)+7,2),"") | I12: =IF(LEFT('📅 Calendrier'!$D10,2)="S7",MID('📅 Calendrier'!$D10,SEARCH("séance",'📅 Calendrier'!$D10)+7,2),"") | J12: =IF(LEFT('📅 Calendrier'!$D11,2)="S7",MID('📅 Calendrier'!$D11,SEARCH("séance",'📅 Calendrier'!$D11)+7,2),"") | K12: =IF(LEFT('📅 Calendrier'!$D13,2)="S7",MID('📅 Calendrier'!$D13,SEARCH("séance",'📅 Calendrier'!$D13)+7,2),"") | L12: =IF(LEFT('📅 Calendrier'!$D14,2)="S7",MID('📅 Calendrier'!$D14,SEARCH("séance",'📅 Calendrier'!$D14)+7,2),"") | M12: =IF(LEFT('📅 Calendrier'!$D15,2)="S7",MID('📅 Calendrier'!$D15,SEARCH("séance",'📅 Calendrier'!$D15)+7,2),"") | N12: =IF(LEFT('📅 Calendrier'!$D16,2)="S7",MID('📅 Calendrier'!$D16,SEARCH("séance",'📅 Calendrier'!$D16)+7,2),"") | O12: =IF(LEFT('📅 Calendrier'!$D17,2)="S7",MID('📅 Calendrier'!$D17,SEARCH("séance",'📅 Calendrier'!$D17)+7,2),"") | P12: =IF(LEFT('📅 Calendrier'!$D18,2)="S7",MID('📅 Calendrier'!$D18,SEARCH("séance",'📅 Calendrier'!$D18)+7,2),"") | Q12: =IF(LEFT('📅 Calendrier'!$D19,2)="S7",MID('📅 Calendrier'!$D19,SEARCH("séance",'📅 Calendrier'!$D19)+7,2),"") | R12: =IF(LEFT('📅 Calendrier'!$D21,2)="S7",MID('📅 Calendrier'!$D21,SEARCH("séance",'📅 Calendrier'!$D21)+7,2),"") | S12: =IF(LEFT('📅 Calendrier'!$D22,2)="S7",MID('📅 Calendrier'!$D22,SEARCH("séance",'📅 Calendrier'!$D22)+7,2),"") | T12: =IF(LEFT('📅 Calendrier'!$D23,2)="S7",MID('📅 Calendrier'!$D23,SEARCH("séance",'📅 Calendrier'!$D23)+7,2),"") | U12: =IF(LEFT('📅 Calendrier'!$D24,2)="S7",MID('📅 Calendrier'!$D24,SEARCH("séance",'📅 Calendrier'!$D24)+7,2),"") | V12: =IF(LEFT('📅 Calendrier'!$D25,2)="S7",MID('📅 Calendrier'!$D25,SEARCH("séance",'📅 Calendrier'!$D25)+7,2),"") | W12: =IF(LEFT('📅 Calendrier'!$D27,2)="S7",MID('📅 Calendrier'!$D27,SEARCH("séance",'📅 Calendrier'!$D27)+7,2),"") | X12: =IF(LEFT('📅 Calendrier'!$D28,2)="S7",MID('📅 Calendrier'!$D28,SEARCH("séance",'📅 Calendrier'!$D28)+7,2),"") | Y12: =IF(LEFT('📅 Calendrier'!$D29,2)="S7",MID('📅 Calendrier'!$D29,SEARCH("séance",'📅 Calendrier'!$D29)+7,2),"") | Z12: =IF(LEFT('📅 Calendrier'!$D30,2)="S7",MID('📅 Calendrier'!$D30,SEARCH("séance",'📅 Calendrier'!$D30)+7,2),"") | AA12: =IF(LEFT('📅 Calendrier'!$D31,2)="S7",MID('📅 Calendrier'!$D31,SEARCH("séance",'📅 Calendrier'!$D31)+7,2),"") | AB12: =IF(LEFT('📅 Calendrier'!$D32,2)="S7",MID('📅 Calendrier'!$D32,SEARCH("séance",'📅 Calendrier'!$D32)+7,2),"") | AC12: =IF(LEFT('📅 Calendrier'!$D33,2)="S7",MID('📅 Calendrier'!$D33,SEARCH("séance",'📅 Calendrier'!$D33)+7,2),"") -> 1 | AD12: =IF(LEFT('📅 Calendrier'!$D34,2)="S7",MID('📅 Calendrier'!$D34,SEARCH("séance",'📅 Calendrier'!$D34)+7,2),"") | AE12: =IF(LEFT('📅 Calendrier'!$D36,2)="S7",MID('📅 Calendrier'!$D36,SEARCH("séance",'📅 Calendrier'!$D36)+7,2),"") -> 2 | AF12: =IF(LEFT('📅 Calendrier'!$D37,2)="S7",MID('📅 Calendrier'!$D37,SEARCH("séance",'📅 Calendrier'!$D37)+7,2),"") -> 3 | AG12: =IF(LEFT('📅 Calendrier'!$D38,2)="S7",MID('📅 Calendrier'!$D38,SEARCH("séance",'📅 Calendrier'!$D38)+7,2),"") -> 4 | AH12: =IF(LEFT('📅 Calendrier'!$D39,2)="S7",MID('📅 Calendrier'!$D39,SEARCH("séance",'📅 Calendrier'!$D39)+7,2),"") -> 5 | AI12: =IF(LEFT('📅 Calendrier'!$D40,2)="S7",MID('📅 Calendrier'!$D40,SEARCH("séance",'📅 Calendrier'!$D40)+7,2),"") -> 6 | AJ12: =IF(LEFT('📅 Calendrier'!$D41,2)="S7",MID('📅 Calendrier'!$D41,SEARCH("séance",'📅 Calendrier'!$D41)+7,2),"") | AK12: =IF(LEFT('📅 Calendrier'!$D42,2)="S7",MID('📅 Calendrier'!$D42,SEARCH("séance",'📅 Calendrier'!$D42)+7,2),"") | AL12: =IF(LEFT('📅 Calendrier'!$D43,2)="S7",MID('📅 Calendrier'!$D43,SEARCH("séance",'📅 Calendrier'!$D43)+7,2),"") | AM12: =IF(LEFT('📅 Calendrier'!$D44,2)="S7",MID('📅 Calendrier'!$D44,SEARCH("séance",'📅 Calendrier'!$D44)+7,2),"")
B13: ⏳ Tampons (rattrapage) | C13: =IF(LEFT('📅 Calendrier'!$D4,1)="⏳","⏳","") | D13: =IF(LEFT('📅 Calendrier'!$D5,1)="⏳","⏳","") | E13: =IF(LEFT('📅 Calendrier'!$D6,1)="⏳","⏳","") | F13: =IF(LEFT('📅 Calendrier'!$D7,1)="⏳","⏳","") | G13: =IF(LEFT('📅 Calendrier'!$D8,1)="⏳","⏳","") | H13: =IF(LEFT('📅 Calendrier'!$D9,1)="⏳","⏳","") | I13: =IF(LEFT('📅 Calendrier'!$D10,1)="⏳","⏳","") | J13: =IF(LEFT('📅 Calendrier'!$D11,1)="⏳","⏳","") -> ⏳ | K13: =IF(LEFT('📅 Calendrier'!$D13,1)="⏳","⏳","") | L13: =IF(LEFT('📅 Calendrier'!$D14,1)="⏳","⏳","") | M13: =IF(LEFT('📅 Calendrier'!$D15,1)="⏳","⏳","") | N13: =IF(LEFT('📅 Calendrier'!$D16,1)="⏳","⏳","") | O13: =IF(LEFT('📅 Calendrier'!$D17,1)="⏳","⏳","") | P13: =IF(LEFT('📅 Calendrier'!$D18,1)="⏳","⏳","") | Q13: =IF(LEFT('📅 Calendrier'!$D19,1)="⏳","⏳","") -> ⏳ | R13: =IF(LEFT('📅 Calendrier'!$D21,1)="⏳","⏳","") | S13: =IF(LEFT('📅 Calendrier'!$D22,1)="⏳","⏳","") | T13: =IF(LEFT('📅 Calendrier'!$D23,1)="⏳","⏳","") | U13: =IF(LEFT('📅 Calendrier'!$D24,1)="⏳","⏳","") | V13: =IF(LEFT('📅 Calendrier'!$D25,1)="⏳","⏳","") -> ⏳ | W13: =IF(LEFT('📅 Calendrier'!$D27,1)="⏳","⏳","") | X13: =IF(LEFT('📅 Calendrier'!$D28,1)="⏳","⏳","") | Y13: =IF(LEFT('📅 Calendrier'!$D29,1)="⏳","⏳","") | Z13: =IF(LEFT('📅 Calendrier'!$D30,1)="⏳","⏳","") | AA13: =IF(LEFT('📅 Calendrier'!$D31,1)="⏳","⏳","") | AB13: =IF(LEFT('📅 Calendrier'!$D32,1)="⏳","⏳","") | AC13: =IF(LEFT('📅 Calendrier'!$D33,1)="⏳","⏳","") | AD13: =IF(LEFT('📅 Calendrier'!$D34,1)="⏳","⏳","") -> ⏳ | AE13: =IF(LEFT('📅 Calendrier'!$D36,1)="⏳","⏳","") | AF13: =IF(LEFT('📅 Calendrier'!$D37,1)="⏳","⏳","") | AG13: =IF(LEFT('📅 Calendrier'!$D38,1)="⏳","⏳","") | AH13: =IF(LEFT('📅 Calendrier'!$D39,1)="⏳","⏳","") | AI13: =IF(LEFT('📅 Calendrier'!$D40,1)="⏳","⏳","") | AJ13: =IF(LEFT('📅 Calendrier'!$D41,1)="⏳","⏳","") -> ⏳ | AK13: =IF(LEFT('📅 Calendrier'!$D42,1)="⏳","⏳","") -> ⏳ | AL13: =IF(LEFT('📅 Calendrier'!$D43,1)="⏳","⏳","") -> ⏳ | AM13: =IF(LEFT('📅 Calendrier'!$D44,1)="⏳","⏳","") -> ⏳
B14: ⚠ Imprévus (saisis au Calendrier) | C14: =IF('📅 Calendrier'!$G4<>"","⚠","") | D14: =IF('📅 Calendrier'!$G5<>"","⚠","") | E14: =IF('📅 Calendrier'!$G6<>"","⚠","") | F14: =IF('📅 Calendrier'!$G7<>"","⚠","") | G14: =IF('📅 Calendrier'!$G8<>"","⚠","") | H14: =IF('📅 Calendrier'!$G9<>"","⚠","") | I14: =IF('📅 Calendrier'!$G10<>"","⚠","") | J14: =IF('📅 Calendrier'!$G11<>"","⚠","") | K14: =IF('📅 Calendrier'!$G13<>"","⚠","") | L14: =IF('📅 Calendrier'!$G14<>"","⚠","") | M14: =IF('📅 Calendrier'!$G15<>"","⚠","") | N14: =IF('📅 Calendrier'!$G16<>"","⚠","") | O14: =IF('📅 Calendrier'!$G17<>"","⚠","") | P14: =IF('📅 Calendrier'!$G18<>"","⚠","") | Q14: =IF('📅 Calendrier'!$G19<>"","⚠","") | R14: =IF('📅 Calendrier'!$G21<>"","⚠","") | S14: =IF('📅 Calendrier'!$G22<>"","⚠","") | T14: =IF('📅 Calendrier'!$G23<>"","⚠","") | U14: =IF('📅 Calendrier'!$G24<>"","⚠","") | V14: =IF('📅 Calendrier'!$G25<>"","⚠","") | W14: =IF('📅 Calendrier'!$G27<>"","⚠","") | X14: =IF('📅 Calendrier'!$G28<>"","⚠","") | Y14: =IF('📅 Calendrier'!$G29<>"","⚠","") | Z14: =IF('📅 Calendrier'!$G30<>"","⚠","") | AA14: =IF('📅 Calendrier'!$G31<>"","⚠","") | AB14: =IF('📅 Calendrier'!$G32<>"","⚠","") | AC14: =IF('📅 Calendrier'!$G33<>"","⚠","") | AD14: =IF('📅 Calendrier'!$G34<>"","⚠","") | AE14: =IF('📅 Calendrier'!$G36<>"","⚠","") | AF14: =IF('📅 Calendrier'!$G37<>"","⚠","") | AG14: =IF('📅 Calendrier'!$G38<>"","⚠","") | AH14: =IF('📅 Calendrier'!$G39<>"","⚠","") | AI14: =IF('📅 Calendrier'!$G40<>"","⚠","") | AJ14: =IF('📅 Calendrier'!$G41<>"","⚠","") | AK14: =IF('📅 Calendrier'!$G42<>"","⚠","") | AL14: =IF('📅 Calendrier'!$G43<>"","⚠","") | AM14: =IF('📅 Calendrier'!$G44<>"","⚠","")
B16: Une case = 1 semaine (1 séance de 1 h 30) ; le numéro = n° de séance dans la séquence. Pour insérer un imprévu : onglet 📅 Calendrier, colonne « ⚠ Imprévu ? », choisir dans le menu de la semaine concernée — la frise et la progression se recalculent immédiatement. Cliquer sur un titre de séquence ouvre son générateur.

Sheet 📚 Référentiel Cycle 4
A1: RÉFÉRENTIEL DE COMPÉTENCES — TECHNOLOGIE CYCLE 4
A2: 9 compétences × 3 niveaux (5e / 4e / 3e) — programme 2024 · vision complète du cycle pour situer la 5e
F3: ◀ Accueil
A4: Code | B4: Niveau | C4: Compétence / sous-compétence (intitulé officiel 2024) | D4: Thème | E4: Domaine(s) socle | F4: Évaluable
A5: C1 | B5: — | C5: Décrire les liens entre usages et évolutions technologiques des objets et des systèmes techniques | D5: Thème 1 : Les objets et les systèmes techniques : leurs usages et leurs interactions à découvrir et à analyser | E5: D2, D3, D4, D5 | F5: Oui
A6: 5e_C1.1 | B6: 5e | C6: Collecter, trier et analyser des données. | D6: Thème 1 | E6: D2, D4 | F6: Oui
A7: 5e_C1.2 | B7: 5e | C7: Comparer des principes techniques pour une même fonction technique. | D7: Thème 1 | E7: D2, D4 | F7: Oui
A8: 5e_C1.3 | B8: 5e | C8: Décrire le rôle des systèmes d’information dans le partage d’information. | D8: Thème 1 | E8: D2, D5 | F8: Oui
A9: 5e_C1.4 | B9: 5e | C9: Recenser des données, les identifier, les classer, les représenter, les stocker, les retrouver dans une arborescence. | D9: Thème 1 | E9: D2 | F9: Oui
A10: 5e_C1.5 | B10: 5e | C10: Identifier des règles permettant de sécuriser un environnement numérique (bases de la cybersécurité) et des règles de respect de la propriété intellectuelle. | D10: Thème 1 | E10: D3 | F10: Oui
A11: 5e_C1.6 | B11: 5e | C11: Appréhender la responsabilité de chacun dans les dérives (cyberviolence, atteinte à la vie privée, aux données personnelles, usurpation d’identité). | D11: Thème 1 | E11: D3 | F11: Oui
A12: 4e_C1.1 | B12: 4e | C12: Mettre en relation les OST avec leurs usages. | D12: Thème 1 | E12: D4, D5 | F12: Oui
A13: 4e_C1.2 | B13: 4e | C13: Identifier les avantages et les inconvénients associés aux évolutions technologiques et informatiques. | D13: Thème 1 | E13: D3, D4, D5 | F13: Oui
A14: 4e_C1.3 | B14: 4e | C14: Justifier l’évolution d’un OST pour répondre à l’évolution des besoins. | D14: Thème 1 | E14: D3, D4, D5 | F14: Oui
A15: 4e_C1.4 | B15: 4e | C15: Identifier et appliquer les règles pour un usage raisonné des objets communicants et des environnements numériques (propriété intellectuelle, identité numérique, témoins de connexion, géolocalisation). | D15: Thème 1 | E15: D1.3, D2, D3, D4 | F15: Oui
... A127: 3e_C9.2 | B127: 3e | C127: Réaliser et mettre au point un programme commandant un système réel incluant une interaction entre un humain et une machine. | D127: Thème 3 | E127: D1.3, D2, D4 | F127: Oui
A129: 114 sous-compétences listées · Source : BO n°9 du 29/02/2024 (arrêté du 22/01/2024) · codes Nathan (éd. 2024).

Sheet 📗 Référentiel 5e
A1: RÉFÉRENTIEL DE COMPÉTENCES — TECHNOLOGIE 5e
A2: Les compétences parentes C1 → C9 et leurs déclinaisons du niveau 5e — celles travaillées dans ce classeur
F3: ◀ Accueil
A4: Code | B4: Niveau | C4: Compétence / sous-compétence (intitulé officiel 2024) | D4: Thème | E4: Domaine(s) socle | F4: Évaluable
A5: C1 | B5: — | C5: Décrire les liens entre usages et évolutions technologiques des objets et des systèmes techniques | D5: Thème 1 : Les objets et les systèmes techniques : leurs usages et leurs interactions à découvrir et à analyser | E5: D2, D3, D4, D5 | F5: Oui
A6: 5e_C1.1 | B6: 5e | C6: Collecter, trier et analyser des données. | D6: Thème 1 | E6: D2, D4 | F6: Oui
A7: 5e_C1.2 | B7: 5e | C7: Comparer des principes techniques pour une même fonction technique. | D7: Thème 1 | E7: D2, D4 | F7: Oui
A8: 5e_C1.3 | B8: 5e | C8: Décrire le rôle des systèmes d’information dans le partage d’information. | D8: Thème 1 | E8: D2, D5 | F8: Oui
A9: 5e_C1.4 | B9: 5e | C9: Recenser des données, les identifier, les classer, les représenter, les stocker, les retrouver dans une arborescence. | D9: Thème 1 | E9: D2 | F9: Oui
A10: 5e_C1.5 | B10: 5e | C10: Identifier des règles permettant de sécuriser un environnement numérique (bases de la cybersécurité) et des règles de respect de la propriété intellectuelle. | D10: Thème 1 | E10: D3 | F10: Oui
A11: 5e_C1.6 | B11: 5e | C11: Appréhender la responsabilité de chacun dans les dérives (cyberviolence, atteinte à la vie privée, aux données personnelles, usurpation d’identité). | D11: Thème 1 | E11: D3 | F11: Oui
A12: C2 | B12: — | C12: Décrire les interactions entre un objet ou un système technique, son environnement et les utilisateurs | D12: Thème 1 | E12: D4, D5 | F12: Oui
A13: 5e_C2.1 | B13: 5e | C13: Faire la liste des interacteurs extérieurs d’un OST. | D13: Thème 1 | E13: D4 | F13: Oui
A14: 5e_C2.2 | B14: 5e | C14: Repérer et expliquer les choix de conception dans les domaines de l’ergonomie et de la sécurité ou en lien avec des objectifs de développement durable. | D14: Thème 1 | E14: D4, D5 | F14: Oui
A15: C3 | B15: — | C15: Caractériser et choisir un objet ou un système technique selon différents critères | D15: Thème 1 | E15: D1.3, D2, D3, D4, D5 | F15: Oui
... A51: 5e_C9.3 | B51: 5e | C51: Réaliser et mettre au point un programme simple commandant un OST. | D51: Thème 3 | E51: D1.3, D2, D4 | F51: Oui
A53: 38 sous-compétences listées · Source : BO n°9 du 29/02/2024 (arrêté du 22/01/2024) · codes Nathan (éd. 2024).

Sheet 🧭 Progression
A1: PROGRESSION ANNUELLE 5e — 2026-2027 · 7 séquences · base : Référentiel 2024 (onglet Progression 5e)
K2: ◀ Accueil
A3: N° | B3: Période | C3: Titre (support actualisé) | D3: Problématique | E3: Thème | F3: Codes 2024 | G3: Séances | H3: Répartition 🏫 / 🏠 / 🔁 | I3: Ressources en ligne (dépôt) | J3: Cahier Nathan 5e (repères) | K3: IA responsable | L3: Début (AUTO) | M3: Fin (AUTO)
A4: 1 | B4: P1 | C4: Bien démarrer : mon environnement numérique au collège | D4: Comment organiser et sécuriser mon espace de travail numérique ? | E4: Thème 1 | F4: 5e_C1.4, C1.5, C1.6 | G4: 3 | H4: Séance 1 🏫 (prise en main ENT) · 2 🔁 (arborescence : exercice en ligne à la maison) · 3 🏫 (mots de passe + bilan) | I4: 🔜 À produire (Thème 1) | J4: Prob. 3 p.23-30 (vie privée) · Point méthode 3 p.88 (arborescence) · Vers Pix D4 p.119-124 | K4: IA Thème 1 | L4: =IFERROR(INDEX('📅 Calendrier'!$A$4:$A$44,MATCH("S1 · séance 1",'📅 Calendrier'!$D$4:$D$44,0))&" ("&INDEX('📅 Calendrier'!$B$4:$B$44,MATCH("S1 · séance 1",'📅 Calendrier'!$D$4:$D$44,0))&")","⚠ hors année !") -> S01 (31/08/2026) | M4: =IFERROR(INDEX('📅 Calendrier'!$A$4:$A$44,MATCH("S1 · séance 3",'📅 Calendrier'!$D$4:$D$44,0))&" ("&INDEX('📅 Calendrier'!$B$4:$B$44,MATCH("S1 · séance 3",'📅 Calendrier'!$D$4:$D$44,0))&")","⚠ hors année !") -> S03 (14/09/2026)
A5: 2 | B5: P1 | C5: Comparer pour choisir : quel objet répond le mieux au besoin ? | D5: Comment choisir le meilleur objet technique parmi plusieurs ? | E5: Thème 1 | F5: 5e_C1.1, C1.2, C1.3, C3.1, C3.3 | G5: 4 | H5: Séances 1-2 🏫 (objets réels, tableau comparatif) · 3 🔁 (recherche doc maison) · 4 🏫 (choix argumenté + éval.) | I5: 🔜 À produire (Thème 1) | J5: Prob. 1 p.7-14 (évolution des objets) · Prob. 2 p.15-22 (choisir le bon vélo électrique) | K5: IA Thème 1 | L5: =IFERROR(INDEX('📅 Calendrier'!$A$4:$A$44,MATCH("S2 · séance 1",'📅 Calendrier'!$D$4:$D$44,0))&" ("&INDEX('📅 Calendrier'!$B$4:$B$44,MATCH("S2 · séance 1",'📅 Calendrier'!$D$4:$D$44,0))&")","⚠ hors année !") -> S04 (21/09/2026) | M5: =IFERROR(INDEX('📅 Calendrier'!$A$4:$A$44,MATCH("S2 · séance 4",'📅 Calendrier'!$D$4:$D$44,0))&" ("&INDEX('📅 Calendrier'!$B$4:$B$44,MATCH("S2 · séance 4",'📅 Calendrier'!$D$4:$D$44,0))&")","⚠ hors année !") -> S07 (12/10/2026)
A6: 3 | B6: P2 | C6: La chaîne d'énergie : comment un objet transforme-t-il l'énergie ? | D6: Comment l'énergie circule-t-elle dans un objet technique ? | E6: Thème 1 | F6: 5e_C2.1, C2.2 (Th.1) + 5e_C4.1, C4.2, C4.3 (Th.2) | G6: 4 | H6: Séances 1-2 🏫 (maquette moteur/LED) · 3 🔁 (séances 1-2 du lampadaire en ligne à la maison) · 4 🏫 (schéma-bloc + éval.) | I6: ✅ Partiel : « Lampadaire intelligent » séances 1-2 (C4.1-C4.3) · 🔜 C2.1-C2.2 (Thème 1) | J6: Prob. 6 p.45-50 (l'énergie dans un TGV) · Point méthode 6 p.91 (chaîne d'énergie) | K6: IA Th.1 + Fable | L6: =IFERROR(INDEX('📅 Calendrier'!$A$4:$A$44,MATCH("S3 · séance 1",'📅 Calendrier'!$D$4:$D$44,0))&" ("&INDEX('📅 Calendrier'!$B$4:$B$44,MATCH("S3 · séance 1",'📅 Calendrier'!$D$4:$D$44,0))&")","⚠ hors année !") -> S09 (02/11/2026) | M6: =IFERROR(INDEX('📅 Calendrier'!$A$4:$A$44,MATCH("S3 · séance 4",'📅 Calendrier'!$D$4:$D$44,0))&" ("&INDEX('📅 Calendrier'!$B$4:$B$44,MATCH("S3 · séance 4",'📅 Calendrier'!$D$4:$D$44,0))&")","⚠ hors année !") -> S12 (23/11/2026)
A7: 4 | B7: P2/P3 | C7: Le lampadaire intelligent (1) : chaîne d'information, données et premiers programmes | D7: Comment un objet capte-t-il, décide-t-il, agit-il — et comment le décrire en données ? | E7: Thème 2 | F7: 5e_C4.5, C4.6 + 5e_C6.1, C6.2, C6.3 | G7: 5 | H7: Séance 1 🔁 (simulateur maison) · 2 🏫 (données/descripteurs) · 3-4 🏫 (programme par blocs) · 5 🏠 QCM + 🏫 éval. | I7: ✅ Séquence + QCM 32 q + synthèses (C4.5-C4.6) · 🔜 Îlot 5e_C6 (Fable, même objet-fil) | J7: Prob. 4 p.31-36 (système automatisé) · Prob. 7 p.51-58 (programmer une fonctionnalité) · PM 7 p.92 | K7: Fable (Th. 2) | L7: =IFERROR(INDEX('📅 Calendrier'!$A$4:$A$44,MATCH("S4 · séance 1",'📅 Calendrier'!$D$4:$D$44,0))&" ("&INDEX('📅 Calendrier'!$B$4:$B$44,MATCH("S4 · séance 1",'📅 Calendrier'!$D$4:$D$44,0))&")","⚠ hors année !") -> S13 (30/11/2026) | M7: =IFERROR(INDEX('📅 Calendrier'!$A$4:$A$44,MATCH("S4 · séance 5",'📅 Calendrier'!$D$4:$D$44,0))&" ("&INDEX('📅 Calendrier'!$B$4:$B$44,MATCH("S4 · séance 5",'📅 Calendrier'!$D$4:$D$44,0))&")","⚠ hors année !") -> S18 (18/01/2027)
A8: 5 | B8: P3/P4 | C8: Le lampadaire intelligent (2) : le réseau local du collège | D8: Comment les informations circulent-elles entre les postes du collège ? | E8: Thème 2 | F8: 5e_C4.7, C4.8 | G8: 3 | H8: Séance 1 🏫 (jeu du courrier débranché, enveloppes réelles) · 2 🔁 (schéma actif + simulateur maison) · 3 🏠 QCM ciblé + 🏫 bilan | I8: ✅ Séquence (séances 5) + QCM (8 q ciblées C4.7-C4.8) + synthèses | J8: Point méthode 4 p.89 (adresse IP) · Vers Pix D2/D5 p.103-110, 125-128 | K8: Fable (Th. 2) | L8: =IFERROR(INDEX('📅 Calendrier'!$A$4:$A$44,MATCH("S5 · séance 1",'📅 Calendrier'!$D$4:$D$44,0))&" ("&INDEX('📅 Calendrier'!$B$4:$B$44,MATCH("S5 · séance 1",'📅 Calendrier'!$D$4:$D$44,0))&")","⚠ hors année !") -> S19 (25/01/2027) | M8: =IFERROR(INDEX('📅 Calendrier'!$A$4:$A$44,MATCH("S5 · séance 3",'📅 Calendrier'!$D$4:$D$44,0))&" ("&INDEX('📅 Calendrier'!$B$4:$B$44,MATCH("S5 · séance 3",'📅 Calendrier'!$D$4:$D$44,0))&")","⚠ hors année !") -> S22 (01/03/2027)
A9: 6 | B9: P4 | C9: SOS panne : dépanner un objet technique | D9: Comment identifier et réparer la panne d'un objet technique ? | E9: Thème 2 | F9: 5e_C5.1, C5.2, C5.3 | G9: 4 | H9: Séances 1-2 🏫 (objets à démonter, protocole) · 3 🏫 (découverte imprimante 3D) · 4 🔁 (fiche d'intervention + QCM maison) | I9: 🔜 À produire (Fable — prévu avant le 27/07 si possible, sinon après Conseil) | J9: Prob. 5 p.37-44 (réparer un sac à dos) · Point méthode 5 p.90 (imprimante 3D) | K9: Fable (Th. 2) | L9: =IFERROR(INDEX('📅 Calendrier'!$A$4:$A$44,MATCH("S6 · séance 1",'📅 Calendrier'!$D$4:$D$44,0))&" ("&INDEX('📅 Calendrier'!$B$4:$B$44,MATCH("S6 · séance 1",'📅 Calendrier'!$D$4:$D$44,0))&")","⚠ hors année !") -> S23 (08/03/2027) | M9: =IFERROR(INDEX('📅 Calendrier'!$A$4:$A$44,MATCH("S6 · séance 4",'📅 Calendrier'!$D$4:$D$44,0))&" ("&INDEX('📅 Calendrier'!$B$4:$B$44,MATCH("S6 · séance 4",'📅 Calendrier'!$D$4:$D$44,0))&")","⚠ hors année !") -> S26 (29/03/2027)
A10: 7 | B10: P4/P5 | C10: Mini-projet : concevoir et fabriquer un objet utile | D10: Comment concevoir, fabriquer et programmer un objet répondant à un besoin ? | E10: Thème 3 | F10: 5e_C7.1→C7.6, C8.1→C8.3, C9.1→C9.3 | G10: 6 | H10: Séances 1-5 🏫 (démarche de projet, prototypage) · entre séances 🏠 (recherches, croquis) · 6 🏫 revue de projet | I10: 🔜 À produire (Thème 3) | J10: Prob. 8 p.59-64 · Prob. 9 p.65-70 · Prob. 10 p.71-78 · Prob. 11 p.79-85 · PM 9/11 | K10: IA Thème 3 | L10: =IFERROR(INDEX('📅 Calendrier'!$A$4:$A$44,MATCH("S7 · séance 1",'📅 Calendrier'!$D$4:$D$44,0))&" ("&INDEX('📅 Calendrier'!$B$4:$B$44,MATCH("S7 · séance 1",'📅 Calendrier'!$D$4:$D$44,0))&")","⚠ hors année !") -> S27 (05/04/2027) | M10: =IFERROR(INDEX('📅 Calendrier'!$A$4:$A$44,MATCH("S7 · séance 6",'📅 Calendrier'!$D$4:$D$44,0))&" ("&INDEX('📅 Calendrier'!$B$4:$B$44,MATCH("S7 · séance 6",'📅 Calendrier'!$D$4:$D$44,0))&")","⚠ hors année !") -> S33 (31/05/2027)
F11: Total séances planifiées : | G11: =SUM(G4:G10) -> 29 | H11: + 7 semaines tampon = 36 semaines (voir Calendrier)
L12: Colonnes AUTO : recalculées selon les imprévus saisis dans le Calendrier.
A13: Statuts : ✅ en ligne · 🔜 à produire · 📘 cahier Nathan. Les titres « Lampadaire intelligent » actualisent les supports du référentiel initial (« Un capteur au jardin » / « Réseaux ») : mêmes codes, même objet-fil réutilisé — décision à entériner au Conseil du 28/07.

Sheet S1
A1: GÉNÉRATEUR DE SÉQUENCE 2024 — S1 · Bien démarrer : mon environnement numérique au collège
A2: Thème 1 · P1 · 3 séances de 1 h 30 · Responsable : IA Thème 1 · CANEVAS À REMPLIR par IA Thème 1 (règle : l'IA du thème est seule à modifier)
E3: ◀ Progression | F3: ◀ Accueil
A4: Problématique | B4: Comment organiser et sécuriser mon espace de travail numérique ?
A5: Situation déclenchante | B5: ⚠ À compléter par IA Thème 1 (canevas pré-rempli par Fable — codes, problématique et repères Nathan posés).
A6: Prérequis | B6: —
A7: Éléments pour la synthèse (objectifs) | B7: ⚠ À compléter par IA Thème 1 (canevas pré-rempli par Fable — codes, problématique et repères Nathan posés).
A8: Piste d'évaluation | B8: Grille de suivi personnel de fichiers + questionnaire
A9: Domaines du socle mobilisés | B9: D2, D3 (détail par code dans le tableau des compétences ci-dessous)
A10: CRCN — compétences numériques (Pix) | B10: 1.2 Gérer des données (Niv. 1-2) · 4.1 Sécuriser l'environnement (Niv. 2) · 4.2 Protéger les données personnelles (Niv. 1-2) · 5.2 Évoluer dans un environnement numérique (Niv. 1-2)
A11: Versions 🅰 / 🅱 / 🅲 | B11: ⚠ À compléter par IA Thème 1 (canevas pré-rempli par Fable — codes, problématique et repères Nathan posés).
A12: Liens EPI / parcours | B12: ⚠ À compléter par IA Thème 1 (canevas pré-rempli par Fable — codes, problématique et repères Nathan posés).
A13: Cahier Nathan 5e | B13: Prob. 3 p.23-30 (vie privée) · Point méthode 3 p.88 (arborescence) · Vers Pix D4 p.119-124
A14: Ressources en ligne | B14: 🔜 À produire (Thème 1)
A16: Compétences du programme 2024
A17: Code | B17: Intitulé officiel | C17: Domaines du socle | D17: Travaillée en | E17: Évaluation LSU
A18: 5e_C1.4 | B18: Recenser des données, les identifier, les classer, les représenter, les stocker, les retrouver dans une arborescence. | C18: D2 | D18: — | E18: → LSU
A19: 5e_C1.5 | B19: Identifier des règles permettant de sécuriser un environnement numérique (bases de la cybersécurité) et des règles de respect de la propriété intellectuelle. | C19: D3 | D19: — | E19: → LSU
A20: 5e_C1.6 | B20: Appréhender la responsabilité de chacun dans les dérives (cyberviolence, atteinte à la vie privée, aux données personnelles, usurpation d’identité). | C20: D3 | D20: — | E20: → LSU
A22: Déroulé, séance par séance — avec cahier de texte Pronote prêt à coller
A23: ■ Séance 1 — semaine S01 — — — [titre de la séance 1 — à compléter]
A24: Question directrice | B24: [question directrice]
A25: Activités & supports | B25: [activités — repères Nathan : Prob. 3 p.23-30 (vie privée) · Point méthode 3 p.88 (arborescence) · Vers Pix D4 p.119-124]
A26: Démarche / organisation | B26: [démarche]
A27: Bilan / trace écrite | B27: [trace écrite]
A28: 📋 CAHIER DE TEXTE Contenu de la séance (copier-coller Pronote) | B28: [Cahier de texte — contenu de la séance 1 : à rédiger par IA Thème 1 — phrase(s) prêtes à coller dans Pronote.]
A29: 📋 CAHIER DE TEXTE Travail à faire (copier-coller Pronote) | B29: [Cahier de texte — travail à faire : à rédiger — indiquer le support (lien en ligne ou pages Nathan), la durée estimée, et « faisable sur téléphone » si c'est le cas.]
A30: Suivi enseignant | B30: Fait le : ____________ | C30: Report / aléa / remarques :
A32: ■ Séance 2 — semaine S02 — — — [titre de la séance 2 — à compléter]
A33: Question directrice | B33: [question directrice]
A34: Activités & supports | B34: [activités — repères Nathan : Prob. 3 p.23-30 (vie privée) · Point méthode 3 p.88 (arborescence) · Vers Pix D4 p.119-124]
A35: Démarche / organisation | B35: [démarche]
A36: Bilan / trace écrite | B36: [trace écrite]
A37: 📋 CAHIER DE TEXTE Contenu de la séance (copier-coller Pronote) | B37: [Cahier de texte — contenu de la séance 2 : à rédiger par IA Thème 1 — phrase(s) prêtes à coller dans Pronote.]
A38: 📋 CAHIER DE TEXTE Travail à faire (copier-coller Pronote) | B38: [Cahier de texte — travail à faire : à rédiger — indiquer le support (lien en ligne ou pages Nathan), la durée estimée, et « faisable sur téléphone » si c'est le cas.]
A39: Suivi enseignant | B39: Fait le : ____________ | C39: Report / aléa / remarques :
A41: ■ Séance 3 — semaine S03 — — — [titre de la séance 3 — à compléter]
A42: Question directrice | B42: [question directrice]
A43: Activités & supports | B43: [activités — repères Nathan : Prob. 3 p.23-30 (vie privée) · Point méthode 3 p.88 (arborescence) · Vers Pix D4 p.119-124]
A44: Démarche / organisation | B44: [démarche]
A45: Bilan / trace écrite | B45: [trace écrite]
A46: 📋 CAHIER DE TEXTE Contenu de la séance (copier-coller Pronote) | B46: [Cahier de texte — contenu de la séance 3 : à rédiger par IA Thème 1 — phrase(s) prêtes à coller dans Pronote.]
A47: 📋 CAHIER DE TEXTE Travail à faire (copier-coller Pronote) | B47: [Cahier de texte — travail à faire : à rédiger — indiquer le support (lien en ligne ou pages Nathan), la durée estimée, et « faisable sur téléphone » si c'est le cas.]
A48: Suivi enseignant | B48: Fait le : ____________ | C48: Report / aléa / remarques :

Sheet S2
A1: GÉNÉRATEUR DE SÉQUENCE 2024 — S2 · Comparer pour choisir : quel objet répond le mieux au besoin ?
A2: Thème 1 · P1 · 4 séances de 1 h 30 · Responsable : IA Thème 1 · CANEVAS À REMPLIR par IA Thème 1 (règle : l'IA du thème est seule à modifier)
E3: ◀ Progression | F3: ◀ Accueil
A4: Problématique | B4: Comment choisir le meilleur objet technique parmi plusieurs ?
A5: Situation déclenchante | B5: ⚠ À compléter par IA Thème 1 (canevas pré-rempli par Fable — codes, problématique et repères Nathan posés).
A6: Prérequis | B6: —
A7: Éléments pour la synthèse (objectifs) | B7: ⚠ À compléter par IA Thème 1 (canevas pré-rempli par Fable — codes, problématique et repères Nathan posés).
A8: Piste d'évaluation | B8: Tableau comparatif argumenté (objets du quotidien)
A9: Domaines du socle mobilisés | B9: D2, D3, D4, D5 (détail par code dans le tableau des compétences ci-dessous)
A10: CRCN — compétences numériques (Pix) | B10: 1.1 Mener une recherche (Niv. 2) · 1.3 Traiter des données (Niv. 2 : tableau comparatif au tableur)
A11: Versions 🅰 / 🅱 / 🅲 | B11: ⚠ À compléter par IA Thème 1 (canevas pré-rempli par Fable — codes, problématique et repères Nathan posés).
A12: Liens EPI / parcours | B12: ⚠ À compléter par IA Thème 1 (canevas pré-rempli par Fable — codes, problématique et repères Nathan posés).
A13: Cahier Nathan 5e | B13: Prob. 1 p.7-14 (évolution des objets) · Prob. 2 p.15-22 (choisir le bon vélo électrique)
A14: Ressources en ligne | B14: 🔜 À produire (Thème 1)
A16: Compétences du programme 2024
A17: Code | B17: Intitulé officiel | C17: Domaines du socle | D17: Travaillée en | E17: Évaluation LSU
A18: 5e_C1.1 | B18: Collecter, trier et analyser des données. | C18: D2, D4 | D18: — | E18: → LSU
A19: 5e_C1.2 | B19: Comparer des principes techniques pour une même fonction technique. | C19: D2, D4 | D19: — | E19: → LSU
A20: 5e_C1.3 | B20: Décrire le rôle des systèmes d’information dans le partage d’information. | C20: D2, D5 | D20: — | E20: → LSU
A21: 5e_C3.1 | B21: Repérer pour un OST les matériaux, les sources et les formes d’énergies, le traitement de l’information. | C21: D2, D4 | D21: — | E21: → LSU
A22: 5e_C3.3 | B22: Choisir un OST parmi plusieurs propositions en vue de répondre à un besoin. | C22: D3, D4, D5 | D22: — | E22: → LSU
A24: Déroulé, séance par séance — avec cahier de texte Pronote prêt à coller
A25: ■ Séance 1 — semaine S04 — — — [titre de la séance 1 — à compléter]
A26: Question directrice | B26: [question directrice]
A27: Activités & supports | B27: [activités — repères Nathan : Prob. 1 p.7-14 (évolution des objets) · Prob. 2 p.15-22 (choisir le bon vélo électrique)]
A28: Démarche / organisation | B28: [démarche]
A29: Bilan / trace écrite | B29: [trace écrite]
A30: 📋 CAHIER DE TEXTE Contenu de la séance (copier-coller Pronote) | B30: [Cahier de texte — contenu de la séance 1 : à rédiger par IA Thème 1 — phrase(s) prêtes à coller dans Pronote.]
A31: 📋 CAHIER DE TEXTE Travail à faire (copier-coller Pronote) | B31: [Cahier de texte — travail à faire : à rédiger — indiquer le support (lien en ligne ou pages Nathan), la durée estimée, et « faisable sur téléphone » si c'est le cas.]
A32: Suivi enseignant | B32: Fait le : ____________ | C32: Report / aléa / remarques :
A34: ■ Séance 2 — semaine S05 — — — [titre de la séance 2 — à compléter]
A35: Question directrice | B35: [question directrice]
A36: Activités & supports | B36: [activités — repères Nathan : Prob. 1 p.7-14 (évolution des objets) · Prob. 2 p.15-22 (choisir le bon vélo électrique)]
A37: Démarche / organisation | B37: [démarche]
A38: Bilan / trace écrite | B38: [trace écrite]
A39: 📋 CAHIER DE TEXTE Contenu de la séance (copier-coller Pronote) | B39: [Cahier de texte — contenu de la séance 2 : à rédiger par IA Thème 1 — phrase(s) prêtes à coller dans Pronote.]
A40: 📋 CAHIER DE TEXTE Travail à faire (copier-coller Pronote) | B40: [Cahier de texte — travail à faire : à rédiger — indiquer le support (lien en ligne ou pages Nathan), la durée estimée, et « faisable sur téléphone » si c'est le cas.]
A41: Suivi enseignant | B41: Fait le : ____________ | C41: Report / aléa / remarques :
A43: ■ Séance 3 — semaine S06 — — — [titre de la séance 3 — à compléter]
A44: Question directrice | B44: [question directrice]
A45: Activités & supports | B45: [activités — repères Nathan : Prob. 1 p.7-14 (évolution des objets) · Prob. 2 p.15-22 (choisir le bon vélo électrique)]
A46: Démarche / organisation | B46: [démarche]
A47: Bilan / trace écrite | B47: [trace écrite]
A48: 📋 CAHIER DE TEXTE Contenu de la séance (copier-coller Pronote) | B48: [Cahier de texte — contenu de la séance 3 : à rédiger par IA Thème 1 — phrase(s) prêtes à coller dans Pronote.]
A49: 📋 CAHIER DE TEXTE Travail à faire (copier-coller Pronote) | B49: [Cahier de texte — travail à faire : à rédiger — indiquer le support (lien en ligne ou pages Nathan), la durée estimée, et « faisable sur téléphone » si c'est le cas.]
A50: Suivi enseignant | B50: Fait le : ____________ | C50: Report / aléa / remarques :
A52: ■ Séance 4 — semaine S07 — — — [titre de la séance 4 — à compléter]
A53: Question directrice | B53: [question directrice]
A54: Activités & supports | B54: [activités — repères Nathan : Prob. 1 p.7-14 (évolution des objets) · Prob. 2 p.15-22 (choisir le bon vélo électrique)]
A55: Démarche / organisation | B55: [démarche]
A56: Bilan / trace écrite | B56: [trace écrite]
A57: 📋 CAHIER DE TEXTE Contenu de la séance (copier-coller Pronote) | B57: [Cahier de texte — contenu de la séance 4 : à rédiger par IA Thème 1 — phrase(s) prêtes à coller dans Pronote.]
A58: 📋 CAHIER DE TEXTE Travail à faire (copier-coller Pronote) | B58: [Cahier de texte — travail à faire : à rédiger — indiquer le support (lien en ligne ou pages Nathan), la durée estimée, et « faisable sur téléphone » si c'est le cas.]
A59: Suivi enseignant | B59: Fait le : ____________ | C59: Report / aléa / remarques :

Sheet S3
A1: GÉNÉRATEUR DE SÉQUENCE 2024 — S3 · La chaîne d'énergie : comment un objet transforme-t-il l'énergie ?
A2: Thème 1 · P2 · 4 séances de 1 h 30 · Responsable : IA Th.1 + Fable · CANEVAS À REMPLIR par IA Th.1 + Fable (règle : l'IA du thème est seule à modifier)
E3: ◀ Progression | F3: ◀ Accueil
A4: Problématique | B4: Comment l'énergie circule-t-elle dans un objet technique ?
A5: Situation déclenchante | B5: ⚠ À compléter par IA Th.1 + Fable (canevas pré-rempli par Fable — codes, problématique et repères Nathan posés).
A6: Prérequis | B6: —
A7: Éléments pour la synthèse (objectifs) | B7: ⚠ À compléter par IA Th.1 + Fable (canevas pré-rempli par Fable — codes, problématique et repères Nathan posés).
A8: Piste d'évaluation | B8: Schéma-bloc de la chaîne d'énergie complété
A9: Domaines du socle mobilisés | B9: D1.3, D2, D4, D5 (détail par code dans le tableau des compétences ci-dessous)
A10: CRCN — compétences numériques (Pix) | B10: 1.3 Traiter des données (Niv. 1 : relevés de mesures au tableur) — séquence surtout manipulatoire
A11: Versions 🅰 / 🅱 / 🅲 | B11: ⚠ À compléter par IA Th.1 + Fable (canevas pré-rempli par Fable — codes, problématique et repères Nathan posés).
A12: Liens EPI / parcours | B12: ⚠ À compléter par IA Th.1 + Fable (canevas pré-rempli par Fable — codes, problématique et repères Nathan posés).
A13: Cahier Nathan 5e | B13: Prob. 6 p.45-50 (l'énergie dans un TGV) · Point méthode 6 p.91 (chaîne d'énergie)
A14: Ressources en ligne | B14: ✅ Partiel : « Lampadaire intelligent » séances 1-2 (C4.1-C4.3) · 🔜 C2.1-C2.2 (Thème 1)
A16: Compétences du programme 2024
A17: Code | B17: Intitulé officiel | C17: Domaines du socle | D17: Travaillée en | E17: Évaluation LSU
A18: 5e_C2.1 | B18: Faire la liste des interacteurs extérieurs d’un OST. | C18: D4 | D18: — | E18: → LSU
A19: 5e_C2.2 | B19: Repérer et expliquer les choix de conception dans les domaines de l’ergonomie et de la sécurité ou en lien avec des objectifs de développement durable. | C19: D4, D5 | D19: — | E19: → LSU
A20: 5e_C4.1 | B20: Associer des solutions techniques à une ou des fonctions techniques. | C20: D2, D4, D5 | D20: séances 1-2 lampadaire ✅ | E20: QCM ciblé → LSU
A21: 5e_C4.2 | B21: Identifier des constituants de la chaîne d’énergie d’un objet technique (l’organisation de la chaîne d’énergie étant fournie). | C21: D1.3, D2, D4 | D21: séances 1-2 lampadaire ✅ | E21: QCM ciblé → LSU
A22: 5e_C4.3 | B22: Indiquer la nature des énergies en entrée et en sortie des constituants de la chaîne d’énergie. | C22: D1.3, D4 | D22: séances 1-2 lampadaire ✅ | E22: QCM ciblé → LSU
A24: Déroulé, séance par séance — avec cahier de texte Pronote prêt à coller
A25: ■ Séance 1 — semaine S09 — — — [titre de la séance 1 — à compléter]
A26: Question directrice | B26: [question directrice]
A27: Activités & supports | B27: [activités — repères Nathan : Prob. 6 p.45-50 (l'énergie dans un TGV) · Point méthode 6 p.91 (chaîne d'énergie)]
A28: Démarche / organisation | B28: [démarche]
A29: Bilan / trace écrite | B29: [trace écrite]
A30: 📋 CAHIER DE TEXTE Contenu de la séance (copier-coller Pronote) | B30: [Cahier de texte — contenu de la séance 1 : à rédiger par IA Th.1 + Fable — phrase(s) prêtes à coller dans Pronote.]
A31: 📋 CAHIER DE TEXTE Travail à faire (copier-coller Pronote) | B31: [Cahier de texte — travail à faire : à rédiger — indiquer le support (lien en ligne ou pages Nathan), la durée estimée, et « faisable sur téléphone » si c'est le cas.]
A32: Suivi enseignant | B32: Fait le : ____________ | C32: Report / aléa / remarques :
A34: ■ Séance 2 — semaine S10 — — — [titre de la séance 2 — à compléter]
A35: Question directrice | B35: [question directrice]
A36: Activités & supports | B36: [activités — repères Nathan : Prob. 6 p.45-50 (l'énergie dans un TGV) · Point méthode 6 p.91 (chaîne d'énergie)]
A37: Démarche / organisation | B37: [démarche]
A38: Bilan / trace écrite | B38: [trace écrite]
A39: 📋 CAHIER DE TEXTE Contenu de la séance (copier-coller Pronote) | B39: [Cahier de texte — contenu de la séance 2 : à rédiger par IA Th.1 + Fable — phrase(s) prêtes à coller dans Pronote.]
A40: 📋 CAHIER DE TEXTE Travail à faire (copier-coller Pronote) | B40: [Cahier de texte — travail à faire : à rédiger — indiquer le support (lien en ligne ou pages Nathan), la durée estimée, et « faisable sur téléphone » si c'est le cas.]
A41: Suivi enseignant | B41: Fait le : ____________ | C41: Report / aléa / remarques :
A43: ■ Séance 3 — semaine S11 — — — [titre de la séance 3 — à compléter]
A44: Question directrice | B44: [question directrice]
A45: Activités & supports | B45: [activités — repères Nathan : Prob. 6 p.45-50 (l'énergie dans un TGV) · Point méthode 6 p.91 (chaîne d'énergie)]
A46: Démarche / organisation | B46: [démarche]
A47: Bilan / trace écrite | B47: [trace écrite]
A48: 📋 CAHIER DE TEXTE Contenu de la séance (copier-coller Pronote) | B48: [Cahier de texte — contenu de la séance 3 : à rédiger par IA Th.1 + Fable — phrase(s) prêtes à coller dans Pronote.]
A49: 📋 CAHIER DE TEXTE Travail à faire (copier-coller Pronote) | B49: [Cahier de texte — travail à faire : à rédiger — indiquer le support (lien en ligne ou pages Nathan), la durée estimée, et « faisable sur téléphone » si c'est le cas.]
A50: Suivi enseignant | B50: Fait le : ____________ | C50: Report / aléa / remarques :
A52: ■ Séance 4 — semaine S12 — — — [titre de la séance 4 — à compléter]
A53: Question directrice | B53: [question directrice]
A54: Activités & supports | B54: [activités — repères Nathan : Prob. 6 p.45-50 (l'énergie dans un TGV) · Point méthode 6 p.91 (chaîne d'énergie)]
A55: Démarche / organisation | B55: [démarche]
A56: Bilan / trace écrite | B56: [trace écrite]
A57: 📋 CAHIER DE TEXTE Contenu de la séance (copier-coller Pronote) | B57: [Cahier de texte — contenu de la séance 4 : à rédiger par IA Th.1 + Fable — phrase(s) prêtes à coller dans Pronote.]
A58: 📋 CAHIER DE TEXTE Travail à faire (copier-coller Pronote) | B58: [Cahier de texte — travail à faire : à rédiger — indiquer le support (lien en ligne ou pages Nathan), la durée estimée, et « faisable sur téléphone » si c'est le cas.]
A59: Suivi enseignant | B59: Fait le : ____________ | C59: Report / aléa / remarques :

Sheet S4
A1: GÉNÉRATEUR DE SÉQUENCE 2024 — S4 · Le lampadaire intelligent (1) : chaîne d'information, données et premiers programmes
A2: Thème 2 · P2/P3 · 5 séances de 1 h 30 · Responsable : Fable (Th. 2) · Séances 1-2 : ressources ✅ en ligne · séances 3-5 : îlot 5e_C6 🔜 (même objet-fil)
E3: ◀ Progression | F3: ◀ Accueil
A4: Problématique | B4: Comment un objet capte-t-il, décide-t-il, agit-il — et comment le décrire en données ?
A5: Situation déclenchante | B5: La mairie a installé des lampadaires solaires sur le parking du collège ; l'un reste allumé en plein jour, un autre ne s'allume plus. Le club techno doit expliquer comment ils « décident » et aider la mairie à les suivre à distance.
A6: Prérequis | B6: Séquence S3 (chaîne d'énergie du lampadaire, séances 1-2 en ligne déjà vues).
A7: Éléments pour la synthèse (objectifs) | B7: Chaîne d'information = ACQUÉRIR (capteurs) → TRAITER (carte + règle SI…ALORS) → COMMANDER · l'information commande l'énergie · descripteur / type / format · un programme lit des données et en produit.
A8: Piste d'évaluation | B8: Formative : vérificateurs intégrés + verrou expérientiel (simulateur). QCM 32 q (mode « compétence ciblée »). Sommative en fin de séquence (corrigé non publié).
A9: Domaines du socle mobilisés | B9: D1.3, D2, D4 (détail par code dans le tableau des compétences ci-dessous)
A10: CRCN — compétences numériques (Pix) | B10: 3.4 Programmer (Niv. 1-2 : lire, construire et modifier un programme simple) · 1.3 Traiter des données (Niv. 2 : trier et organiser la table des lampadaires)
A11: Versions 🅰 / 🅱 / 🅲 | B11: 🅰 sortie parking + maquette Grove (capteur lumière, PIR, LED — très basse tension) · 🅱 simulateur intégré à la page · 🅲 fiches papier imprimables.
A12: Liens EPI / parcours | B12: EDD : pollution lumineuse, sobriété énergétique · lien mairie/commune (usage citoyen des données).
A13: Cahier Nathan 5e | B13: Prob. 4 p.31-36 (système automatisé) · Prob. 7 p.51-58 (programmer une fonctionnalité) · PM 7 p.92
A14: Ressources en ligne | B14: ✅ Séquence + QCM 32 q + synthèses (C4.5-C4.6) · 🔜 Îlot 5e_C6 (Fable, même objet-fil)
A16: Compétences du programme 2024
A17: Code | B17: Intitulé officiel | C17: Domaines du socle | D17: Travaillée en | E17: Évaluation LSU
A18: 5e_C4.5 | B18: Identifier des constituants de la chaîne d’information d’un OST (l’organisation de la chaîne d’information étant fournie). | C18: D1.3, D2, D4 | D18: Séances 1-2 | E18: Formative (vérificateurs en ligne) + QCM ciblé → LSU
A19: 5e_C4.6 | B19: Déterminer des descripteurs permettant de décrire des objets sous forme de données en précisant leurs types et leurs formats. | C19: D1.3, D2, D4 | D19: Séance 2 | E19: Formative + QCM ciblé → LSU
A20: 5e_C6.1 | B20: Identifier les données utilisées et produites par le programme associé à une fonctionnalité d’un OST (à partir d’un programme existant). | C20: D1.3, D2, D4 | D20: Séances 3-4 | E20: 🔜 avec l'îlot 5e_C6 (même objet-fil)
A21: 5e_C6.2 | B21: Comprendre et traduire en un algorithme en langage naturel le programme associé à une fonctionnalité d’un OST. | C21: D1.3, D4 | D21: Séances 3-4 | E21: 🔜 avec l'îlot 5e_C6
A22: 5e_C6.3 | B22: Modifier les paramètres d’un programme et identifier ou évaluer ses effets en termes de fonctionnalité. | C22: D1.3, D4 | D22: Séances 4-5 | E22: 🔜 avec l'îlot 5e_C6 + évaluation sommative
A24: Déroulé, séance par séance — avec cahier de texte Pronote prêt à coller
A25: ■ Séance 1 — semaine S13 — 🔁 Hybride — La chaîne d'information du lampadaire
A26: Question directrice | B26: Comment le lampadaire « sait-il » quand s'allumer ?
A27: Activités & supports | B27: Lancement 🏫 (20 min) : situation déclenchante + hypothèses (activité en ligne). Puis activité 3 de la séquence : chaîne d'information + simulateur (jour / nuit / nuit + passage). Séquence en ligne : https://pll-process.github.io/en-ligne-pour-le-cycle-4/theme-2-structure-fonctionnement-comportement/C4-decrire-et-caracteriser-lorganisation/5e/5e_C4.1/sequence_5e_C4.1-C4.8_lampadaire_intelligent.html
A28: Démarche / organisation | B28: Investigation. En classe : vidéoprojection + binômes sur postes ; à la maison : terminer le simulateur (verrou expérientiel : les 3 situations doivent être observées).
A29: Bilan / trace écrite | B29: Schéma des deux chaînes (SVG de la séquence) collé/recopié ; règle SI nuit ET passage → pleine puissance.
A30: 📋 CAHIER DE TEXTE Contenu de la séance (copier-coller Pronote) | B30: Séquence « Le lampadaire intelligent » — Séance 1 : la chaîne d'information. Hypothèses, puis découverte du simulateur : comportements jour / nuit / nuit + passage. Trace écrite : ACQUÉRIR → TRAITER → COMMANDER ; la chaîne d'information commande la chaîne d'énergie.
A31: 📋 CAHIER DE TEXTE Travail à faire (copier-coller Pronote) | B31: Terminer l'activité 3 (simulateur du lampadaire) en ligne : https://pll-process.github.io/en-ligne-pour-le-cycle-4/theme-2-structure-fonctionnement-comportement/C4-decrire-et-caracteriser-lorganisation/5e/5e_C4.1/sequence_5e_C4.1-C4.8_lampadaire_intelligent.html — les 3 situations doivent être réellement observées (la page le vérifie). Environ 20 min, faisable sur téléphone. Aucun compte requis, le travail se sauvegarde sur l'appareil.
A32: Suivi enseignant | B32: Fait le : ____________ | C32: Report / aléa / remarques :
A34: ■ Séance 2 — semaine S14 — 🏫 En classe — Décrire les lampadaires par des données
A35: Question directrice | B35: Comment la mairie peut-elle suivre 6 lampadaires sans se déplacer ?
A36: Activités & supports | B36: Activité 4 de la séquence : table des 6 lampadaires — descripteurs, types, formats ; lire les données pour agir (L5 prioritaire, L3 batterie faible). Séquence en ligne : https://pll-process.github.io/en-ligne-pour-le-cycle-4/theme-2-structure-fonctionnement-comportement/C4-decrire-et-caracteriser-lorganisation/5e/5e_C4.1/sequence_5e_C4.1-C4.8_lampadaire_intelligent.html
A37: Démarche / organisation | B37: Résolution de problème en binômes ; correction collective avec les vérificateurs de la page.
A38: Bilan / trace écrite | B38: Définitions descripteur / type / format ; une ligne = un objet complet.
A39: 📋 CAHIER DE TEXTE Contenu de la séance (copier-coller Pronote) | B39: Séance 2 : décrire les lampadaires par des données. Descripteurs, types et formats ; lecture de la table des 6 lampadaires de la mairie pour décider des interventions. Trace écrite : descripteur / type / format.
A40: 📋 CAHIER DE TEXTE Travail à faire (copier-coller Pronote) | B40: QCM d'entraînement, mode « Compétence ciblée » 5e_C4.5 puis 5e_C4.6 (8 questions) : https://pll-process.github.io/en-ligne-pour-le-cycle-4/theme-2-structure-fonctionnement-comportement/C4-decrire-et-caracteriser-lorganisation/5e/5e_C4.1/qcm_5e_C4.1-C4.8_lampadaire_intelligent.html — corrections détaillées incluses ; refaire ses erreurs. ≈ 15 min.
A41: Suivi enseignant | B41: Fait le : ____________ | C41: Report / aléa / remarques :
A43: ■ Séance 3 — semaine S16 — 🏫 En classe — Le programme du lampadaire : lire les données (5e_C6.1)
A44: Question directrice | B44: Quelles données le programme du lampadaire utilise-t-il et produit-il ?
A45: Activités & supports | B45: Îlot 5e_C6 (🔜 en production — même objet-fil) : identifier les données du programme par blocs du lampadaire. En attendant : Nathan Prob. 4 p.31-36 (système automatisé) + Prob. 7 p.52-54.
A46: Démarche / organisation | B46: Investigation guidée ; programme par blocs vidéoprojeté.
A47: Bilan / trace écrite | B47: Données utilisées (capteurs) / données produites (ordres).
A48: 📋 CAHIER DE TEXTE Contenu de la séance (copier-coller Pronote) | B48: Séance 3 : le programme du lampadaire — quelles données entrent (capteurs), quelles données sortent (ordres à la LED). Activités du cahier Nathan p.31-36 / p.52-54.
A49: 📋 CAHIER DE TEXTE Travail à faire (copier-coller Pronote) | B49: Relire la trace écrite ; terminer l'activité du cahier Nathan commencée en classe (p.54). [Lien de la séquence en ligne 5e_C6 : sera ajouté dès sa mise en ligne.]
A50: Suivi enseignant | B50: Fait le : ____________ | C50: Report / aléa / remarques :
A52: ■ Séance 4 — semaine S17 — 🏫 En classe — Modifier une fonctionnalité (5e_C6.2, C6.3)
A53: Question directrice | B53: Comment changer le comportement du lampadaire sans le démonter ?
A54: Activités & supports | B54: Îlot 5e_C6 (🔜) : modifier un paramètre du programme par blocs (durée de la pleine puissance, seuil nuit) et tester. Nathan Prob. 7 p.55-58 (programmer l'inclinaison d'un vélo).
A55: Démarche / organisation | B55: Résolution de problème en binômes sur postes (VittaScience / Scratch).
A56: Bilan / trace écrite | B56: Modifier = changer UN paramètre puis TESTER ; on garde la version qui marche.
A57: 📋 CAHIER DE TEXTE Contenu de la séance (copier-coller Pronote) | B57: Séance 4 : modifier une fonctionnalité du programme (seuil, durée) et tester. Démarche : je modifie UN paramètre → je teste → je valide. Cahier Nathan p.55-58.
A58: 📋 CAHIER DE TEXTE Travail à faire (copier-coller Pronote) | B58: Préparer l'évaluation : refaire le QCM complet (32 questions) en mode « Parcours complet » : https://pll-process.github.io/en-ligne-pour-le-cycle-4/theme-2-structure-fonctionnement-comportement/C4-decrire-et-caracteriser-lorganisation/5e/5e_C4.1/qcm_5e_C4.1-C4.8_lampadaire_intelligent.html · relire la synthèse : https://pll-process.github.io/en-ligne-pour-le-cycle-4/theme-2-structure-fonctionnement-comportement/C4-decrire-et-caracteriser-lorganisation/5e/5e_C4.1/Synth%C3%A8ses/synthese_eleve_5e_C4.1-C4.8.html ≈ 30 min, en 2 fois si besoin (la page reprend où tu t'es arrêté).
A59: Suivi enseignant | B59: Fait le : ____________ | C59: Report / aléa / remarques :
A61: ■ Séance 5 — semaine S18 — 🏠 puis 🏫 — Bilan et évaluation de la séquence
A62: Question directrice | B62: Qu'ai-je appris — et où en suis-je, code par code ?
A63: Activités & supports | B63: Correction commentée du QCM (bilan par compétence affiché par la page) ; évaluation sommative sur table (corrigé non publié) ; auto-positionnement LSU.
A64: Démarche / organisation | B64: Bilan collectif 30 min + évaluation 45 min + retour sur les hypothèses de la séance 1.
A65: Bilan / trace écrite | B65: Synthèse élève distribuée (imprimable 1 page A4).
A66: 📋 CAHIER DE TEXTE Contenu de la séance (copier-coller Pronote) | B66: Séance 5 : bilan de la séquence « Le lampadaire intelligent » (chaîne d'information, données, programme) et évaluation. Distribution de la synthèse (aussi en ligne).
A67: 📋 CAHIER DE TEXTE Travail à faire (copier-coller Pronote) | B67: Rien à faire — la séquence est terminée. Pour réviser plus tard : le QCM reste disponible en mode « Uniquement mes erreurs ».
A68: Suivi enseignant | B68: Fait le : ____________ | C68: Report / aléa / remarques :

Sheet S5
A1: GÉNÉRATEUR DE SÉQUENCE 2024 — S5 · Le lampadaire intelligent (2) : le réseau local du collège
A2: Thème 2 · P3/P4 · 3 séances de 1 h 30 · Responsable : Fable (Th. 2) · Ressources ✅ en ligne (séquence lampadaire, séances 5-6 + QCM ciblé)
E3: ◀ Progression | F3: ◀ Accueil
A4: Problématique | B4: Comment les informations circulent-elles entre les postes du collège ?
A5: Situation déclenchante | B5: Une impression lancée depuis la salle de techno sort au CDI ; deux tablettes portent le même nom et le réseau « se trompe ». Comment le réseau du collège sait-il à qui livrer ?
A6: Prérequis | B6: Séquence S4 (chaîne d'information : le lampadaire communique déjà son état).
A7: Éléments pour la synthèse (objectifs) | B7: Composants du réseau local : terminaux, commutateur, borne Wi-Fi, serveur · liaisons filaires / sans fil · chaque terminal a un nom et une adresse UNIQUES : sans identification, pas de livraison.
A8: Piste d'évaluation | B8: Formative : jeu du courrier (act. 6 en ligne, jouable avec enveloppes réelles) ; schéma de réseau légendé ; QCM ciblé C4.7-C4.8 (8 q).
A9: Domaines du socle mobilisés | B9: D2, D4 (détail par code dans le tableau des compétences ci-dessous)
A10: CRCN — compétences numériques (Pix) | B10: 5.1 Résoudre des problèmes techniques (Niv. 1-2 : composants, connexion, identification) · 2.1 Interagir (Niv. 1-2 : règles de la communication en réseau)
A11: Versions 🅰 / 🅱 / 🅲 | B11: 🅰 jeu du courrier avec enveloppes réelles + visite de la baie de brassage du collège · 🅱 schéma actif + activités en ligne · 🅲 fiches papier.
A12: Liens EPI / parcours | B12: Vers Pix D2 (communication) et D5 (résoudre des problèmes techniques) · Point méthode Nathan 4 p.89 (adresse IP).
A13: Cahier Nathan 5e | B13: Point méthode 4 p.89 (adresse IP) · Vers Pix D2/D5 p.103-110, 125-128
A14: Ressources en ligne | B14: ✅ Séquence (séances 5) + QCM (8 q ciblées C4.7-C4.8) + synthèses
A16: Compétences du programme 2024
A17: Code | B17: Intitulé officiel | C17: Domaines du socle | D17: Travaillée en | E17: Évaluation LSU
A18: 5e_C4.7 | B18: Identifier les composants qui constituent un réseau local (terminaux, commutateurs, liaisons filaires et sans fil (WiFi)) et sa topologie. | C18: D2, D4 | D18: Séances 1-2 | E18: Formative + QCM ciblé → LSU
A19: 5e_C4.8 | B19: Justifier la nécessité d’identifier les terminaux pour communiquer sur un réseau local (activité débranchée et vérification par un outil de simulation). | C19: D2, D4 | D19: Séances 1-3 | E19: Formative (jeu du courrier) + QCM ciblé → LSU
A21: Déroulé, séance par séance — avec cahier de texte Pronote prêt à coller
A22: ■ Séance 1 — semaine S19 — 🏫 En classe — Le jeu du courrier : pourquoi s'identifier ?
A23: Question directrice | B23: Que se passe-t-il si deux terminaux portent le même nom ?
A24: Activités & supports | B24: Jeu du courrier débranché (version 🅰 : enveloppes réelles, élèves-facteurs) puis vérification sur l'activité 6 en ligne : conflit TABLETTE-07, message sans destinataire. Séquence en ligne : https://pll-process.github.io/en-ligne-pour-le-cycle-4/theme-2-structure-fonctionnement-comportement/C4-decrire-et-caracteriser-lorganisation/5e/5e_C4.1/sequence_5e_C4.1-C4.8_lampadaire_intelligent.html
A25: Démarche / organisation | B25: Activité débranchée collective (30 min) + correction sur la page (le programme de 5e prescrit exactement cela : activité débranchée + vérification par simulation).
A26: Bilan / trace écrite | B26: Un nom et une adresse UNIQUES par terminal — comme une lettre : sans destinataire unique, pas de livraison.
A27: 📋 CAHIER DE TEXTE Contenu de la séance (copier-coller Pronote) | B27: Séquence « Le réseau du collège » — Séance 1 : jeu du courrier (activité débranchée). Conflit de noms, message sans destinataire. Règle : chaque terminal du réseau doit être identifié de façon unique.
A28: 📋 CAHIER DE TEXTE Travail à faire (copier-coller Pronote) | B28: Refaire l'activité 6 (jeu du courrier) en ligne pour vérifier ta règle : https://pll-process.github.io/en-ligne-pour-le-cycle-4/theme-2-structure-fonctionnement-comportement/C4-decrire-et-caracteriser-lorganisation/5e/5e_C4.1/sequence_5e_C4.1-C4.8_lampadaire_intelligent.html ≈ 10 min.
A29: Suivi enseignant | B29: Fait le : ____________ | C29: Report / aléa / remarques :
A31: ■ Séance 2 — semaine S21 — 🔁 Hybride — Les composants du réseau local
A32: Question directrice | B32: Quel chemin suit mon fichier quand j'imprime au CDI ?
A33: Activités & supports | B33: Activité 5 : schéma du réseau du collège (terminaux, commutateur, borne Wi-Fi, serveur, liaisons filaires/sans fil) ; si possible, visite de la salle info / baie de brassage. Séquence en ligne : https://pll-process.github.io/en-ligne-pour-le-cycle-4/theme-2-structure-fonctionnement-comportement/C4-decrire-et-caracteriser-lorganisation/5e/5e_C4.1/sequence_5e_C4.1-C4.8_lampadaire_intelligent.html
A34: Démarche / organisation | B34: Investigation ; repérage des équipements RÉELS du collège puis schéma actif en ligne.
A35: Bilan / trace écrite | B35: Schéma de réseau local légendé (évaluation-repère du référentiel).
A36: 📋 CAHIER DE TEXTE Contenu de la séance (copier-coller Pronote) | B36: Séance 2 : les composants du réseau local du collège — terminaux, commutateur, borne Wi-Fi, serveur ; liaisons filaires et sans fil. Schéma légendé dans le cahier.
A37: 📋 CAHIER DE TEXTE Travail à faire (copier-coller Pronote) | B37: Terminer l'activité 5 en ligne (schéma du réseau) : https://pll-process.github.io/en-ligne-pour-le-cycle-4/theme-2-structure-fonctionnement-comportement/C4-decrire-et-caracteriser-lorganisation/5e/5e_C4.1/sequence_5e_C4.1-C4.8_lampadaire_intelligent.html puis QCM mode « Compétence ciblée » 5e_C4.7 : https://pll-process.github.io/en-ligne-pour-le-cycle-4/theme-2-structure-fonctionnement-comportement/C4-decrire-et-caracteriser-lorganisation/5e/5e_C4.1/qcm_5e_C4.1-C4.8_lampadaire_intelligent.html ≈ 20 min.
A38: Suivi enseignant | B38: Fait le : ____________ | C38: Report / aléa / remarques :
A40: ■ Séance 3 — semaine S22 — 🏠 puis 🏫 — Bilan réseau + évaluation
A41: Question directrice | B41: Où en suis-je sur C4.7 et C4.8 ?
A42: Activités & supports | B42: Correction du QCM ciblé C4.7-C4.8 fait à la maison ; évaluation courte (schéma à légender + 2 questions d'identification) ; ouverture : et entre deux réseaux ? (Internet — vu en 4e/3e).
A43: Démarche / organisation | B43: Bilan collectif + évaluation 30 min.
A44: Bilan / trace écrite | B44: Synthèse (partie réseau) distribuée.
A45: 📋 CAHIER DE TEXTE Contenu de la séance (copier-coller Pronote) | B45: Séance 3 : bilan de la mini-séquence réseau et évaluation (schéma du réseau local + identification des terminaux).
A46: 📋 CAHIER DE TEXTE Travail à faire (copier-coller Pronote) | B46: Fait avant la séance : QCM mode « Compétence ciblée » 5e_C4.8 : https://pll-process.github.io/en-ligne-pour-le-cycle-4/theme-2-structure-fonctionnement-comportement/C4-decrire-et-caracteriser-lorganisation/5e/5e_C4.1/qcm_5e_C4.1-C4.8_lampadaire_intelligent.html ≈ 10 min. Après la séance : rien — pour réviser, mode « Uniquement mes erreurs ».
A47: Suivi enseignant | B47: Fait le : ____________ | C47: Report / aléa / remarques :

Sheet S6
A1: GÉNÉRATEUR DE SÉQUENCE 2024 — S6 · SOS panne : dépanner un objet technique
A2: Thème 2 · P4 · 4 séances de 1 h 30 · Responsable : Fable (Th. 2) · Ressources en ligne 🔜 (Fable) — repères Nathan posés, cahier de texte pré-rédigé à ajuster
E3: ◀ Progression | F3: ◀ Accueil
A4: Problématique | B4: Comment identifier et réparer la panne d'un objet technique ?
A5: Situation déclenchante | B5: Le sac à dos de la vie scolaire, la souris de la salle info, la trottinette d'un élève : trois objets en panne. Jeter… ou réparer ? (Ouverture EDD : économiser les ressources.)
A6: Prérequis | B6: S2 (observation d'objets réels), S3 (constituants).
A7: Éléments pour la synthèse (objectifs) | B7: Repérer VISUELLEMENT une pièce défectueuse · réparer en suivant un protocole FOURNI · découvrir les procédés d'un atelier de fabrication (imprimante 3D).
A8: Piste d'évaluation | B8: Fiche d'intervention technicien complétée (évaluation-repère du référentiel) ; QCM 🔜 avec la séquence en ligne.
A9: Domaines du socle mobilisés | B9: D1.3, D2, D3, D4, D5 (détail par code dans le tableau des compétences ci-dessous)
A10: CRCN — compétences numériques (Pix) | B10: 5.1 Résoudre des problèmes techniques (Niv. 1 : identifier un problème simple) — séquence essentiellement manipulatoire
A11: Versions 🅰 / 🅱 / 🅲 | B11: 🅰 objets réels à démonter + visite atelier/imprimante 3D · 🅱 simulateur de diagnostic en ligne (🔜, sur le modèle 3e « SOS station ») · 🅲 fiches papier Nathan.
A12: Liens EPI / parcours | B12: EDD (réparer plutôt que jeter, indice de réparabilité) · parcours Avenir (métiers de la maintenance).
A13: Cahier Nathan 5e | B13: Prob. 5 p.37-44 (réparer un sac à dos) · Point méthode 5 p.90 (imprimante 3D)
A14: Ressources en ligne | B14: 🔜 À produire (Fable — prévu avant le 27/07 si possible, sinon après Conseil)
A16: Compétences du programme 2024
A17: Code | B17: Intitulé officiel | C17: Domaines du socle | D17: Travaillée en | E17: Évaluation LSU
A18: 5e_C5.1 | B18: Repérer visuellement une pièce défectueuse. | C18: D1.3, D2, D4 | D18: Séances 1-2 | E18: Formative → LSU
A19: 5e_C5.2 | B19: Réaliser une réparation en suivant un protocole fourni. | C19: D2, D3, D4 | D19: Séances 2-3 | E19: Formative (protocole suivi) → LSU
A20: 5e_C5.3 | B20: Découvrir les procédés de réalisation présents dans un atelier de fabrication collaboratif. | C20: D2, D3, D4, D5 | D20: Séance 3 | E20: Découverte (atelier de fabrication) → LSU
A22: Déroulé, séance par séance — avec cahier de texte Pronote prêt à coller
A23: ■ Séance 1 — semaine S23 — 🏫 En classe — Observer pour diagnostiquer (5e_C5.1)
A24: Question directrice | B24: Comment repérer À L'ŒIL la pièce défectueuse ?
A25: Activités & supports | B25: Ateliers tournants : 3 objets en panne « visible » (couture, câble, pièce cassée). Nathan Prob. 5 p.37-40. [Séquence en ligne 🔜 : simulateur de diagnostic 5e.]
A26: Démarche / organisation | B26: Résolution de problème en îlots ; fiche d'observation.
A27: Bilan / trace écrite | B27: Démarche : observer → localiser → nommer la pièce défectueuse.
A28: 📋 CAHIER DE TEXTE Contenu de la séance (copier-coller Pronote) | B28: Séquence « SOS panne » — Séance 1 : repérer visuellement une pièce défectueuse (3 objets étudiés en îlots). Fiche d'observation complétée.
A29: 📋 CAHIER DE TEXTE Travail à faire (copier-coller Pronote) | B29: Cahier Nathan p.38-39 : terminer l'activité d'observation. [Lien séquence en ligne : à ajouter dès mise en ligne.]
A30: Suivi enseignant | B30: Fait le : ____________ | C30: Report / aléa / remarques :
A32: ■ Séance 2 — semaine S24 — 🏫 En classe — Réparer avec un protocole (5e_C5.2)
A33: Question directrice | B33: Comment réparer SANS improviser ?
A34: Activités & supports | B34: Réparation guidée par protocole fourni (sac à dos Nathan p.44 / objet réel du collège). Sécurité outillage.
A35: Démarche / organisation | B35: Binômes, protocole pas à pas, vérification à chaque étape.
A36: Bilan / trace écrite | B36: Un protocole garantit le résultat et la sécurité ; on teste APRÈS la réparation.
A37: 📋 CAHIER DE TEXTE Contenu de la séance (copier-coller Pronote) | B37: Séance 2 : réparer en suivant un protocole fourni (démarche de réparation du sac à dos). Test de la réparation.
A38: 📋 CAHIER DE TEXTE Travail à faire (copier-coller Pronote) | B38: Compléter la fiche d'intervention (partie « opérations effectuées »). ≈ 10 min.
A39: Suivi enseignant | B39: Fait le : ____________ | C39: Report / aléa / remarques :
A41: ■ Séance 3 — semaine S25 — 🏫 En classe — L'atelier de fabrication (5e_C5.3)
A42: Question directrice | B42: Et si la pièce n'existe plus ? — découverte de l'impression 3D
A43: Activités & supports | B43: Découverte de l'imprimante 3D du collège (Nathan Point méthode 5 p.90) : du modèle à la pièce. Démonstration d'impression.
A44: Démarche / organisation | B44: Investigation ; observation d'une impression lancée en début d'heure.
A45: Bilan / trace écrite | B45: Procédés d'un atelier de fabrication : imprimer, découper, assembler.
A46: 📋 CAHIER DE TEXTE Contenu de la séance (copier-coller Pronote) | B46: Séance 3 : découverte de l'atelier de fabrication — l'imprimante 3D, du modèle numérique à la pièce réelle. Nathan p.90.
A47: 📋 CAHIER DE TEXTE Travail à faire (copier-coller Pronote) | B47: QCM de la séquence en ligne [🔜 lien à ajouter] OU Nathan « Je fais le bilan » p.43. ≈ 15 min.
A48: Suivi enseignant | B48: Fait le : ____________ | C48: Report / aléa / remarques :
A50: ■ Séance 4 — semaine S26 — 🏠 puis 🏫 — Bilan + fiche d'intervention notée
A51: Question directrice | B51: Suis-je capable de remplir une fiche d'intervention complète ?
A52: Activités & supports | B52: Évaluation : fiche d'intervention technicien sur un cas nouveau ; bilan de séquence.
A53: Démarche / organisation | B53: Individuel 45 min + correction collective.
A54: Bilan / trace écrite | B54: Synthèse distribuée.
A55: 📋 CAHIER DE TEXTE Contenu de la séance (copier-coller Pronote) | B55: Séance 4 : évaluation — fiche d'intervention technicien sur un nouveau cas de panne ; bilan de la séquence SOS panne.
A56: 📋 CAHIER DE TEXTE Travail à faire (copier-coller Pronote) | B56: Fait avant la séance : relire la fiche d'intervention type et le bilan Nathan p.43. Après : rien.
A57: Suivi enseignant | B57: Fait le : ____________ | C57: Report / aléa / remarques :

Sheet S7
A1: GÉNÉRATEUR DE SÉQUENCE 2024 — S7 · Mini-projet : concevoir et fabriquer un objet utile
A2: Thème 3 · P4/P5 · 6 séances de 1 h 30 · Responsable : IA Thème 3 · CANEVAS À REMPLIR par IA Thème 3 (règle : l'IA du thème est seule à modifier)
E3: ◀ Progression | F3: ◀ Accueil
A4: Problématique | B4: Comment concevoir, fabriquer et programmer un objet répondant à un besoin ?
A5: Situation déclenchante | B5: ⚠ À compléter par IA Thème 3 (canevas pré-rempli par Fable — codes, problématique et repères Nathan posés).
A6: Prérequis | B6: —
A7: Éléments pour la synthèse (objectifs) | B7: ⚠ À compléter par IA Thème 3 (canevas pré-rempli par Fable — codes, problématique et repères Nathan posés).
A8: Piste d'évaluation | B8: Revue de projet + prototype fonctionnel
A9: Domaines du socle mobilisés | B9: D1.3, D2, D3, D4, D5 (détail par code dans le tableau des compétences ci-dessous)
A10: CRCN — compétences numériques (Pix) | B10: 3.4 Programmer (Niv. 2) · 2.3 Collaborer (Niv. 1-2 : coproduction du projet) · 3.2 Documents visuels (Niv. 1 : photos du prototype)
A11: Versions 🅰 / 🅱 / 🅲 | B11: ⚠ À compléter par IA Thème 3 (canevas pré-rempli par Fable — codes, problématique et repères Nathan posés).
A12: Liens EPI / parcours | B12: ⚠ À compléter par IA Thème 3 (canevas pré-rempli par Fable — codes, problématique et repères Nathan posés).
A13: Cahier Nathan 5e | B13: Prob. 8 p.59-64 · Prob. 9 p.65-70 · Prob. 10 p.71-78 · Prob. 11 p.79-85 · PM 9/11
A14: Ressources en ligne | B14: 🔜 À produire (Thème 3)
A16: Compétences du programme 2024
A17: Code | B17: Intitulé officiel | C17: Domaines du socle | D17: Travaillée en | E17: Évaluation LSU
A18: 5e_C7.1 | B18: Suivre un processus de conception et de réalisation dans une durée, avec des tâches identifiées. | C18: D2, D4, D5 | D18: — | E18: → LSU
A19: 5e_C7.2 | B19: Fabriquer une solution pour améliorer un OST existant. | C19: D2, D3, D4 | D19: — | E19: → LSU
A20: 5e_C7.3 | B20: Choisir un matériau parmi plusieurs proposés en fonction de leurs caractéristiques. | C20: D3, D4, D5 | D20: — | E20: → LSU
A21: 5e_C7.4 | B21: Choisir une source d’énergie parmi plusieurs proposées et une forme d’énergie possible. | C21: D3, D4, D5 | D21: — | E21: → LSU
A22: 5e_C7.5 | B22: Assembler les constituants fournis pour réaliser un prototype. | C22: D2, D3, D4 | D22: — | E22: → LSU
A23: 5e_C7.6 | B23: Mettre en œuvre les moyens pour réaliser une forme selon une procédure fournie. | C23: D2, D3, D4 | D23: — | E23: → LSU
A24: 5e_C8.1 | B24: Utiliser une simulation fournie pour valider la tenue mécanique d’un matériau. | C24: D1.3, D2, D4 | D24: — | E24: → LSU
A25: 5e_C8.2 | B25: Mettre en œuvre un protocole de test fourni pour valider la tenue mécanique d’un matériau. | C25: D1.3, D2, D3, D4 | D25: — | E25: → LSU
A26: 5e_C8.3 | B26: Vérifier le comportement et les performances d’un objet technique en suivant un protocole fourni. | C26: D1.3, D2, D4, D5 | D26: — | E26: → LSU
A27: 5e_C9.1 | B27: Analyser un programme simple fourni et tester s’il répond au besoin ou au problème posé. | C27: D1.3, D2, D4 | D27: — | E27: → LSU
A28: 5e_C9.2 | B28: Modifier un programme fourni pour répondre au besoin ou à un problème posé. | C28: D1.3, D2, D4 | D28: — | E28: → LSU
A29: 5e_C9.3 | B29: Réaliser et mettre au point un programme simple commandant un OST. | C29: D1.3, D2, D4 | D29: — | E29: → LSU
A31: Déroulé, séance par séance — avec cahier de texte Pronote prêt à coller
A32: ■ Séance 1 — semaine S27 — — — [titre de la séance 1 — à compléter]
A33: Question directrice | B33: [question directrice]
A34: Activités & supports | B34: [activités — repères Nathan : Prob. 8 p.59-64 · Prob. 9 p.65-70 · Prob. 10 p.71-78 · Prob. 11 p.79-85 · PM 9/11]
A35: Démarche / organisation | B35: [démarche]
A36: Bilan / trace écrite | B36: [trace écrite]
A37: 📋 CAHIER DE TEXTE Contenu de la séance (copier-coller Pronote) | B37: [Cahier de texte — contenu de la séance 1 : à rédiger par IA Thème 3 — phrase(s) prêtes à coller dans Pronote.]
A38: 📋 CAHIER DE TEXTE Travail à faire (copier-coller Pronote) | B38: [Cahier de texte — travail à faire : à rédiger — indiquer le support (lien en ligne ou pages Nathan), la durée estimée, et « faisable sur téléphone » si c'est le cas.]
A39: Suivi enseignant | B39: Fait le : ____________ | C39: Report / aléa / remarques :
A41: ■ Séance 2 — semaine S29 — — — [titre de la séance 2 — à compléter]
A42: Question directrice | B42: [question directrice]
A43: Activités & supports | B43: [activités — repères Nathan : Prob. 8 p.59-64 · Prob. 9 p.65-70 · Prob. 10 p.71-78 · Prob. 11 p.79-85 · PM 9/11]
A44: Démarche / organisation | B44: [démarche]
A45: Bilan / trace écrite | B45: [trace écrite]
A46: 📋 CAHIER DE TEXTE Contenu de la séance (copier-coller Pronote) | B46: [Cahier de texte — contenu de la séance 2 : à rédiger par IA Thème 3 — phrase(s) prêtes à coller dans Pronote.]
A47: 📋 CAHIER DE TEXTE Travail à faire (copier-coller Pronote) | B47: [Cahier de texte — travail à faire : à rédiger — indiquer le support (lien en ligne ou pages Nathan), la durée estimée, et « faisable sur téléphone » si c'est le cas.]
A48: Suivi enseignant | B48: Fait le : ____________ | C48: Report / aléa / remarques :
A50: ■ Séance 3 — semaine S30 — — — [titre de la séance 3 — à compléter]
A51: Question directrice | B51: [question directrice]
A52: Activités & supports | B52: [activités — repères Nathan : Prob. 8 p.59-64 · Prob. 9 p.65-70 · Prob. 10 p.71-78 · Prob. 11 p.79-85 · PM 9/11]
A53: Démarche / organisation | B53: [démarche]
A54: Bilan / trace écrite | B54: [trace écrite]
A55: 📋 CAHIER DE TEXTE Contenu de la séance (copier-coller Pronote) | B55: [Cahier de texte — contenu de la séance 3 : à rédiger par IA Thème 3 — phrase(s) prêtes à coller dans Pronote.]
A56: 📋 CAHIER DE TEXTE Travail à faire (copier-coller Pronote) | B56: [Cahier de texte — travail à faire : à rédiger — indiquer le support (lien en ligne ou pages Nathan), la durée estimée, et « faisable sur téléphone » si c'est le cas.]
A57: Suivi enseignant | B57: Fait le : ____________ | C57: Report / aléa / remarques :
A59: ■ Séance 4 — semaine S31 — — — [titre de la séance 4 — à compléter]
A60: Question directrice | B60: [question directrice]
A61: Activités & supports | B61: [activités — repères Nathan : Prob. 8 p.59-64 · Prob. 9 p.65-70 · Prob. 10 p.71-78 · Prob. 11 p.79-85 · PM 9/11]
A62: Démarche / organisation | B62: [démarche]
A63: Bilan / trace écrite | B63: [trace écrite]
A64: 📋 CAHIER DE TEXTE Contenu de la séance (copier-coller Pronote) | B64: [Cahier de texte — contenu de la séance 4 : à rédiger par IA Thème 3 — phrase(s) prêtes à coller dans Pronote.]
A65: 📋 CAHIER DE TEXTE Travail à faire (copier-coller Pronote) | B65: [Cahier de texte — travail à faire : à rédiger — indiquer le support (lien en ligne ou pages Nathan), la durée estimée, et « faisable sur téléphone » si c'est le cas.]
A66: Suivi enseignant | B66: Fait le : ____________ | C66: Report / aléa / remarques :
A68: ■ Séance 5 — semaine S32 — — — [titre de la séance 5 — à compléter]
A69: Question directrice | B69: [question directrice]
A70: Activités & supports | B70: [activités — repères Nathan : Prob. 8 p.59-64 · Prob. 9 p.65-70 · Prob. 10 p.71-78 · Prob. 11 p.79-85 · PM 9/11]
A71: Démarche / organisation | B71: [démarche]
A72: Bilan / trace écrite | B72: [trace écrite]
A73: 📋 CAHIER DE TEXTE Contenu de la séance (copier-coller Pronote) | B73: [Cahier de texte — contenu de la séance 5 : à rédiger par IA Thème 3 — phrase(s) prêtes à coller dans Pronote.]
A74: 📋 CAHIER DE TEXTE Travail à faire (copier-coller Pronote) | B74: [Cahier de texte — travail à faire : à rédiger — indiquer le support (lien en ligne ou pages Nathan), la durée estimée, et « faisable sur téléphone » si c'est le cas.]
A75: Suivi enseignant | B75: Fait le : ____________ | C75: Report / aléa / remarques :
A77: ■ Séance 6 — semaine S33 — — — [titre de la séance 6 — à compléter]
A78: Question directrice | B78: [question directrice]
A79: Activités & supports | B79: [activités — repères Nathan : Prob. 8 p.59-64 · Prob. 9 p.65-70 · Prob. 10 p.71-78 · Prob. 11 p.79-85 · PM 9/11]
A80: Démarche / organisation | B80: [démarche]
A81: Bilan / trace écrite | B81: [trace écrite]
A82: 📋 CAHIER DE TEXTE Contenu de la séance (copier-coller Pronote) | B82: [Cahier de texte — contenu de la séance 6 : à rédiger par IA Thème 3 — phrase(s) prêtes à coller dans Pronote.]
A83: 📋 CAHIER DE TEXTE Travail à faire (copier-coller Pronote) | B83: [Cahier de texte — travail à faire : à rédiger — indiquer le support (lien en ligne ou pages Nathan), la durée estimée, et « faisable sur téléphone » si c'est le cas.]
A84: Suivi enseignant | B84: Fait le : ____________ | C84: Report / aléa / remarques :

Sheet ⚙ Moteur
A1: ⚙ MOTEUR DE LA PROGRESSION — ordre officiel des créneaux
A2: Ne modifier cet onglet qu'en Conseil. Le calendrier place ces 37 créneaux, dans l'ordre, sur les semaines SANS imprévu. Marquer un imprévu dans le Calendrier (colonne ⚠) décale automatiquement tout ce qui suit ; la réserve de fin d'année absorbe le décalage.
A4: N° | B4: Créneau
A5: 1 | B5: S1 · séance 1
A6: 2 | B6: S1 · séance 2
A7: 3 | B7: S1 · séance 3
A8: 4 | B8: S2 · séance 1
A9: 5 | B9: S2 · séance 2
A10: 6 | B10: S2 · séance 3
A11: 7 | B11: S2 · séance 4
A12: 8 | B12: ⏳ TAMPON P1 — rattrapage / remédiation
A13: 9 | B13: S3 · séance 1
A14: 10 | B14: S3 · séance 2
A15: 11 | B15: S3 · séance 3
A16: 12 | B16: S3 · séance 4
... A41: 37 | B41: ⏳ TAMPON P5 — réserve d (fin des cours)
