Workbook

Sheet 🏠 Accueil
A1: TECHNOLOGIE 4e Progression annuelle 2026-2027 · Académie de Martinique
A5: Programme 2024 (BO n°9 du 29/02/2024) · 1 h 30 / semaine · cahier Nathan 4e (éd. 2024) · ressources en ligne du dépôt « En ligne pour le cycle 4 »
B7: 📊 L'année en un coup d'œil
B8: 37 | D8: ='🧭 Progression'!G11 | F8: 9
B9: Semaines de cours | D9: Séances planifiées | F9: Semaines tampon (aléas)
B11: 7 | D11: 38 (+C4.3 réintégré) | F11: 6 QCM ✅ · séquences 🔜
B12: Séquences | D12: Codes 4e travaillés | F12: Ressources en ligne
B14: 🧭 Naviguer dans le classeur (cliquer)
B15: ▸ 📅 Calendrier | C15: 37 semaines, vacances, fériés, tampons, imprévus | E15: ▸ 🗓 Frise de l'année | F15: les 7 séquences posées sur l'année (vue gantt)
B16: ▸ 📚 Référentiel Cycle 4 | C16: C1 → C9 : les 114 sous-compétences du cycle | E16: ▸ 📗 Référentiel 4e | F16: les 38 sous-compétences du niveau
B17: ▸ 🧭 Progression | C17: les 7 séquences : codes, répartition 🏫🏠🔁, ressources | E17: ▸ S1 | F17: Objets qui évoluent — IA Thème 1 (canevas)
B18: ▸ S2 | C18: Identité numérique — IA Thème 1 (canevas) | E18: ▸ S3 | F18: Ergonomie et choix argumenté — IA Thème 1 (canevas)
B19: ▸ S4 | C19: Jardin connecté : chaînes — Fable (pré-rempli, QCM ✅) | E19: ▸ S5 | F19: Objets connectés en réseau — Fable (pré-rempli, QCM ✅)
B20: ▸ S6 | C20: Réparer sans notice (+C4.3) — Fable (pré-rempli) | E20: ▸ S7 | F20: Projet nouvelle fonction — IA Thème 3 (canevas)
B22: 📖 Mode d'emploi express
B23: 🏫 / 🏠 / 🔁 | C23: En classe (matériel, collectif, évaluations) · À la maison (QCM, synthèses, simulateurs — corrections intégrées, faisables sur téléphone) · Hybride/classe inversée.
B24: ⏳ Tampons | C24: 9 semaines NON planifiées absorbent les aléas. Moteur automatique : colonne « ⚠ Imprévu ? » du Calendrier (ou la grande fenêtre de la version macros) — toutes les séances se décalent, frise et progression se recalculent. Alerte 🛑 au-delà de 9 imprévus.
B25: 📋 Cahier de texte | C25: Blocs jaunes prêts pour Pronote dans chaque générateur : un clic sur le libellé les copie (version macros).
B26: ✅ 🔜 📘 | C26: Ressource en ligne · à produire · cahier Nathan. Chaque IA de thème remplit SES générateurs — canevas 5e validé par Pascal le 23/07.
B27: ⚠ Correctif C4.3 | C27: Le référentiel initial ne rattachait 4e_C4.3 (forme d'une pièce ↔ procédé) à aucune séquence : réintégré dans S6 « Réparer sans notice ». À entériner au Conseil du 28/07.
B28: 📆 Calendrier | C28: Martinique 2026-2027 : rentrée mar. 1/09 · Toussaint 20/10→3/11 · Noël 19/12→4/01 · Carnaval 6→22/02 · Pâques 20/04→3/05 · fin 3/07. À confirmer sur ac-martinique.fr.
B30: Classeur généré par Fable (IA du Thème 2) — canevas 5e validé par Pascal · dépôt : pll-process.github.io/en-ligne-pour-le-cycle-4

Sheet 📅 Calendrier
A1: CALENDRIER 4e — année scolaire 2026-2027 (académie de Martinique) — 1 séance de 1 h 30 par semaine
D2: =IF(COUNTIF($G$4:$G$44,"<>")>9,"🛑 "&COUNTIF($G$4:$G$44,"<>")&" imprévus : la réserve (9) est dépassée — arbitrage nécessaire !","✔ Réserve d'aléas : "&(9-COUNTIF($G$4:$G$44,"<>"))&" semaine(s) tampon restante(s) sur 9") | F2: ◀ Accueil
A3: Sem. | B3: Lundi de la semaine | C3: Période | D3: Affectation (AUTO — se recalcule) | E3: Repères / jours fériés | F3: Aléas / notes (à remplir) | G3: ⚠ Imprévu ? (menu déroulant) | H3: n° créneau (auto)
A4: S01 | B4: 31/08/2026 | C4: P1 | D4: =IF($G4<>"",$G4&" — les séances suivantes se décalent d'une semaine",INDEX('⚙ Moteur'!$B$5:$B$41,$H4)) | E4: Rentrée des élèves mardi 1er septembre. | H4: =IF($G4<>"",0,0+1)
A5: S02 | B5: 07/09/2026 | C5: P1 | D5: =IF($G5<>"",$G5&" — les séances suivantes se décalent d'une semaine",INDEX('⚙ Moteur'!$B$5:$B$41,$H5)) | H5: =IF($G5<>"",H4,H4+1)
A6: S03 | B6: 14/09/2026 | C6: P1 | D6: =IF($G6<>"",$G6&" — les séances suivantes se décalent d'une semaine",INDEX('⚙ Moteur'!$B$5:$B$41,$H6)) | H6: =IF($G6<>"",H5,H5+1)
A7: S04 | B7: 21/09/2026 | C7: P1 | D7: =IF($G7<>"",$G7&" — les séances suivantes se décalent d'une semaine",INDEX('⚙ Moteur'!$B$5:$B$41,$H7)) | H7: =IF($G7<>"",H6,H6+1)
A8: S05 | B8: 28/09/2026 | C8: P1 | D8: =IF($G8<>"",$G8&" — les séances suivantes se décalent d'une semaine",INDEX('⚙ Moteur'!$B$5:$B$41,$H8)) | H8: =IF($G8<>"",H7,H7+1)
A9: S06 | B9: 05/10/2026 | C9: P1 | D9: =IF($G9<>"",$G9&" — les séances suivantes se décalent d'une semaine",INDEX('⚙ Moteur'!$B$5:$B$41,$H9)) | H9: =IF($G9<>"",H8,H8+1)
A10: S07 | B10: 12/10/2026 | C10: P1 | D10: =IF($G10<>"",$G10&" — les séances suivantes se décalent d'une semaine",INDEX('⚙ Moteur'!$B$5:$B$41,$H10)) | H10: =IF($G10<>"",H9,H9+1)
A11: S08 | B11: 19/10/2026 | C11: P1 | D11: =IF($G11<>"",$G11&" — les séances suivantes se décalent d'une semaine",INDEX('⚙ Moteur'!$B$5:$B$41,$H11)) | H11: =IF($G11<>"",H10,H10+1)
A12: 🏖 Vacances de la Toussaint : 20/10 → 3/11
A13: S09 | B13: 02/11/2026 | C13: P2 | D13: =IF($G13<>"",$G13&" — les séances suivantes se décalent d'une semaine",INDEX('⚙ Moteur'!$B$5:$B$41,$H13)) | H13: =IF($G13<>"",H11,H11+1)
A14: S10 | B14: 09/11/2026 | C14: P2 | D14: =IF($G14<>"",$G14&" — les séances suivantes se décalent d'une semaine",INDEX('⚙ Moteur'!$B$5:$B$41,$H14)) | E14: Mer. 11/11 férié (Armistice) | H14: =IF($G14<>"",H13,H13+1)
A15: S11 | B15: 16/11/2026 | C15: P2 | D15: =IF($G15<>"",$G15&" — les séances suivantes se décalent d'une semaine",INDEX('⚙ Moteur'!$B$5:$B$41,$H15)) | H15: =IF($G15<>"",H14,H14+1)
A16: S12 | B16: 23/11/2026 | C16: P2 | D16: =IF($G16<>"",$G16&" — les séances suivantes se décalent d'une semaine",INDEX('⚙ Moteur'!$B$5:$B$41,$H16)) | H16: =IF($G16<>"",H15,H15+1)
A17: S13 | B17: 30/11/2026 | C17: P2 | D17: =IF($G17<>"",$G17&" — les séances suivantes se décalent d'une semaine",INDEX('⚙ Moteur'!$B$5:$B$41,$H17)) | H17: =IF($G17<>"",H16,H16+1)
A18: S14 | B18: 07/12/2026 | C18: P2 | D18: =IF($G18<>"",$G18&" — les séances suivantes se décalent d'une semaine",INDEX('⚙ Moteur'!$B$5:$B$41,$H18)) | H18: =IF($G18<>"",H17,H17+1)
A19: S15 | B19: 14/12/2026 | C19: P2 | D19: =IF($G19<>"",$G19&" — les séances suivantes se décalent d'une semaine",INDEX('⚙ Moteur'!$B$5:$B$41,$H19)) | H19: =IF($G19<>"",H18,H18+1)
A20: 🏖 Vacances de Noël : 19/12 → 4/01
A21: S16 | B21: 04/01/2027 | C21: P3 | D21: =IF($G21<>"",$G21&" — les séances suivantes se décalent d'une semaine",INDEX('⚙ Moteur'!$B$5:$B$41,$H21)) | H21: =IF($G21<>"",H19,H19+1)
A22: S17 | B22: 11/01/2027 | C22: P3 | D22: =IF($G22<>"",$G22&" — les séances suivantes se décalent d'une semaine",INDEX('⚙ Moteur'!$B$5:$B$41,$H22)) | H22: =IF($G22<>"",H21,H21+1)
A23: S18 | B23: 18/01/2027 | C23: P3 | D23: =IF($G23<>"",$G23&" — les séances suivantes se décalent d'une semaine",INDEX('⚙ Moteur'!$B$5:$B$41,$H23)) | H23: =IF($G23<>"",H22,H22+1)
A24: S19 | B24: 25/01/2027 | C24: P3 | D24: =IF($G24<>"",$G24&" — les séances suivantes se décalent d'une semaine",INDEX('⚙ Moteur'!$B$5:$B$41,$H24)) | H24: =IF($G24<>"",H23,H23+1)
A25: S20 | B25: 01/02/2027 | C25: P3 | D25: =IF($G25<>"",$G25&" — les séances suivantes se décalent d'une semaine",INDEX('⚙ Moteur'!$B$5:$B$41,$H25)) | H25: =IF($G25<>"",H24,H24+1)
A26: 🏖 Vacances de Carnaval : 6/02 → 22/02
A27: S21 | B27: 22/02/2027 | C27: P4 | D27: =IF($G27<>"",$G27&" — les séances suivantes se décalent d'une semaine",INDEX('⚙ Moteur'!$B$5:$B$41,$H27)) | H27: =IF($G27<>"",H25,H25+1)
A28: S22 | B28: 01/03/2027 | C28: P4 | D28: =IF($G28<>"",$G28&" — les séances suivantes se décalent d'une semaine",INDEX('⚙ Moteur'!$B$5:$B$41,$H28)) | H28: =IF($G28<>"",H27,H27+1)
A29: S23 | B29: 08/03/2027 | C29: P4 | D29: =IF($G29<>"",$G29&" — les séances suivantes se décalent d'une semaine",INDEX('⚙ Moteur'!$B$5:$B$41,$H29)) | H29: =IF($G29<>"",H28,H28+1)
A30: S24 | B30: 15/03/2027 | C30: P4 | D30: =IF($G30<>"",$G30&" — les séances suivantes se décalent d'une semaine",INDEX('⚙ Moteur'!$B$5:$B$41,$H30)) | H30: =IF($G30<>"",H29,H29+1)
A31: S25 | B31: 22/03/2027 | C31: P4 | D31: =IF($G31<>"",$G31&" — les séances suivantes se décalent d'une semaine",INDEX('⚙ Moteur'!$B$5:$B$41,$H31)) | E31: Ven. 26/03 férié (Vendredi saint, Martinique) | H31: =IF($G31<>"",H30,H30+1)
A32: S26 | B32: 29/03/2027 | C32: P4 | D32: =IF($G32<>"",$G32&" — les séances suivantes se décalent d'une semaine",INDEX('⚙ Moteur'!$B$5:$B$41,$H32)) | E32: Lun. 29/03 férié (lundi de Pâques) | H32: =IF($G32<>"",H31,H31+1)
A33: S27 | B33: 05/04/2027 | C33: P4 | D33: =IF($G33<>"",$G33&" — les séances suivantes se décalent d'une semaine",INDEX('⚙ Moteur'!$B$5:$B$41,$H33)) | H33: =IF($G33<>"",H32,H32+1)
A34: S28 | B34: 12/04/2027 | C34: P4 | D34: =IF($G34<>"",$G34&" — les séances suivantes se décalent d'une semaine",INDEX('⚙ Moteur'!$B$5:$B$41,$H34)) | H34: =IF($G34<>"",H33,H33+1)
A35: 🏖 Vacances de Pâques : 20/04 → 3/05
A36: S29 | B36: 03/05/2027 | C36: P5 | D36: =IF($G36<>"",$G36&" — les séances suivantes se décalent d'une semaine",INDEX('⚙ Moteur'!$B$5:$B$41,$H36)) | E36: Jeu. 6/05 férié (Ascension) — pont probable ven. 7/05 | H36: =IF($G36<>"",H34,H34+1)
A37: S30 | B37: 10/05/2027 | C37: P5 | D37: =IF($G37<>"",$G37&" — les séances suivantes se décalent d'une semaine",INDEX('⚙ Moteur'!$B$5:$B$41,$H37)) | H37: =IF($G37<>"",H36,H36+1)
A38: S31 | B38: 17/05/2027 | C38: P5 | D38: =IF($G38<>"",$G38&" — les séances suivantes se décalent d'une semaine",INDEX('⚙ Moteur'!$B$5:$B$41,$H38)) | E38: Lun. 17/05 férié (Pentecôte); Ven. 21/05 : veille du 22 mai (abolition) — commémorations | H38: =IF($G38<>"",H37,H37+1)
A39: S32 | B39: 24/05/2027 | C39: P5 | D39: =IF($G39<>"",$G39&" — les séances suivantes se décalent d'une semaine",INDEX('⚙ Moteur'!$B$5:$B$41,$H39)) | H39: =IF($G39<>"",H38,H38+1)
A40: S33 | B40: 31/05/2027 | C40: P5 | D40: =IF($G40<>"",$G40&" — les séances suivantes se décalent d'une semaine",INDEX('⚙ Moteur'!$B$5:$B$41,$H40)) | H40: =IF($G40<>"",H39,H39+1)
A41: S34 | B41: 07/06/2027 | C41: P5 | D41: =IF($G41<>"",$G41&" — les séances suivantes se décalent d'une semaine",INDEX('⚙ Moteur'!$B$5:$B$41,$H41)) | H41: =IF($G41<>"",H40,H40+1)
A42: S35 | B42: 14/06/2027 | C42: P5 | D42: =IF($G42<>"",$G42&" — les séances suivantes se décalent d'une semaine",INDEX('⚙ Moteur'!$B$5:$B$41,$H42)) | H42: =IF($G42<>"",H41,H41+1)
A43: S36 | B43: 21/06/2027 | C43: P5 | D43: =IF($G43<>"",$G43&" — les séances suivantes se décalent d'une semaine",INDEX('⚙ Moteur'!$B$5:$B$41,$H43)) | H43: =IF($G43<>"",H42,H42+1)
A44: S37 | B44: 28/06/2027 | C44: P5 | D44: =IF($G44<>"",$G44&" — les séances suivantes se décalent d'une semaine",INDEX('⚙ Moteur'!$B$5:$B$41,$H44)) | H44: =IF($G44<>"",H43,H43+1)
A45: 🏖 Fin des cours : 3 juillet 2027
A47: Synthèse
B48: Semaines de cours au total | C48: 37
B49: … dont semaines tampon | C49: =COUNTIF(D4:D44,"⏳*")
B50: … dont semaines avec séance planifiée | C50: =COUNTIF(D4:D44,"S*")
B51: Moteur automatique : marquer un ⚠ imprévu en colonne G décale toutes les séances suivantes (calendrier, frise et progression se recalculent). Un jour férié sur ton créneau = un imprévu à marquer aussi.

Sheet 🗓 Frise de l'année
A1: FRISE DE L'ANNÉE 4e — se recalcule automatiquement selon les imprévus du Calendrier
B2: ='📅 Calendrier'!D2 | P2: ◀ Accueil
C3: P1 (8 sem.) | K3: P2 (7 sem.) | R3: P3 (5 sem.) | W3: P4 (8 sem.) | AE3: P5 (9 sem.)
C4: S01 | D4: S02 | E4: S03 | F4: S04 | G4: S05 | H4: S06 | I4: S07 | J4: S08 | K4: S09 | L4: S10 | M4: S11 | N4: S12 | O4: S13 | P4: S14 | Q4: S15 | R4: S16 | S4: S17 | T4: S18 | U4: S19 | V4: S20 | W4: S21 | X4: S22 | Y4: S23 | Z4: S24 | AA4: S25 | AB4: S26 | AC4: S27 | AD4: S28 | AE4: S29 | AF4: S30 | AG4: S31 | AH4: S32 | AI4: S33 | AJ4: S34 | AK4: S35 | AL4: S36 | AM4: S37
C5: 31/08 | D5: 07/09 | E5: 14/09 | F5: 21/09 | G5: 28/09 | H5: 05/10 | I5: 12/10 | J5: 19/10 | K5: 02/11 | L5: 09/11 | M5: 16/11 | N5: 23/11 | O5: 30/11 | P5: 07/12 | Q5: 14/12 | R5: 04/01 | S5: 11/01 | T5: 18/01 | U5: 25/01 | V5: 01/02 | W5: 22/02 | X5: 01/03 | Y5: 08/03 | Z5: 15/03 | AA5: 22/03 | AB5: 29/03 | AC5: 05/04 | AD5: 12/04 | AE5: 03/05 | AF5: 10/05 | AG5: 17/05 | AH5: 24/05 | AI5: 31/05 | AJ5: 07/06 | AK5: 14/06 | AL5: 21/06 | AM5: 28/06
B6: S1 · Objets qui évoluent | C6: =IF(LEFT('📅 Calendrier'!$D4,2)="S1",MID('📅 Calendrier'!$D4,SEARCH("séance",'📅 Calendrier'!$D4)+7,2),"") | D6: =IF(LEFT('📅 Calendrier'!$D5,2)="S1",MID('📅 Calendrier'!$D5,SEARCH("séance",'📅 Calendrier'!$D5)+7,2),"") | E6: =IF(LEFT('📅 Calendrier'!$D6,2)="S1",MID('📅 Calendrier'!$D6,SEARCH("séance",'📅 Calendrier'!$D6)+7,2),"") | F6: =IF(LEFT('📅 Calendrier'!$D7,2)="S1",MID('📅 Calendrier'!$D7,SEARCH("séance",'📅 Calendrier'!$D7)+7,2),"") | G6: =IF(LEFT('📅 Calendrier'!$D8,2)="S1",MID('📅 Calendrier'!$D8,SEARCH("séance",'📅 Calendrier'!$D8)+7,2),"") | H6: =IF(LEFT('📅 Calendrier'!$D9,2)="S1",MID('📅 Calendrier'!$D9,SEARCH("séance",'📅 Calendrier'!$D9)+7,2),"") | I6: =IF(LEFT('📅 Calendrier'!$D10,2)="S1",MID('📅 Calendrier'!$D10,SEARCH("séance",'📅 Calendrier'!$D10)+7,2),"") | J6: =IF(LEFT('📅 Calendrier'!$D11,2)="S1",MID('📅 Calendrier'!$D11,SEARCH("séance",'📅 Calendrier'!$D11)+7,2),"") | K6: =IF(LEFT('📅 Calendrier'!$D13,2)="S1",MID('📅 Calendrier'!$D13,SEARCH("séance",'📅 Calendrier'!$D13)+7,2),"") | L6: =IF(LEFT('📅 Calendrier'!$D14,2)="S1",MID('📅 Calendrier'!$D14,SEARCH("séance",'📅 Calendrier'!$D14)+7,2),"") | M6: =IF(LEFT('📅 Calendrier'!$D15,2)="S1",MID('📅 Calendrier'!$D15,SEARCH("séance",'📅 Calendrier'!$D15)+7,2),"") | N6: =IF(LEFT('📅 Calendrier'!$D16,2)="S1",MID('📅 Calendrier'!$D16,SEARCH("séance",'📅 Calendrier'!$D16)+7,2),"") | O6: =IF(LEFT('📅 Calendrier'!$D17,2)="S1",MID('📅 Calendrier'!$D17,SEARCH("séance",'📅 Calendrier'!$D17)+7,2),"") | P6: =IF(LEFT('📅 Calendrier'!$D18,2)="S1",MID('📅 Calendrier'!$D18,SEARCH("séance",'📅 Calendrier'!$D18)+7,2),"") | Q6: =IF(LEFT('📅 Calendrier'!$D19,2)="S1",MID('📅 Calendrier'!$D19,SEARCH("séance",'📅 Calendrier'!$D19)+7,2),"") | R6: =IF(LEFT('📅 Calendrier'!$D21,2)="S1",MID('📅 Calendrier'!$D21,SEARCH("séance",'📅 Calendrier'!$D21)+7,2),"") | S6: =IF(LEFT('📅 Calendrier'!$D22,2)="S1",MID('📅 Calendrier'!$D22,SEARCH("séance",'📅 Calendrier'!$D22)+7,2),"") | T6: =IF(LEFT('📅 Calendrier'!$D23,2)="S1",MID('📅 Calendrier'!$D23,SEARCH("séance",'📅 Calendrier'!$D23)+7,2),"") | U6: =IF(LEFT('📅 Calendrier'!$D24,2)="S1",MID('📅 Calendrier'!$D24,SEARCH("séance",'📅 Calendrier'!$D24)+7,2),"") | V6: =IF(LEFT('📅 Calendrier'!$D25,2)="S1",MID('📅 Calendrier'!$D25,SEARCH("séance",'📅 Calendrier'!$D25)+7,2),"") | W6: =IF(LEFT('📅 Calendrier'!$D27,2)="S1",MID('📅 Calendrier'!$D27,SEARCH("séance",'📅 Calendrier'!$D27)+7,2),"") | X6: =IF(LEFT('📅 Calendrier'!$D28,2)="S1",MID('📅 Calendrier'!$D28,SEARCH("séance",'📅 Calendrier'!$D28)+7,2),"") | Y6: =IF(LEFT('📅 Calendrier'!$D29,2)="S1",MID('📅 Calendrier'!$D29,SEARCH("séance",'📅 Calendrier'!$D29)+7,2),"") | Z6: =IF(LEFT('📅 Calendrier'!$D30,2)="S1",MID('📅 Calendrier'!$D30,SEARCH("séance",'📅 Calendrier'!$D30)+7,2),"") | AA6: =IF(LEFT('📅 Calendrier'!$D31,2)="S1",MID('📅 Calendrier'!$D31,SEARCH("séance",'📅 Calendrier'!$D31)+7,2),"") | AB6: =IF(LEFT('📅 Calendrier'!$D32,2)="S1",MID('📅 Calendrier'!$D32,SEARCH("séance",'📅 Calendrier'!$D32)+7,2),"") | AC6: =IF(LEFT('📅 Calendrier'!$D33,2)="S1",MID('📅 Calendrier'!$D33,SEARCH("séance",'📅 Calendrier'!$D33)+7,2),"") | AD6: =IF(LEFT('📅 Calendrier'!$D34,2)="S1",MID('📅 Calendrier'!$D34,SEARCH("séance",'📅 Calendrier'!$D34)+7,2),"") | AE6: =IF(LEFT('📅 Calendrier'!$D36,2)="S1",MID('📅 Calendrier'!$D36,SEARCH("séance",'📅 Calendrier'!$D36)+7,2),"") | AF6: =IF(LEFT('📅 Calendrier'!$D37,2)="S1",MID('📅 Calendrier'!$D37,SEARCH("séance",'📅 Calendrier'!$D37)+7,2),"") | AG6: =IF(LEFT('📅 Calendrier'!$D38,2)="S1",MID('📅 Calendrier'!$D38,SEARCH("séance",'📅 Calendrier'!$D38)+7,2),"") | AH6: =IF(LEFT('📅 Calendrier'!$D39,2)="S1",MID('📅 Calendrier'!$D39,SEARCH("séance",'📅 Calendrier'!$D39)+7,2),"") | AI6: =IF(LEFT('📅 Calendrier'!$D40,2)="S1",MID('📅 Calendrier'!$D40,SEARCH("séance",'📅 Calendrier'!$D40)+7,2),"") | AJ6: =IF(LEFT('📅 Calendrier'!$D41,2)="S1",MID('📅 Calendrier'!$D41,SEARCH("séance",'📅 Calendrier'!$D41)+7,2),"") | AK6: =IF(LEFT('📅 Calendrier'!$D42,2)="S1",MID('📅 Calendrier'!$D42,SEARCH("séance",'📅 Calendrier'!$D42)+7,2),"") | AL6: =IF(LEFT('📅 Calendrier'!$D43,2)="S1",MID('📅 Calendrier'!$D43,SEARCH("séance",'📅 Calendrier'!$D43)+7,2),"") | AM6: =IF(LEFT('📅 Calendrier'!$D44,2)="S1",MID('📅 Calendrier'!$D44,SEARCH("séance",'📅 Calendrier'!$D44)+7,2),"")
B7: S2 · Identité numérique | C7: =IF(LEFT('📅 Calendrier'!$D4,2)="S2",MID('📅 Calendrier'!$D4,SEARCH("séance",'📅 Calendrier'!$D4)+7,2),"") | D7: =IF(LEFT('📅 Calendrier'!$D5,2)="S2",MID('📅 Calendrier'!$D5,SEARCH("séance",'📅 Calendrier'!$D5)+7,2),"") | E7: =IF(LEFT('📅 Calendrier'!$D6,2)="S2",MID('📅 Calendrier'!$D6,SEARCH("séance",'📅 Calendrier'!$D6)+7,2),"") | F7: =IF(LEFT('📅 Calendrier'!$D7,2)="S2",MID('📅 Calendrier'!$D7,SEARCH("séance",'📅 Calendrier'!$D7)+7,2),"") | G7: =IF(LEFT('📅 Calendrier'!$D8,2)="S2",MID('📅 Calendrier'!$D8,SEARCH("séance",'📅 Calendrier'!$D8)+7,2),"") | H7: =IF(LEFT('📅 Calendrier'!$D9,2)="S2",MID('📅 Calendrier'!$D9,SEARCH("séance",'📅 Calendrier'!$D9)+7,2),"") | I7: =IF(LEFT('📅 Calendrier'!$D10,2)="S2",MID('📅 Calendrier'!$D10,SEARCH("séance",'📅 Calendrier'!$D10)+7,2),"") | J7: =IF(LEFT('📅 Calendrier'!$D11,2)="S2",MID('📅 Calendrier'!$D11,SEARCH("séance",'📅 Calendrier'!$D11)+7,2),"") | K7: =IF(LEFT('📅 Calendrier'!$D13,2)="S2",MID('📅 Calendrier'!$D13,SEARCH("séance",'📅 Calendrier'!$D13)+7,2),"") | L7: =IF(LEFT('📅 Calendrier'!$D14,2)="S2",MID('📅 Calendrier'!$D14,SEARCH("séance",'📅 Calendrier'!$D14)+7,2),"") | M7: =IF(LEFT('📅 Calendrier'!$D15,2)="S2",MID('📅 Calendrier'!$D15,SEARCH("séance",'📅 Calendrier'!$D15)+7,2),"") | N7: =IF(LEFT('📅 Calendrier'!$D16,2)="S2",MID('📅 Calendrier'!$D16,SEARCH("séance",'📅 Calendrier'!$D16)+7,2),"") | O7: =IF(LEFT('📅 Calendrier'!$D17,2)="S2",MID('📅 Calendrier'!$D17,SEARCH("séance",'📅 Calendrier'!$D17)+7,2),"") | P7: =IF(LEFT('📅 Calendrier'!$D18,2)="S2",MID('📅 Calendrier'!$D18,SEARCH("séance",'📅 Calendrier'!$D18)+7,2),"") | Q7: =IF(LEFT('📅 Calendrier'!$D19,2)="S2",MID('📅 Calendrier'!$D19,SEARCH("séance",'📅 Calendrier'!$D19)+7,2),"") | R7: =IF(LEFT('📅 Calendrier'!$D21,2)="S2",MID('📅 Calendrier'!$D21,SEARCH("séance",'📅 Calendrier'!$D21)+7,2),"") | S7: =IF(LEFT('📅 Calendrier'!$D22,2)="S2",MID('📅 Calendrier'!$D22,SEARCH("séance",'📅 Calendrier'!$D22)+7,2),"") | T7: =IF(LEFT('📅 Calendrier'!$D23,2)="S2",MID('📅 Calendrier'!$D23,SEARCH("séance",'📅 Calendrier'!$D23)+7,2),"") | U7: =IF(LEFT('📅 Calendrier'!$D24,2)="S2",MID('📅 Calendrier'!$D24,SEARCH("séance",'📅 Calendrier'!$D24)+7,2),"") | V7: =IF(LEFT('📅 Calendrier'!$D25,2)="S2",MID('📅 Calendrier'!$D25,SEARCH("séance",'📅 Calendrier'!$D25)+7,2),"") | W7: =IF(LEFT('📅 Calendrier'!$D27,2)="S2",MID('📅 Calendrier'!$D27,SEARCH("séance",'📅 Calendrier'!$D27)+7,2),"") | X7: =IF(LEFT('📅 Calendrier'!$D28,2)="S2",MID('📅 Calendrier'!$D28,SEARCH("séance",'📅 Calendrier'!$D28)+7,2),"") | Y7: =IF(LEFT('📅 Calendrier'!$D29,2)="S2",MID('📅 Calendrier'!$D29,SEARCH("séance",'📅 Calendrier'!$D29)+7,2),"") | Z7: =IF(LEFT('📅 Calendrier'!$D30,2)="S2",MID('📅 Calendrier'!$D30,SEARCH("séance",'📅 Calendrier'!$D30)+7,2),"") | AA7: =IF(LEFT('📅 Calendrier'!$D31,2)="S2",MID('📅 Calendrier'!$D31,SEARCH("séance",'📅 Calendrier'!$D31)+7,2),"") | AB7: =IF(LEFT('📅 Calendrier'!$D32,2)="S2",MID('📅 Calendrier'!$D32,SEARCH("séance",'📅 Calendrier'!$D32)+7,2),"") | AC7: =IF(LEFT('📅 Calendrier'!$D33,2)="S2",MID('📅 Calendrier'!$D33,SEARCH("séance",'📅 Calendrier'!$D33)+7,2),"") | AD7: =IF(LEFT('📅 Calendrier'!$D34,2)="S2",MID('📅 Calendrier'!$D34,SEARCH("séance",'📅 Calendrier'!$D34)+7,2),"") | AE7: =IF(LEFT('📅 Calendrier'!$D36,2)="S2",MID('📅 Calendrier'!$D36,SEARCH("séance",'📅 Calendrier'!$D36)+7,2),"") | AF7: =IF(LEFT('📅 Calendrier'!$D37,2)="S2",MID('📅 Calendrier'!$D37,SEARCH("séance",'📅 Calendrier'!$D37)+7,2),"") | AG7: =IF(LEFT('📅 Calendrier'!$D38,2)="S2",MID('📅 Calendrier'!$D38,SEARCH("séance",'📅 Calendrier'!$D38)+7,2),"") | AH7: =IF(LEFT('📅 Calendrier'!$D39,2)="S2",MID('📅 Calendrier'!$D39,SEARCH("séance",'📅 Calendrier'!$D39)+7,2),"") | AI7: =IF(LEFT('📅 Calendrier'!$D40,2)="S2",MID('📅 Calendrier'!$D40,SEARCH("séance",'📅 Calendrier'!$D40)+7,2),"") | AJ7: =IF(LEFT('📅 Calendrier'!$D41,2)="S2",MID('📅 Calendrier'!$D41,SEARCH("séance",'📅 Calendrier'!$D41)+7,2),"") | AK7: =IF(LEFT('📅 Calendrier'!$D42,2)="S2",MID('📅 Calendrier'!$D42,SEARCH("séance",'📅 Calendrier'!$D42)+7,2),"") | AL7: =IF(LEFT('📅 Calendrier'!$D43,2)="S2",MID('📅 Calendrier'!$D43,SEARCH("séance",'📅 Calendrier'!$D43)+7,2),"") | AM7: =IF(LEFT('📅 Calendrier'!$D44,2)="S2",MID('📅 Calendrier'!$D44,SEARCH("séance",'📅 Calendrier'!$D44)+7,2),"")
B8: S3 · Ergonomie & choix argumenté | C8: =IF(LEFT('📅 Calendrier'!$D4,2)="S3",MID('📅 Calendrier'!$D4,SEARCH("séance",'📅 Calendrier'!$D4)+7,2),"") | D8: =IF(LEFT('📅 Calendrier'!$D5,2)="S3",MID('📅 Calendrier'!$D5,SEARCH("séance",'📅 Calendrier'!$D5)+7,2),"") | E8: =IF(LEFT('📅 Calendrier'!$D6,2)="S3",MID('📅 Calendrier'!$D6,SEARCH("séance",'📅 Calendrier'!$D6)+7,2),"") | F8: =IF(LEFT('📅 Calendrier'!$D7,2)="S3",MID('📅 Calendrier'!$D7,SEARCH("séance",'📅 Calendrier'!$D7)+7,2),"") | G8: =IF(LEFT('📅 Calendrier'!$D8,2)="S3",MID('📅 Calendrier'!$D8,SEARCH("séance",'📅 Calendrier'!$D8)+7,2),"") | H8: =IF(LEFT('📅 Calendrier'!$D9,2)="S3",MID('📅 Calendrier'!$D9,SEARCH("séance",'📅 Calendrier'!$D9)+7,2),"") | I8: =IF(LEFT('📅 Calendrier'!$D10,2)="S3",MID('📅 Calendrier'!$D10,SEARCH("séance",'📅 Calendrier'!$D10)+7,2),"") | J8: =IF(LEFT('📅 Calendrier'!$D11,2)="S3",MID('📅 Calendrier'!$D11,SEARCH("séance",'📅 Calendrier'!$D11)+7,2),"") | K8: =IF(LEFT('📅 Calendrier'!$D13,2)="S3",MID('📅 Calendrier'!$D13,SEARCH("séance",'📅 Calendrier'!$D13)+7,2),"") | L8: =IF(LEFT('📅 Calendrier'!$D14,2)="S3",MID('📅 Calendrier'!$D14,SEARCH("séance",'📅 Calendrier'!$D14)+7,2),"") | M8: =IF(LEFT('📅 Calendrier'!$D15,2)="S3",MID('📅 Calendrier'!$D15,SEARCH("séance",'📅 Calendrier'!$D15)+7,2),"") | N8: =IF(LEFT('📅 Calendrier'!$D16,2)="S3",MID('📅 Calendrier'!$D16,SEARCH("séance",'📅 Calendrier'!$D16)+7,2),"") | O8: =IF(LEFT('📅 Calendrier'!$D17,2)="S3",MID('📅 Calendrier'!$D17,SEARCH("séance",'📅 Calendrier'!$D17)+7,2),"") | P8: =IF(LEFT('📅 Calendrier'!$D18,2)="S3",MID('📅 Calendrier'!$D18,SEARCH("séance",'📅 Calendrier'!$D18)+7,2),"") | Q8: =IF(LEFT('📅 Calendrier'!$D19,2)="S3",MID('📅 Calendrier'!$D19,SEARCH("séance",'📅 Calendrier'!$D19)+7,2),"") | R8: =IF(LEFT('📅 Calendrier'!$D21,2)="S3",MID('📅 Calendrier'!$D21,SEARCH("séance",'📅 Calendrier'!$D21)+7,2),"") | S8: =IF(LEFT('📅 Calendrier'!$D22,2)="S3",MID('📅 Calendrier'!$D22,SEARCH("séance",'📅 Calendrier'!$D22)+7,2),"") | T8: =IF(LEFT('📅 Calendrier'!$D23,2)="S3",MID('📅 Calendrier'!$D23,SEARCH("séance",'📅 Calendrier'!$D23)+7,2),"") | U8: =IF(LEFT('📅 Calendrier'!$D24,2)="S3",MID('📅 Calendrier'!$D24,SEARCH("séance",'📅 Calendrier'!$D24)+7,2),"") | V8: =IF(LEFT('📅 Calendrier'!$D25,2)="S3",MID('📅 Calendrier'!$D25,SEARCH("séance",'📅 Calendrier'!$D25)+7,2),"") | W8: =IF(LEFT('📅 Calendrier'!$D27,2)="S3",MID('📅 Calendrier'!$D27,SEARCH("séance",'📅 Calendrier'!$D27)+7,2),"") | X8: =IF(LEFT('📅 Calendrier'!$D28,2)="S3",MID('📅 Calendrier'!$D28,SEARCH("séance",'📅 Calendrier'!$D28)+7,2),"") | Y8: =IF(LEFT('📅 Calendrier'!$D29,2)="S3",MID('📅 Calendrier'!$D29,SEARCH("séance",'📅 Calendrier'!$D29)+7,2),"") | Z8: =IF(LEFT('📅 Calendrier'!$D30,2)="S3",MID('📅 Calendrier'!$D30,SEARCH("séance",'📅 Calendrier'!$D30)+7,2),"") | AA8: =IF(LEFT('📅 Calendrier'!$D31,2)="S3",MID('📅 Calendrier'!$D31,SEARCH("séance",'📅 Calendrier'!$D31)+7,2),"") | AB8: =IF(LEFT('📅 Calendrier'!$D32,2)="S3",MID('📅 Calendrier'!$D32,SEARCH("séance",'📅 Calendrier'!$D32)+7,2),"") | AC8: =IF(LEFT('📅 Calendrier'!$D33,2)="S3",MID('📅 Calendrier'!$D33,SEARCH("séance",'📅 Calendrier'!$D33)+7,2),"") | AD8: =IF(LEFT('📅 Calendrier'!$D34,2)="S3",MID('📅 Calendrier'!$D34,SEARCH("séance",'📅 Calendrier'!$D34)+7,2),"") | AE8: =IF(LEFT('📅 Calendrier'!$D36,2)="S3",MID('📅 Calendrier'!$D36,SEARCH("séance",'📅 Calendrier'!$D36)+7,2),"") | AF8: =IF(LEFT('📅 Calendrier'!$D37,2)="S3",MID('📅 Calendrier'!$D37,SEARCH("séance",'📅 Calendrier'!$D37)+7,2),"") | AG8: =IF(LEFT('📅 Calendrier'!$D38,2)="S3",MID('📅 Calendrier'!$D38,SEARCH("séance",'📅 Calendrier'!$D38)+7,2),"") | AH8: =IF(LEFT('📅 Calendrier'!$D39,2)="S3",MID('📅 Calendrier'!$D39,SEARCH("séance",'📅 Calendrier'!$D39)+7,2),"") | AI8: =IF(LEFT('📅 Calendrier'!$D40,2)="S3",MID('📅 Calendrier'!$D40,SEARCH("séance",'📅 Calendrier'!$D40)+7,2),"") | AJ8: =IF(LEFT('📅 Calendrier'!$D41,2)="S3",MID('📅 Calendrier'!$D41,SEARCH("séance",'📅 Calendrier'!$D41)+7,2),"") | AK8: =IF(LEFT('📅 Calendrier'!$D42,2)="S3",MID('📅 Calendrier'!$D42,SEARCH("séance",'📅 Calendrier'!$D42)+7,2),"") | AL8: =IF(LEFT('📅 Calendrier'!$D43,2)="S3",MID('📅 Calendrier'!$D43,SEARCH("séance",'📅 Calendrier'!$D43)+7,2),"") | AM8: =IF(LEFT('📅 Calendrier'!$D44,2)="S3",MID('📅 Calendrier'!$D44,SEARCH("séance",'📅 Calendrier'!$D44)+7,2),"")
B9: S4 · Jardin connecté : chaînes | C9: =IF(LEFT('📅 Calendrier'!$D4,2)="S4",MID('📅 Calendrier'!$D4,SEARCH("séance",'📅 Calendrier'!$D4)+7,2),"") | D9: =IF(LEFT('📅 Calendrier'!$D5,2)="S4",MID('📅 Calendrier'!$D5,SEARCH("séance",'📅 Calendrier'!$D5)+7,2),"") | E9: =IF(LEFT('📅 Calendrier'!$D6,2)="S4",MID('📅 Calendrier'!$D6,SEARCH("séance",'📅 Calendrier'!$D6)+7,2),"") | F9: =IF(LEFT('📅 Calendrier'!$D7,2)="S4",MID('📅 Calendrier'!$D7,SEARCH("séance",'📅 Calendrier'!$D7)+7,2),"") | G9: =IF(LEFT('📅 Calendrier'!$D8,2)="S4",MID('📅 Calendrier'!$D8,SEARCH("séance",'📅 Calendrier'!$D8)+7,2),"") | H9: =IF(LEFT('📅 Calendrier'!$D9,2)="S4",MID('📅 Calendrier'!$D9,SEARCH("séance",'📅 Calendrier'!$D9)+7,2),"") | I9: =IF(LEFT('📅 Calendrier'!$D10,2)="S4",MID('📅 Calendrier'!$D10,SEARCH("séance",'📅 Calendrier'!$D10)+7,2),"") | J9: =IF(LEFT('📅 Calendrier'!$D11,2)="S4",MID('📅 Calendrier'!$D11,SEARCH("séance",'📅 Calendrier'!$D11)+7,2),"") | K9: =IF(LEFT('📅 Calendrier'!$D13,2)="S4",MID('📅 Calendrier'!$D13,SEARCH("séance",'📅 Calendrier'!$D13)+7,2),"") | L9: =IF(LEFT('📅 Calendrier'!$D14,2)="S4",MID('📅 Calendrier'!$D14,SEARCH("séance",'📅 Calendrier'!$D14)+7,2),"") | M9: =IF(LEFT('📅 Calendrier'!$D15,2)="S4",MID('📅 Calendrier'!$D15,SEARCH("séance",'📅 Calendrier'!$D15)+7,2),"") | N9: =IF(LEFT('📅 Calendrier'!$D16,2)="S4",MID('📅 Calendrier'!$D16,SEARCH("séance",'📅 Calendrier'!$D16)+7,2),"") | O9: =IF(LEFT('📅 Calendrier'!$D17,2)="S4",MID('📅 Calendrier'!$D17,SEARCH("séance",'📅 Calendrier'!$D17)+7,2),"") | P9: =IF(LEFT('📅 Calendrier'!$D18,2)="S4",MID('📅 Calendrier'!$D18,SEARCH("séance",'📅 Calendrier'!$D18)+7,2),"") | Q9: =IF(LEFT('📅 Calendrier'!$D19,2)="S4",MID('📅 Calendrier'!$D19,SEARCH("séance",'📅 Calendrier'!$D19)+7,2),"") | R9: =IF(LEFT('📅 Calendrier'!$D21,2)="S4",MID('📅 Calendrier'!$D21,SEARCH("séance",'📅 Calendrier'!$D21)+7,2),"") | S9: =IF(LEFT('📅 Calendrier'!$D22,2)="S4",MID('📅 Calendrier'!$D22,SEARCH("séance",'📅 Calendrier'!$D22)+7,2),"") | T9: =IF(LEFT('📅 Calendrier'!$D23,2)="S4",MID('📅 Calendrier'!$D23,SEARCH("séance",'📅 Calendrier'!$D23)+7,2),"") | U9: =IF(LEFT('📅 Calendrier'!$D24,2)="S4",MID('📅 Calendrier'!$D24,SEARCH("séance",'📅 Calendrier'!$D24)+7,2),"") | V9: =IF(LEFT('📅 Calendrier'!$D25,2)="S4",MID('📅 Calendrier'!$D25,SEARCH("séance",'📅 Calendrier'!$D25)+7,2),"") | W9: =IF(LEFT('📅 Calendrier'!$D27,2)="S4",MID('📅 Calendrier'!$D27,SEARCH("séance",'📅 Calendrier'!$D27)+7,2),"") | X9: =IF(LEFT('📅 Calendrier'!$D28,2)="S4",MID('📅 Calendrier'!$D28,SEARCH("séance",'📅 Calendrier'!$D28)+7,2),"") | Y9: =IF(LEFT('📅 Calendrier'!$D29,2)="S4",MID('📅 Calendrier'!$D29,SEARCH("séance",'📅 Calendrier'!$D29)+7,2),"") | Z9: =IF(LEFT('📅 Calendrier'!$D30,2)="S4",MID('📅 Calendrier'!$D30,SEARCH("séance",'📅 Calendrier'!$D30)+7,2),"") | AA9: =IF(LEFT('📅 Calendrier'!$D31,2)="S4",MID('📅 Calendrier'!$D31,SEARCH("séance",'📅 Calendrier'!$D31)+7,2),"") | AB9: =IF(LEFT('📅 Calendrier'!$D32,2)="S4",MID('📅 Calendrier'!$D32,SEARCH("séance",'📅 Calendrier'!$D32)+7,2),"") | AC9: =IF(LEFT('📅 Calendrier'!$D33,2)="S4",MID('📅 Calendrier'!$D33,SEARCH("séance",'📅 Calendrier'!$D33)+7,2),"") | AD9: =IF(LEFT('📅 Calendrier'!$D34,2)="S4",MID('📅 Calendrier'!$D34,SEARCH("séance",'📅 Calendrier'!$D34)+7,2),"") | AE9: =IF(LEFT('📅 Calendrier'!$D36,2)="S4",MID('📅 Calendrier'!$D36,SEARCH("séance",'📅 Calendrier'!$D36)+7,2),"") | AF9: =IF(LEFT('📅 Calendrier'!$D37,2)="S4",MID('📅 Calendrier'!$D37,SEARCH("séance",'📅 Calendrier'!$D37)+7,2),"") | AG9: =IF(LEFT('📅 Calendrier'!$D38,2)="S4",MID('📅 Calendrier'!$D38,SEARCH("séance",'📅 Calendrier'!$D38)+7,2),"") | AH9: =IF(LEFT('📅 Calendrier'!$D39,2)="S4",MID('📅 Calendrier'!$D39,SEARCH("séance",'📅 Calendrier'!$D39)+7,2),"") | AI9: =IF(LEFT('📅 Calendrier'!$D40,2)="S4",MID('📅 Calendrier'!$D40,SEARCH("séance",'📅 Calendrier'!$D40)+7,2),"") | AJ9: =IF(LEFT('📅 Calendrier'!$D41,2)="S4",MID('📅 Calendrier'!$D41,SEARCH("séance",'📅 Calendrier'!$D41)+7,2),"") | AK9: =IF(LEFT('📅 Calendrier'!$D42,2)="S4",MID('📅 Calendrier'!$D42,SEARCH("séance",'📅 Calendrier'!$D42)+7,2),"") | AL9: =IF(LEFT('📅 Calendrier'!$D43,2)="S4",MID('📅 Calendrier'!$D43,SEARCH("séance",'📅 Calendrier'!$D43)+7,2),"") | AM9: =IF(LEFT('📅 Calendrier'!$D44,2)="S4",MID('📅 Calendrier'!$D44,SEARCH("séance",'📅 Calendrier'!$D44)+7,2),"")
B10: S5 · Objets connectés en réseau | C10: =IF(LEFT('📅 Calendrier'!$D4,2)="S5",MID('📅 Calendrier'!$D4,SEARCH("séance",'📅 Calendrier'!$D4)+7,2),"") | D10: =IF(LEFT('📅 Calendrier'!$D5,2)="S5",MID('📅 Calendrier'!$D5,SEARCH("séance",'📅 Calendrier'!$D5)+7,2),"") | E10: =IF(LEFT('📅 Calendrier'!$D6,2)="S5",MID('📅 Calendrier'!$D6,SEARCH("séance",'📅 Calendrier'!$D6)+7,2),"") | F10: =IF(LEFT('📅 Calendrier'!$D7,2)="S5",MID('📅 Calendrier'!$D7,SEARCH("séance",'📅 Calendrier'!$D7)+7,2),"") | G10: =IF(LEFT('📅 Calendrier'!$D8,2)="S5",MID('📅 Calendrier'!$D8,SEARCH("séance",'📅 Calendrier'!$D8)+7,2),"") | H10: =IF(LEFT('📅 Calendrier'!$D9,2)="S5",MID('📅 Calendrier'!$D9,SEARCH("séance",'📅 Calendrier'!$D9)+7,2),"") | I10: =IF(LEFT('📅 Calendrier'!$D10,2)="S5",MID('📅 Calendrier'!$D10,SEARCH("séance",'📅 Calendrier'!$D10)+7,2),"") | J10: =IF(LEFT('📅 Calendrier'!$D11,2)="S5",MID('📅 Calendrier'!$D11,SEARCH("séance",'📅 Calendrier'!$D11)+7,2),"") | K10: =IF(LEFT('📅 Calendrier'!$D13,2)="S5",MID('📅 Calendrier'!$D13,SEARCH("séance",'📅 Calendrier'!$D13)+7,2),"") | L10: =IF(LEFT('📅 Calendrier'!$D14,2)="S5",MID('📅 Calendrier'!$D14,SEARCH("séance",'📅 Calendrier'!$D14)+7,2),"") | M10: =IF(LEFT('📅 Calendrier'!$D15,2)="S5",MID('📅 Calendrier'!$D15,SEARCH("séance",'📅 Calendrier'!$D15)+7,2),"") | N10: =IF(LEFT('📅 Calendrier'!$D16,2)="S5",MID('📅 Calendrier'!$D16,SEARCH("séance",'📅 Calendrier'!$D16)+7,2),"") | O10: =IF(LEFT('📅 Calendrier'!$D17,2)="S5",MID('📅 Calendrier'!$D17,SEARCH("séance",'📅 Calendrier'!$D17)+7,2),"") | P10: =IF(LEFT('📅 Calendrier'!$D18,2)="S5",MID('📅 Calendrier'!$D18,SEARCH("séance",'📅 Calendrier'!$D18)+7,2),"") | Q10: =IF(LEFT('📅 Calendrier'!$D19,2)="S5",MID('📅 Calendrier'!$D19,SEARCH("séance",'📅 Calendrier'!$D19)+7,2),"") | R10: =IF(LEFT('📅 Calendrier'!$D21,2)="S5",MID('📅 Calendrier'!$D21,SEARCH("séance",'📅 Calendrier'!$D21)+7,2),"") | S10: =IF(LEFT('📅 Calendrier'!$D22,2)="S5",MID('📅 Calendrier'!$D22,SEARCH("séance",'📅 Calendrier'!$D22)+7,2),"") | T10: =IF(LEFT('📅 Calendrier'!$D23,2)="S5",MID('📅 Calendrier'!$D23,SEARCH("séance",'📅 Calendrier'!$D23)+7,2),"") | U10: =IF(LEFT('📅 Calendrier'!$D24,2)="S5",MID('📅 Calendrier'!$D24,SEARCH("séance",'📅 Calendrier'!$D24)+7,2),"") | V10: =IF(LEFT('📅 Calendrier'!$D25,2)="S5",MID('📅 Calendrier'!$D25,SEARCH("séance",'📅 Calendrier'!$D25)+7,2),"") | W10: =IF(LEFT('📅 Calendrier'!$D27,2)="S5",MID('📅 Calendrier'!$D27,SEARCH("séance",'📅 Calendrier'!$D27)+7,2),"") | X10: =IF(LEFT('📅 Calendrier'!$D28,2)="S5",MID('📅 Calendrier'!$D28,SEARCH("séance",'📅 Calendrier'!$D28)+7,2),"") | Y10: =IF(LEFT('📅 Calendrier'!$D29,2)="S5",MID('📅 Calendrier'!$D29,SEARCH("séance",'📅 Calendrier'!$D29)+7,2),"") | Z10: =IF(LEFT('📅 Calendrier'!$D30,2)="S5",MID('📅 Calendrier'!$D30,SEARCH("séance",'📅 Calendrier'!$D30)+7,2),"") | AA10: =IF(LEFT('📅 Calendrier'!$D31,2)="S5",MID('📅 Calendrier'!$D31,SEARCH("séance",'📅 Calendrier'!$D31)+7,2),"") | AB10: =IF(LEFT('📅 Calendrier'!$D32,2)="S5",MID('📅 Calendrier'!$D32,SEARCH("séance",'📅 Calendrier'!$D32)+7,2),"") | AC10: =IF(LEFT('📅 Calendrier'!$D33,2)="S5",MID('📅 Calendrier'!$D33,SEARCH("séance",'📅 Calendrier'!$D33)+7,2),"") | AD10: =IF(LEFT('📅 Calendrier'!$D34,2)="S5",MID('📅 Calendrier'!$D34,SEARCH("séance",'📅 Calendrier'!$D34)+7,2),"") | AE10: =IF(LEFT('📅 Calendrier'!$D36,2)="S5",MID('📅 Calendrier'!$D36,SEARCH("séance",'📅 Calendrier'!$D36)+7,2),"") | AF10: =IF(LEFT('📅 Calendrier'!$D37,2)="S5",MID('📅 Calendrier'!$D37,SEARCH("séance",'📅 Calendrier'!$D37)+7,2),"") | AG10: =IF(LEFT('📅 Calendrier'!$D38,2)="S5",MID('📅 Calendrier'!$D38,SEARCH("séance",'📅 Calendrier'!$D38)+7,2),"") | AH10: =IF(LEFT('📅 Calendrier'!$D39,2)="S5",MID('📅 Calendrier'!$D39,SEARCH("séance",'📅 Calendrier'!$D39)+7,2),"") | AI10: =IF(LEFT('📅 Calendrier'!$D40,2)="S5",MID('📅 Calendrier'!$D40,SEARCH("séance",'📅 Calendrier'!$D40)+7,2),"") | AJ10: =IF(LEFT('📅 Calendrier'!$D41,2)="S5",MID('📅 Calendrier'!$D41,SEARCH("séance",'📅 Calendrier'!$D41)+7,2),"") | AK10: =IF(LEFT('📅 Calendrier'!$D42,2)="S5",MID('📅 Calendrier'!$D42,SEARCH("séance",'📅 Calendrier'!$D42)+7,2),"") | AL10: =IF(LEFT('📅 Calendrier'!$D43,2)="S5",MID('📅 Calendrier'!$D43,SEARCH("séance",'📅 Calendrier'!$D43)+7,2),"") | AM10: =IF(LEFT('📅 Calendrier'!$D44,2)="S5",MID('📅 Calendrier'!$D44,SEARCH("séance",'📅 Calendrier'!$D44)+7,2),"")
B11: S6 · Réparer sans notice (+C4.3) | C11: =IF(LEFT('📅 Calendrier'!$D4,2)="S6",MID('📅 Calendrier'!$D4,SEARCH("séance",'📅 Calendrier'!$D4)+7,2),"") | D11: =IF(LEFT('📅 Calendrier'!$D5,2)="S6",MID('📅 Calendrier'!$D5,SEARCH("séance",'📅 Calendrier'!$D5)+7,2),"") | E11: =IF(LEFT('📅 Calendrier'!$D6,2)="S6",MID('📅 Calendrier'!$D6,SEARCH("séance",'📅 Calendrier'!$D6)+7,2),"") | F11: =IF(LEFT('📅 Calendrier'!$D7,2)="S6",MID('📅 Calendrier'!$D7,SEARCH("séance",'📅 Calendrier'!$D7)+7,2),"") | G11: =IF(LEFT('📅 Calendrier'!$D8,2)="S6",MID('📅 Calendrier'!$D8,SEARCH("séance",'📅 Calendrier'!$D8)+7,2),"") | H11: =IF(LEFT('📅 Calendrier'!$D9,2)="S6",MID('📅 Calendrier'!$D9,SEARCH("séance",'📅 Calendrier'!$D9)+7,2),"") | I11: =IF(LEFT('📅 Calendrier'!$D10,2)="S6",MID('📅 Calendrier'!$D10,SEARCH("séance",'📅 Calendrier'!$D10)+7,2),"") | J11: =IF(LEFT('📅 Calendrier'!$D11,2)="S6",MID('📅 Calendrier'!$D11,SEARCH("séance",'📅 Calendrier'!$D11)+7,2),"") | K11: =IF(LEFT('📅 Calendrier'!$D13,2)="S6",MID('📅 Calendrier'!$D13,SEARCH("séance",'📅 Calendrier'!$D13)+7,2),"") | L11: =IF(LEFT('📅 Calendrier'!$D14,2)="S6",MID('📅 Calendrier'!$D14,SEARCH("séance",'📅 Calendrier'!$D14)+7,2),"") | M11: =IF(LEFT('📅 Calendrier'!$D15,2)="S6",MID('📅 Calendrier'!$D15,SEARCH("séance",'📅 Calendrier'!$D15)+7,2),"") | N11: =IF(LEFT('📅 Calendrier'!$D16,2)="S6",MID('📅 Calendrier'!$D16,SEARCH("séance",'📅 Calendrier'!$D16)+7,2),"") | O11: =IF(LEFT('📅 Calendrier'!$D17,2)="S6",MID('📅 Calendrier'!$D17,SEARCH("séance",'📅 Calendrier'!$D17)+7,2),"") | P11: =IF(LEFT('📅 Calendrier'!$D18,2)="S6",MID('📅 Calendrier'!$D18,SEARCH("séance",'📅 Calendrier'!$D18)+7,2),"") | Q11: =IF(LEFT('📅 Calendrier'!$D19,2)="S6",MID('📅 Calendrier'!$D19,SEARCH("séance",'📅 Calendrier'!$D19)+7,2),"") | R11: =IF(LEFT('📅 Calendrier'!$D21,2)="S6",MID('📅 Calendrier'!$D21,SEARCH("séance",'📅 Calendrier'!$D21)+7,2),"") | S11: =IF(LEFT('📅 Calendrier'!$D22,2)="S6",MID('📅 Calendrier'!$D22,SEARCH("séance",'📅 Calendrier'!$D22)+7,2),"") | T11: =IF(LEFT('📅 Calendrier'!$D23,2)="S6",MID('📅 Calendrier'!$D23,SEARCH("séance",'📅 Calendrier'!$D23)+7,2),"") | U11: =IF(LEFT('📅 Calendrier'!$D24,2)="S6",MID('📅 Calendrier'!$D24,SEARCH("séance",'📅 Calendrier'!$D24)+7,2),"") | V11: =IF(LEFT('📅 Calendrier'!$D25,2)="S6",MID('📅 Calendrier'!$D25,SEARCH("séance",'📅 Calendrier'!$D25)+7,2),"") | W11: =IF(LEFT('📅 Calendrier'!$D27,2)="S6",MID('📅 Calendrier'!$D27,SEARCH("séance",'📅 Calendrier'!$D27)+7,2),"") | X11: =IF(LEFT('📅 Calendrier'!$D28,2)="S6",MID('📅 Calendrier'!$D28,SEARCH("séance",'📅 Calendrier'!$D28)+7,2),"") | Y11: =IF(LEFT('📅 Calendrier'!$D29,2)="S6",MID('📅 Calendrier'!$D29,SEARCH("séance",'📅 Calendrier'!$D29)+7,2),"") | Z11: =IF(LEFT('📅 Calendrier'!$D30,2)="S6",MID('📅 Calendrier'!$D30,SEARCH("séance",'📅 Calendrier'!$D30)+7,2),"") | AA11: =IF(LEFT('📅 Calendrier'!$D31,2)="S6",MID('📅 Calendrier'!$D31,SEARCH("séance",'📅 Calendrier'!$D31)+7,2),"") | AB11: =IF(LEFT('📅 Calendrier'!$D32,2)="S6",MID('📅 Calendrier'!$D32,SEARCH("séance",'📅 Calendrier'!$D32)+7,2),"") | AC11: =IF(LEFT('📅 Calendrier'!$D33,2)="S6",MID('📅 Calendrier'!$D33,SEARCH("séance",'📅 Calendrier'!$D33)+7,2),"") | AD11: =IF(LEFT('📅 Calendrier'!$D34,2)="S6",MID('📅 Calendrier'!$D34,SEARCH("séance",'📅 Calendrier'!$D34)+7,2),"") | AE11: =IF(LEFT('📅 Calendrier'!$D36,2)="S6",MID('📅 Calendrier'!$D36,SEARCH("séance",'📅 Calendrier'!$D36)+7,2),"") | AF11: =IF(LEFT('📅 Calendrier'!$D37,2)="S6",MID('📅 Calendrier'!$D37,SEARCH("séance",'📅 Calendrier'!$D37)+7,2),"") | AG11: =IF(LEFT('📅 Calendrier'!$D38,2)="S6",MID('📅 Calendrier'!$D38,SEARCH("séance",'📅 Calendrier'!$D38)+7,2),"") | AH11: =IF(LEFT('📅 Calendrier'!$D39,2)="S6",MID('📅 Calendrier'!$D39,SEARCH("séance",'📅 Calendrier'!$D39)+7,2),"") | AI11: =IF(LEFT('📅 Calendrier'!$D40,2)="S6",MID('📅 Calendrier'!$D40,SEARCH("séance",'📅 Calendrier'!$D40)+7,2),"") | AJ11: =IF(LEFT('📅 Calendrier'!$D41,2)="S6",MID('📅 Calendrier'!$D41,SEARCH("séance",'📅 Calendrier'!$D41)+7,2),"") | AK11: =IF(LEFT('📅 Calendrier'!$D42,2)="S6",MID('📅 Calendrier'!$D42,SEARCH("séance",'📅 Calendrier'!$D42)+7,2),"") | AL11: =IF(LEFT('📅 Calendrier'!$D43,2)="S6",MID('📅 Calendrier'!$D43,SEARCH("séance",'📅 Calendrier'!$D43)+7,2),"") | AM11: =IF(LEFT('📅 Calendrier'!$D44,2)="S6",MID('📅 Calendrier'!$D44,SEARCH("séance",'📅 Calendrier'!$D44)+7,2),"")
B12: S7 · Projet nouvelle fonction | C12: =IF(LEFT('📅 Calendrier'!$D4,2)="S7",MID('📅 Calendrier'!$D4,SEARCH("séance",'📅 Calendrier'!$D4)+7,2),"") | D12: =IF(LEFT('📅 Calendrier'!$D5,2)="S7",MID('📅 Calendrier'!$D5,SEARCH("séance",'📅 Calendrier'!$D5)+7,2),"") | E12: =IF(LEFT('📅 Calendrier'!$D6,2)="S7",MID('📅 Calendrier'!$D6,SEARCH("séance",'📅 Calendrier'!$D6)+7,2),"") | F12: =IF(LEFT('📅 Calendrier'!$D7,2)="S7",MID('📅 Calendrier'!$D7,SEARCH("séance",'📅 Calendrier'!$D7)+7,2),"") | G12: =IF(LEFT('📅 Calendrier'!$D8,2)="S7",MID('📅 Calendrier'!$D8,SEARCH("séance",'📅 Calendrier'!$D8)+7,2),"") | H12: =IF(LEFT('📅 Calendrier'!$D9,2)="S7",MID('📅 Calendrier'!$D9,SEARCH("séance",'📅 Calendrier'!$D9)+7,2),"") | I12: =IF(LEFT('📅 Calendrier'!$D10,2)="S7",MID('📅 Calendrier'!$D10,SEARCH("séance",'📅 Calendrier'!$D10)+7,2),"") | J12: =IF(LEFT('📅 Calendrier'!$D11,2)="S7",MID('📅 Calendrier'!$D11,SEARCH("séance",'📅 Calendrier'!$D11)+7,2),"") | K12: =IF(LEFT('📅 Calendrier'!$D13,2)="S7",MID('📅 Calendrier'!$D13,SEARCH("séance",'📅 Calendrier'!$D13)+7,2),"") | L12: =IF(LEFT('📅 Calendrier'!$D14,2)="S7",MID('📅 Calendrier'!$D14,SEARCH("séance",'📅 Calendrier'!$D14)+7,2),"") | M12: =IF(LEFT('📅 Calendrier'!$D15,2)="S7",MID('📅 Calendrier'!$D15,SEARCH("séance",'📅 Calendrier'!$D15)+7,2),"") | N12: =IF(LEFT('📅 Calendrier'!$D16,2)="S7",MID('📅 Calendrier'!$D16,SEARCH("séance",'📅 Calendrier'!$D16)+7,2),"") | O12: =IF(LEFT('📅 Calendrier'!$D17,2)="S7",MID('📅 Calendrier'!$D17,SEARCH("séance",'📅 Calendrier'!$D17)+7,2),"") | P12: =IF(LEFT('📅 Calendrier'!$D18,2)="S7",MID('📅 Calendrier'!$D18,SEARCH("séance",'📅 Calendrier'!$D18)+7,2),"") | Q12: =IF(LEFT('📅 Calendrier'!$D19,2)="S7",MID('📅 Calendrier'!$D19,SEARCH("séance",'📅 Calendrier'!$D19)+7,2),"") | R12: =IF(LEFT('📅 Calendrier'!$D21,2)="S7",MID('📅 Calendrier'!$D21,SEARCH("séance",'📅 Calendrier'!$D21)+7,2),"") | S12: =IF(LEFT('📅 Calendrier'!$D22,2)="S7",MID('📅 Calendrier'!$D22,SEARCH("séance",'📅 Calendrier'!$D22)+7,2),"") | T12: =IF(LEFT('📅 Calendrier'!$D23,2)="S7",MID('📅 Calendrier'!$D23,SEARCH("séance",'📅 Calendrier'!$D23)+7,2),"") | U12: =IF(LEFT('📅 Calendrier'!$D24,2)="S7",MID('📅 Calendrier'!$D24,SEARCH("séance",'📅 Calendrier'!$D24)+7,2),"") | V12: =IF(LEFT('📅 Calendrier'!$D25,2)="S7",MID('📅 Calendrier'!$D25,SEARCH("séance",'📅 Calendrier'!$D25)+7,2),"") | W12: =IF(LEFT('📅 Calendrier'!$D27,2)="S7",MID('📅 Calendrier'!$D27,SEARCH("séance",'📅 Calendrier'!$D27)+7,2),"") | X12: =IF(LEFT('📅 Calendrier'!$D28,2)="S7",MID('📅 Calendrier'!$D28,SEARCH("séance",'📅 Calendrier'!$D28)+7,2),"") | Y12: =IF(LEFT('📅 Calendrier'!$D29,2)="S7",MID('📅 Calendrier'!$D29,SEARCH("séance",'📅 Calendrier'!$D29)+7,2),"") | Z12: =IF(LEFT('📅 Calendrier'!$D30,2)="S7",MID('📅 Calendrier'!$D30,SEARCH("séance",'📅 Calendrier'!$D30)+7,2),"") | AA12: =IF(LEFT('📅 Calendrier'!$D31,2)="S7",MID('📅 Calendrier'!$D31,SEARCH("séance",'📅 Calendrier'!$D31)+7,2),"") | AB12: =IF(LEFT('📅 Calendrier'!$D32,2)="S7",MID('📅 Calendrier'!$D32,SEARCH("séance",'📅 Calendrier'!$D32)+7,2),"") | AC12: =IF(LEFT('📅 Calendrier'!$D33,2)="S7",MID('📅 Calendrier'!$D33,SEARCH("séance",'📅 Calendrier'!$D33)+7,2),"") | AD12: =IF(LEFT('📅 Calendrier'!$D34,2)="S7",MID('📅 Calendrier'!$D34,SEARCH("séance",'📅 Calendrier'!$D34)+7,2),"") | AE12: =IF(LEFT('📅 Calendrier'!$D36,2)="S7",MID('📅 Calendrier'!$D36,SEARCH("séance",'📅 Calendrier'!$D36)+7,2),"") | AF12: =IF(LEFT('📅 Calendrier'!$D37,2)="S7",MID('📅 Calendrier'!$D37,SEARCH("séance",'📅 Calendrier'!$D37)+7,2),"") | AG12: =IF(LEFT('📅 Calendrier'!$D38,2)="S7",MID('📅 Calendrier'!$D38,SEARCH("séance",'📅 Calendrier'!$D38)+7,2),"") | AH12: =IF(LEFT('📅 Calendrier'!$D39,2)="S7",MID('📅 Calendrier'!$D39,SEARCH("séance",'📅 Calendrier'!$D39)+7,2),"") | AI12: =IF(LEFT('📅 Calendrier'!$D40,2)="S7",MID('📅 Calendrier'!$D40,SEARCH("séance",'📅 Calendrier'!$D40)+7,2),"") | AJ12: =IF(LEFT('📅 Calendrier'!$D41,2)="S7",MID('📅 Calendrier'!$D41,SEARCH("séance",'📅 Calendrier'!$D41)+7,2),"") | AK12: =IF(LEFT('📅 Calendrier'!$D42,2)="S7",MID('📅 Calendrier'!$D42,SEARCH("séance",'📅 Calendrier'!$D42)+7,2),"") | AL12: =IF(LEFT('📅 Calendrier'!$D43,2)="S7",MID('📅 Calendrier'!$D43,SEARCH("séance",'📅 Calendrier'!$D43)+7,2),"") | AM12: =IF(LEFT('📅 Calendrier'!$D44,2)="S7",MID('📅 Calendrier'!$D44,SEARCH("séance",'📅 Calendrier'!$D44)+7,2),"")
B13: ⏳ Tampons (rattrapage) | C13: =IF(LEFT('📅 Calendrier'!$D4,1)="⏳","⏳","") | D13: =IF(LEFT('📅 Calendrier'!$D5,1)="⏳","⏳","") | E13: =IF(LEFT('📅 Calendrier'!$D6,1)="⏳","⏳","") | F13: =IF(LEFT('📅 Calendrier'!$D7,1)="⏳","⏳","") | G13: =IF(LEFT('📅 Calendrier'!$D8,1)="⏳","⏳","") | H13: =IF(LEFT('📅 Calendrier'!$D9,1)="⏳","⏳","") | I13: =IF(LEFT('📅 Calendrier'!$D10,1)="⏳","⏳","") | J13: =IF(LEFT('📅 Calendrier'!$D11,1)="⏳","⏳","") | K13: =IF(LEFT('📅 Calendrier'!$D13,1)="⏳","⏳","") | L13: =IF(LEFT('📅 Calendrier'!$D14,1)="⏳","⏳","") | M13: =IF(LEFT('📅 Calendrier'!$D15,1)="⏳","⏳","") | N13: =IF(LEFT('📅 Calendrier'!$D16,1)="⏳","⏳","") | O13: =IF(LEFT('📅 Calendrier'!$D17,1)="⏳","⏳","") | P13: =IF(LEFT('📅 Calendrier'!$D18,1)="⏳","⏳","") | Q13: =IF(LEFT('📅 Calendrier'!$D19,1)="⏳","⏳","") | R13: =IF(LEFT('📅 Calendrier'!$D21,1)="⏳","⏳","") | S13: =IF(LEFT('📅 Calendrier'!$D22,1)="⏳","⏳","") | T13: =IF(LEFT('📅 Calendrier'!$D23,1)="⏳","⏳","") | U13: =IF(LEFT('📅 Calendrier'!$D24,1)="⏳","⏳","") | V13: =IF(LEFT('📅 Calendrier'!$D25,1)="⏳","⏳","") | W13: =IF(LEFT('📅 Calendrier'!$D27,1)="⏳","⏳","") | X13: =IF(LEFT('📅 Calendrier'!$D28,1)="⏳","⏳","") | Y13: =IF(LEFT('📅 Calendrier'!$D29,1)="⏳","⏳","") | Z13: =IF(LEFT('📅 Calendrier'!$D30,1)="⏳","⏳","") | AA13: =IF(LEFT('📅 Calendrier'!$D31,1)="⏳","⏳","") | AB13: =IF(LEFT('📅 Calendrier'!$D32,1)="⏳","⏳","") | AC13: =IF(LEFT('📅 Calendrier'!$D33,1)="⏳","⏳","") | AD13: =IF(LEFT('📅 Calendrier'!$D34,1)="⏳","⏳","") | AE13: =IF(LEFT('📅 Calendrier'!$D36,1)="⏳","⏳","") | AF13: =IF(LEFT('📅 Calendrier'!$D37,1)="⏳","⏳","") | AG13: =IF(LEFT('📅 Calendrier'!$D38,1)="⏳","⏳","") | AH13: =IF(LEFT('📅 Calendrier'!$D39,1)="⏳","⏳","") | AI13: =IF(LEFT('📅 Calendrier'!$D40,1)="⏳","⏳","") | AJ13: =IF(LEFT('📅 Calendrier'!$D41,1)="⏳","⏳","") | AK13: =IF(LEFT('📅 Calendrier'!$D42,1)="⏳","⏳","") | AL13: =IF(LEFT('📅 Calendrier'!$D43,1)="⏳","⏳","") | AM13: =IF(LEFT('📅 Calendrier'!$D44,1)="⏳","⏳","")
B14: ⚠ Imprévus (saisis au Calendrier) | C14: =IF('📅 Calendrier'!$G4<>"","⚠","") | D14: =IF('📅 Calendrier'!$G5<>"","⚠","") | E14: =IF('📅 Calendrier'!$G6<>"","⚠","") | F14: =IF('📅 Calendrier'!$G7<>"","⚠","") | G14: =IF('📅 Calendrier'!$G8<>"","⚠","") | H14: =IF('📅 Calendrier'!$G9<>"","⚠","") | I14: =IF('📅 Calendrier'!$G10<>"","⚠","") | J14: =IF('📅 Calendrier'!$G11<>"","⚠","") | K14: =IF('📅 Calendrier'!$G13<>"","⚠","") | L14: =IF('📅 Calendrier'!$G14<>"","⚠","") | M14: =IF('📅 Calendrier'!$G15<>"","⚠","") | N14: =IF('📅 Calendrier'!$G16<>"","⚠","") | O14: =IF('📅 Calendrier'!$G17<>"","⚠","") | P14: =IF('📅 Calendrier'!$G18<>"","⚠","") | Q14: =IF('📅 Calendrier'!$G19<>"","⚠","") | R14: =IF('📅 Calendrier'!$G21<>"","⚠","") | S14: =IF('📅 Calendrier'!$G22<>"","⚠","") | T14: =IF('📅 Calendrier'!$G23<>"","⚠","") | U14: =IF('📅 Calendrier'!$G24<>"","⚠","") | V14: =IF('📅 Calendrier'!$G25<>"","⚠","") | W14: =IF('📅 Calendrier'!$G27<>"","⚠","") | X14: =IF('📅 Calendrier'!$G28<>"","⚠","") | Y14: =IF('📅 Calendrier'!$G29<>"","⚠","") | Z14: =IF('📅 Calendrier'!$G30<>"","⚠","") | AA14: =IF('📅 Calendrier'!$G31<>"","⚠","") | AB14: =IF('📅 Calendrier'!$G32<>"","⚠","") | AC14: =IF('📅 Calendrier'!$G33<>"","⚠","") | AD14: =IF('📅 Calendrier'!$G34<>"","⚠","") | AE14: =IF('📅 Calendrier'!$G36<>"","⚠","") | AF14: =IF('📅 Calendrier'!$G37<>"","⚠","") | AG14: =IF('📅 Calendrier'!$G38<>"","⚠","") | AH14: =IF('📅 Calendrier'!$G39<>"","⚠","") | AI14: =IF('📅 Calendrier'!$G40<>"","⚠","") | AJ14: =IF('📅 Calendrier'!$G41<>"","⚠","") | AK14: =IF('📅 Calendrier'!$G42<>"","⚠","") | AL14: =IF('📅 Calendrier'!$G43<>"","⚠","") | AM14: =IF('📅 Calendrier'!$G44<>"","⚠","")
B16: Une case = 1 semaine (1 séance de 1 h 30) ; le numéro = n° de séance dans la séquence. Imprévu : onglet 📅 Calendrier, colonne « ⚠ Imprévu ? » (ou la grande fenêtre de la version macros) — tout se recalcule immédiatement.

Sheet 📚 Référentiel Cycle 4
A1: RÉFÉRENTIEL DE COMPÉTENCES — TECHNOLOGIE CYCLE 4
A2: 9 compétences × 3 niveaux (5e / 4e / 3e) — programme 2024 · vision complète du cycle pour situer la 4e
F3: ◀ Accueil
A4: Code | B4: Niveau | C4: Compétence / sous-compétence (intitulé officiel 2024) | D4: Thème | E4: Domaine(s) socle | F4: Évaluable
A5: C1 | B5: — | C5: Décrire les liens entre usages et évolutions technologiques des objets et des systèmes techniques | D5: Thème 1 : Les objets et les systèmes techniques : leurs usages et leurs interactions à découvrir et à analyser | E5: D2, D3, D4, D5 | F5: Oui
A6: 5e_C1.1 | B6: 5e | C6: Collecter, trier et analyser des données. | D6: Thème 1 | E6: D2, D4 | F6: Oui
A7: 5e_C1.2 | B7: 5e | C7: Comparer des principes techniques pour une même fonction technique. | D7: Thème 1 | E7: D2, D4 | F7: Oui
A8: 5e_C1.3 | B8: 5e | C8: Décrire le rôle des systèmes d’information dans le partage d’information. | D8: Thème 1 | E8: D2, D5 | F8: Oui
A9: 5e_C1.4 | B9: 5e | C9: Recenser des données, les identifier, les classer, les représenter, les stocker, les retrouver dans une arborescence. | D9: Thème 1 | E9: D2 | F9: Oui
A10: 5e_C1.5 | B10: 5e | C10: Identifier des règles permettant de sécuriser un environnement numérique (bases de la cybersécurité) et des règles de respect de la propriété intellectuelle. | D10: Thème 1 | E10: D3 | F10: Oui
A11: 5e_C1.6 | B11: 5e | C11: Appréhender la responsabilité de chacun dans les dérives (cyberviolence, atteinte à la vie privée, aux données personnelles, usurpation d’identité). | D11: Thème 1 | E11: D3 | F11: Oui
A12: 4e_C1.1 | B12: 4e | C12: Mettre en relation les OST avec leurs usages. | D12: Thème 1 | E12: D4, D5 | F12: Oui
A13: 4e_C1.2 | B13: 4e | C13: Identifier les avantages et les inconvénients associés aux évolutions technologiques et informatiques. | D13: Thème 1 | E13: D3, D4, D5 | F13: Oui
A14: 4e_C1.3 | B14: 4e | C14: Justifier l’évolution d’un OST pour répondre à l’évolution des besoins. | D14: Thème 1 | E14: D3, D4, D5 | F14: Oui
A15: 4e_C1.4 | B15: 4e | C15: Identifier et appliquer les règles pour un usage raisonné des objets communicants et des environnements numériques (propriété intellectuelle, identité numérique, témoins de connexion, géolocalisation). | D15: Thème 1 | E15: D1.3, D2, D3, D4 | F15: Oui
... A127: 3e_C9.2 | B127: 3e | C127: Réaliser et mettre au point un programme commandant un système réel incluant une interaction entre un humain et une machine. | D127: Thème 3 | E127: D1.3, D2, D4 | F127: Oui
A129: 114 sous-compétences listées · Source : BO n°9 du 29/02/2024 · codes Nathan (éd. 2024).

Sheet 📗 Référentiel 4e
A1: RÉFÉRENTIEL DE COMPÉTENCES — TECHNOLOGIE 4e
A2: Les compétences parentes C1 → C9 et leurs déclinaisons du niveau 4e — celles travaillées dans ce classeur
F3: ◀ Accueil
A4: Code | B4: Niveau | C4: Compétence / sous-compétence (intitulé officiel 2024) | D4: Thème | E4: Domaine(s) socle | F4: Évaluable
A5: C1 | B5: — | C5: Décrire les liens entre usages et évolutions technologiques des objets et des systèmes techniques | D5: Thème 1 : Les objets et les systèmes techniques : leurs usages et leurs interactions à découvrir et à analyser | E5: D2, D3, D4, D5 | F5: Oui
A6: 4e_C1.1 | B6: 4e | C6: Mettre en relation les OST avec leurs usages. | D6: Thème 1 | E6: D4, D5 | F6: Oui
A7: 4e_C1.2 | B7: 4e | C7: Identifier les avantages et les inconvénients associés aux évolutions technologiques et informatiques. | D7: Thème 1 | E7: D3, D4, D5 | F7: Oui
A8: 4e_C1.3 | B8: 4e | C8: Justifier l’évolution d’un OST pour répondre à l’évolution des besoins. | D8: Thème 1 | E8: D3, D4, D5 | F8: Oui
A9: 4e_C1.4 | B9: 4e | C9: Identifier et appliquer les règles pour un usage raisonné des objets communicants et des environnements numériques (propriété intellectuelle, identité numérique, témoins de connexion, géolocalisation). | D9: Thème 1 | E9: D1.3, D2, D3, D4 | F9: Oui
A10: C2 | B10: — | C10: Décrire les interactions entre un objet ou un système technique, son environnement et les utilisateurs | D10: Thème 1 | E10: D4, D5 | F10: Oui
A11: 4e_C2.1 | B11: 4e | C11: Décrire l’expérience de l’utilisateur (ressenti et facilité d’usage) d’un OST en partant du langage naturel (texte, croquis) pour aboutir aux schémas, graphiques, algorithmes. | D11: Thème 1 | E11: D1.3, D4, D5 | F11: Oui
A12: 4e_C2.2 | B12: 4e | C12: Repérer et expliquer les contraintes, exigences prises en compte (sécurité, incidences environnementales, formes et fonctions, ergonomie, qualité, fiabilité) pour répondre aux attentes des utilisateurs. | D12: Thème 1 | E12: D3, D4, D5 | F12: Oui
A13: C3 | B13: — | C13: Caractériser et choisir un objet ou un système technique selon différents critères | D13: Thème 1 | E13: D1.3, D2, D3, D4, D5 | F13: Oui
A14: 4e_C3.1 | B14: 4e | C14: Identifier les caractéristiques à prendre en compte dans le choix d’un OST en vue de répondre à un besoin. | D14: Thème 1 | E14: D3, D4, D5 | F14: Oui
A15: 4e_C3.2 | B15: 4e | C15: Comparer qualitativement et/ou quantitativement (incidences environnementales, bilan carbone, efficacité énergétique) plusieurs OST répondant au même besoin et arrêter un choix. | D15: Thème 1 | E15: D1.3, D2, D3, D4, D5 | F15: Oui
... A51: 4e_C9.3 | B51: 4e | C51: Réaliser et mettre au point un programme commandant un système réel incluant éventuellement une interaction entre un humain et une machine. | D51: Thème 3 | E51: D1.3, D2, D4 | F51: Oui
A53: 38 sous-compétences listées · Source : BO n°9 du 29/02/2024 · codes Nathan (éd. 2024).

Sheet 🧭 Progression
A1: PROGRESSION ANNUELLE 4e — 2026-2027 · 7 séquences · base : Référentiel 2024 (+ correctif C4.3)
K2: ◀ Accueil
A3: N° | B3: Période | C3: Titre | D3: Problématique | E3: Thème | F3: Codes 2024 | G3: Séances | H3: Répartition 🏫 / 🏠 / 🔁 | I3: Ressources en ligne (dépôt) | J3: Cahier Nathan 4e (repères) | K3: IA responsable | L3: Début (AUTO) | M3: Fin (AUTO)
A4: 1 | B4: P1 | C4: Des objets qui évoluent : usages, avantages, limites | D4: Pourquoi et comment les objets techniques évoluent-ils dans le temps ? | E4: Thème 1 | F4: 4e_C1.1, C1.2, C1.3 | G4: 3 | H4: Séances 1-2 🏫 (frises, familles/lignées) · 3 🔁 (recherche doc à la maison, argumentaire en classe) | I4: 🔜 À produire (Thème 1) | J4: Prob. 1 p.7-12 (évolution d'un objet : aspirateurs, avions, conservation des aliments) | K4: IA Thème 1 | L4: =IFERROR(INDEX('📅 Calendrier'!$A$4:$A$54,MATCH("S1 · séance 1",'📅 Calendrier'!$D$4:$D$54,0))&" ("&INDEX('📅 Calendrier'!$B$4:$B$54,MATCH("S1 · séance 1",'📅 Calendrier'!$D$4:$D$54,0))&")","⚠ hors année !") | M4: =IFERROR(INDEX('📅 Calendrier'!$A$4:$A$54,MATCH("S1 · séance 3",'📅 Calendrier'!$D$4:$D$54,0))&" ("&INDEX('📅 Calendrier'!$B$4:$B$54,MATCH("S1 · séance 3",'📅 Calendrier'!$D$4:$D$54,0))&")","⚠ hors année !")
A5: 2 | B5: P1 | C5: Naviguer en sécurité : identité numérique et usage raisonné | D5: Quelles traces je laisse en ligne, et comment les maîtriser ? | E5: Thème 1 | F5: 4e_C1.4 | G5: 2 | H5: Séance 1 🏫 (étude de cas) · 2 🔁 (audit de ses propres réglages à la maison, bilan en classe) | I5: 🔜 À produire (Thème 1) | J5: Vers Pix — Domaine 4 Protection et sécurité (fin du cahier) · rappels Prob. 1 | K5: IA Thème 1 | L5: =IFERROR(INDEX('📅 Calendrier'!$A$4:$A$54,MATCH("S2 · séance 1",'📅 Calendrier'!$D$4:$D$54,0))&" ("&INDEX('📅 Calendrier'!$B$4:$B$54,MATCH("S2 · séance 1",'📅 Calendrier'!$D$4:$D$54,0))&")","⚠ hors année !") | M5: =IFERROR(INDEX('📅 Calendrier'!$A$4:$A$54,MATCH("S2 · séance 2",'📅 Calendrier'!$D$4:$D$54,0))&" ("&INDEX('📅 Calendrier'!$B$4:$B$54,MATCH("S2 · séance 2",'📅 Calendrier'!$D$4:$D$54,0))&")","⚠ hors année !")
A6: 3 | B6: P1/P2 | C6: Concevoir pour l'utilisateur : ergonomie et choix argumenté | D6: Comment choisir un objet technique en croisant plusieurs critères (usage, mesure, environnement) ? | E6: Thème 1 | F6: 4e_C2.1, C2.2, C3.1, C3.2, C3.3 | G6: 4 | H6: Séances 1-2 🏫 (expérience utilisateur, protocole de mesure au multimètre) · 3 🔁 (comparatif à finir) · 4 🏫 (choix argumenté + éval.) | I6: 🔜 À produire (Thème 1) | J6: Prob. 11 p.79-84 (mesurer les performances) · Prob. 10 p.73-78 (impact environnemental) | K6: IA Thème 1 | L6: =IFERROR(INDEX('📅 Calendrier'!$A$4:$A$54,MATCH("S3 · séance 1",'📅 Calendrier'!$D$4:$D$54,0))&" ("&INDEX('📅 Calendrier'!$B$4:$B$54,MATCH("S3 · séance 1",'📅 Calendrier'!$D$4:$D$54,0))&")","⚠ hors année !") | M6: =IFERROR(INDEX('📅 Calendrier'!$A$4:$A$54,MATCH("S3 · séance 4",'📅 Calendrier'!$D$4:$D$54,0))&" ("&INDEX('📅 Calendrier'!$B$4:$B$54,MATCH("S3 · séance 4",'📅 Calendrier'!$D$4:$D$54,0))&")","⚠ hors année !")
A7: 4 | B7: P2/P3 | C7: Automatiser le jardin connecté : chaîne d'énergie et d'information | D7: Comment un système automatisé peut-il réguler l'arrosage d'un jardin ? | E7: Thème 2 | F7: 4e_C4.1, C4.2, C4.4, C4.5, C4.6 | G7: 5 | H7: Séance 1 🏫 (analyse du système) · 2-3 🏫 (chaînes, transformations, capteurs Arduino) · 4 🔁 (données CSV maison) · 5 🏠 QCM + 🏫 éval. | I7: ✅ Partiel : QCM « Jardin connecté », « Automatisation », « eCall » (existants) · 🔜 séquence îlot 4e_C4 (Fable) | J7: Prob. 5 p.37-44 (chaîne d'énergie) · Prob. 3 p.21-28 (fonctionnement) · Prob. 7 p.53-58 (automatiser) | K7: Fable (Th. 2) | L7: =IFERROR(INDEX('📅 Calendrier'!$A$4:$A$54,MATCH("S4 · séance 1",'📅 Calendrier'!$D$4:$D$54,0))&" ("&INDEX('📅 Calendrier'!$B$4:$B$54,MATCH("S4 · séance 1",'📅 Calendrier'!$D$4:$D$54,0))&")","⚠ hors année !") | M7: =IFERROR(INDEX('📅 Calendrier'!$A$4:$A$54,MATCH("S4 · séance 5",'📅 Calendrier'!$D$4:$D$54,0))&" ("&INDEX('📅 Calendrier'!$B$4:$B$54,MATCH("S4 · séance 5",'📅 Calendrier'!$D$4:$D$54,0))&")","⚠ hors année !")
A8: 5 | B8: P3/P4 | C8: Objets connectés en réseau : adresse IP et communication | D8: Comment ajouter un objet connecté à un réseau local et le faire dialoguer ? | E8: Thème 2 | F8: 4e_C4.7, C4.8, C4.9 | G8: 4 | H8: Séance 1 🏫 (rappels 5e + adresse IP) · 2 🏫 (simulateur de réseau) · 3 🔁 (IoT VittaScience) · 4 🏠 QCM + 🏫 bilan | I8: ✅ Partiel : QCM réseaux existant (40 q IP/NFC/RFID/Zigbee) · 🔜 séquence (Fable) | J8: Prob. 2 p.13-20 (connecter un objet à un réseau) · Point méthode adresse IP | K8: Fable (Th. 2) | L8: =IFERROR(INDEX('📅 Calendrier'!$A$4:$A$54,MATCH("S5 · séance 1",'📅 Calendrier'!$D$4:$D$54,0))&" ("&INDEX('📅 Calendrier'!$B$4:$B$54,MATCH("S5 · séance 1",'📅 Calendrier'!$D$4:$D$54,0))&")","⚠ hors année !") | M8: =IFERROR(INDEX('📅 Calendrier'!$A$4:$A$54,MATCH("S5 · séance 4",'📅 Calendrier'!$D$4:$D$54,0))&" ("&INDEX('📅 Calendrier'!$B$4:$B$54,MATCH("S5 · séance 4",'📅 Calendrier'!$D$4:$D$54,0))&")","⚠ hors année !")
A9: 6 | B9: P4 | C9: Réparer sans notice : diagnostic, pièce et programme | D9: Comment diagnostiquer une panne sans protocole fourni, remplacer la pièce et corriger le programme ? | E9: Thème 2 | F9: 4e_C5.1, C5.2, C5.3 + 4e_C6.1, C6.2, C6.3 + 4e_C4.3 (rattaché ici — correctif) | G9: 4 | H9: Séances 1-2 🏫 (diagnostic, hypothèses, remplacement — forme de la pièce ↔ procédé) · 3 🏫 (programme : compléter/corriger) · 4 🔁 (rapport + QCM maison) | I9: ✅ Partiel : QCM « Éclairage automatique », « Algorigrammes domotique » (existants) · 🔜 séquence (Fable, sur le modèle 3e « SOS station ») | J9: Prob. 8 p.61-66 (prolonger la durée de vie) · Prob. 6 p.45-52 (programmer) · Prob. 4 p.29-36 (matériaux et formes → C4.3) | K9: Fable (Th. 2) | L9: =IFERROR(INDEX('📅 Calendrier'!$A$4:$A$54,MATCH("S6 · séance 1",'📅 Calendrier'!$D$4:$D$54,0))&" ("&INDEX('📅 Calendrier'!$B$4:$B$54,MATCH("S6 · séance 1",'📅 Calendrier'!$D$4:$D$54,0))&")","⚠ hors année !") | M9: =IFERROR(INDEX('📅 Calendrier'!$A$4:$A$54,MATCH("S6 · séance 4",'📅 Calendrier'!$D$4:$D$54,0))&" ("&INDEX('📅 Calendrier'!$B$4:$B$54,MATCH("S6 · séance 4",'📅 Calendrier'!$D$4:$D$54,0))&")","⚠ hors année !")
A10: 7 | B10: P4/P5 | C10: Projet : ajouter une nouvelle fonction à un objet connecté | D10: Comment concevoir, réaliser et programmer une nouvelle fonctionnalité ? | E10: Thème 3 | F10: 4e_C7.1→C7.8, C8.1→C8.3, C9.1→C9.3 | G10: 6 | H10: Séances 1-5 🏫 (démarche de projet : cahier des charges → prototype → tests) · entre séances 🏠 (croquis, recherches) · 6 🏫 revue de projet | I10: 🔜 À produire (Thème 3) | J10: Prob. 9 p.67-72 (réaliser/modifier un prototype) · Prob. 10 p.73-78 · Prob. 6 p.45-52 | K10: IA Thème 3 | L10: =IFERROR(INDEX('📅 Calendrier'!$A$4:$A$54,MATCH("S7 · séance 1",'📅 Calendrier'!$D$4:$D$54,0))&" ("&INDEX('📅 Calendrier'!$B$4:$B$54,MATCH("S7 · séance 1",'📅 Calendrier'!$D$4:$D$54,0))&")","⚠ hors année !") | M10: =IFERROR(INDEX('📅 Calendrier'!$A$4:$A$54,MATCH("S7 · séance 6",'📅 Calendrier'!$D$4:$D$54,0))&" ("&INDEX('📅 Calendrier'!$B$4:$B$54,MATCH("S7 · séance 6",'📅 Calendrier'!$D$4:$D$54,0))&")","⚠ hors année !")
F11: Total séances planifiées : | G11: =SUM(G4:G10) | H11: + 9 semaines tampon = 37 semaines (voir Calendrier) · colonnes AUTO recalculées selon les imprévus

Sheet S1
A1: GÉNÉRATEUR DE SÉQUENCE 2024 — S1 · Des objets qui évoluent : usages, avantages, limites
A2: Thème 1 · P1 · 3 séances de 1 h 30 · Responsable : IA Thème 1 · CANEVAS À REMPLIR par IA Thème 1 (règle : l'IA du thème est seule à modifier)
E3: ◀ Progression | F3: ◀ Accueil
A4: Problématique | B4: Pourquoi et comment les objets techniques évoluent-ils dans le temps ?
A5: Situation déclenchante | B5: ⚠ À compléter par IA Thème 1 (canevas pré-rempli par Fable — codes, problématique et repères Nathan posés).
A6: Prérequis | B6: —
A7: Éléments pour la synthèse (objectifs) | B7: ⚠ À compléter par IA Thème 1 (canevas pré-rempli par Fable — codes, problématique et repères Nathan posés).
A8: Piste d'évaluation | B8: Frise/argumentaire sur l'évolution d'un objet
A9: Domaines du socle mobilisés | B9: D3, D4, D5 (détail par code ci-dessous)
A10: CRCN — compétences numériques (Pix) | B10: 1.1 Mener une recherche (Niv. 2-3) · 1.3 Traiter des données (Niv. 2)
A11: Versions 🅰 / 🅱 / 🅲 | B11: ⚠ À compléter par IA Thème 1 (canevas pré-rempli par Fable — codes, problématique et repères Nathan posés).
A12: Liens EPI / parcours | B12: ⚠ À compléter par IA Thème 1 (canevas pré-rempli par Fable — codes, problématique et repères Nathan posés).
A13: Cahier Nathan 4e | B13: Prob. 1 p.7-12 (évolution d'un objet : aspirateurs, avions, conservation des aliments)
A14: Ressources en ligne | B14: 🔜 À produire (Thème 1)
A16: Compétences du programme 2024
A17: Code | B17: Intitulé officiel | C17: Domaines du socle | D17: Travaillée en | E17: Évaluation LSU
A18: 4e_C1.1 | B18: Mettre en relation les OST avec leurs usages. | C18: D4, D5 | D18: — | E18: → LSU
A19: 4e_C1.2 | B19: Identifier les avantages et les inconvénients associés aux évolutions technologiques et informatiques. | C19: D3, D4, D5 | D19: — | E19: → LSU
A20: 4e_C1.3 | B20: Justifier l’évolution d’un OST pour répondre à l’évolution des besoins. | C20: D3, D4, D5 | D20: — | E20: → LSU
A22: Déroulé, séance par séance — avec cahier de texte Pronote prêt à coller
A23: ■ Séance 1 — semaine S01 — — — [titre de la séance 1 — à compléter]
A24: Question directrice | B24: [question directrice]
A25: Activités & supports | B25: [activités — repères Nathan : Prob. 1 p.7-12 (évolution d'un objet : aspirateurs, avions, conservation des aliments)]
A26: Démarche / organisation | B26: [démarche]
A27: Bilan / trace écrite | B27: [trace écrite]
A28: 📋 CAHIER DE TEXTE Contenu de la séance 👆 CLIC = copier pour Pronote | B28: [Cahier de texte — contenu de la séance 1 : à rédiger par IA Thème 1 — phrase(s) prêtes à coller dans Pronote.]
A29: 📋 CAHIER DE TEXTE Travail à faire 👆 CLIC = copier pour Pronote | B29: [Cahier de texte — travail à faire : à rédiger — support (lien ou pages Nathan), durée estimée, « faisable sur téléphone » si c'est le cas.]
A30: Suivi enseignant | B30: Fait le : ____________ | C30: Report / aléa / remarques :
A32: ■ Séance 2 — semaine S02 — — — [titre de la séance 2 — à compléter]
A33: Question directrice | B33: [question directrice]
A34: Activités & supports | B34: [activités — repères Nathan : Prob. 1 p.7-12 (évolution d'un objet : aspirateurs, avions, conservation des aliments)]
A35: Démarche / organisation | B35: [démarche]
A36: Bilan / trace écrite | B36: [trace écrite]
A37: 📋 CAHIER DE TEXTE Contenu de la séance 👆 CLIC = copier pour Pronote | B37: [Cahier de texte — contenu de la séance 2 : à rédiger par IA Thème 1 — phrase(s) prêtes à coller dans Pronote.]
A38: 📋 CAHIER DE TEXTE Travail à faire 👆 CLIC = copier pour Pronote | B38: [Cahier de texte — travail à faire : à rédiger — support (lien ou pages Nathan), durée estimée, « faisable sur téléphone » si c'est le cas.]
A39: Suivi enseignant | B39: Fait le : ____________ | C39: Report / aléa / remarques :
A41: ■ Séance 3 — semaine S03 — — — [titre de la séance 3 — à compléter]
A42: Question directrice | B42: [question directrice]
A43: Activités & supports | B43: [activités — repères Nathan : Prob. 1 p.7-12 (évolution d'un objet : aspirateurs, avions, conservation des aliments)]
A44: Démarche / organisation | B44: [démarche]
A45: Bilan / trace écrite | B45: [trace écrite]
A46: 📋 CAHIER DE TEXTE Contenu de la séance 👆 CLIC = copier pour Pronote | B46: [Cahier de texte — contenu de la séance 3 : à rédiger par IA Thème 1 — phrase(s) prêtes à coller dans Pronote.]
A47: 📋 CAHIER DE TEXTE Travail à faire 👆 CLIC = copier pour Pronote | B47: [Cahier de texte — travail à faire : à rédiger — support (lien ou pages Nathan), durée estimée, « faisable sur téléphone » si c'est le cas.]
A48: Suivi enseignant | B48: Fait le : ____________ | C48: Report / aléa / remarques :

Sheet S2
A1: GÉNÉRATEUR DE SÉQUENCE 2024 — S2 · Naviguer en sécurité : identité numérique et usage raisonné
A2: Thème 1 · P1 · 2 séances de 1 h 30 · Responsable : IA Thème 1 · CANEVAS À REMPLIR par IA Thème 1 (règle : l'IA du thème est seule à modifier)
E3: ◀ Progression | F3: ◀ Accueil
A4: Problématique | B4: Quelles traces je laisse en ligne, et comment les maîtriser ?
A5: Situation déclenchante | B5: ⚠ À compléter par IA Thème 1 (canevas pré-rempli par Fable — codes, problématique et repères Nathan posés).
A6: Prérequis | B6: —
A7: Éléments pour la synthèse (objectifs) | B7: ⚠ À compléter par IA Thème 1 (canevas pré-rempli par Fable — codes, problématique et repères Nathan posés).
A8: Piste d'évaluation | B8: Étude de cas commentée
A9: Domaines du socle mobilisés | B9: D1.3, D2, D3, D4 (détail par code ci-dessous)
A10: CRCN — compétences numériques (Pix) | B10: 4.1 Sécuriser (Niv. 2-3) · 4.2 Protéger les données personnelles (Niv. 2-3) · 2.4 S'insérer dans le monde numérique (Niv. 2)
A11: Versions 🅰 / 🅱 / 🅲 | B11: ⚠ À compléter par IA Thème 1 (canevas pré-rempli par Fable — codes, problématique et repères Nathan posés).
A12: Liens EPI / parcours | B12: ⚠ À compléter par IA Thème 1 (canevas pré-rempli par Fable — codes, problématique et repères Nathan posés).
A13: Cahier Nathan 4e | B13: Vers Pix — Domaine 4 Protection et sécurité (fin du cahier) · rappels Prob. 1
A14: Ressources en ligne | B14: 🔜 À produire (Thème 1)
A16: Compétences du programme 2024
A17: Code | B17: Intitulé officiel | C17: Domaines du socle | D17: Travaillée en | E17: Évaluation LSU
A18: 4e_C1.4 | B18: Identifier et appliquer les règles pour un usage raisonné des objets communicants et des environnements numériques (propriété intellectuelle, identité numérique, témoins de connexion, géolocalisation). | C18: D1.3, D2, D3, D4 | D18: — | E18: → LSU
A20: Déroulé, séance par séance — avec cahier de texte Pronote prêt à coller
A21: ■ Séance 1 — semaine S04 — — — [titre de la séance 1 — à compléter]
A22: Question directrice | B22: [question directrice]
A23: Activités & supports | B23: [activités — repères Nathan : Vers Pix — Domaine 4 Protection et sécurité (fin du cahier) · rappels Prob. 1]
A24: Démarche / organisation | B24: [démarche]
A25: Bilan / trace écrite | B25: [trace écrite]
A26: 📋 CAHIER DE TEXTE Contenu de la séance 👆 CLIC = copier pour Pronote | B26: [Cahier de texte — contenu de la séance 1 : à rédiger par IA Thème 1 — phrase(s) prêtes à coller dans Pronote.]
A27: 📋 CAHIER DE TEXTE Travail à faire 👆 CLIC = copier pour Pronote | B27: [Cahier de texte — travail à faire : à rédiger — support (lien ou pages Nathan), durée estimée, « faisable sur téléphone » si c'est le cas.]
A28: Suivi enseignant | B28: Fait le : ____________ | C28: Report / aléa / remarques :
A30: ■ Séance 2 — semaine S05 — — — [titre de la séance 2 — à compléter]
A31: Question directrice | B31: [question directrice]
A32: Activités & supports | B32: [activités — repères Nathan : Vers Pix — Domaine 4 Protection et sécurité (fin du cahier) · rappels Prob. 1]
A33: Démarche / organisation | B33: [démarche]
A34: Bilan / trace écrite | B34: [trace écrite]
A35: 📋 CAHIER DE TEXTE Contenu de la séance 👆 CLIC = copier pour Pronote | B35: [Cahier de texte — contenu de la séance 2 : à rédiger par IA Thème 1 — phrase(s) prêtes à coller dans Pronote.]
A36: 📋 CAHIER DE TEXTE Travail à faire 👆 CLIC = copier pour Pronote | B36: [Cahier de texte — travail à faire : à rédiger — support (lien ou pages Nathan), durée estimée, « faisable sur téléphone » si c'est le cas.]
A37: Suivi enseignant | B37: Fait le : ____________ | C37: Report / aléa / remarques :

Sheet S3
A1: GÉNÉRATEUR DE SÉQUENCE 2024 — S3 · Concevoir pour l'utilisateur : ergonomie et choix argumenté
A2: Thème 1 · P1/P2 · 4 séances de 1 h 30 · Responsable : IA Thème 1 · CANEVAS À REMPLIR par IA Thème 1 (règle : l'IA du thème est seule à modifier)
E3: ◀ Progression | F3: ◀ Accueil
A4: Problématique | B4: Comment choisir un objet technique en croisant plusieurs critères (usage, mesure, environnement) ?
A5: Situation déclenchante | B5: ⚠ À compléter par IA Thème 1 (canevas pré-rempli par Fable — codes, problématique et repères Nathan posés).
A6: Prérequis | B6: —
A7: Éléments pour la synthèse (objectifs) | B7: ⚠ À compléter par IA Thème 1 (canevas pré-rempli par Fable — codes, problématique et repères Nathan posés).
A8: Piste d'évaluation | B8: Comparatif multicritère + protocole de mesure
A9: Domaines du socle mobilisés | B9: D1.3, D2, D3, D4, D5 (détail par code ci-dessous)
A10: CRCN — compétences numériques (Pix) | B10: 1.3 Traiter des données (Niv. 2 : comparatif au tableur)
A11: Versions 🅰 / 🅱 / 🅲 | B11: ⚠ À compléter par IA Thème 1 (canevas pré-rempli par Fable — codes, problématique et repères Nathan posés).
A12: Liens EPI / parcours | B12: ⚠ À compléter par IA Thème 1 (canevas pré-rempli par Fable — codes, problématique et repères Nathan posés).
A13: Cahier Nathan 4e | B13: Prob. 11 p.79-84 (mesurer les performances) · Prob. 10 p.73-78 (impact environnemental)
A14: Ressources en ligne | B14: 🔜 À produire (Thème 1)
A16: Compétences du programme 2024
A17: Code | B17: Intitulé officiel | C17: Domaines du socle | D17: Travaillée en | E17: Évaluation LSU
A18: 4e_C2.1 | B18: Décrire l’expérience de l’utilisateur (ressenti et facilité d’usage) d’un OST en partant du langage naturel (texte, croquis) pour aboutir aux schémas, graphiques, algorithmes. | C18: D1.3, D4, D5 | D18: — | E18: → LSU
A19: 4e_C2.2 | B19: Repérer et expliquer les contraintes, exigences prises en compte (sécurité, incidences environnementales, formes et fonctions, ergonomie, qualité, fiabilité) pour répondre aux attentes des utilisateurs. | C19: D3, D4, D5 | D19: — | E19: → LSU
A20: 4e_C3.1 | B20: Identifier les caractéristiques à prendre en compte dans le choix d’un OST en vue de répondre à un besoin. | C20: D3, D4, D5 | D20: — | E20: → LSU
A21: 4e_C3.2 | B21: Comparer qualitativement et/ou quantitativement (incidences environnementales, bilan carbone, efficacité énergétique) plusieurs OST répondant au même besoin et arrêter un choix. | C21: D1.3, D2, D3, D4, D5 | D21: — | E21: → LSU
A22: 4e_C3.3 | B22: Choisir les appareils de mesure à utiliser pour mesurer une performance d’un OST à partir d’un protocole donné. | C22: D1.3, D2, D4 | D22: — | E22: → LSU
A24: Déroulé, séance par séance — avec cahier de texte Pronote prêt à coller
A25: ■ Séance 1 — semaine S06 — — — [titre de la séance 1 — à compléter]
A26: Question directrice | B26: [question directrice]
A27: Activités & supports | B27: [activités — repères Nathan : Prob. 11 p.79-84 (mesurer les performances) · Prob. 10 p.73-78 (impact environnemental)]
A28: Démarche / organisation | B28: [démarche]
A29: Bilan / trace écrite | B29: [trace écrite]
A30: 📋 CAHIER DE TEXTE Contenu de la séance 👆 CLIC = copier pour Pronote | B30: [Cahier de texte — contenu de la séance 1 : à rédiger par IA Thème 1 — phrase(s) prêtes à coller dans Pronote.]
A31: 📋 CAHIER DE TEXTE Travail à faire 👆 CLIC = copier pour Pronote | B31: [Cahier de texte — travail à faire : à rédiger — support (lien ou pages Nathan), durée estimée, « faisable sur téléphone » si c'est le cas.]
A32: Suivi enseignant | B32: Fait le : ____________ | C32: Report / aléa / remarques :
A34: ■ Séance 2 — semaine S07 — — — [titre de la séance 2 — à compléter]
A35: Question directrice | B35: [question directrice]
A36: Activités & supports | B36: [activités — repères Nathan : Prob. 11 p.79-84 (mesurer les performances) · Prob. 10 p.73-78 (impact environnemental)]
A37: Démarche / organisation | B37: [démarche]
A38: Bilan / trace écrite | B38: [trace écrite]
A39: 📋 CAHIER DE TEXTE Contenu de la séance 👆 CLIC = copier pour Pronote | B39: [Cahier de texte — contenu de la séance 2 : à rédiger par IA Thème 1 — phrase(s) prêtes à coller dans Pronote.]
A40: 📋 CAHIER DE TEXTE Travail à faire 👆 CLIC = copier pour Pronote | B40: [Cahier de texte — travail à faire : à rédiger — support (lien ou pages Nathan), durée estimée, « faisable sur téléphone » si c'est le cas.]
A41: Suivi enseignant | B41: Fait le : ____________ | C41: Report / aléa / remarques :
A43: ■ Séance 3 — semaine S09 — — — [titre de la séance 3 — à compléter]
A44: Question directrice | B44: [question directrice]
A45: Activités & supports | B45: [activités — repères Nathan : Prob. 11 p.79-84 (mesurer les performances) · Prob. 10 p.73-78 (impact environnemental)]
A46: Démarche / organisation | B46: [démarche]
A47: Bilan / trace écrite | B47: [trace écrite]
A48: 📋 CAHIER DE TEXTE Contenu de la séance 👆 CLIC = copier pour Pronote | B48: [Cahier de texte — contenu de la séance 3 : à rédiger par IA Thème 1 — phrase(s) prêtes à coller dans Pronote.]
A49: 📋 CAHIER DE TEXTE Travail à faire 👆 CLIC = copier pour Pronote | B49: [Cahier de texte — travail à faire : à rédiger — support (lien ou pages Nathan), durée estimée, « faisable sur téléphone » si c'est le cas.]
A50: Suivi enseignant | B50: Fait le : ____________ | C50: Report / aléa / remarques :
A52: ■ Séance 4 — semaine S10 — — — [titre de la séance 4 — à compléter]
A53: Question directrice | B53: [question directrice]
A54: Activités & supports | B54: [activités — repères Nathan : Prob. 11 p.79-84 (mesurer les performances) · Prob. 10 p.73-78 (impact environnemental)]
A55: Démarche / organisation | B55: [démarche]
A56: Bilan / trace écrite | B56: [trace écrite]
A57: 📋 CAHIER DE TEXTE Contenu de la séance 👆 CLIC = copier pour Pronote | B57: [Cahier de texte — contenu de la séance 4 : à rédiger par IA Thème 1 — phrase(s) prêtes à coller dans Pronote.]
A58: 📋 CAHIER DE TEXTE Travail à faire 👆 CLIC = copier pour Pronote | B58: [Cahier de texte — travail à faire : à rédiger — support (lien ou pages Nathan), durée estimée, « faisable sur téléphone » si c'est le cas.]
A59: Suivi enseignant | B59: Fait le : ____________ | C59: Report / aléa / remarques :

Sheet S4
A1: GÉNÉRATEUR DE SÉQUENCE 2024 — S4 · Automatiser le jardin connecté : chaîne d'énergie et d'information
A2: Thème 2 · P2/P3 · 5 séances de 1 h 30 · Responsable : Fable (Th. 2) · Pré-rempli par Fable — QCM ✅ en ligne, séquence îlot 4e_C4 🔜
E3: ◀ Progression | F3: ◀ Accueil
A4: Problématique | B4: Comment un système automatisé peut-il réguler l'arrosage d'un jardin ?
A5: Situation déclenchante | B5: Le potager pédagogique du collège meurt à chaque période de vacances : personne pour l'arroser. Le club techno doit concevoir la régulation automatique de l'arrosage — et prouver qu'elle fonctionne avec des données.
A6: Prérequis | B6: 5e : chaînes d'énergie/information sur objet simple (lampadaire). Rappels intégrés en séance 1.
A7: Éléments pour la synthèse (objectifs) | B7: Constituants d'une chaîne d'énergie ET d'information complètes · transformations et flux d'énergie · capteur = grandeur physique → donnée · structurer des données (CSV) pour les exploiter (graphique).
A8: Piste d'évaluation | B8: Formative : vérificateurs + QCM existants (Jardin connecté, Automatisation, eCall). Repère du référentiel : table de données exportée en CSV + graphique. Sommative en séance 5 (corrigé non publié).
A9: Domaines du socle mobilisés | B9: D1.3, D2, D4, D5 (détail par code ci-dessous)
A10: CRCN — compétences numériques (Pix) | B10: 1.3 Traiter des données (Niv. 3 : structurer en CSV, produire un graphique) · 3.4 Programmer (Niv. 2)
A11: Versions 🅰 / 🅱 / 🅲 | B11: 🅰 maquette Arduino + capteurs humidité/luminosité (TBT) · 🅱 VittaScience simulation · 🅲 fiches papier + jeux de données imprimés.
A12: Liens EPI / parcours | B12: EDD (gestion de l'eau) · SVT (besoins des plantes) · mathématiques (graphiques).
A13: Cahier Nathan 4e | B13: Prob. 5 p.37-44 (chaîne d'énergie) · Prob. 3 p.21-28 (fonctionnement) · Prob. 7 p.53-58 (automatiser)
A14: Ressources en ligne | B14: ✅ Partiel : QCM « Jardin connecté », « Automatisation », « eCall » (existants) · 🔜 séquence îlot 4e_C4 (Fable)
A16: Compétences du programme 2024
A17: Code | B17: Intitulé officiel | C17: Domaines du socle | D17: Travaillée en | E17: Évaluation LSU
A18: 4e_C4.1 | B18: Identifier les constituants d’une chaîne d’énergie et les associer à leurs fonctions. | C18: D2, D4, D5 | D18: Séances 1-2 | E18: Formative + QCM ciblé → LSU
A19: 4e_C4.2 | B19: Repérer les transformations d’énergie et les flux d’énergie au sein de l’OST. | C19: D1.3, D2, D4 | D19: Séance 2 | E19: Formative → LSU
A20: 4e_C4.4 | B20: Identifier les constituants de la chaîne d’information d’un objet réel et les associer à leur fonction. | C20: D1.3, D2, D4 | D20: Séance 3 | E20: Formative + QCM eCall → LSU
A21: 4e_C4.5 | B21: Décrire et analyser la transformation des données téléversées ou issues d’un OST. | C21: D1.3, D2, D4 | D21: Séance 3 | E21: Formative → LSU
A22: 4e_C4.6 | B22: Décrire et analyser la structuration d’une table de données qui permet une exploitation et une interprétation du comportement d’un OST. | C22: D1.3, D2, D4 | D22: Séances 4-5 | E22: Table CSV + graphique → LSU
A24: Déroulé, séance par séance — avec cahier de texte Pronote prêt à coller
A25: ■ Séance 1 — semaine S11 — 🏫 En classe — Analyser le système d'arrosage automatique
A26: Question directrice | B26: De quoi le jardin connecté est-il fait — et qui décide d'arroser ?
A27: Activités & supports | B27: Analyse du système réel/maquette : constituants, frontière énergie/information. QCM de découverte « Automatisation » : https://pll-process.github.io/en-ligne-pour-le-cycle-4/theme-2-structure-fonctionnement-comportement/C4-decrire-et-caracteriser-lorganisation/4e/4e_C4.1/qcm_automatisation_premium.html
A28: Démarche / organisation | B28: Investigation en îlots ; schéma de l'objet complet.
A29: Bilan / trace écrite | B29: Les DEUX chaînes complètes de l'objet (rappel 5e, montée 4e : transformations).
A30: 📋 CAHIER DE TEXTE Contenu de la séance 👆 CLIC = copier pour Pronote | B30: Séquence « Le jardin connecté » — Séance 1 : analyse du système d'arrosage automatique, constituants des chaînes d'énergie et d'information.
A31: 📋 CAHIER DE TEXTE Travail à faire 👆 CLIC = copier pour Pronote | B31: QCM « Automatisation » en ligne (mode découverte, corrections incluses) : https://pll-process.github.io/en-ligne-pour-le-cycle-4/theme-2-structure-fonctionnement-comportement/C4-decrire-et-caracteriser-lorganisation/4e/4e_C4.1/qcm_automatisation_premium.html ≈ 15 min, faisable sur téléphone.
A32: Suivi enseignant | B32: Fait le : ____________ | C32: Report / aléa / remarques :
A34: ■ Séance 2 — semaine S12 — 🏫 En classe — Transformations et flux d'énergie (C4.1, C4.2)
A35: Question directrice | B35: Quel chemin l'énergie suit-elle, et sous quelles formes ?
A36: Activités & supports | B36: Chaîne d'énergie complète de la pompe : repérer les transformations et les flux ; schéma-bloc. Nathan Prob. 5 p.37-44.
A37: Démarche / organisation | B37: Résolution de problème en binômes ; correction vidéoprojetée.
A38: Bilan / trace écrite | B38: Transformation = changement de forme d'énergie ; flux = son chemin.
A39: 📋 CAHIER DE TEXTE Contenu de la séance 👆 CLIC = copier pour Pronote | B39: Séance 2 : transformations et flux d'énergie dans le système d'arrosage (schéma-bloc complété). Cahier Nathan p.37-44.
A40: 📋 CAHIER DE TEXTE Travail à faire 👆 CLIC = copier pour Pronote | B40: Terminer le schéma-bloc du cahier Nathan (p.40-41) ; relire la trace écrite. ≈ 15 min.
A41: Suivi enseignant | B41: Fait le : ____________ | C41: Report / aléa / remarques :
A43: ■ Séance 3 — semaine S13 — 🏫 En classe — Capteurs et chaîne d'information (C4.4, C4.5)
A44: Question directrice | B44: Comment l'humidité du sol devient-elle une décision d'arrosage ?
A45: Activités & supports | B45: Capteurs humidité/luminosité (Arduino réel ou VittaScience) : grandeur physique → signal → donnée → décision. QCM « eCall » (chaîne d'information contextualisée) : https://pll-process.github.io/en-ligne-pour-le-cycle-4/theme-2-structure-fonctionnement-comportement/C4-decrire-et-caracteriser-lorganisation/4e/4e_C4.4/qcm_ecall_chaine_information.html
A46: Démarche / organisation | B46: Manipulation guidée en binômes (version 🅰) ou simulation (🅱).
A47: Bilan / trace écrite | B47: ACQUÉRIR (capteur) → TRAITER (carte) → COMMANDER (électrovanne) ; nature des signaux.
A48: 📋 CAHIER DE TEXTE Contenu de la séance 👆 CLIC = copier pour Pronote | B48: Séance 3 : du capteur à la décision — la chaîne d'information de l'arrosage automatique (manipulation capteurs).
A49: 📋 CAHIER DE TEXTE Travail à faire 👆 CLIC = copier pour Pronote | B49: QCM « eCall — chaîne d'information » : https://pll-process.github.io/en-ligne-pour-le-cycle-4/theme-2-structure-fonctionnement-comportement/C4-decrire-et-caracteriser-lorganisation/4e/4e_C4.4/qcm_ecall_chaine_information.html ≈ 15 min. Corrections détaillées incluses.
A50: Suivi enseignant | B50: Fait le : ____________ | C50: Report / aléa / remarques :
A52: ■ Séance 4 — semaine S14 — 🔁 Hybride — Structurer les données du jardin (C4.6)
A53: Question directrice | B53: Comment garder la trace de ce que mesure le jardin — et la lire ?
A54: Activités & supports | B54: Relevés des capteurs → table structurée (colonnes nommées, types, formats — rappel 5e descripteurs) → export CSV → graphique au tableur. Début en classe, poursuite à la maison.
A55: Démarche / organisation | B55: Travail au poste ; gabarit de tableur fourni.
A56: Bilan / trace écrite | B56: CSV = données séparées par des virgules, lisibles par toutes les machines ; un graphique révèle ce que la table cache.
A57: 📋 CAHIER DE TEXTE Contenu de la séance 👆 CLIC = copier pour Pronote | B57: Séance 4 : structurer les données du jardin (table → CSV → graphique). Début du travail au tableur.
A58: 📋 CAHIER DE TEXTE Travail à faire 👆 CLIC = copier pour Pronote | B58: Terminer la table et le graphique au tableur (gabarit distribué / ENT) ; exporter en CSV. ≈ 25 min. En cas de blocage : noter la question, on corrige en séance 5.
A59: Suivi enseignant | B59: Fait le : ____________ | C59: Report / aléa / remarques :
A61: ■ Séance 5 — semaine S16 — 🏠 puis 🏫 — Bilan et évaluation
A62: Question directrice | B62: Que sait faire notre jardin — et moi, où en suis-je ?
A63: Activités & supports | B63: Correction des graphiques ; bilan des deux chaînes ; évaluation sommative (corrigé non publié). Révision : QCM « Jardin connecté » : https://pll-process.github.io/en-ligne-pour-le-cycle-4/theme-2-structure-fonctionnement-comportement/C6-comprendre-et-modifier-un-programme-associe/4e/4e_C6.2/qcm_jardin_connecte.html
A64: Démarche / organisation | B64: Bilan collectif 30 min + évaluation 45 min.
A65: Bilan / trace écrite | B65: Synthèse distribuée.
A66: 📋 CAHIER DE TEXTE Contenu de la séance 👆 CLIC = copier pour Pronote | B66: Séance 5 : bilan de la séquence « Jardin connecté » et évaluation (chaînes complètes, capteurs, données).
A67: 📋 CAHIER DE TEXTE Travail à faire 👆 CLIC = copier pour Pronote | B67: Fait avant la séance : QCM « Jardin connecté » complet : https://pll-process.github.io/en-ligne-pour-le-cycle-4/theme-2-structure-fonctionnement-comportement/C6-comprendre-et-modifier-un-programme-associe/4e/4e_C6.2/qcm_jardin_connecte.html ≈ 20 min. Après : rien — mode « Uniquement mes erreurs » pour réviser plus tard.
A68: Suivi enseignant | B68: Fait le : ____________ | C68: Report / aléa / remarques :

Sheet S5
A1: GÉNÉRATEUR DE SÉQUENCE 2024 — S5 · Objets connectés en réseau : adresse IP et communication
A2: Thème 2 · P3/P4 · 4 séances de 1 h 30 · Responsable : Fable (Th. 2) · Pré-rempli par Fable — QCM ✅ (sélection), séquence 🔜
E3: ◀ Progression | F3: ◀ Accueil
A4: Problématique | B4: Comment ajouter un objet connecté à un réseau local et le faire dialoguer ?
A5: Situation déclenchante | B5: Le jardin connecté doit envoyer ses mesures au serveur du collège et être consultable depuis la salle des profs : comment lui donner une adresse et le faire dialoguer ?
A6: Prérequis | B6: 5e : composants du réseau local, identification unique (lampadaire). Rappel séance 1.
A7: Éléments pour la synthèse (objectifs) | B7: Adresse IP (fixe) d'un terminal · communication entre terminaux d'un réseau local · ajout d'un objet connecté (IoT) et validation par simulation.
A8: Piste d'évaluation | B8: Repère du référentiel : simulation de réseau validée. QCM réseaux existant (sélection de questions IP). Sommative courte séance 4.
A9: Domaines du socle mobilisés | B9: D2, D4 (détail par code ci-dessous)
A10: CRCN — compétences numériques (Pix) | B10: 5.1 Résoudre des problèmes techniques (Niv. 3) · 5.2 Évoluer dans un environnement numérique (Niv. 2-3)
A11: Versions 🅰 / 🅱 / 🅲 | B11: 🅰 mini-réseau réel (2 postes + commutateur de la salle) · 🅱 simulateur de réseau (Filius/VittaScience IoT) · 🅲 papier : plan d'adressage à compléter.
A12: Liens EPI / parcours | B12: Vers Pix D2/D5 · parcours Avenir (métiers du réseau).
A13: Cahier Nathan 4e | B13: Prob. 2 p.13-20 (connecter un objet à un réseau) · Point méthode adresse IP
A14: Ressources en ligne | B14: ✅ Partiel : QCM réseaux existant (40 q IP/NFC/RFID/Zigbee) · 🔜 séquence (Fable)
A16: Compétences du programme 2024
A17: Code | B17: Intitulé officiel | C17: Domaines du socle | D17: Travaillée en | E17: Évaluation LSU
A18: 4e_C4.7 | B18: Paramétrer une adresse IP fixe pour ajouter un objet connecté à un réseau local. | C18: D2, D4 | D18: Séances 1-2 | E18: Formative + QCM → LSU
A19: 4e_C4.8 | B19: Résoudre des problèmes pour assurer la communication entre les différents terminaux dans un réseau informatique (simulation ou réseau local déconnecté du réseau pédagogique). | C19: D2, D4 | D19: Séances 2-3 | E19: Simulation validée → LSU
A20: 4e_C4.9 | B20: Compléter une simulation fournie pour valider le comportement d’un réseau informatique. | C20: D2, D4 | D20: Séance 3 | E20: Formative → LSU
A22: Déroulé, séance par séance — avec cahier de texte Pronote prêt à coller
A23: ■ Séance 1 — semaine S17 — 🏫 En classe — L'adresse IP : l'identité chiffrée (C4.7)
A24: Question directrice | B24: Le nom ne suffit plus : comment les machines s'adressent-elles vraiment ?
A25: Activités & supports | B25: Du nom (5e) à l'adresse IP (4e) : structure, unicité, adresse fixe pour un serveur. Repérage des IP réelles des postes. Nathan Prob. 2 p.13-20. QCM réseaux (questions IP uniquement, mode ciblé) : https://pll-process.github.io/en-ligne-pour-le-cycle-4/theme-2-structure-fonctionnement-comportement/C4-decrire-et-caracteriser-lorganisation/4e/4e_C4.7/qcm_xxl_40_reseaux_ip_nfc_rfid_zigbee.html
A26: Démarche / organisation | B26: Investigation ; ipconfig sur postes réels.
A27: Bilan / trace écrite | B27: Adresse IP = identité numérique unique du terminal sur le réseau.
A28: 📋 CAHIER DE TEXTE Contenu de la séance 👆 CLIC = copier pour Pronote | B28: Séance 1 : l'adresse IP — identité chiffrée des terminaux (relevé des adresses réelles de la salle). Cahier Nathan p.13-20.
A29: 📋 CAHIER DE TEXTE Travail à faire 👆 CLIC = copier pour Pronote | B29: QCM réseaux en ligne, partie IP : https://pll-process.github.io/en-ligne-pour-le-cycle-4/theme-2-structure-fonctionnement-comportement/C4-decrire-et-caracteriser-lorganisation/4e/4e_C4.7/qcm_xxl_40_reseaux_ip_nfc_rfid_zigbee.html ≈ 15 min (choisir le mode ciblé).
A30: Suivi enseignant | B30: Fait le : ____________ | C30: Report / aléa / remarques :
A32: ■ Séance 2 — semaine S18 — 🏫 En classe — Faire dialoguer deux terminaux (C4.7, C4.8)
A33: Question directrice | B33: Que se passe-t-il exactement quand un poste « parle » à un autre ?
A34: Activités & supports | B34: Simulateur de réseau : construire un mini-réseau (2 postes, commutateur), configurer les IP, envoyer un message, observer le chemin.
A35: Démarche / organisation | B35: Binômes au simulateur ; défi : faire échouer la communication (IP en double, mauvaise passerelle) puis réparer.
A36: Bilan / trace écrite | B36: La communication exige des adresses cohérentes ; la simulation permet de VALIDER avant de câbler.
A37: 📋 CAHIER DE TEXTE Contenu de la séance 👆 CLIC = copier pour Pronote | B37: Séance 2 : simulation de réseau — configuration des adresses IP et dialogue entre deux terminaux ; pannes provoquées et réparées.
A38: 📋 CAHIER DE TEXTE Travail à faire 👆 CLIC = copier pour Pronote | B38: Refaire chez toi le mini-réseau au simulateur (lien ENT) OU schéma d'adressage papier à compléter. ≈ 20 min.
A39: Suivi enseignant | B39: Fait le : ____________ | C39: Report / aléa / remarques :
A41: ■ Séance 3 — semaine S19 — 🔁 Hybride — Connecter l'objet (IoT) au réseau (C4.9)
A42: Question directrice | B42: Comment le jardin envoie-t-il ses mesures au serveur ?
A43: Activités & supports | B43: Ajout d'un objet connecté au réseau simulé (VittaScience IoT / mBlock) : l'objet publie une mesure, un poste la consulte.
A44: Démarche / organisation | B44: Démonstration + binômes ; poursuite à la maison en simulation.
A45: Bilan / trace écrite | B45: Objet connecté = un terminal comme un autre : adresse, règles, dialogue.
A46: 📋 CAHIER DE TEXTE Contenu de la séance 👆 CLIC = copier pour Pronote | B46: Séance 3 : connecter le jardin au réseau du collège (simulation IoT) — l'objet publie ses mesures, un poste les consulte.
A47: 📋 CAHIER DE TEXTE Travail à faire 👆 CLIC = copier pour Pronote | B47: Terminer la simulation IoT commencée en classe (lien ENT). ≈ 20 min.
A48: Suivi enseignant | B48: Fait le : ____________ | C48: Report / aléa / remarques :
A50: ■ Séance 4 — semaine S21 — 🏠 puis 🏫 — Bilan réseau + évaluation
A51: Question directrice | B51: Où en suis-je sur C4.7, C4.8, C4.9 ?
A52: Activités & supports | B52: Correction du QCM fait à la maison ; évaluation : configurer et valider un petit réseau en simulation (repère du référentiel).
A53: Démarche / organisation | B53: Évaluation pratique 40 min + bilan.
A54: Bilan / trace écrite | B54: Synthèse distribuée.
A55: 📋 CAHIER DE TEXTE Contenu de la séance 👆 CLIC = copier pour Pronote | B55: Séance 4 : évaluation pratique — configurer un mini-réseau en simulation et le valider ; bilan de la séquence.
A56: 📋 CAHIER DE TEXTE Travail à faire 👆 CLIC = copier pour Pronote | B56: Fait avant la séance : rejouer le QCM réseaux (questions IP) : https://pll-process.github.io/en-ligne-pour-le-cycle-4/theme-2-structure-fonctionnement-comportement/C4-decrire-et-caracteriser-lorganisation/4e/4e_C4.7/qcm_xxl_40_reseaux_ip_nfc_rfid_zigbee.html ≈ 15 min. Après : rien.
A57: Suivi enseignant | B57: Fait le : ____________ | C57: Report / aléa / remarques :

Sheet S6
A1: GÉNÉRATEUR DE SÉQUENCE 2024 — S6 · Réparer sans notice : diagnostic, pièce et programme
A2: Thème 2 · P4 · 4 séances de 1 h 30 · Responsable : Fable (Th. 2) · Pré-rempli par Fable — 2 QCM ✅, séquence 🔜 · intègre le correctif 4e_C4.3
E3: ◀ Progression | F3: ◀ Accueil
A4: Problématique | B4: Comment diagnostiquer une panne sans protocole fourni, remplacer la pièce et corriger le programme ?
A5: Situation déclenchante | B5: L'éclairage automatique du hall est en panne, sans notice ni SAV. Diagnostiquer, remplacer la pièce (et si elle n'existe plus : la refabriquer — quelle forme, quel procédé ?), corriger le programme.
A6: Prérequis | B6: 5e : panne visuelle + protocole fourni (SOS panne). Montée 4e : SANS notice, avec hypothèses.
A7: Éléments pour la synthèse (objectifs) | B7: Vérifier l'ORIGINE d'un dysfonctionnement (hypothèses → tests) · remplacer sans protocole fourni · forme d'une pièce ↔ procédé de réalisation (C4.3) · analyser les données d'un programme, le compléter, le corriger et le tester.
A8: Piste d'évaluation | B8: Repère du référentiel : rapport de diagnostic + programme corrigé. QCM existants (Éclairage automatique, Algorigrammes domotique). Sommative séance 4.
A9: Domaines du socle mobilisés | B9: D1.3, D2, D3, D4, D5 (détail par code ci-dessous)
A10: CRCN — compétences numériques (Pix) | B10: 3.4 Programmer (Niv. 2-3 : compléter, corriger, tester) · 5.1 Résoudre des problèmes techniques (Niv. 2)
A11: Versions 🅰 / 🅱 / 🅲 | B11: 🅰 objets réels en panne + impression 3D de la pièce · 🅱 simulateur de diagnostic (🔜, modèle 3e « SOS station ») · 🅲 étude de cas papier Nathan.
A12: Liens EPI / parcours | B12: EDD (réparer plutôt que jeter, indice de réparabilité) · parcours Avenir (maintenance).
A13: Cahier Nathan 4e | B13: Prob. 8 p.61-66 (prolonger la durée de vie) · Prob. 6 p.45-52 (programmer) · Prob. 4 p.29-36 (matériaux et formes → C4.3)
A14: Ressources en ligne | B14: ✅ Partiel : QCM « Éclairage automatique », « Algorigrammes domotique » (existants) · 🔜 séquence (Fable, sur le modèle 3e « SOS station »)
A16: Compétences du programme 2024
A17: Code | B17: Intitulé officiel | C17: Domaines du socle | D17: Travaillée en | E17: Évaluation LSU
A18: 4e_C5.1 | B18: Proposer un protocole permettant de vérifier l’origine d’un dysfonctionnement. | C18: D1.3, D2, D4 | D18: Séance 1 | E18: Formative → LSU
A19: 4e_C5.2 | B19: Remplacer une pièce défectueuse sans protocole fourni (la pièce de remplacement étant fournie). | C19: D2, D3, D4 | D19: Séances 1-2 | E19: Rapport de diagnostic → LSU
A20: 4e_C5.3 | B20: Choisir les procédés de réalisation et les mettre en œuvre. | C20: D2, D3, D4 | D20: Séance 2 | E20: Formative → LSU
A21: 4e_C4.3 | B21: Mettre en relation la forme d’une pièce avec le procédé de réalisation. | C21: D3, D4, D5 | D21: Séance 2 | E21: Choix forme/procédé justifié → LSU (correctif : code réintégré)
A22: 4e_C6.1 | B22: Analyser les données et en déduire des modifications à apporter au programme. | C22: D1.3, D2, D4 | D22: Séance 3 | E22: Formative → LSU
A23: 4e_C6.2 | B23: Compléter un programme pour répondre à une fonctionnalité d’un OST. | C23: D1.3, D2, D4 | D23: Séance 3 | E23: Programme complété → LSU
A24: 4e_C6.3 | B24: Tester et valider, dans un environnement simulé ou réel, une modification du programme. | C24: D1.3, D2, D4 | D24: Séances 3-4 | E24: Programme corrigé testé → LSU
A26: Déroulé, séance par séance — avec cahier de texte Pronote prêt à coller
A27: ■ Séance 1 — semaine S22 — 🏫 En classe — Diagnostiquer sans notice (C5.1, C5.2)
A28: Question directrice | B28: Par où commencer quand rien n'est fourni ?
A29: Activités & supports | B29: Objets en panne non documentés : hypothèses, tests ordonnés (alimentation → capteur → carte → actionneur), localisation. Nathan Prob. 8 p.61-66.
A30: Démarche / organisation | B30: Résolution de problème en îlots ; grille d'hypothèses.
A31: Bilan / trace écrite | B31: Démarche : observer → hypothèses → tester DANS L'ORDRE → conclure.
A32: 📋 CAHIER DE TEXTE Contenu de la séance 👆 CLIC = copier pour Pronote | B32: Séance 1 : diagnostiquer une panne SANS notice — hypothèses et tests ordonnés (objets réels). Cahier Nathan p.61-66.
A33: 📋 CAHIER DE TEXTE Travail à faire 👆 CLIC = copier pour Pronote | B33: Compléter la grille d'hypothèses du cas étudié ; lire Nathan p.62-63. ≈ 15 min.
A34: Suivi enseignant | B34: Fait le : ____________ | C34: Report / aléa / remarques :
A36: ■ Séance 2 — semaine S23 — 🏫 En classe — Remplacer la pièce : forme et procédé (C5.3, C4.3)
A37: Question directrice | B37: La pièce n'existe plus : quelle forme lui donner, comment la fabriquer ?
A38: Activités & supports | B38: Relier la FORME de la pièce de remplacement au PROCÉDÉ (impression 3D : formes complexes ; découpe : formes planes ; pliage…). Choix justifié + lancement d'impression. Nathan Prob. 4 p.29-36.
A39: Démarche / organisation | B39: Binômes ; abaque forme↔procédé fournie.
A40: Bilan / trace écrite | B40: Une forme n'est pas gratuite : elle dépend du procédé — et réciproquement (correctif C4.3 réintégré ici).
A41: 📋 CAHIER DE TEXTE Contenu de la séance 👆 CLIC = copier pour Pronote | B41: Séance 2 : remplacer la pièce — relier sa forme au procédé de fabrication (impression 3D / découpe), choix justifié. Nathan p.29-36.
A42: 📋 CAHIER DE TEXTE Travail à faire 👆 CLIC = copier pour Pronote | B42: Terminer la justification écrite du choix forme/procédé. ≈ 10 min.
A43: Suivi enseignant | B43: Fait le : ____________ | C43: Report / aléa / remarques :
A45: ■ Séance 3 — semaine S24 — 🏫 En classe — Corriger le programme (C6.1, C6.2)
A46: Question directrice | B46: La pièce est réparée mais l'objet déraille encore : et si c'était le programme ?
A47: Activités & supports | B47: Analyser les données du programme de l'éclairage, compléter les blocs manquants, corriger l'erreur. QCM « Algorigrammes domotique » : https://pll-process.github.io/en-ligne-pour-le-cycle-4/theme-2-structure-fonctionnement-comportement/C6-comprendre-et-modifier-un-programme-associe/4e/4e_C6.2/qcm_algorigrammes_domotique.html
A48: Démarche / organisation | B48: Binômes sur postes (VittaScience/mBlock).
A49: Bilan / trace écrite | B49: Données utilisées/produites ; compléter ≠ réécrire : on respecte la structure.
A50: 📋 CAHIER DE TEXTE Contenu de la séance 👆 CLIC = copier pour Pronote | B50: Séance 3 : corriger le programme de l'éclairage automatique (données, blocs manquants, erreur corrigée).
A51: 📋 CAHIER DE TEXTE Travail à faire 👆 CLIC = copier pour Pronote | B51: QCM « Algorigrammes domotique » : https://pll-process.github.io/en-ligne-pour-le-cycle-4/theme-2-structure-fonctionnement-comportement/C6-comprendre-et-modifier-un-programme-associe/4e/4e_C6.2/qcm_algorigrammes_domotique.html ≈ 15 min, corrections incluses.
A52: Suivi enseignant | B52: Fait le : ____________ | C52: Report / aléa / remarques :
A54: ■ Séance 4 — semaine S25 — 🔁 Hybride — Tester, prouver, rendre compte (C6.3)
A55: Question directrice | B55: Comment PROUVER que la réparation complète fonctionne ?
A56: Activités & supports | B56: Plan de tests du programme corrigé ; rédaction du rapport de diagnostic (repère du référentiel) ; QCM « Éclairage automatique » à la maison : https://pll-process.github.io/en-ligne-pour-le-cycle-4/theme-2-structure-fonctionnement-comportement/C6-comprendre-et-modifier-un-programme-associe/4e/4e_C6.2/qcm_eclairage_automatique.html
A57: Démarche / organisation | B57: Individuel (rapport) + tests en binômes ; évaluation sommative courte.
A58: Bilan / trace écrite | B58: Un rapport dit : symptôme, cause PROUVÉE, intervention, test final.
A59: 📋 CAHIER DE TEXTE Contenu de la séance 👆 CLIC = copier pour Pronote | B59: Séance 4 : tester le programme corrigé et rédiger le rapport de diagnostic complet ; évaluation.
A60: 📋 CAHIER DE TEXTE Travail à faire 👆 CLIC = copier pour Pronote | B60: Fait avant la séance : QCM « Éclairage automatique » : https://pll-process.github.io/en-ligne-pour-le-cycle-4/theme-2-structure-fonctionnement-comportement/C6-comprendre-et-modifier-un-programme-associe/4e/4e_C6.2/qcm_eclairage_automatique.html ≈ 15 min. Après : rien.
A61: Suivi enseignant | B61: Fait le : ____________ | C61: Report / aléa / remarques :

Sheet S7
A1: GÉNÉRATEUR DE SÉQUENCE 2024 — S7 · Projet : ajouter une nouvelle fonction à un objet connecté
A2: Thème 3 · P4/P5 · 6 séances de 1 h 30 · Responsable : IA Thème 3 · CANEVAS À REMPLIR par IA Thème 3 (règle : l'IA du thème est seule à modifier)
E3: ◀ Progression | F3: ◀ Accueil
A4: Problématique | B4: Comment concevoir, réaliser et programmer une nouvelle fonctionnalité ?
A5: Situation déclenchante | B5: Le collège possède déjà un jardin connecté (ou un système similaire). On souhaite lui ajouter une nouvelle fonction (alerte de niveau d'eau, mode économie, indicateur de qualité…). Les élèves doivent concevoir, valider et programmer cette nouvelle fonction.
A6: Prérequis | B6: Séquences 4e_C6 (jardin connecté), notions de conception (C7) et de validation (C8).
A7: Éléments pour la synthèse (objectifs) | B7: Analyser un besoin, concevoir une solution, écrire un protocole de validation, réaliser les tests, programmer la nouvelle fonction, documenter.
A8: Piste d'évaluation | B8: Revue de projet + prototype fonctionnel + programme
A9: Domaines du socle mobilisés | B9: D1.3, D2, D3, D4, D5 (détail par code ci-dessous)
A10: CRCN — compétences numériques (Pix) | B10: 3.4 Programmer (Niv. 2-3) · 2.3 Collaborer (Niv. 2) · 3.2 Documents visuels (Niv. 2)
A11: Versions 🅰 / 🅱 / 🅲 | B11: A (matériel réel + microcontrôleur) · B (simulation + maquette) · C (bureau d'études papier + rôle)
A12: Liens EPI / parcours | B12: EPI possible avec Mathématiques (traitement de données) et Physique-Chimie
A13: Cahier Nathan 4e | B13: Prob. 9 p.67-72 (réaliser/modifier un prototype) · Prob. 10 p.73-78 · Prob. 6 p.45-52
A14: Ressources en ligne | B14: sequence_4e_C7_jardin-conception.html · sequence_4e_C8_jardin-validation.html + CodeLab Techno
A16: Compétences du programme 2024
A17: Code | B17: Intitulé officiel | C17: Domaines du socle | D17: Travaillée en | E17: Évaluation LSU
A18: 4e_C7.1 | B18: Organiser un processus de conception et de réalisation dans une durée, avec des tâches identifiées. | C18: D2, D4, D5 | D18: S7-1 · S7-2 | E18: → LSU
A19: 4e_C7.2 | B19: Proposer et fabriquer une solution pour ajouter une nouvelle fonction à un OST (croquis, schéma, graphique, algorithme, modélisation). | C19: D2, D3, D4 | D19: S7-1 · S7-2 | E19: → LSU
A20: 4e_C7.3 | B20: Comparer différents matériaux pour choisir le plus adapté. | C20: D3, D4, D5 | D20: S7-2 | E20: → LSU
A21: 4e_C7.4 | B21: Comparer différentes sources d’énergie pour choisir la plus adaptée. | C21: D3, D4, D5 | D21: S7-2 | E21: → LSU
A22: 4e_C7.5 | B22: Identifier les constituants manquants dans un prototype et le compléter. | C22: D2, D3, D4 | D22: S7-2 | E22: → LSU
A23: 4e_C7.6 | B23: Modifier une forme à l’aide d’une modélisation. | C23: D2, D3, D4 | D23: — | E23: → LSU
A24: 4e_C7.7 | B24: Choisir les moyens et produire la forme voulue. | C24: D2, D3, D4 | D24: — | E24: → LSU
A25: 4e_C7.8 | B25: Interfacer un objet technique avec un réseau. | C25: D2, D3, D4 | D25: — | E25: → LSU
A26: 4e_C8.1 | B26: Paramétrer une simulation fournie pour valider la tenue mécanique d’un matériau. | C26: D1.3, D2, D4 | D26: S7-3 | E26: → LSU
A27: 4e_C8.2 | B27: Proposer un protocole de test pour valider la tenue mécanique d’un matériau. | C27: D1.3, D2, D3, D4 | D27: S7-3 | E27: → LSU
A28: 4e_C8.3 | B28: Proposer un protocole de test pour valider le comportement et les performances d’un objet technique. | C28: D1.3, D2, D3, D4, D5 | D28: S7-3 · S7-4 | E28: → LSU
... A31: 4e_C9.3 | B31: Réaliser et mettre au point un programme commandant un système réel incluant éventuellement une interaction entre un humain et une machine. | C31: D1.3, D2, D4 | D31: S7-5 · S7-6 | E31: → LSU
A33: Déroulé, séance par séance — avec cahier de texte Pronote prêt à coller
A34: ■ Séance 1 — semaine S26 — — — Analyse du besoin et cahier des charges
A35: Question directrice | B35: Quel besoin nouveau et quelles contraintes ?
A36: Activités & supports | B36: Analyse du système existant + rédaction d'un mini cahier des charges
A37: Démarche / organisation | B37: Observation + travail de groupe
A38: Bilan / trace écrite | B38: Cahier des charges validé (besoin + contraintes + critères de réussite)
A39: 📋 CAHIER DE TEXTE Contenu de la séance 👆 CLIC = copier pour Pronote | B39: Projet objet connecté : analyse du besoin et rédaction du cahier des charges.
A40: 📋 CAHIER DE TEXTE Travail à faire 👆 CLIC = copier pour Pronote | B40: Finaliser les 3 critères de réussite (10 min).
A41: Suivi enseignant | B41: Fait le : ____________ | C41: Report / aléa / remarques :
A43: ■ Séance 2 — semaine S29 — — — Proposition et choix de solutions
A44: Question directrice | B44: Quelles solutions techniques proposer ?
A45: Activités & supports | B45: 3 solutions (croquis + avantages/inconvénients) + choix motivé
A46: Démarche / organisation | B46: Divergent puis convergent
A47: Bilan / trace écrite | B47: Solution retenue + justification
A48: 📋 CAHIER DE TEXTE Contenu de la séance 👆 CLIC = copier pour Pronote | B48: Proposition de 3 solutions et choix argumenté.
A49: 📋 CAHIER DE TEXTE Travail à faire 👆 CLIC = copier pour Pronote | B49: Compléter le tableau avantages/inconvénients (15 min).
A50: Suivi enseignant | B50: Fait le : ____________ | C50: Report / aléa / remarques :
A52: ■ Séance 3 — semaine S30 — — — Protocole de test et validation
A53: Question directrice | B53: Comment valider la solution avant de programmer ?
A54: Activités & supports | B54: Protocole de test + réalisation + analyse des résultats
A55: Démarche / organisation | B55: Écriture du protocole puis tests
A56: Bilan / trace écrite | B56: Décision de validation ou d'amélioration
A57: 📋 CAHIER DE TEXTE Contenu de la séance 👆 CLIC = copier pour Pronote | B57: Protocole de test et validation de la solution.
A58: 📋 CAHIER DE TEXTE Travail à faire 👆 CLIC = copier pour Pronote | B58: Rédiger une amélioration si nécessaire (10 min).
A59: Suivi enseignant | B59: Fait le : ____________ | C59: Report / aléa / remarques :
A61: ■ Séance 4 — semaine S31 — — — Préparation et première programmation
A62: Question directrice | B62: Comment préparer et commencer à programmer la nouvelle fonction ?
A63: Activités & supports | B63: Algorithme en langage naturel + première version du programme
A64: Démarche / organisation | B64: Guidage progressif
A65: Bilan / trace écrite | B65: Algorithme + début de programme
A66: 📋 CAHIER DE TEXTE Contenu de la séance 👆 CLIC = copier pour Pronote | B66: Algorithme et début de programmation de la nouvelle fonction.
A67: 📋 CAHIER DE TEXTE Travail à faire 👆 CLIC = copier pour Pronote | B67: Compléter l'algorithme (10 min).
A68: Suivi enseignant | B68: Fait le : ____________ | C68: Report / aléa / remarques :
A70: ■ Séance 5 — semaine S32 — — — Programmation et tests itératifs
A71: Question directrice | B71: Comment finaliser et tester le programme ?
A72: Activités & supports | B72: CodeLab Techno + écriture + tests itératifs
A73: Démarche / organisation | B73: Écriture guidée + tests
A74: Bilan / trace écrite | B74: Programme fonctionnel + commentaires
A75: 📋 CAHIER DE TEXTE Contenu de la séance 👆 CLIC = copier pour Pronote | B75: Finalisation et test du programme.
A76: 📋 CAHIER DE TEXTE Travail à faire 👆 CLIC = copier pour Pronote | B76: Tester le programme et noter un bug éventuel (10 min).
A77: Suivi enseignant | B77: Fait le : ____________ | C77: Report / aléa / remarques :
A79: ■ Séance 6 — semaine S33 — — — Documentation et restitution
A80: Question directrice | B80: Comment documenter et présenter le projet ?
A81: Activités & supports | B81: Dossier technique court + démonstration + oral
A82: Démarche / organisation | B82: Finalisation + restitution
A83: Bilan / trace écrite | B83: Dossier + grille d'évaluation
A84: 📋 CAHIER DE TEXTE Contenu de la séance 👆 CLIC = copier pour Pronote | B84: Restitution du projet et bilan.
A85: 📋 CAHIER DE TEXTE Travail à faire 👆 CLIC = copier pour Pronote | B85: Aucune (fin de séquence).
A86: Suivi enseignant | B86: Fait le : ____________ | C86: Report / aléa / remarques :

Sheet ⚙ Moteur
A1: ⚙ MOTEUR DE LA PROGRESSION 4e — ordre officiel des 37 créneaux (28 séances + 9 tampons)
A2: Ne modifier qu'en Conseil. Le Calendrier place ces créneaux, dans l'ordre, sur les semaines sans imprévu.
A4: N° | B4: Créneau
A5: 1 | B5: S1 · séance 1
A6: 2 | B6: S1 · séance 2
A7: 3 | B7: S1 · séance 3
A8: 4 | B8: S2 · séance 1
A9: 5 | B9: S2 · séance 2
A10: 6 | B10: S3 · séance 1
A11: 7 | B11: S3 · séance 2
A12: 8 | B12: ⏳ TAMPON P1 — rattrapage / remédiation
A13: 9 | B13: S3 · séance 3
A14: 10 | B14: S3 · séance 4
A15: 11 | B15: S4 · séance 1
A16: 12 | B16: S4 · séance 2
... A41: 37 | B41: ⏳ TAMPON P5 — réserve d (fin des cours)
