Workbook

Sheet 🏠 Accueil
A1: TECHNOLOGIE 3e Progression annuelle 2026-2027 · Académie de Martinique · année du DNB
A5: Programme 2024 (BO n°9 du 29/02/2024) · 1 h 30 / semaine · cahier Nathan 3e (éd. 2024) · ressources en ligne du dépôt — Thème 2 : 4 séquences complètes ✅
B7: 📊 L'année en un coup d'œil
B8: 37 | D8: ='🧭 Progression'!G13 -> 30 | F8: 4 + 3
B9: Semaines de cours | D9: Séances planifiées | F9: Tampons + révisions DNB
B11: 9 | D11: 38 | F11: 5 ✅ (C4 complet)
B12: Séquences | D12: Codes 3e travaillés | F12: Séquences Thème 2 en ligne
B14: 🧭 Naviguer dans le classeur (cliquer)
B15: ▸ 📅 Calendrier | C15: 37 semaines, DNB, tampons, imprévus | E15: ▸ 🗓 Frise de l'année | F15: les 9 séquences posées sur l'année
B16: ▸ 📚 Référentiel Cycle 4 | C16: les 114 sous-compétences du cycle | E16: ▸ 📗 Référentiel 3e | F16: les 38 sous-compétences du niveau
B17: ▸ 🧭 Progression | C17: 9 séquences : codes, répartition, ressources | E17: ▸ S1 | F17: Innovation et rupture — IA Thème 1
B18: ▸ S2 | C18: Numérique et société — IA Thème 1 | E18: ▸ S3 | F18: Choisir face au DD — IA Thème 1
B19: ▸ S4 | C19: Station cyclonique : chaînes — Fable ✅ (C4.1-2 🔜) | E19: ▸ S5 | F19: Internet Sainte-Luce : réseaux — Fable ✅
B20: ▸ S6 | C20: SOS station + Programmer l'alerte — Fable ✅✅ | E20: ▸ S7 | F20: Fil rouge V1 : cadrage — IA Thème 3
B21: ▸ S8 | C21: Fil rouge V2 : prototypage — IA Thème 3 | E21: ▸ S9 | F21: Fil rouge V3 : validation — IA Thème 3
B23: 📖 Mode d'emploi express
B24: 🏫 / 🏠 / 🔁 | C24: En classe · À la maison (QCM avec corrections intégrées, simulateurs — faisables sur téléphone) · Hybride/classe inversée.
B25: 🎓 Année du DNB | C25: AUCUNE séance nouvelle après début juin : les semaines S35-S37 sont réservées aux révisions (annales, oraux blancs, mode « Uniquement mes erreurs » des QCM). Le référentiel prévoyait 35 séances : IMPOSSIBLE avec le DNB à 1 h 30/sem — ajusté à 30 séances (compressions signalées dans chaque générateur, à entériner au Conseil).
B26: ⏳ Tampons | C26: 4 tampons de période + 3 semaines DNB absorbent les aléas (moteur automatique : colonne « ⚠ Imprévu ? » du Calendrier). Alerte 🛑 au-delà de 7 imprévus.
B27: 📋 Cahier de texte | C27: Blocs jaunes prêts pour Pronote ; un clic les copie (version macros).
B28: ⚠ À produire (Fable) | C28: RÉSOLU le 23/07 : la séquence « L'énergie de la station » (LOT 06) couvre 3e_C4.1 et C4.2 — le générateur S4 pointe vers elle. La compétence C4 de 3e est 100 % outillée en ligne.
B29: 📆 Calendrier | C29: Martinique 2026-2027 (rectorat) — à confirmer sur ac-martinique.fr. Dates DNB nationales : publiées en cours d'année, à reporter dans « Repères ».
B31: Classeur généré par Fable (IA du Thème 2) — canevas validé par Pascal · pll-process.github.io/en-ligne-pour-le-cycle-4

Sheet 📅 Calendrier
A1: CALENDRIER 3e — année scolaire 2026-2027 (académie de Martinique) — 1 séance de 1 h 30 par semaine — année du DNB
D2: =IF(COUNTIF($G$4:$G$44,"<>")>7,"🛑 "&COUNTIF($G$4:$G$44,"<>")&" imprévus : la réserve (7 = 4 tampons + 3 sem. DNB) est dépassée — arbitrage nécessaire !","✔ Réserve d'aléas : "&(7-COUNTIF($G$4:$G$44,"<>"))&" semaine(s) restante(s) sur 7 (4 tampons + 3 sem. DNB)") -> ✔ Réserve d'aléas : 7 semaine(s) restante(s) sur 7 (4 tampons + 3 sem. DNB) | F2: ◀ Accueil
A3: Sem. | B3: Lundi de la semaine | C3: Période | D3: Affectation (AUTO — se recalcule) | E3: Repères / jours fériés / DNB | F3: Aléas / notes (à remplir) | G3: ⚠ Imprévu ? (menu déroulant) | H3: n° créneau (auto)
A4: S01 | B4: 31/08/2026 | C4: P1 | D4: =IF($G4<>"",$G4&" — les séances suivantes se décalent d'une semaine",INDEX('⚙ Moteur'!$B$5:$B$41,$H4)) -> S1 · séance 1 | E4: Rentrée des élèves mardi 1er septembre. | H4: =IF($G4<>"",0,0+1) -> 1
A5: S02 | B5: 07/09/2026 | C5: P1 | D5: =IF($G5<>"",$G5&" — les séances suivantes se décalent d'une semaine",INDEX('⚙ Moteur'!$B$5:$B$41,$H5)) -> S1 · séance 2 | H5: =IF($G5<>"",H4,H4+1) -> 2
A6: S03 | B6: 14/09/2026 | C6: P1 | D6: =IF($G6<>"",$G6&" — les séances suivantes se décalent d'une semaine",INDEX('⚙ Moteur'!$B$5:$B$41,$H6)) -> S1 · séance 3 | H6: =IF($G6<>"",H5,H5+1) -> 3
A7: S04 | B7: 21/09/2026 | C7: P1 | D7: =IF($G7<>"",$G7&" — les séances suivantes se décalent d'une semaine",INDEX('⚙ Moteur'!$B$5:$B$41,$H7)) -> S2 · séance 1 | H7: =IF($G7<>"",H6,H6+1) -> 4
A8: S05 | B8: 28/09/2026 | C8: P1 | D8: =IF($G8<>"",$G8&" — les séances suivantes se décalent d'une semaine",INDEX('⚙ Moteur'!$B$5:$B$41,$H8)) -> S2 · séance 2 | H8: =IF($G8<>"",H7,H7+1) -> 5
A9: S06 | B9: 05/10/2026 | C9: P1 | D9: =IF($G9<>"",$G9&" — les séances suivantes se décalent d'une semaine",INDEX('⚙ Moteur'!$B$5:$B$41,$H9)) -> S3 · séance 1 | H9: =IF($G9<>"",H8,H8+1) -> 6
A10: S07 | B10: 12/10/2026 | C10: P1 | D10: =IF($G10<>"",$G10&" — les séances suivantes se décalent d'une semaine",INDEX('⚙ Moteur'!$B$5:$B$41,$H10)) -> S3 · séance 2 | H10: =IF($G10<>"",H9,H9+1) -> 7
A11: S08 | B11: 19/10/2026 | C11: P1 | D11: =IF($G11<>"",$G11&" — les séances suivantes se décalent d'une semaine",INDEX('⚙ Moteur'!$B$5:$B$41,$H11)) -> ⏳ TAMPON P1 — rattrapage / remédiation | H11: =IF($G11<>"",H10,H10+1) -> 8
A12: 🏖 Vacances de la Toussaint : 20/10 → 3/11
A13: S09 | B13: 02/11/2026 | C13: P2 | D13: =IF($G13<>"",$G13&" — les séances suivantes se décalent d'une semaine",INDEX('⚙ Moteur'!$B$5:$B$41,$H13)) -> S3 · séance 3 | H13: =IF($G13<>"",H11,H11+1) -> 9
A14: S10 | B14: 09/11/2026 | C14: P2 | D14: =IF($G14<>"",$G14&" — les séances suivantes se décalent d'une semaine",INDEX('⚙ Moteur'!$B$5:$B$41,$H14)) -> S4 · séance 1 | E14: Mer. 11/11 férié (Armistice) | H14: =IF($G14<>"",H13,H13+1) -> 10
A15: S11 | B15: 16/11/2026 | C15: P2 | D15: =IF($G15<>"",$G15&" — les séances suivantes se décalent d'une semaine",INDEX('⚙ Moteur'!$B$5:$B$41,$H15)) -> S4 · séance 2 | H15: =IF($G15<>"",H14,H14+1) -> 11
A16: S12 | B16: 23/11/2026 | C16: P2 | D16: =IF($G16<>"",$G16&" — les séances suivantes se décalent d'une semaine",INDEX('⚙ Moteur'!$B$5:$B$41,$H16)) -> S4 · séance 3 | H16: =IF($G16<>"",H15,H15+1) -> 12
A17: S13 | B17: 30/11/2026 | C17: P2 | D17: =IF($G17<>"",$G17&" — les séances suivantes se décalent d'une semaine",INDEX('⚙ Moteur'!$B$5:$B$41,$H17)) -> S4 · séance 4 | H17: =IF($G17<>"",H16,H16+1) -> 13
A18: S14 | B18: 07/12/2026 | C18: P2 | D18: =IF($G18<>"",$G18&" — les séances suivantes se décalent d'une semaine",INDEX('⚙ Moteur'!$B$5:$B$41,$H18)) -> S4 · séance 5 | H18: =IF($G18<>"",H17,H17+1) -> 14
A19: S15 | B19: 14/12/2026 | C19: P2 | D19: =IF($G19<>"",$G19&" — les séances suivantes se décalent d'une semaine",INDEX('⚙ Moteur'!$B$5:$B$41,$H19)) -> ⏳ TAMPON P2 — rattrapage / remédiation | H19: =IF($G19<>"",H18,H18+1) -> 15
A20: 🏖 Vacances de Noël : 19/12 → 4/01
A21: S16 | B21: 04/01/2027 | C21: P3 | D21: =IF($G21<>"",$G21&" — les séances suivantes se décalent d'une semaine",INDEX('⚙ Moteur'!$B$5:$B$41,$H21)) -> S5 · séance 1 | H21: =IF($G21<>"",H19,H19+1) -> 16
A22: S17 | B22: 11/01/2027 | C22: P3 | D22: =IF($G22<>"",$G22&" — les séances suivantes se décalent d'une semaine",INDEX('⚙ Moteur'!$B$5:$B$41,$H22)) -> S5 · séance 2 | H22: =IF($G22<>"",H21,H21+1) -> 17
A23: S18 | B23: 18/01/2027 | C23: P3 | D23: =IF($G23<>"",$G23&" — les séances suivantes se décalent d'une semaine",INDEX('⚙ Moteur'!$B$5:$B$41,$H23)) -> S5 · séance 3 | H23: =IF($G23<>"",H22,H22+1) -> 18
A24: S19 | B24: 25/01/2027 | C24: P3 | D24: =IF($G24<>"",$G24&" — les séances suivantes se décalent d'une semaine",INDEX('⚙ Moteur'!$B$5:$B$41,$H24)) -> S6 · séance 1 | H24: =IF($G24<>"",H23,H23+1) -> 19
A25: S20 | B25: 01/02/2027 | C25: P3 | D25: =IF($G25<>"",$G25&" — les séances suivantes se décalent d'une semaine",INDEX('⚙ Moteur'!$B$5:$B$41,$H25)) -> ⏳ TAMPON P3 — rattrapage / remédiation | H25: =IF($G25<>"",H24,H24+1) -> 20
A26: 🏖 Vacances de Carnaval : 6/02 → 22/02
A27: S21 | B27: 22/02/2027 | C27: P4 | D27: =IF($G27<>"",$G27&" — les séances suivantes se décalent d'une semaine",INDEX('⚙ Moteur'!$B$5:$B$41,$H27)) -> S6 · séance 2 | H27: =IF($G27<>"",H25,H25+1) -> 21
A28: S22 | B28: 01/03/2027 | C28: P4 | D28: =IF($G28<>"",$G28&" — les séances suivantes se décalent d'une semaine",INDEX('⚙ Moteur'!$B$5:$B$41,$H28)) -> S6 · séance 3 | H28: =IF($G28<>"",H27,H27+1) -> 22
A29: S23 | B29: 08/03/2027 | C29: P4 | D29: =IF($G29<>"",$G29&" — les séances suivantes se décalent d'une semaine",INDEX('⚙ Moteur'!$B$5:$B$41,$H29)) -> S6 · séance 4 | H29: =IF($G29<>"",H28,H28+1) -> 23
A30: S24 | B30: 15/03/2027 | C30: P4 | D30: =IF($G30<>"",$G30&" — les séances suivantes se décalent d'une semaine",INDEX('⚙ Moteur'!$B$5:$B$41,$H30)) -> S7 · séance 1 | H30: =IF($G30<>"",H29,H29+1) -> 24
A31: S25 | B31: 22/03/2027 | C31: P4 | D31: =IF($G31<>"",$G31&" — les séances suivantes se décalent d'une semaine",INDEX('⚙ Moteur'!$B$5:$B$41,$H31)) -> S7 · séance 2 | E31: Ven. 26/03 férié (Vendredi saint) | H31: =IF($G31<>"",H30,H30+1) -> 25
A32: S26 | B32: 29/03/2027 | C32: P4 | D32: =IF($G32<>"",$G32&" — les séances suivantes se décalent d'une semaine",INDEX('⚙ Moteur'!$B$5:$B$41,$H32)) -> S7 · séance 3 | E32: Lun. 29/03 férié (lundi de Pâques) | H32: =IF($G32<>"",H31,H31+1) -> 26
A33: S27 | B33: 05/04/2027 | C33: P4 | D33: =IF($G33<>"",$G33&" — les séances suivantes se décalent d'une semaine",INDEX('⚙ Moteur'!$B$5:$B$41,$H33)) -> S8 · séance 1 | H33: =IF($G33<>"",H32,H32+1) -> 27
A34: S28 | B34: 12/04/2027 | C34: P4 | D34: =IF($G34<>"",$G34&" — les séances suivantes se décalent d'une semaine",INDEX('⚙ Moteur'!$B$5:$B$41,$H34)) -> ⏳ TAMPON P4 — rattrapage / remédiation | H34: =IF($G34<>"",H33,H33+1) -> 28
A35: 🏖 Vacances de Pâques : 20/04 → 3/05
A36: S29 | B36: 03/05/2027 | C36: P5 | D36: =IF($G36<>"",$G36&" — les séances suivantes se décalent d'une semaine",INDEX('⚙ Moteur'!$B$5:$B$41,$H36)) -> S8 · séance 2 | E36: Jeu. 6/05 férié (Ascension) — pont probable | H36: =IF($G36<>"",H34,H34+1) -> 29
A37: S30 | B37: 10/05/2027 | C37: P5 | D37: =IF($G37<>"",$G37&" — les séances suivantes se décalent d'une semaine",INDEX('⚙ Moteur'!$B$5:$B$41,$H37)) -> S8 · séance 3 | H37: =IF($G37<>"",H36,H36+1) -> 30
A38: S31 | B38: 17/05/2027 | C38: P5 | D38: =IF($G38<>"",$G38&" — les séances suivantes se décalent d'une semaine",INDEX('⚙ Moteur'!$B$5:$B$41,$H38)) -> S8 · séance 4 | E38: Lun. 17/05 férié (Pentecôte) | H38: =IF($G38<>"",H37,H37+1) -> 31
A39: S32 | B39: 24/05/2027 | C39: P5 | D39: =IF($G39<>"",$G39&" — les séances suivantes se décalent d'une semaine",INDEX('⚙ Moteur'!$B$5:$B$41,$H39)) -> S9 · séance 1 | H39: =IF($G39<>"",H38,H38+1) -> 32
A40: S33 | B40: 31/05/2027 | C40: P5 | D40: =IF($G40<>"",$G40&" — les séances suivantes se décalent d'une semaine",INDEX('⚙ Moteur'!$B$5:$B$41,$H40)) -> S9 · séance 2 | H40: =IF($G40<>"",H39,H39+1) -> 33
A41: S34 | B41: 07/06/2027 | C41: P5 | D41: =IF($G41<>"",$G41&" — les séances suivantes se décalent d'une semaine",INDEX('⚙ Moteur'!$B$5:$B$41,$H41)) -> S9 · séance 3 | H41: =IF($G41<>"",H40,H40+1) -> 34
A42: S35 | B42: 14/06/2027 | C42: P5 | D42: =IF($G42<>"",$G42&" — les séances suivantes se décalent d'une semaine",INDEX('⚙ Moteur'!$B$5:$B$41,$H42)) -> ⏳ 🎓 RÉVISIONS DNB — annales, oraux blancs (a) | H42: =IF($G42<>"",H41,H41+1) -> 35
A43: S36 | B43: 21/06/2027 | C43: P5 | D43: =IF($G43<>"",$G43&" — les séances suivantes se décalent d'une semaine",INDEX('⚙ Moteur'!$B$5:$B$41,$H43)) -> ⏳ 🎓 RÉVISIONS DNB — annales, oraux blancs (b) | E43: ⚑ DNB : épreuves écrites fin juin (dates officielles à reporter ici) | H43: =IF($G43<>"",H42,H42+1) -> 36
A44: S37 | B44: 28/06/2027 | C44: P5 | D44: =IF($G44<>"",$G44&" — les séances suivantes se décalent d'une semaine",INDEX('⚙ Moteur'!$B$5:$B$41,$H44)) -> ⏳ 🎓 RÉVISIONS DNB + rattrapages (c) | H44: =IF($G44<>"",H43,H43+1) -> 37
A45: 🏖 Fin des cours : 3 juillet 2027
A47: Synthèse
B48: Semaines de cours au total | C48: 37
B49: … dont tampons + révisions DNB | C49: =COUNTIF(D4:D44,"⏳*") -> 7
B50: … dont semaines avec séance planifiée | C50: =COUNTIF(D4:D44,"S*") -> 30
B51: Année DNB : ajusté de 35 → 30 séances (référentiel sur-planifié pour 1 h 30/sem + DNB — à entériner au Conseil). Les dates officielles du DNB seront reportées dans « Repères » dès parution.

Sheet 🗓 Frise de l'année
A1: FRISE DE L'ANNÉE 3e — se recalcule automatiquement selon les imprévus du Calendrier
B2: ='📅 Calendrier'!D2 -> ✔ Réserve d'aléas : 7 semaine(s) restante(s) sur 7 (4 tampons + 3 sem. DNB) | P2: ◀ Accueil
C3: P1 (8 sem.) | K3: P2 (7 sem.) | R3: P3 (5 sem.) | W3: P4 (8 sem.) | AE3: P5 (9 sem.)
C4: S01 | D4: S02 | E4: S03 | F4: S04 | G4: S05 | H4: S06 | I4: S07 | J4: S08 | K4: S09 | L4: S10 | M4: S11 | N4: S12 | O4: S13 | P4: S14 | Q4: S15 | R4: S16 | S4: S17 | T4: S18 | U4: S19 | V4: S20 | W4: S21 | X4: S22 | Y4: S23 | Z4: S24 | AA4: S25 | AB4: S26 | AC4: S27 | AD4: S28 | AE4: S29 | AF4: S30 | AG4: S31 | AH4: S32 | AI4: S33 | AJ4: S34 | AK4: S35 | AL4: S36 | AM4: S37
C5: 31/08 | D5: 07/09 | E5: 14/09 | F5: 21/09 | G5: 28/09 | H5: 05/10 | I5: 12/10 | J5: 19/10 | K5: 02/11 | L5: 09/11 | M5: 16/11 | N5: 23/11 | O5: 30/11 | P5: 07/12 | Q5: 14/12 | R5: 04/01 | S5: 11/01 | T5: 18/01 | U5: 25/01 | V5: 01/02 | W5: 22/02 | X5: 01/03 | Y5: 08/03 | Z5: 15/03 | AA5: 22/03 | AB5: 29/03 | AC5: 05/04 | AD5: 12/04 | AE5: 03/05 | AF5: 10/05 | AG5: 17/05 | AH5: 24/05 | AI5: 31/05 | AJ5: 07/06 | AK5: 14/06 | AL5: 21/06 | AM5: 28/06
B6: S1 · Innovation et rupture | C6: =IF(LEFT('📅 Calendrier'!$D4,2)="S1",MID('📅 Calendrier'!$D4,SEARCH("séance",'📅 Calendrier'!$D4)+7,2),"") -> 1 | D6: =IF(LEFT('📅 Calendrier'!$D5,2)="S1",MID('📅 Calendrier'!$D5,SEARCH("séance",'📅 Calendrier'!$D5)+7,2),"") -> 2 | E6: =IF(LEFT('📅 Calendrier'!$D6,2)="S1",MID('📅 Calendrier'!$D6,SEARCH("séance",'📅 Calendrier'!$D6)+7,2),"") -> 3 | F6: =IF(LEFT('📅 Calendrier'!$D7,2)="S1",MID('📅 Calendrier'!$D7,SEARCH("séance",'📅 Calendrier'!$D7)+7,2),"") | G6: =IF(LEFT('📅 Calendrier'!$D8,2)="S1",MID('📅 Calendrier'!$D8,SEARCH("séance",'📅 Calendrier'!$D8)+7,2),"") | H6: =IF(LEFT('📅 Calendrier'!$D9,2)="S1",MID('📅 Calendrier'!$D9,SEARCH("séance",'📅 Calendrier'!$D9)+7,2),"") | I6: =IF(LEFT('📅 Calendrier'!$D10,2)="S1",MID('📅 Calendrier'!$D10,SEARCH("séance",'📅 Calendrier'!$D10)+7,2),"") | J6: =IF(LEFT('📅 Calendrier'!$D11,2)="S1",MID('📅 Calendrier'!$D11,SEARCH("séance",'📅 Calendrier'!$D11)+7,2),"") | K6: =IF(LEFT('📅 Calendrier'!$D13,2)="S1",MID('📅 Calendrier'!$D13,SEARCH("séance",'📅 Calendrier'!$D13)+7,2),"") | L6: =IF(LEFT('📅 Calendrier'!$D14,2)="S1",MID('📅 Calendrier'!$D14,SEARCH("séance",'📅 Calendrier'!$D14)+7,2),"") | M6: =IF(LEFT('📅 Calendrier'!$D15,2)="S1",MID('📅 Calendrier'!$D15,SEARCH("séance",'📅 Calendrier'!$D15)+7,2),"") | N6: =IF(LEFT('📅 Calendrier'!$D16,2)="S1",MID('📅 Calendrier'!$D16,SEARCH("séance",'📅 Calendrier'!$D16)+7,2),"") | O6: =IF(LEFT('📅 Calendrier'!$D17,2)="S1",MID('📅 Calendrier'!$D17,SEARCH("séance",'📅 Calendrier'!$D17)+7,2),"") | P6: =IF(LEFT('📅 Calendrier'!$D18,2)="S1",MID('📅 Calendrier'!$D18,SEARCH("séance",'📅 Calendrier'!$D18)+7,2),"") | Q6: =IF(LEFT('📅 Calendrier'!$D19,2)="S1",MID('📅 Calendrier'!$D19,SEARCH("séance",'📅 Calendrier'!$D19)+7,2),"") | R6: =IF(LEFT('📅 Calendrier'!$D21,2)="S1",MID('📅 Calendrier'!$D21,SEARCH("séance",'📅 Calendrier'!$D21)+7,2),"") | S6: =IF(LEFT('📅 Calendrier'!$D22,2)="S1",MID('📅 Calendrier'!$D22,SEARCH("séance",'📅 Calendrier'!$D22)+7,2),"") | T6: =IF(LEFT('📅 Calendrier'!$D23,2)="S1",MID('📅 Calendrier'!$D23,SEARCH("séance",'📅 Calendrier'!$D23)+7,2),"") | U6: =IF(LEFT('📅 Calendrier'!$D24,2)="S1",MID('📅 Calendrier'!$D24,SEARCH("séance",'📅 Calendrier'!$D24)+7,2),"") | V6: =IF(LEFT('📅 Calendrier'!$D25,2)="S1",MID('📅 Calendrier'!$D25,SEARCH("séance",'📅 Calendrier'!$D25)+7,2),"") | W6: =IF(LEFT('📅 Calendrier'!$D27,2)="S1",MID('📅 Calendrier'!$D27,SEARCH("séance",'📅 Calendrier'!$D27)+7,2),"") | X6: =IF(LEFT('📅 Calendrier'!$D28,2)="S1",MID('📅 Calendrier'!$D28,SEARCH("séance",'📅 Calendrier'!$D28)+7,2),"") | Y6: =IF(LEFT('📅 Calendrier'!$D29,2)="S1",MID('📅 Calendrier'!$D29,SEARCH("séance",'📅 Calendrier'!$D29)+7,2),"") | Z6: =IF(LEFT('📅 Calendrier'!$D30,2)="S1",MID('📅 Calendrier'!$D30,SEARCH("séance",'📅 Calendrier'!$D30)+7,2),"") | AA6: =IF(LEFT('📅 Calendrier'!$D31,2)="S1",MID('📅 Calendrier'!$D31,SEARCH("séance",'📅 Calendrier'!$D31)+7,2),"") | AB6: =IF(LEFT('📅 Calendrier'!$D32,2)="S1",MID('📅 Calendrier'!$D32,SEARCH("séance",'📅 Calendrier'!$D32)+7,2),"") | AC6: =IF(LEFT('📅 Calendrier'!$D33,2)="S1",MID('📅 Calendrier'!$D33,SEARCH("séance",'📅 Calendrier'!$D33)+7,2),"") | AD6: =IF(LEFT('📅 Calendrier'!$D34,2)="S1",MID('📅 Calendrier'!$D34,SEARCH("séance",'📅 Calendrier'!$D34)+7,2),"") | AE6: =IF(LEFT('📅 Calendrier'!$D36,2)="S1",MID('📅 Calendrier'!$D36,SEARCH("séance",'📅 Calendrier'!$D36)+7,2),"") | AF6: =IF(LEFT('📅 Calendrier'!$D37,2)="S1",MID('📅 Calendrier'!$D37,SEARCH("séance",'📅 Calendrier'!$D37)+7,2),"") | AG6: =IF(LEFT('📅 Calendrier'!$D38,2)="S1",MID('📅 Calendrier'!$D38,SEARCH("séance",'📅 Calendrier'!$D38)+7,2),"") | AH6: =IF(LEFT('📅 Calendrier'!$D39,2)="S1",MID('📅 Calendrier'!$D39,SEARCH("séance",'📅 Calendrier'!$D39)+7,2),"") | AI6: =IF(LEFT('📅 Calendrier'!$D40,2)="S1",MID('📅 Calendrier'!$D40,SEARCH("séance",'📅 Calendrier'!$D40)+7,2),"") | AJ6: =IF(LEFT('📅 Calendrier'!$D41,2)="S1",MID('📅 Calendrier'!$D41,SEARCH("séance",'📅 Calendrier'!$D41)+7,2),"") | AK6: =IF(LEFT('📅 Calendrier'!$D42,2)="S1",MID('📅 Calendrier'!$D42,SEARCH("séance",'📅 Calendrier'!$D42)+7,2),"") | AL6: =IF(LEFT('📅 Calendrier'!$D43,2)="S1",MID('📅 Calendrier'!$D43,SEARCH("séance",'📅 Calendrier'!$D43)+7,2),"") | AM6: =IF(LEFT('📅 Calendrier'!$D44,2)="S1",MID('📅 Calendrier'!$D44,SEARCH("séance",'📅 Calendrier'!$D44)+7,2),"")
B7: S2 · Numérique et société | C7: =IF(LEFT('📅 Calendrier'!$D4,2)="S2",MID('📅 Calendrier'!$D4,SEARCH("séance",'📅 Calendrier'!$D4)+7,2),"") | D7: =IF(LEFT('📅 Calendrier'!$D5,2)="S2",MID('📅 Calendrier'!$D5,SEARCH("séance",'📅 Calendrier'!$D5)+7,2),"") | E7: =IF(LEFT('📅 Calendrier'!$D6,2)="S2",MID('📅 Calendrier'!$D6,SEARCH("séance",'📅 Calendrier'!$D6)+7,2),"") | F7: =IF(LEFT('📅 Calendrier'!$D7,2)="S2",MID('📅 Calendrier'!$D7,SEARCH("séance",'📅 Calendrier'!$D7)+7,2),"") -> 1 | G7: =IF(LEFT('📅 Calendrier'!$D8,2)="S2",MID('📅 Calendrier'!$D8,SEARCH("séance",'📅 Calendrier'!$D8)+7,2),"") -> 2 | H7: =IF(LEFT('📅 Calendrier'!$D9,2)="S2",MID('📅 Calendrier'!$D9,SEARCH("séance",'📅 Calendrier'!$D9)+7,2),"") | I7: =IF(LEFT('📅 Calendrier'!$D10,2)="S2",MID('📅 Calendrier'!$D10,SEARCH("séance",'📅 Calendrier'!$D10)+7,2),"") | J7: =IF(LEFT('📅 Calendrier'!$D11,2)="S2",MID('📅 Calendrier'!$D11,SEARCH("séance",'📅 Calendrier'!$D11)+7,2),"") | K7: =IF(LEFT('📅 Calendrier'!$D13,2)="S2",MID('📅 Calendrier'!$D13,SEARCH("séance",'📅 Calendrier'!$D13)+7,2),"") | L7: =IF(LEFT('📅 Calendrier'!$D14,2)="S2",MID('📅 Calendrier'!$D14,SEARCH("séance",'📅 Calendrier'!$D14)+7,2),"") | M7: =IF(LEFT('📅 Calendrier'!$D15,2)="S2",MID('📅 Calendrier'!$D15,SEARCH("séance",'📅 Calendrier'!$D15)+7,2),"") | N7: =IF(LEFT('📅 Calendrier'!$D16,2)="S2",MID('📅 Calendrier'!$D16,SEARCH("séance",'📅 Calendrier'!$D16)+7,2),"") | O7: =IF(LEFT('📅 Calendrier'!$D17,2)="S2",MID('📅 Calendrier'!$D17,SEARCH("séance",'📅 Calendrier'!$D17)+7,2),"") | P7: =IF(LEFT('📅 Calendrier'!$D18,2)="S2",MID('📅 Calendrier'!$D18,SEARCH("séance",'📅 Calendrier'!$D18)+7,2),"") | Q7: =IF(LEFT('📅 Calendrier'!$D19,2)="S2",MID('📅 Calendrier'!$D19,SEARCH("séance",'📅 Calendrier'!$D19)+7,2),"") | R7: =IF(LEFT('📅 Calendrier'!$D21,2)="S2",MID('📅 Calendrier'!$D21,SEARCH("séance",'📅 Calendrier'!$D21)+7,2),"") | S7: =IF(LEFT('📅 Calendrier'!$D22,2)="S2",MID('📅 Calendrier'!$D22,SEARCH("séance",'📅 Calendrier'!$D22)+7,2),"") | T7: =IF(LEFT('📅 Calendrier'!$D23,2)="S2",MID('📅 Calendrier'!$D23,SEARCH("séance",'📅 Calendrier'!$D23)+7,2),"") | U7: =IF(LEFT('📅 Calendrier'!$D24,2)="S2",MID('📅 Calendrier'!$D24,SEARCH("séance",'📅 Calendrier'!$D24)+7,2),"") | V7: =IF(LEFT('📅 Calendrier'!$D25,2)="S2",MID('📅 Calendrier'!$D25,SEARCH("séance",'📅 Calendrier'!$D25)+7,2),"") | W7: =IF(LEFT('📅 Calendrier'!$D27,2)="S2",MID('📅 Calendrier'!$D27,SEARCH("séance",'📅 Calendrier'!$D27)+7,2),"") | X7: =IF(LEFT('📅 Calendrier'!$D28,2)="S2",MID('📅 Calendrier'!$D28,SEARCH("séance",'📅 Calendrier'!$D28)+7,2),"") | Y7: =IF(LEFT('📅 Calendrier'!$D29,2)="S2",MID('📅 Calendrier'!$D29,SEARCH("séance",'📅 Calendrier'!$D29)+7,2),"") | Z7: =IF(LEFT('📅 Calendrier'!$D30,2)="S2",MID('📅 Calendrier'!$D30,SEARCH("séance",'📅 Calendrier'!$D30)+7,2),"") | AA7: =IF(LEFT('📅 Calendrier'!$D31,2)="S2",MID('📅 Calendrier'!$D31,SEARCH("séance",'📅 Calendrier'!$D31)+7,2),"") | AB7: =IF(LEFT('📅 Calendrier'!$D32,2)="S2",MID('📅 Calendrier'!$D32,SEARCH("séance",'📅 Calendrier'!$D32)+7,2),"") | AC7: =IF(LEFT('📅 Calendrier'!$D33,2)="S2",MID('📅 Calendrier'!$D33,SEARCH("séance",'📅 Calendrier'!$D33)+7,2),"") | AD7: =IF(LEFT('📅 Calendrier'!$D34,2)="S2",MID('📅 Calendrier'!$D34,SEARCH("séance",'📅 Calendrier'!$D34)+7,2),"") | AE7: =IF(LEFT('📅 Calendrier'!$D36,2)="S2",MID('📅 Calendrier'!$D36,SEARCH("séance",'📅 Calendrier'!$D36)+7,2),"") | AF7: =IF(LEFT('📅 Calendrier'!$D37,2)="S2",MID('📅 Calendrier'!$D37,SEARCH("séance",'📅 Calendrier'!$D37)+7,2),"") | AG7: =IF(LEFT('📅 Calendrier'!$D38,2)="S2",MID('📅 Calendrier'!$D38,SEARCH("séance",'📅 Calendrier'!$D38)+7,2),"") | AH7: =IF(LEFT('📅 Calendrier'!$D39,2)="S2",MID('📅 Calendrier'!$D39,SEARCH("séance",'📅 Calendrier'!$D39)+7,2),"") | AI7: =IF(LEFT('📅 Calendrier'!$D40,2)="S2",MID('📅 Calendrier'!$D40,SEARCH("séance",'📅 Calendrier'!$D40)+7,2),"") | AJ7: =IF(LEFT('📅 Calendrier'!$D41,2)="S2",MID('📅 Calendrier'!$D41,SEARCH("séance",'📅 Calendrier'!$D41)+7,2),"") | AK7: =IF(LEFT('📅 Calendrier'!$D42,2)="S2",MID('📅 Calendrier'!$D42,SEARCH("séance",'📅 Calendrier'!$D42)+7,2),"") | AL7: =IF(LEFT('📅 Calendrier'!$D43,2)="S2",MID('📅 Calendrier'!$D43,SEARCH("séance",'📅 Calendrier'!$D43)+7,2),"") | AM7: =IF(LEFT('📅 Calendrier'!$D44,2)="S2",MID('📅 Calendrier'!$D44,SEARCH("séance",'📅 Calendrier'!$D44)+7,2),"")
B8: S3 · Choisir face au DD | C8: =IF(LEFT('📅 Calendrier'!$D4,2)="S3",MID('📅 Calendrier'!$D4,SEARCH("séance",'📅 Calendrier'!$D4)+7,2),"") | D8: =IF(LEFT('📅 Calendrier'!$D5,2)="S3",MID('📅 Calendrier'!$D5,SEARCH("séance",'📅 Calendrier'!$D5)+7,2),"") | E8: =IF(LEFT('📅 Calendrier'!$D6,2)="S3",MID('📅 Calendrier'!$D6,SEARCH("séance",'📅 Calendrier'!$D6)+7,2),"") | F8: =IF(LEFT('📅 Calendrier'!$D7,2)="S3",MID('📅 Calendrier'!$D7,SEARCH("séance",'📅 Calendrier'!$D7)+7,2),"") | G8: =IF(LEFT('📅 Calendrier'!$D8,2)="S3",MID('📅 Calendrier'!$D8,SEARCH("séance",'📅 Calendrier'!$D8)+7,2),"") | H8: =IF(LEFT('📅 Calendrier'!$D9,2)="S3",MID('📅 Calendrier'!$D9,SEARCH("séance",'📅 Calendrier'!$D9)+7,2),"") -> 1 | I8: =IF(LEFT('📅 Calendrier'!$D10,2)="S3",MID('📅 Calendrier'!$D10,SEARCH("séance",'📅 Calendrier'!$D10)+7,2),"") -> 2 | J8: =IF(LEFT('📅 Calendrier'!$D11,2)="S3",MID('📅 Calendrier'!$D11,SEARCH("séance",'📅 Calendrier'!$D11)+7,2),"") | K8: =IF(LEFT('📅 Calendrier'!$D13,2)="S3",MID('📅 Calendrier'!$D13,SEARCH("séance",'📅 Calendrier'!$D13)+7,2),"") -> 3 | L8: =IF(LEFT('📅 Calendrier'!$D14,2)="S3",MID('📅 Calendrier'!$D14,SEARCH("séance",'📅 Calendrier'!$D14)+7,2),"") | M8: =IF(LEFT('📅 Calendrier'!$D15,2)="S3",MID('📅 Calendrier'!$D15,SEARCH("séance",'📅 Calendrier'!$D15)+7,2),"") | N8: =IF(LEFT('📅 Calendrier'!$D16,2)="S3",MID('📅 Calendrier'!$D16,SEARCH("séance",'📅 Calendrier'!$D16)+7,2),"") | O8: =IF(LEFT('📅 Calendrier'!$D17,2)="S3",MID('📅 Calendrier'!$D17,SEARCH("séance",'📅 Calendrier'!$D17)+7,2),"") | P8: =IF(LEFT('📅 Calendrier'!$D18,2)="S3",MID('📅 Calendrier'!$D18,SEARCH("séance",'📅 Calendrier'!$D18)+7,2),"") | Q8: =IF(LEFT('📅 Calendrier'!$D19,2)="S3",MID('📅 Calendrier'!$D19,SEARCH("séance",'📅 Calendrier'!$D19)+7,2),"") | R8: =IF(LEFT('📅 Calendrier'!$D21,2)="S3",MID('📅 Calendrier'!$D21,SEARCH("séance",'📅 Calendrier'!$D21)+7,2),"") | S8: =IF(LEFT('📅 Calendrier'!$D22,2)="S3",MID('📅 Calendrier'!$D22,SEARCH("séance",'📅 Calendrier'!$D22)+7,2),"") | T8: =IF(LEFT('📅 Calendrier'!$D23,2)="S3",MID('📅 Calendrier'!$D23,SEARCH("séance",'📅 Calendrier'!$D23)+7,2),"") | U8: =IF(LEFT('📅 Calendrier'!$D24,2)="S3",MID('📅 Calendrier'!$D24,SEARCH("séance",'📅 Calendrier'!$D24)+7,2),"") | V8: =IF(LEFT('📅 Calendrier'!$D25,2)="S3",MID('📅 Calendrier'!$D25,SEARCH("séance",'📅 Calendrier'!$D25)+7,2),"") | W8: =IF(LEFT('📅 Calendrier'!$D27,2)="S3",MID('📅 Calendrier'!$D27,SEARCH("séance",'📅 Calendrier'!$D27)+7,2),"") | X8: =IF(LEFT('📅 Calendrier'!$D28,2)="S3",MID('📅 Calendrier'!$D28,SEARCH("séance",'📅 Calendrier'!$D28)+7,2),"") | Y8: =IF(LEFT('📅 Calendrier'!$D29,2)="S3",MID('📅 Calendrier'!$D29,SEARCH("séance",'📅 Calendrier'!$D29)+7,2),"") | Z8: =IF(LEFT('📅 Calendrier'!$D30,2)="S3",MID('📅 Calendrier'!$D30,SEARCH("séance",'📅 Calendrier'!$D30)+7,2),"") | AA8: =IF(LEFT('📅 Calendrier'!$D31,2)="S3",MID('📅 Calendrier'!$D31,SEARCH("séance",'📅 Calendrier'!$D31)+7,2),"") | AB8: =IF(LEFT('📅 Calendrier'!$D32,2)="S3",MID('📅 Calendrier'!$D32,SEARCH("séance",'📅 Calendrier'!$D32)+7,2),"") | AC8: =IF(LEFT('📅 Calendrier'!$D33,2)="S3",MID('📅 Calendrier'!$D33,SEARCH("séance",'📅 Calendrier'!$D33)+7,2),"") | AD8: =IF(LEFT('📅 Calendrier'!$D34,2)="S3",MID('📅 Calendrier'!$D34,SEARCH("séance",'📅 Calendrier'!$D34)+7,2),"") | AE8: =IF(LEFT('📅 Calendrier'!$D36,2)="S3",MID('📅 Calendrier'!$D36,SEARCH("séance",'📅 Calendrier'!$D36)+7,2),"") | AF8: =IF(LEFT('📅 Calendrier'!$D37,2)="S3",MID('📅 Calendrier'!$D37,SEARCH("séance",'📅 Calendrier'!$D37)+7,2),"") | AG8: =IF(LEFT('📅 Calendrier'!$D38,2)="S3",MID('📅 Calendrier'!$D38,SEARCH("séance",'📅 Calendrier'!$D38)+7,2),"") | AH8: =IF(LEFT('📅 Calendrier'!$D39,2)="S3",MID('📅 Calendrier'!$D39,SEARCH("séance",'📅 Calendrier'!$D39)+7,2),"") | AI8: =IF(LEFT('📅 Calendrier'!$D40,2)="S3",MID('📅 Calendrier'!$D40,SEARCH("séance",'📅 Calendrier'!$D40)+7,2),"") | AJ8: =IF(LEFT('📅 Calendrier'!$D41,2)="S3",MID('📅 Calendrier'!$D41,SEARCH("séance",'📅 Calendrier'!$D41)+7,2),"") | AK8: =IF(LEFT('📅 Calendrier'!$D42,2)="S3",MID('📅 Calendrier'!$D42,SEARCH("séance",'📅 Calendrier'!$D42)+7,2),"") | AL8: =IF(LEFT('📅 Calendrier'!$D43,2)="S3",MID('📅 Calendrier'!$D43,SEARCH("séance",'📅 Calendrier'!$D43)+7,2),"") | AM8: =IF(LEFT('📅 Calendrier'!$D44,2)="S3",MID('📅 Calendrier'!$D44,SEARCH("séance",'📅 Calendrier'!$D44)+7,2),"")
B9: S4 · Station cyclonique : chaînes | C9: =IF(LEFT('📅 Calendrier'!$D4,2)="S4",MID('📅 Calendrier'!$D4,SEARCH("séance",'📅 Calendrier'!$D4)+7,2),"") | D9: =IF(LEFT('📅 Calendrier'!$D5,2)="S4",MID('📅 Calendrier'!$D5,SEARCH("séance",'📅 Calendrier'!$D5)+7,2),"") | E9: =IF(LEFT('📅 Calendrier'!$D6,2)="S4",MID('📅 Calendrier'!$D6,SEARCH("séance",'📅 Calendrier'!$D6)+7,2),"") | F9: =IF(LEFT('📅 Calendrier'!$D7,2)="S4",MID('📅 Calendrier'!$D7,SEARCH("séance",'📅 Calendrier'!$D7)+7,2),"") | G9: =IF(LEFT('📅 Calendrier'!$D8,2)="S4",MID('📅 Calendrier'!$D8,SEARCH("séance",'📅 Calendrier'!$D8)+7,2),"") | H9: =IF(LEFT('📅 Calendrier'!$D9,2)="S4",MID('📅 Calendrier'!$D9,SEARCH("séance",'📅 Calendrier'!$D9)+7,2),"") | I9: =IF(LEFT('📅 Calendrier'!$D10,2)="S4",MID('📅 Calendrier'!$D10,SEARCH("séance",'📅 Calendrier'!$D10)+7,2),"") | J9: =IF(LEFT('📅 Calendrier'!$D11,2)="S4",MID('📅 Calendrier'!$D11,SEARCH("séance",'📅 Calendrier'!$D11)+7,2),"") | K9: =IF(LEFT('📅 Calendrier'!$D13,2)="S4",MID('📅 Calendrier'!$D13,SEARCH("séance",'📅 Calendrier'!$D13)+7,2),"") | L9: =IF(LEFT('📅 Calendrier'!$D14,2)="S4",MID('📅 Calendrier'!$D14,SEARCH("séance",'📅 Calendrier'!$D14)+7,2),"") -> 1 | M9: =IF(LEFT('📅 Calendrier'!$D15,2)="S4",MID('📅 Calendrier'!$D15,SEARCH("séance",'📅 Calendrier'!$D15)+7,2),"") -> 2 | N9: =IF(LEFT('📅 Calendrier'!$D16,2)="S4",MID('📅 Calendrier'!$D16,SEARCH("séance",'📅 Calendrier'!$D16)+7,2),"") -> 3 | O9: =IF(LEFT('📅 Calendrier'!$D17,2)="S4",MID('📅 Calendrier'!$D17,SEARCH("séance",'📅 Calendrier'!$D17)+7,2),"") -> 4 | P9: =IF(LEFT('📅 Calendrier'!$D18,2)="S4",MID('📅 Calendrier'!$D18,SEARCH("séance",'📅 Calendrier'!$D18)+7,2),"") -> 5 | Q9: =IF(LEFT('📅 Calendrier'!$D19,2)="S4",MID('📅 Calendrier'!$D19,SEARCH("séance",'📅 Calendrier'!$D19)+7,2),"") | R9: =IF(LEFT('📅 Calendrier'!$D21,2)="S4",MID('📅 Calendrier'!$D21,SEARCH("séance",'📅 Calendrier'!$D21)+7,2),"") | S9: =IF(LEFT('📅 Calendrier'!$D22,2)="S4",MID('📅 Calendrier'!$D22,SEARCH("séance",'📅 Calendrier'!$D22)+7,2),"") | T9: =IF(LEFT('📅 Calendrier'!$D23,2)="S4",MID('📅 Calendrier'!$D23,SEARCH("séance",'📅 Calendrier'!$D23)+7,2),"") | U9: =IF(LEFT('📅 Calendrier'!$D24,2)="S4",MID('📅 Calendrier'!$D24,SEARCH("séance",'📅 Calendrier'!$D24)+7,2),"") | V9: =IF(LEFT('📅 Calendrier'!$D25,2)="S4",MID('📅 Calendrier'!$D25,SEARCH("séance",'📅 Calendrier'!$D25)+7,2),"") | W9: =IF(LEFT('📅 Calendrier'!$D27,2)="S4",MID('📅 Calendrier'!$D27,SEARCH("séance",'📅 Calendrier'!$D27)+7,2),"") | X9: =IF(LEFT('📅 Calendrier'!$D28,2)="S4",MID('📅 Calendrier'!$D28,SEARCH("séance",'📅 Calendrier'!$D28)+7,2),"") | Y9: =IF(LEFT('📅 Calendrier'!$D29,2)="S4",MID('📅 Calendrier'!$D29,SEARCH("séance",'📅 Calendrier'!$D29)+7,2),"") | Z9: =IF(LEFT('📅 Calendrier'!$D30,2)="S4",MID('📅 Calendrier'!$D30,SEARCH("séance",'📅 Calendrier'!$D30)+7,2),"") | AA9: =IF(LEFT('📅 Calendrier'!$D31,2)="S4",MID('📅 Calendrier'!$D31,SEARCH("séance",'📅 Calendrier'!$D31)+7,2),"") | AB9: =IF(LEFT('📅 Calendrier'!$D32,2)="S4",MID('📅 Calendrier'!$D32,SEARCH("séance",'📅 Calendrier'!$D32)+7,2),"") | AC9: =IF(LEFT('📅 Calendrier'!$D33,2)="S4",MID('📅 Calendrier'!$D33,SEARCH("séance",'📅 Calendrier'!$D33)+7,2),"") | AD9: =IF(LEFT('📅 Calendrier'!$D34,2)="S4",MID('📅 Calendrier'!$D34,SEARCH("séance",'📅 Calendrier'!$D34)+7,2),"") | AE9: =IF(LEFT('📅 Calendrier'!$D36,2)="S4",MID('📅 Calendrier'!$D36,SEARCH("séance",'📅 Calendrier'!$D36)+7,2),"") | AF9: =IF(LEFT('📅 Calendrier'!$D37,2)="S4",MID('📅 Calendrier'!$D37,SEARCH("séance",'📅 Calendrier'!$D37)+7,2),"") | AG9: =IF(LEFT('📅 Calendrier'!$D38,2)="S4",MID('📅 Calendrier'!$D38,SEARCH("séance",'📅 Calendrier'!$D38)+7,2),"") | AH9: =IF(LEFT('📅 Calendrier'!$D39,2)="S4",MID('📅 Calendrier'!$D39,SEARCH("séance",'📅 Calendrier'!$D39)+7,2),"") | AI9: =IF(LEFT('📅 Calendrier'!$D40,2)="S4",MID('📅 Calendrier'!$D40,SEARCH("séance",'📅 Calendrier'!$D40)+7,2),"") | AJ9: =IF(LEFT('📅 Calendrier'!$D41,2)="S4",MID('📅 Calendrier'!$D41,SEARCH("séance",'📅 Calendrier'!$D41)+7,2),"") | AK9: =IF(LEFT('📅 Calendrier'!$D42,2)="S4",MID('📅 Calendrier'!$D42,SEARCH("séance",'📅 Calendrier'!$D42)+7,2),"") | AL9: =IF(LEFT('📅 Calendrier'!$D43,2)="S4",MID('📅 Calendrier'!$D43,SEARCH("séance",'📅 Calendrier'!$D43)+7,2),"") | AM9: =IF(LEFT('📅 Calendrier'!$D44,2)="S4",MID('📅 Calendrier'!$D44,SEARCH("séance",'📅 Calendrier'!$D44)+7,2),"")
B10: S5 · Internet Sainte-Luce : réseaux | C10: =IF(LEFT('📅 Calendrier'!$D4,2)="S5",MID('📅 Calendrier'!$D4,SEARCH("séance",'📅 Calendrier'!$D4)+7,2),"") | D10: =IF(LEFT('📅 Calendrier'!$D5,2)="S5",MID('📅 Calendrier'!$D5,SEARCH("séance",'📅 Calendrier'!$D5)+7,2),"") | E10: =IF(LEFT('📅 Calendrier'!$D6,2)="S5",MID('📅 Calendrier'!$D6,SEARCH("séance",'📅 Calendrier'!$D6)+7,2),"") | F10: =IF(LEFT('📅 Calendrier'!$D7,2)="S5",MID('📅 Calendrier'!$D7,SEARCH("séance",'📅 Calendrier'!$D7)+7,2),"") | G10: =IF(LEFT('📅 Calendrier'!$D8,2)="S5",MID('📅 Calendrier'!$D8,SEARCH("séance",'📅 Calendrier'!$D8)+7,2),"") | H10: =IF(LEFT('📅 Calendrier'!$D9,2)="S5",MID('📅 Calendrier'!$D9,SEARCH("séance",'📅 Calendrier'!$D9)+7,2),"") | I10: =IF(LEFT('📅 Calendrier'!$D10,2)="S5",MID('📅 Calendrier'!$D10,SEARCH("séance",'📅 Calendrier'!$D10)+7,2),"") | J10: =IF(LEFT('📅 Calendrier'!$D11,2)="S5",MID('📅 Calendrier'!$D11,SEARCH("séance",'📅 Calendrier'!$D11)+7,2),"") | K10: =IF(LEFT('📅 Calendrier'!$D13,2)="S5",MID('📅 Calendrier'!$D13,SEARCH("séance",'📅 Calendrier'!$D13)+7,2),"") | L10: =IF(LEFT('📅 Calendrier'!$D14,2)="S5",MID('📅 Calendrier'!$D14,SEARCH("séance",'📅 Calendrier'!$D14)+7,2),"") | M10: =IF(LEFT('📅 Calendrier'!$D15,2)="S5",MID('📅 Calendrier'!$D15,SEARCH("séance",'📅 Calendrier'!$D15)+7,2),"") | N10: =IF(LEFT('📅 Calendrier'!$D16,2)="S5",MID('📅 Calendrier'!$D16,SEARCH("séance",'📅 Calendrier'!$D16)+7,2),"") | O10: =IF(LEFT('📅 Calendrier'!$D17,2)="S5",MID('📅 Calendrier'!$D17,SEARCH("séance",'📅 Calendrier'!$D17)+7,2),"") | P10: =IF(LEFT('📅 Calendrier'!$D18,2)="S5",MID('📅 Calendrier'!$D18,SEARCH("séance",'📅 Calendrier'!$D18)+7,2),"") | Q10: =IF(LEFT('📅 Calendrier'!$D19,2)="S5",MID('📅 Calendrier'!$D19,SEARCH("séance",'📅 Calendrier'!$D19)+7,2),"") | R10: =IF(LEFT('📅 Calendrier'!$D21,2)="S5",MID('📅 Calendrier'!$D21,SEARCH("séance",'📅 Calendrier'!$D21)+7,2),"") -> 1 | S10: =IF(LEFT('📅 Calendrier'!$D22,2)="S5",MID('📅 Calendrier'!$D22,SEARCH("séance",'📅 Calendrier'!$D22)+7,2),"") -> 2 | T10: =IF(LEFT('📅 Calendrier'!$D23,2)="S5",MID('📅 Calendrier'!$D23,SEARCH("séance",'📅 Calendrier'!$D23)+7,2),"") -> 3 | U10: =IF(LEFT('📅 Calendrier'!$D24,2)="S5",MID('📅 Calendrier'!$D24,SEARCH("séance",'📅 Calendrier'!$D24)+7,2),"") | V10: =IF(LEFT('📅 Calendrier'!$D25,2)="S5",MID('📅 Calendrier'!$D25,SEARCH("séance",'📅 Calendrier'!$D25)+7,2),"") | W10: =IF(LEFT('📅 Calendrier'!$D27,2)="S5",MID('📅 Calendrier'!$D27,SEARCH("séance",'📅 Calendrier'!$D27)+7,2),"") | X10: =IF(LEFT('📅 Calendrier'!$D28,2)="S5",MID('📅 Calendrier'!$D28,SEARCH("séance",'📅 Calendrier'!$D28)+7,2),"") | Y10: =IF(LEFT('📅 Calendrier'!$D29,2)="S5",MID('📅 Calendrier'!$D29,SEARCH("séance",'📅 Calendrier'!$D29)+7,2),"") | Z10: =IF(LEFT('📅 Calendrier'!$D30,2)="S5",MID('📅 Calendrier'!$D30,SEARCH("séance",'📅 Calendrier'!$D30)+7,2),"") | AA10: =IF(LEFT('📅 Calendrier'!$D31,2)="S5",MID('📅 Calendrier'!$D31,SEARCH("séance",'📅 Calendrier'!$D31)+7,2),"") | AB10: =IF(LEFT('📅 Calendrier'!$D32,2)="S5",MID('📅 Calendrier'!$D32,SEARCH("séance",'📅 Calendrier'!$D32)+7,2),"") | AC10: =IF(LEFT('📅 Calendrier'!$D33,2)="S5",MID('📅 Calendrier'!$D33,SEARCH("séance",'📅 Calendrier'!$D33)+7,2),"") | AD10: =IF(LEFT('📅 Calendrier'!$D34,2)="S5",MID('📅 Calendrier'!$D34,SEARCH("séance",'📅 Calendrier'!$D34)+7,2),"") | AE10: =IF(LEFT('📅 Calendrier'!$D36,2)="S5",MID('📅 Calendrier'!$D36,SEARCH("séance",'📅 Calendrier'!$D36)+7,2),"") | AF10: =IF(LEFT('📅 Calendrier'!$D37,2)="S5",MID('📅 Calendrier'!$D37,SEARCH("séance",'📅 Calendrier'!$D37)+7,2),"") | AG10: =IF(LEFT('📅 Calendrier'!$D38,2)="S5",MID('📅 Calendrier'!$D38,SEARCH("séance",'📅 Calendrier'!$D38)+7,2),"") | AH10: =IF(LEFT('📅 Calendrier'!$D39,2)="S5",MID('📅 Calendrier'!$D39,SEARCH("séance",'📅 Calendrier'!$D39)+7,2),"") | AI10: =IF(LEFT('📅 Calendrier'!$D40,2)="S5",MID('📅 Calendrier'!$D40,SEARCH("séance",'📅 Calendrier'!$D40)+7,2),"") | AJ10: =IF(LEFT('📅 Calendrier'!$D41,2)="S5",MID('📅 Calendrier'!$D41,SEARCH("séance",'📅 Calendrier'!$D41)+7,2),"") | AK10: =IF(LEFT('📅 Calendrier'!$D42,2)="S5",MID('📅 Calendrier'!$D42,SEARCH("séance",'📅 Calendrier'!$D42)+7,2),"") | AL10: =IF(LEFT('📅 Calendrier'!$D43,2)="S5",MID('📅 Calendrier'!$D43,SEARCH("séance",'📅 Calendrier'!$D43)+7,2),"") | AM10: =IF(LEFT('📅 Calendrier'!$D44,2)="S5",MID('📅 Calendrier'!$D44,SEARCH("séance",'📅 Calendrier'!$D44)+7,2),"")
B11: S6 · SOS station + Programmer | C11: =IF(LEFT('📅 Calendrier'!$D4,2)="S6",MID('📅 Calendrier'!$D4,SEARCH("séance",'📅 Calendrier'!$D4)+7,2),"") | D11: =IF(LEFT('📅 Calendrier'!$D5,2)="S6",MID('📅 Calendrier'!$D5,SEARCH("séance",'📅 Calendrier'!$D5)+7,2),"") | E11: =IF(LEFT('📅 Calendrier'!$D6,2)="S6",MID('📅 Calendrier'!$D6,SEARCH("séance",'📅 Calendrier'!$D6)+7,2),"") | F11: =IF(LEFT('📅 Calendrier'!$D7,2)="S6",MID('📅 Calendrier'!$D7,SEARCH("séance",'📅 Calendrier'!$D7)+7,2),"") | G11: =IF(LEFT('📅 Calendrier'!$D8,2)="S6",MID('📅 Calendrier'!$D8,SEARCH("séance",'📅 Calendrier'!$D8)+7,2),"") | H11: =IF(LEFT('📅 Calendrier'!$D9,2)="S6",MID('📅 Calendrier'!$D9,SEARCH("séance",'📅 Calendrier'!$D9)+7,2),"") | I11: =IF(LEFT('📅 Calendrier'!$D10,2)="S6",MID('📅 Calendrier'!$D10,SEARCH("séance",'📅 Calendrier'!$D10)+7,2),"") | J11: =IF(LEFT('📅 Calendrier'!$D11,2)="S6",MID('📅 Calendrier'!$D11,SEARCH("séance",'📅 Calendrier'!$D11)+7,2),"") | K11: =IF(LEFT('📅 Calendrier'!$D13,2)="S6",MID('📅 Calendrier'!$D13,SEARCH("séance",'📅 Calendrier'!$D13)+7,2),"") | L11: =IF(LEFT('📅 Calendrier'!$D14,2)="S6",MID('📅 Calendrier'!$D14,SEARCH("séance",'📅 Calendrier'!$D14)+7,2),"") | M11: =IF(LEFT('📅 Calendrier'!$D15,2)="S6",MID('📅 Calendrier'!$D15,SEARCH("séance",'📅 Calendrier'!$D15)+7,2),"") | N11: =IF(LEFT('📅 Calendrier'!$D16,2)="S6",MID('📅 Calendrier'!$D16,SEARCH("séance",'📅 Calendrier'!$D16)+7,2),"") | O11: =IF(LEFT('📅 Calendrier'!$D17,2)="S6",MID('📅 Calendrier'!$D17,SEARCH("séance",'📅 Calendrier'!$D17)+7,2),"") | P11: =IF(LEFT('📅 Calendrier'!$D18,2)="S6",MID('📅 Calendrier'!$D18,SEARCH("séance",'📅 Calendrier'!$D18)+7,2),"") | Q11: =IF(LEFT('📅 Calendrier'!$D19,2)="S6",MID('📅 Calendrier'!$D19,SEARCH("séance",'📅 Calendrier'!$D19)+7,2),"") | R11: =IF(LEFT('📅 Calendrier'!$D21,2)="S6",MID('📅 Calendrier'!$D21,SEARCH("séance",'📅 Calendrier'!$D21)+7,2),"") | S11: =IF(LEFT('📅 Calendrier'!$D22,2)="S6",MID('📅 Calendrier'!$D22,SEARCH("séance",'📅 Calendrier'!$D22)+7,2),"") | T11: =IF(LEFT('📅 Calendrier'!$D23,2)="S6",MID('📅 Calendrier'!$D23,SEARCH("séance",'📅 Calendrier'!$D23)+7,2),"") | U11: =IF(LEFT('📅 Calendrier'!$D24,2)="S6",MID('📅 Calendrier'!$D24,SEARCH("séance",'📅 Calendrier'!$D24)+7,2),"") -> 1 | V11: =IF(LEFT('📅 Calendrier'!$D25,2)="S6",MID('📅 Calendrier'!$D25,SEARCH("séance",'📅 Calendrier'!$D25)+7,2),"") | W11: =IF(LEFT('📅 Calendrier'!$D27,2)="S6",MID('📅 Calendrier'!$D27,SEARCH("séance",'📅 Calendrier'!$D27)+7,2),"") -> 2 | X11: =IF(LEFT('📅 Calendrier'!$D28,2)="S6",MID('📅 Calendrier'!$D28,SEARCH("séance",'📅 Calendrier'!$D28)+7,2),"") -> 3 | Y11: =IF(LEFT('📅 Calendrier'!$D29,2)="S6",MID('📅 Calendrier'!$D29,SEARCH("séance",'📅 Calendrier'!$D29)+7,2),"") -> 4 | Z11: =IF(LEFT('📅 Calendrier'!$D30,2)="S6",MID('📅 Calendrier'!$D30,SEARCH("séance",'📅 Calendrier'!$D30)+7,2),"") | AA11: =IF(LEFT('📅 Calendrier'!$D31,2)="S6",MID('📅 Calendrier'!$D31,SEARCH("séance",'📅 Calendrier'!$D31)+7,2),"") | AB11: =IF(LEFT('📅 Calendrier'!$D32,2)="S6",MID('📅 Calendrier'!$D32,SEARCH("séance",'📅 Calendrier'!$D32)+7,2),"") | AC11: =IF(LEFT('📅 Calendrier'!$D33,2)="S6",MID('📅 Calendrier'!$D33,SEARCH("séance",'📅 Calendrier'!$D33)+7,2),"") | AD11: =IF(LEFT('📅 Calendrier'!$D34,2)="S6",MID('📅 Calendrier'!$D34,SEARCH("séance",'📅 Calendrier'!$D34)+7,2),"") | AE11: =IF(LEFT('📅 Calendrier'!$D36,2)="S6",MID('📅 Calendrier'!$D36,SEARCH("séance",'📅 Calendrier'!$D36)+7,2),"") | AF11: =IF(LEFT('📅 Calendrier'!$D37,2)="S6",MID('📅 Calendrier'!$D37,SEARCH("séance",'📅 Calendrier'!$D37)+7,2),"") | AG11: =IF(LEFT('📅 Calendrier'!$D38,2)="S6",MID('📅 Calendrier'!$D38,SEARCH("séance",'📅 Calendrier'!$D38)+7,2),"") | AH11: =IF(LEFT('📅 Calendrier'!$D39,2)="S6",MID('📅 Calendrier'!$D39,SEARCH("séance",'📅 Calendrier'!$D39)+7,2),"") | AI11: =IF(LEFT('📅 Calendrier'!$D40,2)="S6",MID('📅 Calendrier'!$D40,SEARCH("séance",'📅 Calendrier'!$D40)+7,2),"") | AJ11: =IF(LEFT('📅 Calendrier'!$D41,2)="S6",MID('📅 Calendrier'!$D41,SEARCH("séance",'📅 Calendrier'!$D41)+7,2),"") | AK11: =IF(LEFT('📅 Calendrier'!$D42,2)="S6",MID('📅 Calendrier'!$D42,SEARCH("séance",'📅 Calendrier'!$D42)+7,2),"") | AL11: =IF(LEFT('📅 Calendrier'!$D43,2)="S6",MID('📅 Calendrier'!$D43,SEARCH("séance",'📅 Calendrier'!$D43)+7,2),"") | AM11: =IF(LEFT('📅 Calendrier'!$D44,2)="S6",MID('📅 Calendrier'!$D44,SEARCH("séance",'📅 Calendrier'!$D44)+7,2),"")
B12: S7 · Fil rouge V1 : cadrage | C12: =IF(LEFT('📅 Calendrier'!$D4,2)="S7",MID('📅 Calendrier'!$D4,SEARCH("séance",'📅 Calendrier'!$D4)+7,2),"") | D12: =IF(LEFT('📅 Calendrier'!$D5,2)="S7",MID('📅 Calendrier'!$D5,SEARCH("séance",'📅 Calendrier'!$D5)+7,2),"") | E12: =IF(LEFT('📅 Calendrier'!$D6,2)="S7",MID('📅 Calendrier'!$D6,SEARCH("séance",'📅 Calendrier'!$D6)+7,2),"") | F12: =IF(LEFT('📅 Calendrier'!$D7,2)="S7",MID('📅 Calendrier'!$D7,SEARCH("séance",'📅 Calendrier'!$D7)+7,2),"") | G12: =IF(LEFT('📅 Calendrier'!$D8,2)="S7",MID('📅 Calendrier'!$D8,SEARCH("séance",'📅 Calendrier'!$D8)+7,2),"") | H12: =IF(LEFT('📅 Calendrier'!$D9,2)="S7",MID('📅 Calendrier'!$D9,SEARCH("séance",'📅 Calendrier'!$D9)+7,2),"") | I12: =IF(LEFT('📅 Calendrier'!$D10,2)="S7",MID('📅 Calendrier'!$D10,SEARCH("séance",'📅 Calendrier'!$D10)+7,2),"") | J12: =IF(LEFT('📅 Calendrier'!$D11,2)="S7",MID('📅 Calendrier'!$D11,SEARCH("séance",'📅 Calendrier'!$D11)+7,2),"") | K12: =IF(LEFT('📅 Calendrier'!$D13,2)="S7",MID('📅 Calendrier'!$D13,SEARCH("séance",'📅 Calendrier'!$D13)+7,2),"") | L12: =IF(LEFT('📅 Calendrier'!$D14,2)="S7",MID('📅 Calendrier'!$D14,SEARCH("séance",'📅 Calendrier'!$D14)+7,2),"") | M12: =IF(LEFT('📅 Calendrier'!$D15,2)="S7",MID('📅 Calendrier'!$D15,SEARCH("séance",'📅 Calendrier'!$D15)+7,2),"") | N12: =IF(LEFT('📅 Calendrier'!$D16,2)="S7",MID('📅 Calendrier'!$D16,SEARCH("séance",'📅 Calendrier'!$D16)+7,2),"") | O12: =IF(LEFT('📅 Calendrier'!$D17,2)="S7",MID('📅 Calendrier'!$D17,SEARCH("séance",'📅 Calendrier'!$D17)+7,2),"") | P12: =IF(LEFT('📅 Calendrier'!$D18,2)="S7",MID('📅 Calendrier'!$D18,SEARCH("séance",'📅 Calendrier'!$D18)+7,2),"") | Q12: =IF(LEFT('📅 Calendrier'!$D19,2)="S7",MID('📅 Calendrier'!$D19,SEARCH("séance",'📅 Calendrier'!$D19)+7,2),"") | R12: =IF(LEFT('📅 Calendrier'!$D21,2)="S7",MID('📅 Calendrier'!$D21,SEARCH("séance",'📅 Calendrier'!$D21)+7,2),"") | S12: =IF(LEFT('📅 Calendrier'!$D22,2)="S7",MID('📅 Calendrier'!$D22,SEARCH("séance",'📅 Calendrier'!$D22)+7,2),"") | T12: =IF(LEFT('📅 Calendrier'!$D23,2)="S7",MID('📅 Calendrier'!$D23,SEARCH("séance",'📅 Calendrier'!$D23)+7,2),"") | U12: =IF(LEFT('📅 Calendrier'!$D24,2)="S7",MID('📅 Calendrier'!$D24,SEARCH("séance",'📅 Calendrier'!$D24)+7,2),"") | V12: =IF(LEFT('📅 Calendrier'!$D25,2)="S7",MID('📅 Calendrier'!$D25,SEARCH("séance",'📅 Calendrier'!$D25)+7,2),"") | W12: =IF(LEFT('📅 Calendrier'!$D27,2)="S7",MID('📅 Calendrier'!$D27,SEARCH("séance",'📅 Calendrier'!$D27)+7,2),"") | X12: =IF(LEFT('📅 Calendrier'!$D28,2)="S7",MID('📅 Calendrier'!$D28,SEARCH("séance",'📅 Calendrier'!$D28)+7,2),"") | Y12: =IF(LEFT('📅 Calendrier'!$D29,2)="S7",MID('📅 Calendrier'!$D29,SEARCH("séance",'📅 Calendrier'!$D29)+7,2),"") | Z12: =IF(LEFT('📅 Calendrier'!$D30,2)="S7",MID('📅 Calendrier'!$D30,SEARCH("séance",'📅 Calendrier'!$D30)+7,2),"") -> 1 | AA12: =IF(LEFT('📅 Calendrier'!$D31,2)="S7",MID('📅 Calendrier'!$D31,SEARCH("séance",'📅 Calendrier'!$D31)+7,2),"") -> 2 | AB12: =IF(LEFT('📅 Calendrier'!$D32,2)="S7",MID('📅 Calendrier'!$D32,SEARCH("séance",'📅 Calendrier'!$D32)+7,2),"") -> 3 | AC12: =IF(LEFT('📅 Calendrier'!$D33,2)="S7",MID('📅 Calendrier'!$D33,SEARCH("séance",'📅 Calendrier'!$D33)+7,2),"") | AD12: =IF(LEFT('📅 Calendrier'!$D34,2)="S7",MID('📅 Calendrier'!$D34,SEARCH("séance",'📅 Calendrier'!$D34)+7,2),"") | AE12: =IF(LEFT('📅 Calendrier'!$D36,2)="S7",MID('📅 Calendrier'!$D36,SEARCH("séance",'📅 Calendrier'!$D36)+7,2),"") | AF12: =IF(LEFT('📅 Calendrier'!$D37,2)="S7",MID('📅 Calendrier'!$D37,SEARCH("séance",'📅 Calendrier'!$D37)+7,2),"") | AG12: =IF(LEFT('📅 Calendrier'!$D38,2)="S7",MID('📅 Calendrier'!$D38,SEARCH("séance",'📅 Calendrier'!$D38)+7,2),"") | AH12: =IF(LEFT('📅 Calendrier'!$D39,2)="S7",MID('📅 Calendrier'!$D39,SEARCH("séance",'📅 Calendrier'!$D39)+7,2),"") | AI12: =IF(LEFT('📅 Calendrier'!$D40,2)="S7",MID('📅 Calendrier'!$D40,SEARCH("séance",'📅 Calendrier'!$D40)+7,2),"") | AJ12: =IF(LEFT('📅 Calendrier'!$D41,2)="S7",MID('📅 Calendrier'!$D41,SEARCH("séance",'📅 Calendrier'!$D41)+7,2),"") | AK12: =IF(LEFT('📅 Calendrier'!$D42,2)="S7",MID('📅 Calendrier'!$D42,SEARCH("séance",'📅 Calendrier'!$D42)+7,2),"") | AL12: =IF(LEFT('📅 Calendrier'!$D43,2)="S7",MID('📅 Calendrier'!$D43,SEARCH("séance",'📅 Calendrier'!$D43)+7,2),"") | AM12: =IF(LEFT('📅 Calendrier'!$D44,2)="S7",MID('📅 Calendrier'!$D44,SEARCH("séance",'📅 Calendrier'!$D44)+7,2),"")
B13: S8 · Fil rouge V2 : prototypage | C13: =IF(LEFT('📅 Calendrier'!$D4,2)="S8",MID('📅 Calendrier'!$D4,SEARCH("séance",'📅 Calendrier'!$D4)+7,2),"") | D13: =IF(LEFT('📅 Calendrier'!$D5,2)="S8",MID('📅 Calendrier'!$D5,SEARCH("séance",'📅 Calendrier'!$D5)+7,2),"") | E13: =IF(LEFT('📅 Calendrier'!$D6,2)="S8",MID('📅 Calendrier'!$D6,SEARCH("séance",'📅 Calendrier'!$D6)+7,2),"") | F13: =IF(LEFT('📅 Calendrier'!$D7,2)="S8",MID('📅 Calendrier'!$D7,SEARCH("séance",'📅 Calendrier'!$D7)+7,2),"") | G13: =IF(LEFT('📅 Calendrier'!$D8,2)="S8",MID('📅 Calendrier'!$D8,SEARCH("séance",'📅 Calendrier'!$D8)+7,2),"") | H13: =IF(LEFT('📅 Calendrier'!$D9,2)="S8",MID('📅 Calendrier'!$D9,SEARCH("séance",'📅 Calendrier'!$D9)+7,2),"") | I13: =IF(LEFT('📅 Calendrier'!$D10,2)="S8",MID('📅 Calendrier'!$D10,SEARCH("séance",'📅 Calendrier'!$D10)+7,2),"") | J13: =IF(LEFT('📅 Calendrier'!$D11,2)="S8",MID('📅 Calendrier'!$D11,SEARCH("séance",'📅 Calendrier'!$D11)+7,2),"") | K13: =IF(LEFT('📅 Calendrier'!$D13,2)="S8",MID('📅 Calendrier'!$D13,SEARCH("séance",'📅 Calendrier'!$D13)+7,2),"") | L13: =IF(LEFT('📅 Calendrier'!$D14,2)="S8",MID('📅 Calendrier'!$D14,SEARCH("séance",'📅 Calendrier'!$D14)+7,2),"") | M13: =IF(LEFT('📅 Calendrier'!$D15,2)="S8",MID('📅 Calendrier'!$D15,SEARCH("séance",'📅 Calendrier'!$D15)+7,2),"") | N13: =IF(LEFT('📅 Calendrier'!$D16,2)="S8",MID('📅 Calendrier'!$D16,SEARCH("séance",'📅 Calendrier'!$D16)+7,2),"") | O13: =IF(LEFT('📅 Calendrier'!$D17,2)="S8",MID('📅 Calendrier'!$D17,SEARCH("séance",'📅 Calendrier'!$D17)+7,2),"") | P13: =IF(LEFT('📅 Calendrier'!$D18,2)="S8",MID('📅 Calendrier'!$D18,SEARCH("séance",'📅 Calendrier'!$D18)+7,2),"") | Q13: =IF(LEFT('📅 Calendrier'!$D19,2)="S8",MID('📅 Calendrier'!$D19,SEARCH("séance",'📅 Calendrier'!$D19)+7,2),"") | R13: =IF(LEFT('📅 Calendrier'!$D21,2)="S8",MID('📅 Calendrier'!$D21,SEARCH("séance",'📅 Calendrier'!$D21)+7,2),"") | S13: =IF(LEFT('📅 Calendrier'!$D22,2)="S8",MID('📅 Calendrier'!$D22,SEARCH("séance",'📅 Calendrier'!$D22)+7,2),"") | T13: =IF(LEFT('📅 Calendrier'!$D23,2)="S8",MID('📅 Calendrier'!$D23,SEARCH("séance",'📅 Calendrier'!$D23)+7,2),"") | U13: =IF(LEFT('📅 Calendrier'!$D24,2)="S8",MID('📅 Calendrier'!$D24,SEARCH("séance",'📅 Calendrier'!$D24)+7,2),"") | V13: =IF(LEFT('📅 Calendrier'!$D25,2)="S8",MID('📅 Calendrier'!$D25,SEARCH("séance",'📅 Calendrier'!$D25)+7,2),"") | W13: =IF(LEFT('📅 Calendrier'!$D27,2)="S8",MID('📅 Calendrier'!$D27,SEARCH("séance",'📅 Calendrier'!$D27)+7,2),"") | X13: =IF(LEFT('📅 Calendrier'!$D28,2)="S8",MID('📅 Calendrier'!$D28,SEARCH("séance",'📅 Calendrier'!$D28)+7,2),"") | Y13: =IF(LEFT('📅 Calendrier'!$D29,2)="S8",MID('📅 Calendrier'!$D29,SEARCH("séance",'📅 Calendrier'!$D29)+7,2),"") | Z13: =IF(LEFT('📅 Calendrier'!$D30,2)="S8",MID('📅 Calendrier'!$D30,SEARCH("séance",'📅 Calendrier'!$D30)+7,2),"") | AA13: =IF(LEFT('📅 Calendrier'!$D31,2)="S8",MID('📅 Calendrier'!$D31,SEARCH("séance",'📅 Calendrier'!$D31)+7,2),"") | AB13: =IF(LEFT('📅 Calendrier'!$D32,2)="S8",MID('📅 Calendrier'!$D32,SEARCH("séance",'📅 Calendrier'!$D32)+7,2),"") | AC13: =IF(LEFT('📅 Calendrier'!$D33,2)="S8",MID('📅 Calendrier'!$D33,SEARCH("séance",'📅 Calendrier'!$D33)+7,2),"") -> 1 | AD13: =IF(LEFT('📅 Calendrier'!$D34,2)="S8",MID('📅 Calendrier'!$D34,SEARCH("séance",'📅 Calendrier'!$D34)+7,2),"") | AE13: =IF(LEFT('📅 Calendrier'!$D36,2)="S8",MID('📅 Calendrier'!$D36,SEARCH("séance",'📅 Calendrier'!$D36)+7,2),"") -> 2 | AF13: =IF(LEFT('📅 Calendrier'!$D37,2)="S8",MID('📅 Calendrier'!$D37,SEARCH("séance",'📅 Calendrier'!$D37)+7,2),"") -> 3 | AG13: =IF(LEFT('📅 Calendrier'!$D38,2)="S8",MID('📅 Calendrier'!$D38,SEARCH("séance",'📅 Calendrier'!$D38)+7,2),"") -> 4 | AH13: =IF(LEFT('📅 Calendrier'!$D39,2)="S8",MID('📅 Calendrier'!$D39,SEARCH("séance",'📅 Calendrier'!$D39)+7,2),"") | AI13: =IF(LEFT('📅 Calendrier'!$D40,2)="S8",MID('📅 Calendrier'!$D40,SEARCH("séance",'📅 Calendrier'!$D40)+7,2),"") | AJ13: =IF(LEFT('📅 Calendrier'!$D41,2)="S8",MID('📅 Calendrier'!$D41,SEARCH("séance",'📅 Calendrier'!$D41)+7,2),"") | AK13: =IF(LEFT('📅 Calendrier'!$D42,2)="S8",MID('📅 Calendrier'!$D42,SEARCH("séance",'📅 Calendrier'!$D42)+7,2),"") | AL13: =IF(LEFT('📅 Calendrier'!$D43,2)="S8",MID('📅 Calendrier'!$D43,SEARCH("séance",'📅 Calendrier'!$D43)+7,2),"") | AM13: =IF(LEFT('📅 Calendrier'!$D44,2)="S8",MID('📅 Calendrier'!$D44,SEARCH("séance",'📅 Calendrier'!$D44)+7,2),"")
B14: S9 · Fil rouge V3 : validation | C14: =IF(LEFT('📅 Calendrier'!$D4,2)="S9",MID('📅 Calendrier'!$D4,SEARCH("séance",'📅 Calendrier'!$D4)+7,2),"") | D14: =IF(LEFT('📅 Calendrier'!$D5,2)="S9",MID('📅 Calendrier'!$D5,SEARCH("séance",'📅 Calendrier'!$D5)+7,2),"") | E14: =IF(LEFT('📅 Calendrier'!$D6,2)="S9",MID('📅 Calendrier'!$D6,SEARCH("séance",'📅 Calendrier'!$D6)+7,2),"") | F14: =IF(LEFT('📅 Calendrier'!$D7,2)="S9",MID('📅 Calendrier'!$D7,SEARCH("séance",'📅 Calendrier'!$D7)+7,2),"") | G14: =IF(LEFT('📅 Calendrier'!$D8,2)="S9",MID('📅 Calendrier'!$D8,SEARCH("séance",'📅 Calendrier'!$D8)+7,2),"") | H14: =IF(LEFT('📅 Calendrier'!$D9,2)="S9",MID('📅 Calendrier'!$D9,SEARCH("séance",'📅 Calendrier'!$D9)+7,2),"") | I14: =IF(LEFT('📅 Calendrier'!$D10,2)="S9",MID('📅 Calendrier'!$D10,SEARCH("séance",'📅 Calendrier'!$D10)+7,2),"") | J14: =IF(LEFT('📅 Calendrier'!$D11,2)="S9",MID('📅 Calendrier'!$D11,SEARCH("séance",'📅 Calendrier'!$D11)+7,2),"") | K14: =IF(LEFT('📅 Calendrier'!$D13,2)="S9",MID('📅 Calendrier'!$D13,SEARCH("séance",'📅 Calendrier'!$D13)+7,2),"") | L14: =IF(LEFT('📅 Calendrier'!$D14,2)="S9",MID('📅 Calendrier'!$D14,SEARCH("séance",'📅 Calendrier'!$D14)+7,2),"") | M14: =IF(LEFT('📅 Calendrier'!$D15,2)="S9",MID('📅 Calendrier'!$D15,SEARCH("séance",'📅 Calendrier'!$D15)+7,2),"") | N14: =IF(LEFT('📅 Calendrier'!$D16,2)="S9",MID('📅 Calendrier'!$D16,SEARCH("séance",'📅 Calendrier'!$D16)+7,2),"") | O14: =IF(LEFT('📅 Calendrier'!$D17,2)="S9",MID('📅 Calendrier'!$D17,SEARCH("séance",'📅 Calendrier'!$D17)+7,2),"") | P14: =IF(LEFT('📅 Calendrier'!$D18,2)="S9",MID('📅 Calendrier'!$D18,SEARCH("séance",'📅 Calendrier'!$D18)+7,2),"") | Q14: =IF(LEFT('📅 Calendrier'!$D19,2)="S9",MID('📅 Calendrier'!$D19,SEARCH("séance",'📅 Calendrier'!$D19)+7,2),"") | R14: =IF(LEFT('📅 Calendrier'!$D21,2)="S9",MID('📅 Calendrier'!$D21,SEARCH("séance",'📅 Calendrier'!$D21)+7,2),"") | S14: =IF(LEFT('📅 Calendrier'!$D22,2)="S9",MID('📅 Calendrier'!$D22,SEARCH("séance",'📅 Calendrier'!$D22)+7,2),"") | T14: =IF(LEFT('📅 Calendrier'!$D23,2)="S9",MID('📅 Calendrier'!$D23,SEARCH("séance",'📅 Calendrier'!$D23)+7,2),"") | U14: =IF(LEFT('📅 Calendrier'!$D24,2)="S9",MID('📅 Calendrier'!$D24,SEARCH("séance",'📅 Calendrier'!$D24)+7,2),"") | V14: =IF(LEFT('📅 Calendrier'!$D25,2)="S9",MID('📅 Calendrier'!$D25,SEARCH("séance",'📅 Calendrier'!$D25)+7,2),"") | W14: =IF(LEFT('📅 Calendrier'!$D27,2)="S9",MID('📅 Calendrier'!$D27,SEARCH("séance",'📅 Calendrier'!$D27)+7,2),"") | X14: =IF(LEFT('📅 Calendrier'!$D28,2)="S9",MID('📅 Calendrier'!$D28,SEARCH("séance",'📅 Calendrier'!$D28)+7,2),"") | Y14: =IF(LEFT('📅 Calendrier'!$D29,2)="S9",MID('📅 Calendrier'!$D29,SEARCH("séance",'📅 Calendrier'!$D29)+7,2),"") | Z14: =IF(LEFT('📅 Calendrier'!$D30,2)="S9",MID('📅 Calendrier'!$D30,SEARCH("séance",'📅 Calendrier'!$D30)+7,2),"") | AA14: =IF(LEFT('📅 Calendrier'!$D31,2)="S9",MID('📅 Calendrier'!$D31,SEARCH("séance",'📅 Calendrier'!$D31)+7,2),"") | AB14: =IF(LEFT('📅 Calendrier'!$D32,2)="S9",MID('📅 Calendrier'!$D32,SEARCH("séance",'📅 Calendrier'!$D32)+7,2),"") | AC14: =IF(LEFT('📅 Calendrier'!$D33,2)="S9",MID('📅 Calendrier'!$D33,SEARCH("séance",'📅 Calendrier'!$D33)+7,2),"") | AD14: =IF(LEFT('📅 Calendrier'!$D34,2)="S9",MID('📅 Calendrier'!$D34,SEARCH("séance",'📅 Calendrier'!$D34)+7,2),"") | AE14: =IF(LEFT('📅 Calendrier'!$D36,2)="S9",MID('📅 Calendrier'!$D36,SEARCH("séance",'📅 Calendrier'!$D36)+7,2),"") | AF14: =IF(LEFT('📅 Calendrier'!$D37,2)="S9",MID('📅 Calendrier'!$D37,SEARCH("séance",'📅 Calendrier'!$D37)+7,2),"") | AG14: =IF(LEFT('📅 Calendrier'!$D38,2)="S9",MID('📅 Calendrier'!$D38,SEARCH("séance",'📅 Calendrier'!$D38)+7,2),"") | AH14: =IF(LEFT('📅 Calendrier'!$D39,2)="S9",MID('📅 Calendrier'!$D39,SEARCH("séance",'📅 Calendrier'!$D39)+7,2),"") -> 1 | AI14: =IF(LEFT('📅 Calendrier'!$D40,2)="S9",MID('📅 Calendrier'!$D40,SEARCH("séance",'📅 Calendrier'!$D40)+7,2),"") -> 2 | AJ14: =IF(LEFT('📅 Calendrier'!$D41,2)="S9",MID('📅 Calendrier'!$D41,SEARCH("séance",'📅 Calendrier'!$D41)+7,2),"") -> 3 | AK14: =IF(LEFT('📅 Calendrier'!$D42,2)="S9",MID('📅 Calendrier'!$D42,SEARCH("séance",'📅 Calendrier'!$D42)+7,2),"") | AL14: =IF(LEFT('📅 Calendrier'!$D43,2)="S9",MID('📅 Calendrier'!$D43,SEARCH("séance",'📅 Calendrier'!$D43)+7,2),"") | AM14: =IF(LEFT('📅 Calendrier'!$D44,2)="S9",MID('📅 Calendrier'!$D44,SEARCH("séance",'📅 Calendrier'!$D44)+7,2),"")
B15: ⏳ Tampons + 🎓 révisions DNB | C15: =IF(LEFT('📅 Calendrier'!$D4,1)="⏳","⏳","") | D15: =IF(LEFT('📅 Calendrier'!$D5,1)="⏳","⏳","") | E15: =IF(LEFT('📅 Calendrier'!$D6,1)="⏳","⏳","") | F15: =IF(LEFT('📅 Calendrier'!$D7,1)="⏳","⏳","") | G15: =IF(LEFT('📅 Calendrier'!$D8,1)="⏳","⏳","") | H15: =IF(LEFT('📅 Calendrier'!$D9,1)="⏳","⏳","") | I15: =IF(LEFT('📅 Calendrier'!$D10,1)="⏳","⏳","") | J15: =IF(LEFT('📅 Calendrier'!$D11,1)="⏳","⏳","") -> ⏳ | K15: =IF(LEFT('📅 Calendrier'!$D13,1)="⏳","⏳","") | L15: =IF(LEFT('📅 Calendrier'!$D14,1)="⏳","⏳","") | M15: =IF(LEFT('📅 Calendrier'!$D15,1)="⏳","⏳","") | N15: =IF(LEFT('📅 Calendrier'!$D16,1)="⏳","⏳","") | O15: =IF(LEFT('📅 Calendrier'!$D17,1)="⏳","⏳","") | P15: =IF(LEFT('📅 Calendrier'!$D18,1)="⏳","⏳","") | Q15: =IF(LEFT('📅 Calendrier'!$D19,1)="⏳","⏳","") -> ⏳ | R15: =IF(LEFT('📅 Calendrier'!$D21,1)="⏳","⏳","") | S15: =IF(LEFT('📅 Calendrier'!$D22,1)="⏳","⏳","") | T15: =IF(LEFT('📅 Calendrier'!$D23,1)="⏳","⏳","") | U15: =IF(LEFT('📅 Calendrier'!$D24,1)="⏳","⏳","") | V15: =IF(LEFT('📅 Calendrier'!$D25,1)="⏳","⏳","") -> ⏳ | W15: =IF(LEFT('📅 Calendrier'!$D27,1)="⏳","⏳","") | X15: =IF(LEFT('📅 Calendrier'!$D28,1)="⏳","⏳","") | Y15: =IF(LEFT('📅 Calendrier'!$D29,1)="⏳","⏳","") | Z15: =IF(LEFT('📅 Calendrier'!$D30,1)="⏳","⏳","") | AA15: =IF(LEFT('📅 Calendrier'!$D31,1)="⏳","⏳","") | AB15: =IF(LEFT('📅 Calendrier'!$D32,1)="⏳","⏳","") | AC15: =IF(LEFT('📅 Calendrier'!$D33,1)="⏳","⏳","") | AD15: =IF(LEFT('📅 Calendrier'!$D34,1)="⏳","⏳","") -> ⏳ | AE15: =IF(LEFT('📅 Calendrier'!$D36,1)="⏳","⏳","") | AF15: =IF(LEFT('📅 Calendrier'!$D37,1)="⏳","⏳","") | AG15: =IF(LEFT('📅 Calendrier'!$D38,1)="⏳","⏳","") | AH15: =IF(LEFT('📅 Calendrier'!$D39,1)="⏳","⏳","") | AI15: =IF(LEFT('📅 Calendrier'!$D40,1)="⏳","⏳","") | AJ15: =IF(LEFT('📅 Calendrier'!$D41,1)="⏳","⏳","") | AK15: =IF(LEFT('📅 Calendrier'!$D42,1)="⏳","⏳","") -> ⏳ | AL15: =IF(LEFT('📅 Calendrier'!$D43,1)="⏳","⏳","") -> ⏳ | AM15: =IF(LEFT('📅 Calendrier'!$D44,1)="⏳","⏳","") -> ⏳
B16: ⚠ Imprévus (saisis au Calendrier) | C16: =IF('📅 Calendrier'!$G4<>"","⚠","") | D16: =IF('📅 Calendrier'!$G5<>"","⚠","") | E16: =IF('📅 Calendrier'!$G6<>"","⚠","") | F16: =IF('📅 Calendrier'!$G7<>"","⚠","") | G16: =IF('📅 Calendrier'!$G8<>"","⚠","") | H16: =IF('📅 Calendrier'!$G9<>"","⚠","") | I16: =IF('📅 Calendrier'!$G10<>"","⚠","") | J16: =IF('📅 Calendrier'!$G11<>"","⚠","") | K16: =IF('📅 Calendrier'!$G13<>"","⚠","") | L16: =IF('📅 Calendrier'!$G14<>"","⚠","") | M16: =IF('📅 Calendrier'!$G15<>"","⚠","") | N16: =IF('📅 Calendrier'!$G16<>"","⚠","") | O16: =IF('📅 Calendrier'!$G17<>"","⚠","") | P16: =IF('📅 Calendrier'!$G18<>"","⚠","") | Q16: =IF('📅 Calendrier'!$G19<>"","⚠","") | R16: =IF('📅 Calendrier'!$G21<>"","⚠","") | S16: =IF('📅 Calendrier'!$G22<>"","⚠","") | T16: =IF('📅 Calendrier'!$G23<>"","⚠","") | U16: =IF('📅 Calendrier'!$G24<>"","⚠","") | V16: =IF('📅 Calendrier'!$G25<>"","⚠","") | W16: =IF('📅 Calendrier'!$G27<>"","⚠","") | X16: =IF('📅 Calendrier'!$G28<>"","⚠","") | Y16: =IF('📅 Calendrier'!$G29<>"","⚠","") | Z16: =IF('📅 Calendrier'!$G30<>"","⚠","") | AA16: =IF('📅 Calendrier'!$G31<>"","⚠","") | AB16: =IF('📅 Calendrier'!$G32<>"","⚠","") | AC16: =IF('📅 Calendrier'!$G33<>"","⚠","") | AD16: =IF('📅 Calendrier'!$G34<>"","⚠","") | AE16: =IF('📅 Calendrier'!$G36<>"","⚠","") | AF16: =IF('📅 Calendrier'!$G37<>"","⚠","") | AG16: =IF('📅 Calendrier'!$G38<>"","⚠","") | AH16: =IF('📅 Calendrier'!$G39<>"","⚠","") | AI16: =IF('📅 Calendrier'!$G40<>"","⚠","") | AJ16: =IF('📅 Calendrier'!$G41<>"","⚠","") | AK16: =IF('📅 Calendrier'!$G42<>"","⚠","") | AL16: =IF('📅 Calendrier'!$G43<>"","⚠","") | AM16: =IF('📅 Calendrier'!$G44<>"","⚠","")
B18: Une case = 1 semaine (1 séance de 1 h 30) ; le numéro = n° de séance dans la séquence. Imprévu : onglet 📅 Calendrier, colonne « ⚠ Imprévu ? » (ou la grande fenêtre de la version macros) — tout se recalcule immédiatement.

Sheet 📚 Référentiel Cycle 4
A1: RÉFÉRENTIEL DE COMPÉTENCES — TECHNOLOGIE CYCLE 4
A2: 9 compétences × 3 niveaux (5e / 4e / 3e) — programme 2024 · vision complète du cycle pour situer la 3e
F3: ◀ Accueil
A4: Code | B4: Niveau | C4: Compétence / sous-compétence (intitulé officiel 2024) | D4: Thème | E4: Domaine(s) socle | F4: Évaluable
A5: C1 | B5: — | C5: Décrire les liens entre usages et évolutions technologiques des objets et des systèmes techniques | D5: Thème 1 : Les objets et les systèmes techniques : leurs usages et leurs interactions à découvrir et à analyser | E5: D2, D3, D4, D5 | F5: Oui
A6: 5e_C1.1 | B6: 5e | C6: Collecter, trier et analyser des données. | D6: Thème 1 | E6: D2, D4 | F6: Oui
A7: 5e_C1.2 | B7: 5e | C7: Comparer des principes techniques pour une même fonction technique. | D7: Thème 1 | E7: D2, D4 | F7: Oui
A8: 5e_C1.3 | B8: 5e | C8: Décrire le rôle des systèmes d’information dans le partage d’information. | D8: Thème 1 | E8: D2, D5 | F8: Oui
A9: 5e_C1.4 | B9: 5e | C9: Recenser des données, les identifier, les classer, les représenter, les stocker, les retrouver dans une arborescence. | D9: Thème 1 | E9: D2 | F9: Oui
A10: 5e_C1.5 | B10: 5e | C10: Identifier des règles permettant de sécuriser un environnement numérique (bases de la cybersécurité) et des règles de respect de la propriété intellectuelle. | D10: Thème 1 | E10: D3 | F10: Oui
A11: 5e_C1.6 | B11: 5e | C11: Appréhender la responsabilité de chacun dans les dérives (cyberviolence, atteinte à la vie privée, aux données personnelles, usurpation d’identité). | D11: Thème 1 | E11: D3 | F11: Oui
A12: 4e_C1.1 | B12: 4e | C12: Mettre en relation les OST avec leurs usages. | D12: Thème 1 | E12: D4, D5 | F12: Oui
A13: 4e_C1.2 | B13: 4e | C13: Identifier les avantages et les inconvénients associés aux évolutions technologiques et informatiques. | D13: Thème 1 | E13: D3, D4, D5 | F13: Oui
A14: 4e_C1.3 | B14: 4e | C14: Justifier l’évolution d’un OST pour répondre à l’évolution des besoins. | D14: Thème 1 | E14: D3, D4, D5 | F14: Oui
A15: 4e_C1.4 | B15: 4e | C15: Identifier et appliquer les règles pour un usage raisonné des objets communicants et des environnements numériques (propriété intellectuelle, identité numérique, témoins de connexion, géolocalisation). | D15: Thème 1 | E15: D1.3, D2, D3, D4 | F15: Oui
... A127: 3e_C9.2 | B127: 3e | C127: Réaliser et mettre au point un programme commandant un système réel incluant une interaction entre un humain et une machine. | D127: Thème 3 | E127: D1.3, D2, D4 | F127: Oui
A129: 114 sous-compétences listées · Source : BO n°9 du 29/02/2024 · codes Nathan (éd. 2024).

Sheet 📗 Référentiel 3e
A1: RÉFÉRENTIEL DE COMPÉTENCES — TECHNOLOGIE 3e
A2: Les compétences parentes C1 → C9 et leurs déclinaisons du niveau 3e — celles travaillées dans ce classeur
F3: ◀ Accueil
A4: Code | B4: Niveau | C4: Compétence / sous-compétence (intitulé officiel 2024) | D4: Thème | E4: Domaine(s) socle | F4: Évaluable
A5: C1 | B5: — | C5: Décrire les liens entre usages et évolutions technologiques des objets et des systèmes techniques | D5: Thème 1 : Les objets et les systèmes techniques : leurs usages et leurs interactions à découvrir et à analyser | E5: D2, D3, D4, D5 | F5: Oui
A6: 3e_C1.1 | B6: 3e | C6: Identifier les innovations de rupture qui sont attachées à l’évolution d’un OST. | D6: Thème 1 | E6: D3, D4, D5 | F6: Oui
A7: 3e_C1.2 | B7: 3e | C7: Mettre en relation une découverte scientifique avec ses développements technologiques et leurs effets sur la société. | D7: Thème 1 | E7: D3, D4, D5 | F7: Oui
A8: 3e_C1.3 | B8: 3e | C8: Exprimer dans un argumentaire court l’incidence d’un OST sur la société. | D8: Thème 1 | E8: D3, D4, D5 | F8: Oui
A9: 3e_C1.4 | B9: 3e | C9: Exprimer dans un argumentaire court l’incidence des contraintes sociétales sur les OST. | D9: Thème 1 | E9: D3, D4, D5 | F9: Oui
A10: 3e_C1.5 | B10: 3e | C10: Exprimer dans un argumentaire court le rôle du développement stratégique du numérique au sein de la société et des environnements professionnels (ou des métiers). | D10: Thème 1 | E10: D1.3, D2, D3 | F10: Oui
A11: C2 | B11: — | C11: Décrire les interactions entre un objet ou un système technique, son environnement et les utilisateurs | D11: Thème 1 | E11: D4, D5 | F11: Oui
A12: 3e_C2.1 | B12: 3e | C12: Décrire l’expérience de l’utilisateur d’un OST à l’aide de modes de représentation choisis. | D12: Thème 1 | E12: D1.3, D4, D5 | F12: Oui
A13: C3 | B13: — | C13: Caractériser et choisir un objet ou un système technique selon différents critères | D13: Thème 1 | E13: D1.3, D2, D3, D4, D5 | F13: Oui
A14: 3e_C3.1 | B14: 3e | C14: Établir une liste d’OST possibles en vue de répondre à un besoin. | D14: Thème 1 | E14: D3, D4, D5 | F14: Oui
A15: 3e_C3.2 | B15: 3e | C15: Choisir un OST et argumenter ce choix en prenant en compte son cycle de vie et les trois piliers du développement durable. | D15: Thème 1 | E15: D3, D4, D5 | F15: Oui
... A51: 3e_C9.2 | B51: 3e | C51: Réaliser et mettre au point un programme commandant un système réel incluant une interaction entre un humain et une machine. | D51: Thème 3 | E51: D1.3, D2, D4 | F51: Oui
A53: 38 sous-compétences listées · Source : BO n°9 du 29/02/2024 · codes Nathan (éd. 2024).

Sheet 🧭 Progression
A1: PROGRESSION ANNUELLE 3e — 2026-2027 · 9 séquences · base : Référentiel 2024 (ajustée DNB : 35 → 30 séances)
K2: ◀ Accueil
A3: N° | B3: Période | C3: Titre | D3: Problématique | E3: Thème | F3: Codes 2024 | G3: Séances | H3: Répartition 🏫 / 🏠 / 🔁 | I3: Ressources en ligne (dépôt) | J3: Cahier Nathan 3e (repères) | K3: IA responsable | L3: Début (AUTO) | M3: Fin (AUTO)
A4: 1 | B4: P1 | C4: Innovation et rupture : comment les objets techniques évoluent-ils ? | D4: Qu'est-ce qui distingue une invention, une innovation et une innovation de rupture ? | E4: Thème 1 | F4: 3e_C1.1, C1.2, C1.3, C1.4 | G4: 3 | H4: Séances 1-2 🏫 · 3 🔁 (veille d'information à la maison, argumentaire en classe) | I4: 🔜 À produire (Thème 1) | J4: Cahier Nathan 3e (spécimen) — chapitre évolution/innovation | K4: IA Thème 1 | L4: =IFERROR(INDEX('📅 Calendrier'!$A$4:$A$54,MATCH("S1 · séance 1",'📅 Calendrier'!$D$4:$D$54,0))&" ("&INDEX('📅 Calendrier'!$B$4:$B$54,MATCH("S1 · séance 1",'📅 Calendrier'!$D$4:$D$54,0))&")","⚠ hors année !") -> S01 (31/08/2026) | M4: =IFERROR(INDEX('📅 Calendrier'!$A$4:$A$54,MATCH("S1 · séance 3",'📅 Calendrier'!$D$4:$D$54,0))&" ("&INDEX('📅 Calendrier'!$B$4:$B$54,MATCH("S1 · séance 3",'📅 Calendrier'!$D$4:$D$54,0))&")","⚠ hors année !") -> S03 (14/09/2026)
A5: 2 | B5: P1 | C5: Le numérique dans la société : quel rôle stratégique ? | D5: Quel est le rôle du numérique dans la société et le monde professionnel ? | E5: Thème 1 | F5: 3e_C1.5, C2.1 | G5: 2 | H5: Séance 1 🏫 (étude de cas) · 2 🔁 (enquête métiers à la maison, restitution) | I5: 🔜 À produire (Thème 1) | J5: Cahier Nathan 3e (spécimen) — chapitre numérique et société | K5: IA Thème 1 | L5: =IFERROR(INDEX('📅 Calendrier'!$A$4:$A$54,MATCH("S2 · séance 1",'📅 Calendrier'!$D$4:$D$54,0))&" ("&INDEX('📅 Calendrier'!$B$4:$B$54,MATCH("S2 · séance 1",'📅 Calendrier'!$D$4:$D$54,0))&")","⚠ hors année !") -> S04 (21/09/2026) | M5: =IFERROR(INDEX('📅 Calendrier'!$A$4:$A$54,MATCH("S2 · séance 2",'📅 Calendrier'!$D$4:$D$54,0))&" ("&INDEX('📅 Calendrier'!$B$4:$B$54,MATCH("S2 · séance 2",'📅 Calendrier'!$D$4:$D$54,0))&")","⚠ hors année !") -> S05 (28/09/2026)
A6: 3 | B6: P1/P2 | C6: Choisir un objet technique face aux enjeux du développement durable | D6: Comment choisir un objet technique adapté aux contraintes climatiques et environnementales ? | E6: Thème 1 | F6: 3e_C3.1, C3.2, C3.3, C3.4 | G6: 3 | H6: Séances 1-2 🏫 (cycle de vie, 3 piliers, contexte cyclonique) · 3 🔁 (comparatif + éval.) | I6: 🔜 À produire (Thème 1) — lien EDD : indice de réparabilité évoqué dans « SOS station » (Thème 2) | J6: Cahier Nathan 3e (spécimen) — chapitre développement durable | K6: IA Thème 1 | L6: =IFERROR(INDEX('📅 Calendrier'!$A$4:$A$54,MATCH("S3 · séance 1",'📅 Calendrier'!$D$4:$D$54,0))&" ("&INDEX('📅 Calendrier'!$B$4:$B$54,MATCH("S3 · séance 1",'📅 Calendrier'!$D$4:$D$54,0))&")","⚠ hors année !") -> S06 (05/10/2026) | M6: =IFERROR(INDEX('📅 Calendrier'!$A$4:$A$54,MATCH("S3 · séance 3",'📅 Calendrier'!$D$4:$D$54,0))&" ("&INDEX('📅 Calendrier'!$B$4:$B$54,MATCH("S3 · séance 3",'📅 Calendrier'!$D$4:$D$54,0))&")","⚠ hors année !") -> S09 (02/11/2026)
A7: 4 | B7: P2 | C7: La station d'alerte cyclonique : chaînes complètes d'un objet connecté | D7: Comment un objet connecté gère-t-il ses échanges d'énergie et d'information — et comment l'élaborer soi-même ? | E7: Thème 2 | F7: 3e_C4.1, C4.2 🔜, C4.3, C4.4, C4.5, C4.6 | G7: 5 | H7: Séance 1 🔁 (simulateur CAN maison) · 2-3 🏫 (chaîne d'info, données) · 4 🏫 (élaborer chaîne d'énergie + matériaux — 🔜) · 5 🏠 QCM + 🏫 éval. | I7: ✅ Séquence + QCM 32 q + synthèses (C4.3→C4.6, LOT 01) · ✅ « L'énergie de la station » (C4.1-C4.2, LOT 06 : séquence + QCM 30 q + synthèses) | J7: Cahier Nathan 3e (spécimen) — chapitres chaînes d'énergie/information | K7: Fable (Th. 2) | L7: =IFERROR(INDEX('📅 Calendrier'!$A$4:$A$54,MATCH("S4 · séance 1",'📅 Calendrier'!$D$4:$D$54,0))&" ("&INDEX('📅 Calendrier'!$B$4:$B$54,MATCH("S4 · séance 1",'📅 Calendrier'!$D$4:$D$54,0))&")","⚠ hors année !") -> S10 (09/11/2026) | M7: =IFERROR(INDEX('📅 Calendrier'!$A$4:$A$54,MATCH("S4 · séance 5",'📅 Calendrier'!$D$4:$D$54,0))&" ("&INDEX('📅 Calendrier'!$B$4:$B$54,MATCH("S4 · séance 5",'📅 Calendrier'!$D$4:$D$54,0))&")","⚠ hors année !") -> S14 (07/12/2026)
A8: 5 | B8: P3 | C8: Internet jusqu'à Sainte-Luce : réseaux et routage | D8: Comment un message circule-t-il d'un réseau à un autre, et comment s'en protéger ? | E8: Thème 2 | F8: 3e_C4.7, C4.8 | G8: 3 | H8: Séance 1 🔁 (simulateurs paquets/routage maison) · 2 🏫 (jeu du routeur, panne de câble) · 3 🏠 QCM + 🏫 bilan | I8: ✅ Séquence + QCM 30 q + synthèses (LOT 02 : découpage en paquets, routage, résilience) | J8: Cahier Nathan 3e (spécimen) — chapitre réseaux/Internet | K8: Fable (Th. 2) | L8: =IFERROR(INDEX('📅 Calendrier'!$A$4:$A$54,MATCH("S5 · séance 1",'📅 Calendrier'!$D$4:$D$54,0))&" ("&INDEX('📅 Calendrier'!$B$4:$B$54,MATCH("S5 · séance 1",'📅 Calendrier'!$D$4:$D$54,0))&")","⚠ hors année !") -> S16 (04/01/2027) | M8: =IFERROR(INDEX('📅 Calendrier'!$A$4:$A$54,MATCH("S5 · séance 3",'📅 Calendrier'!$D$4:$D$54,0))&" ("&INDEX('📅 Calendrier'!$B$4:$B$54,MATCH("S5 · séance 3",'📅 Calendrier'!$D$4:$D$54,0))&")","⚠ hors année !") -> S18 (18/01/2027)
A9: 6 | B9: P3/P4 | C9: SOS station + Programmer l'alerte : diagnostiquer, réparer, modifier | D9: Comment diagnostiquer une panne, la réparer, et modifier le programme sans rien casser ? | E9: Thème 2 | F9: 3e_C5.1, C5.2, C5.3, C5.4 + 3e_C6.1, C6.2 (existant), C6.3 | G9: 4 | H9: Séances 1-2 🏫+🔁 (simulateur de dépannage 2 pannes) · 3-4 🏫 (CodeLab : modifier + plan de tests) · QCM 🏠 entre les séances | I9: ✅ DEUX séquences complètes : « SOS station » (LOT 03) et « Programmer l'alerte » (LOT 04, CodeLab Techno) + 2 QCM (32 q + 30 q) + synthèses · C6.2 : séquence « Algorigrammes DNB » existante | J9: Cahier Nathan 3e (spécimen) — chapitres panne/programme | K9: Fable (Th. 2) | L9: =IFERROR(INDEX('📅 Calendrier'!$A$4:$A$54,MATCH("S6 · séance 1",'📅 Calendrier'!$D$4:$D$54,0))&" ("&INDEX('📅 Calendrier'!$B$4:$B$54,MATCH("S6 · séance 1",'📅 Calendrier'!$D$4:$D$54,0))&")","⚠ hors année !") -> S19 (25/01/2027) | M9: =IFERROR(INDEX('📅 Calendrier'!$A$4:$A$54,MATCH("S6 · séance 4",'📅 Calendrier'!$D$4:$D$54,0))&" ("&INDEX('📅 Calendrier'!$B$4:$B$54,MATCH("S6 · séance 4",'📅 Calendrier'!$D$4:$D$54,0))&")","⚠ hors année !") -> S23 (08/03/2027)
A10: 7 | B10: P4 | C10: Projet fil rouge — Volet 1 : cadrage, besoin et organisation | D10: Comment bien se préparer et s'organiser pour un projet d'innovation ? | E10: Thème 3 | F10: 3e_C7.1 + 3e_C4.5 (réinvestie) | G10: 3 | H10: Séances 1-3 🏫 (démarche de projet) · entre séances 🏠 (recherches) | I10: 🔜 À produire (Thème 3) | J10: Cahier Nathan 3e (spécimen) — démarche de projet | K10: IA Thème 3 | L10: =IFERROR(INDEX('📅 Calendrier'!$A$4:$A$54,MATCH("S7 · séance 1",'📅 Calendrier'!$D$4:$D$54,0))&" ("&INDEX('📅 Calendrier'!$B$4:$B$54,MATCH("S7 · séance 1",'📅 Calendrier'!$D$4:$D$54,0))&")","⚠ hors année !") -> S24 (15/03/2027) | M10: =IFERROR(INDEX('📅 Calendrier'!$A$4:$A$54,MATCH("S7 · séance 3",'📅 Calendrier'!$D$4:$D$54,0))&" ("&INDEX('📅 Calendrier'!$B$4:$B$54,MATCH("S7 · séance 3",'📅 Calendrier'!$D$4:$D$54,0))&")","⚠ hors année !") -> S26 (29/03/2027)
A11: 8 | B11: P4/P5 | C11: Projet fil rouge — Volet 2 : solutions techniques et prototypage | D11: Quelles solutions techniques retenir, et comment réaliser le prototype ? | E11: Thème 3 | F11: 3e_C7.2→C7.8 | G11: 4 | H11: Séances 1-4 🏫 (conception, réalisation) · 🏠 (croquis, impression 3D à suivre) | I11: 🔜 À produire (Thème 3) | J11: Cahier Nathan 3e (spécimen) | K11: IA Thème 3 | L11: =IFERROR(INDEX('📅 Calendrier'!$A$4:$A$54,MATCH("S8 · séance 1",'📅 Calendrier'!$D$4:$D$54,0))&" ("&INDEX('📅 Calendrier'!$B$4:$B$54,MATCH("S8 · séance 1",'📅 Calendrier'!$D$4:$D$54,0))&")","⚠ hors année !") -> S27 (05/04/2027) | M11: =IFERROR(INDEX('📅 Calendrier'!$A$4:$A$54,MATCH("S8 · séance 4",'📅 Calendrier'!$D$4:$D$54,0))&" ("&INDEX('📅 Calendrier'!$B$4:$B$54,MATCH("S8 · séance 4",'📅 Calendrier'!$D$4:$D$54,0))&")","⚠ hors année !") -> S31 (17/05/2027)
A12: 9 | B12: P5 | C12: Projet fil rouge — Volet 3 : validation et mise au point | D12: Comment vérifier que le prototype répond au cahier des charges ? | E12: Thème 3 | F12: 3e_C8.1, C8.2, C8.3 + 3e_C9.1, C9.2 | G12: 3 | H12: Séances 1-2 🏫 (tests, mise au point) · 3 🏫 revue de projet finale (avant DNB) | I12: 🔜 À produire (Thème 3) | J12: Cahier Nathan 3e (spécimen) | K12: IA Thème 3 | L12: =IFERROR(INDEX('📅 Calendrier'!$A$4:$A$54,MATCH("S9 · séance 1",'📅 Calendrier'!$D$4:$D$54,0))&" ("&INDEX('📅 Calendrier'!$B$4:$B$54,MATCH("S9 · séance 1",'📅 Calendrier'!$D$4:$D$54,0))&")","⚠ hors année !") -> S32 (24/05/2027) | M12: =IFERROR(INDEX('📅 Calendrier'!$A$4:$A$54,MATCH("S9 · séance 3",'📅 Calendrier'!$D$4:$D$54,0))&" ("&INDEX('📅 Calendrier'!$B$4:$B$54,MATCH("S9 · séance 3",'📅 Calendrier'!$D$4:$D$54,0))&")","⚠ hors année !") -> S34 (07/06/2027)
F13: Total séances planifiées : | G13: =SUM(G4:G12) -> 30 | H13: + 4 tampons + 3 semaines révisions DNB = 37 (voir Calendrier) · colonnes AUTO recalculées selon les imprévus

Sheet S1
A1: GÉNÉRATEUR DE SÉQUENCE 2024 — S1 · Innovation et rupture : comment les objets techniques évoluent-ils ?
A2: Thème 1 · P1 · 3 séances de 1 h 30 · Responsable : IA Thème 1 · CANEVAS À REMPLIR par IA Thème 1 (règle : l'IA du thème est seule à modifier)
E3: ◀ Progression | F3: ◀ Accueil
A4: Problématique | B4: Qu'est-ce qui distingue une invention, une innovation et une innovation de rupture ?
A5: Situation déclenchante | B5: ⚠ À compléter par IA Thème 1 (canevas pré-rempli par Fable — codes, problématique et repères posés).
A6: Prérequis | B6: —
A7: Éléments pour la synthèse (objectifs) | B7: ⚠ À compléter par IA Thème 1 (canevas pré-rempli par Fable — codes, problématique et repères posés).
A8: Piste d'évaluation | B8: Frise invention/innovation argumentée
A9: Domaines du socle mobilisés | B9: D3, D4, D5 (détail par code ci-dessous)
A10: CRCN — compétences numériques (Pix) | B10: 1.1 Mener une veille d'information (Niv. 3)
A11: Versions 🅰 / 🅱 / 🅲 | B11: ⚠ À compléter par IA Thème 1 (canevas pré-rempli par Fable — codes, problématique et repères posés).
A12: Liens EPI / parcours | B12: ⚠ À compléter par IA Thème 1 (canevas pré-rempli par Fable — codes, problématique et repères posés).
A13: Cahier Nathan 3e | B13: Cahier Nathan 3e (spécimen) — chapitre évolution/innovation
A14: Ressources en ligne | B14: 🔜 À produire (Thème 1)
A16: Compétences du programme 2024
A17: Code | B17: Intitulé officiel | C17: Domaines du socle | D17: Travaillée en | E17: Évaluation LSU
A18: 3e_C1.1 | B18: Identifier les innovations de rupture qui sont attachées à l’évolution d’un OST. | C18: D3, D4, D5 | D18: — | E18: → LSU
A19: 3e_C1.2 | B19: Mettre en relation une découverte scientifique avec ses développements technologiques et leurs effets sur la société. | C19: D3, D4, D5 | D19: — | E19: → LSU
A20: 3e_C1.3 | B20: Exprimer dans un argumentaire court l’incidence d’un OST sur la société. | C20: D3, D4, D5 | D20: — | E20: → LSU
A21: 3e_C1.4 | B21: Exprimer dans un argumentaire court l’incidence des contraintes sociétales sur les OST. | C21: D3, D4, D5 | D21: — | E21: → LSU
A23: Déroulé, séance par séance — avec cahier de texte Pronote prêt à coller
A24: ■ Séance 1 — semaine S01 — — — [titre de la séance 1 — à compléter]
A25: Question directrice | B25: [question directrice]
A26: Activités & supports | B26: [activités — repères : Cahier Nathan 3e (spécimen) — chapitre évolution/innovation]
A27: Démarche / organisation | B27: [démarche]
A28: Bilan / trace écrite | B28: [trace écrite]
A29: 📋 CAHIER DE TEXTE Contenu de la séance 👆 CLIC = copier pour Pronote | B29: [Cahier de texte — contenu de la séance 1 : à rédiger par IA Thème 1.]
A30: 📋 CAHIER DE TEXTE Travail à faire 👆 CLIC = copier pour Pronote | B30: [Cahier de texte — travail à faire : à rédiger — support, durée, « faisable sur téléphone » le cas échéant.]
A31: Suivi enseignant | B31: Fait le : ____________ | C31: Report / aléa / remarques :
A33: ■ Séance 2 — semaine S02 — — — [titre de la séance 2 — à compléter]
A34: Question directrice | B34: [question directrice]
A35: Activités & supports | B35: [activités — repères : Cahier Nathan 3e (spécimen) — chapitre évolution/innovation]
A36: Démarche / organisation | B36: [démarche]
A37: Bilan / trace écrite | B37: [trace écrite]
A38: 📋 CAHIER DE TEXTE Contenu de la séance 👆 CLIC = copier pour Pronote | B38: [Cahier de texte — contenu de la séance 2 : à rédiger par IA Thème 1.]
A39: 📋 CAHIER DE TEXTE Travail à faire 👆 CLIC = copier pour Pronote | B39: [Cahier de texte — travail à faire : à rédiger — support, durée, « faisable sur téléphone » le cas échéant.]
A40: Suivi enseignant | B40: Fait le : ____________ | C40: Report / aléa / remarques :
A42: ■ Séance 3 — semaine S03 — — — [titre de la séance 3 — à compléter]
A43: Question directrice | B43: [question directrice]
A44: Activités & supports | B44: [activités — repères : Cahier Nathan 3e (spécimen) — chapitre évolution/innovation]
A45: Démarche / organisation | B45: [démarche]
A46: Bilan / trace écrite | B46: [trace écrite]
A47: 📋 CAHIER DE TEXTE Contenu de la séance 👆 CLIC = copier pour Pronote | B47: [Cahier de texte — contenu de la séance 3 : à rédiger par IA Thème 1.]
A48: 📋 CAHIER DE TEXTE Travail à faire 👆 CLIC = copier pour Pronote | B48: [Cahier de texte — travail à faire : à rédiger — support, durée, « faisable sur téléphone » le cas échéant.]
A49: Suivi enseignant | B49: Fait le : ____________ | C49: Report / aléa / remarques :

Sheet S2
A1: GÉNÉRATEUR DE SÉQUENCE 2024 — S2 · Le numérique dans la société : quel rôle stratégique ?
A2: Thème 1 · P1 · 2 séances de 1 h 30 · Responsable : IA Thème 1 · CANEVAS À REMPLIR par IA Thème 1 (règle : l'IA du thème est seule à modifier)
E3: ◀ Progression | F3: ◀ Accueil
A4: Problématique | B4: Quel est le rôle du numérique dans la société et le monde professionnel ?
A5: Situation déclenchante | B5: ⚠ À compléter par IA Thème 1 (canevas pré-rempli par Fable — codes, problématique et repères posés).
A6: Prérequis | B6: —
A7: Éléments pour la synthèse (objectifs) | B7: ⚠ À compléter par IA Thème 1 (canevas pré-rempli par Fable — codes, problématique et repères posés).
A8: Piste d'évaluation | B8: Étude de cas commentée
A9: Domaines du socle mobilisés | B9: D1.3, D2, D3, D4, D5 (détail par code ci-dessous)
A10: CRCN — compétences numériques (Pix) | B10: 2.4 S'insérer dans le monde numérique (Niv. 3)
A11: Versions 🅰 / 🅱 / 🅲 | B11: ⚠ À compléter par IA Thème 1 (canevas pré-rempli par Fable — codes, problématique et repères posés).
A12: Liens EPI / parcours | B12: ⚠ À compléter par IA Thème 1 (canevas pré-rempli par Fable — codes, problématique et repères posés).
A13: Cahier Nathan 3e | B13: Cahier Nathan 3e (spécimen) — chapitre numérique et société
A14: Ressources en ligne | B14: 🔜 À produire (Thème 1)
A16: Compétences du programme 2024
A17: Code | B17: Intitulé officiel | C17: Domaines du socle | D17: Travaillée en | E17: Évaluation LSU
A18: 3e_C1.5 | B18: Exprimer dans un argumentaire court le rôle du développement stratégique du numérique au sein de la société et des environnements professionnels (ou des métiers). | C18: D1.3, D2, D3 | D18: — | E18: → LSU
A19: 3e_C2.1 | B19: Décrire l’expérience de l’utilisateur d’un OST à l’aide de modes de représentation choisis. | C19: D1.3, D4, D5 | D19: — | E19: → LSU
A21: Déroulé, séance par séance — avec cahier de texte Pronote prêt à coller
A22: ■ Séance 1 — semaine S04 — — — [titre de la séance 1 — à compléter]
A23: Question directrice | B23: [question directrice]
A24: Activités & supports | B24: [activités — repères : Cahier Nathan 3e (spécimen) — chapitre numérique et société]
A25: Démarche / organisation | B25: [démarche]
A26: Bilan / trace écrite | B26: [trace écrite]
A27: 📋 CAHIER DE TEXTE Contenu de la séance 👆 CLIC = copier pour Pronote | B27: [Cahier de texte — contenu de la séance 1 : à rédiger par IA Thème 1.]
A28: 📋 CAHIER DE TEXTE Travail à faire 👆 CLIC = copier pour Pronote | B28: [Cahier de texte — travail à faire : à rédiger — support, durée, « faisable sur téléphone » le cas échéant.]
A29: Suivi enseignant | B29: Fait le : ____________ | C29: Report / aléa / remarques :
A31: ■ Séance 2 — semaine S05 — — — [titre de la séance 2 — à compléter]
A32: Question directrice | B32: [question directrice]
A33: Activités & supports | B33: [activités — repères : Cahier Nathan 3e (spécimen) — chapitre numérique et société]
A34: Démarche / organisation | B34: [démarche]
A35: Bilan / trace écrite | B35: [trace écrite]
A36: 📋 CAHIER DE TEXTE Contenu de la séance 👆 CLIC = copier pour Pronote | B36: [Cahier de texte — contenu de la séance 2 : à rédiger par IA Thème 1.]
A37: 📋 CAHIER DE TEXTE Travail à faire 👆 CLIC = copier pour Pronote | B37: [Cahier de texte — travail à faire : à rédiger — support, durée, « faisable sur téléphone » le cas échéant.]
A38: Suivi enseignant | B38: Fait le : ____________ | C38: Report / aléa / remarques :

Sheet S3
A1: GÉNÉRATEUR DE SÉQUENCE 2024 — S3 · Choisir un objet technique face aux enjeux du développement durable
A2: Thème 1 · P1/P2 · 3 séances de 1 h 30 · Responsable : IA Thème 1 · CANEVAS À REMPLIR par IA Thème 1 (règle : l'IA du thème est seule à modifier)
E3: ◀ Progression | F3: ◀ Accueil
A4: Problématique | B4: Comment choisir un objet technique adapté aux contraintes climatiques et environnementales ?
A5: Situation déclenchante | B5: ⚠ À compléter par IA Thème 1 (canevas pré-rempli par Fable — codes, problématique et repères posés).
A6: Prérequis | B6: —
A7: Éléments pour la synthèse (objectifs) | B7: ⚠ À compléter par IA Thème 1 (canevas pré-rempli par Fable — codes, problématique et repères posés).
A8: Piste d'évaluation | B8: Choix argumenté (cycle de vie, 3 piliers)
A9: Domaines du socle mobilisés | B9: D1.3, D2, D3, D4, D5 (détail par code ci-dessous)
A10: CRCN — compétences numériques (Pix) | B10: 1.3 Traiter des données (Niv. 2-3)
A11: Versions 🅰 / 🅱 / 🅲 | B11: ⚠ À compléter par IA Thème 1 (canevas pré-rempli par Fable — codes, problématique et repères posés).
A12: Liens EPI / parcours | B12: ⚠ À compléter par IA Thème 1 (canevas pré-rempli par Fable — codes, problématique et repères posés).
A13: Cahier Nathan 3e | B13: Cahier Nathan 3e (spécimen) — chapitre développement durable
A14: Ressources en ligne | B14: 🔜 À produire (Thème 1) — lien EDD : indice de réparabilité évoqué dans « SOS station » (Thème 2)
A16: Compétences du programme 2024
A17: Code | B17: Intitulé officiel | C17: Domaines du socle | D17: Travaillée en | E17: Évaluation LSU
A18: 3e_C3.1 | B18: Établir une liste d’OST possibles en vue de répondre à un besoin. | C18: D3, D4, D5 | D18: — | E18: → LSU
A19: 3e_C3.2 | B19: Choisir un OST et argumenter ce choix en prenant en compte son cycle de vie et les trois piliers du développement durable. | C19: D3, D4, D5 | D19: — | E19: → LSU
A20: 3e_C3.3 | B20: Évaluer les OST selon des exigences ou des critères identifiés (caractéristiques, performances, coût, indice de réparabilité). | C20: D3, D4, D5 | D20: — | E20: → LSU
A21: 3e_C3.4 | B21: Définir et mettre en œuvre un protocole pour mesurer une caractéristique, une performance d’un OST. | C21: D1.3, D2, D4 | D21: — | E21: → LSU
A23: Déroulé, séance par séance — avec cahier de texte Pronote prêt à coller
A24: ■ Séance 1 — semaine S06 — — — [titre de la séance 1 — à compléter]
A25: Question directrice | B25: [question directrice]
A26: Activités & supports | B26: [activités — repères : Cahier Nathan 3e (spécimen) — chapitre développement durable]
A27: Démarche / organisation | B27: [démarche]
A28: Bilan / trace écrite | B28: [trace écrite]
A29: 📋 CAHIER DE TEXTE Contenu de la séance 👆 CLIC = copier pour Pronote | B29: [Cahier de texte — contenu de la séance 1 : à rédiger par IA Thème 1.]
A30: 📋 CAHIER DE TEXTE Travail à faire 👆 CLIC = copier pour Pronote | B30: [Cahier de texte — travail à faire : à rédiger — support, durée, « faisable sur téléphone » le cas échéant.]
A31: Suivi enseignant | B31: Fait le : ____________ | C31: Report / aléa / remarques :
A33: ■ Séance 2 — semaine S07 — — — [titre de la séance 2 — à compléter]
A34: Question directrice | B34: [question directrice]
A35: Activités & supports | B35: [activités — repères : Cahier Nathan 3e (spécimen) — chapitre développement durable]
A36: Démarche / organisation | B36: [démarche]
A37: Bilan / trace écrite | B37: [trace écrite]
A38: 📋 CAHIER DE TEXTE Contenu de la séance 👆 CLIC = copier pour Pronote | B38: [Cahier de texte — contenu de la séance 2 : à rédiger par IA Thème 1.]
A39: 📋 CAHIER DE TEXTE Travail à faire 👆 CLIC = copier pour Pronote | B39: [Cahier de texte — travail à faire : à rédiger — support, durée, « faisable sur téléphone » le cas échéant.]
A40: Suivi enseignant | B40: Fait le : ____________ | C40: Report / aléa / remarques :
A42: ■ Séance 3 — semaine S09 — — — [titre de la séance 3 — à compléter]
A43: Question directrice | B43: [question directrice]
A44: Activités & supports | B44: [activités — repères : Cahier Nathan 3e (spécimen) — chapitre développement durable]
A45: Démarche / organisation | B45: [démarche]
A46: Bilan / trace écrite | B46: [trace écrite]
A47: 📋 CAHIER DE TEXTE Contenu de la séance 👆 CLIC = copier pour Pronote | B47: [Cahier de texte — contenu de la séance 3 : à rédiger par IA Thème 1.]
A48: 📋 CAHIER DE TEXTE Travail à faire 👆 CLIC = copier pour Pronote | B48: [Cahier de texte — travail à faire : à rédiger — support, durée, « faisable sur téléphone » le cas échéant.]
A49: Suivi enseignant | B49: Fait le : ____________ | C49: Report / aléa / remarques :

Sheet S4
A1: GÉNÉRATEUR DE SÉQUENCE 2024 — S4 · La station d'alerte cyclonique : chaînes complètes d'un objet connecté
A2: Thème 2 · P2 · 5 séances de 1 h 30 · Responsable : Fable (Th. 2) · ✅ TOUTES les ressources en ligne (LOT 01 + LOT 06) — séquence 100 % outillée
E3: ◀ Progression | F3: ◀ Accueil
A4: Problématique | B4: Comment un objet connecté gère-t-il ses échanges d'énergie et d'information — et comment l'élaborer soi-même ?
A5: Situation déclenchante | B5: Un cyclone menace la Martinique : la station d'alerte du collège doit mesurer, décider et alerter — comprendre ses chaînes pour pouvoir l'améliorer.
A6: Prérequis | B6: 5e/4e : chaînes fournies puis complétées. En 3e : on les élabore.
A7: Éléments pour la synthèse (objectifs) | B7: Décrire un OST par sa chaîne d'information · grandeurs analogiques → données exploitables (CAN) · caractériser les données · ÉLABORER soi-même une chaîne d'énergie (schéma-bloc) et justifier matériau/procédé (montée 3e).
A8: Piste d'évaluation | B8: Formative : vérificateurs de la séquence + QCM 32 q (bilan par code → LSU). Sommative séance 5 (corrigé non publié). Données 48 h simulées (CSV/ODS/XLSX) pour l'exploitation.
A9: Domaines du socle mobilisés | B9: D1.3, D2, D3, D4, D5 (détail par code ci-dessous)
A10: CRCN — compétences numériques (Pix) | B10: 1.3 Traiter des données (Niv. 3) · 5.1 Résoudre des problèmes techniques (Niv. 3)
A11: Versions 🅰 / 🅱 / 🅲 | B11: 🅰 Arduino/Grove (TBT) · 🅱 VittaScience · 🅲 tout dans la page (simulateur CAN intégré).
A12: Liens EPI / parcours | B12: EDD / risques majeurs (contexte cyclonique Martinique) · mathématiques (données, graphiques).
A13: Cahier Nathan 3e | B13: Cahier Nathan 3e (spécimen) — chapitres chaînes d'énergie/information
A14: Ressources en ligne | B14: ✅ Séquence + QCM 32 q + synthèses (C4.3→C4.6, LOT 01) · ✅ « L'énergie de la station » (C4.1-C4.2, LOT 06 : séquence + QCM 30 q + synthèses)
A16: Compétences du programme 2024
A17: Code | B17: Intitulé officiel | C17: Domaines du socle | D17: Travaillée en | E17: Évaluation LSU
A18: 3e_C4.1 | B18: Élaborer, à l’aide d’un schéma bloc, la chaîne d’énergie d’un OST. | C18: D1.3, D2, D4 | D18: Séance 4 (✅ en ligne) | E18: Schéma-bloc élaboré → LSU
A19: 3e_C4.2 | B19: Justifier le choix d’un matériau et de son procédé de mise en forme au regard des contraintes techniques et environnementales. | C19: D3, D4, D5 | D19: Séance 4 (✅ en ligne) | E19: Justification matériau/procédé → LSU
A20: 3e_C4.3 | B20: Décrire un OST en caractérisant sa chaîne d’information. | C20: D1.3, D2, D4 | D20: Séances 1-2 | E20: Formative (vérificateurs) + QCM → LSU
A21: 3e_C4.4 | B21: Associer des grandeurs analogiques issues d’un OST à des données exploitables. | C21: D1.3, D2, D4 | D21: Séance 2 (simulateur CAN) | E21: Formative + QCM → LSU
A22: 3e_C4.5 | B22: Représenter sous forme de données les informations de diverses natures utilisées par un OST. | C22: D1.3, D2, D4 | D22: Séance 3 | E22: Formative + QCM → LSU
A23: 3e_C4.6 | B23: Identifier, selon les cas, leur mise en forme, leur transmission ou leur stockage dans des fichiers (texte, image, nombre) afin de comprendre le fonctionnement de l’OST. | C23: D1.3, D2, D4 | D23: Séance 3 | E23: Formative + QCM → LSU
A25: Déroulé, séance par séance — avec cahier de texte Pronote prêt à coller
A26: ■ Séance 1 — semaine S10 — 🔁 Hybride — La station et sa chaîne d'information (C4.3)
A27: Question directrice | B27: Comment la station « sait-elle » qu'un cyclone approche ?
A28: Activités & supports | B28: Séquence en ligne, activités 1-2 : constituants, chaîne d'information complète. Lancement en classe, poursuite à la maison. https://pll-process.github.io/en-ligne-pour-le-cycle-4/theme-2-structure-fonctionnement-comportement/C4-decrire-et-caracteriser-lorganisation/3e/3e_C4.3/sequence_3e_C4.3-C4.6_station_alerte_cyclonique.html
A29: Démarche / organisation | B29: Investigation ; binômes sur postes puis autonomie.
A30: Bilan / trace écrite | B30: Chaîne d'information caractérisée (ACQUÉRIR/TRAITER/COMMUNIQUER).
A31: 📋 CAHIER DE TEXTE Contenu de la séance 👆 CLIC = copier pour Pronote | B31: Séquence « Station d'alerte cyclonique » — Séance 1 : la chaîne d'information de la station (activités en ligne 1-2).
A32: 📋 CAHIER DE TEXTE Travail à faire 👆 CLIC = copier pour Pronote | B32: Terminer les activités 1-2 en ligne : https://pll-process.github.io/en-ligne-pour-le-cycle-4/theme-2-structure-fonctionnement-comportement/C4-decrire-et-caracteriser-lorganisation/3e/3e_C4.3/sequence_3e_C4.3-C4.6_station_alerte_cyclonique.html ≈ 25 min, faisable sur téléphone, sauvegarde automatique.
A33: Suivi enseignant | B33: Fait le : ____________ | C33: Report / aléa / remarques :
A35: ■ Séance 2 — semaine S11 — 🏫 En classe — Du signal analogique à la donnée (C4.4)
A36: Question directrice | B36: Comment 967,4 hPa devient-il un nombre dans la machine ?
A37: Activités & supports | B37: Activité simulateur de CAN de la séquence (verrou expérientiel) ; grandeurs analogiques → données exploitables. https://pll-process.github.io/en-ligne-pour-le-cycle-4/theme-2-structure-fonctionnement-comportement/C4-decrire-et-caracteriser-lorganisation/3e/3e_C4.3/sequence_3e_C4.3-C4.6_station_alerte_cyclonique.html
A38: Démarche / organisation | B38: Binômes ; le simulateur doit être RÉELLEMENT manipulé (la page le vérifie).
A39: Bilan / trace écrite | B39: CAN : échantillonner, quantifier, coder.
A40: 📋 CAHIER DE TEXTE Contenu de la séance 👆 CLIC = copier pour Pronote | B40: Séance 2 : du signal analogique à la donnée — simulateur de conversion (CAN) de la station.
A41: 📋 CAHIER DE TEXTE Travail à faire 👆 CLIC = copier pour Pronote | B41: QCM mode « Compétence ciblée » 3e_C4.4 : https://pll-process.github.io/en-ligne-pour-le-cycle-4/theme-2-structure-fonctionnement-comportement/C4-decrire-et-caracteriser-lorganisation/3e/3e_C4.3/qcm_3e_C4.3-C4.6_station_alerte_cyclonique.html ≈ 15 min.
A42: Suivi enseignant | B42: Fait le : ____________ | C42: Report / aléa / remarques :
A44: ■ Séance 3 — semaine S12 — 🏫 En classe — Exploiter les données de la station (C4.5, C4.6)
A45: Question directrice | B45: Que disent 48 h de données quand un cyclone approche ?
A46: Activités & supports | B46: Exploitation du jeu de données 48 h (CSV/tableur) : seuils d'alerte, durées, rafale max. Activités 5-6 en ligne. https://pll-process.github.io/en-ligne-pour-le-cycle-4/theme-2-structure-fonctionnement-comportement/C4-decrire-et-caracteriser-lorganisation/3e/3e_C4.3/sequence_3e_C4.3-C4.6_station_alerte_cyclonique.html
A47: Démarche / organisation | B47: Résolution de problème au tableur + vérificateurs en ligne.
A48: Bilan / trace écrite | B48: Caractériser des données pour DÉCIDER (niveaux de vigilance).
A49: 📋 CAHIER DE TEXTE Contenu de la séance 👆 CLIC = copier pour Pronote | B49: Séance 3 : exploiter 48 h de données de la station (tableur + activités en ligne 5-6) — seuils et vigilances.
A50: 📋 CAHIER DE TEXTE Travail à faire 👆 CLIC = copier pour Pronote | B50: Terminer l'activité 6 en ligne : https://pll-process.github.io/en-ligne-pour-le-cycle-4/theme-2-structure-fonctionnement-comportement/C4-decrire-et-caracteriser-lorganisation/3e/3e_C4.3/sequence_3e_C4.3-C4.6_station_alerte_cyclonique.html ≈ 20 min.
A51: Suivi enseignant | B51: Fait le : ____________ | C51: Report / aléa / remarques :
A53: ■ Séance 4 — semaine S13 — 🏫 En classe — Élaborer la chaîne d'énergie, justifier les choix (C4.1, C4.2 — 🔜)
A54: Question directrice | B54: À toi de concevoir : quelle chaîne d'énergie pour une station autonome, quels matériaux face aux embruns ?
A55: Activités & supports | B55: Séquence en ligne « L'énergie de la station » : élaboration du schéma-bloc (palette avec intrus), dimensionnement 72 h au simulateur (verrou expérientiel), contraintes du site et choix matériau/procédé justifiés. https://pll-process.github.io/en-ligne-pour-le-cycle-4/theme-2-structure-fonctionnement-comportement/C4-decrire-et-caracteriser-lorganisation/3e/3e_C4.1/sequence_3e_C4.1-C4.2_energie_station.html
A56: Démarche / organisation | B56: Conception en binômes, mise en commun critique.
A57: Bilan / trace écrite | B57: Élaborer ≠ compléter : on choisit ET on justifie.
A58: 📋 CAHIER DE TEXTE Contenu de la séance 👆 CLIC = copier pour Pronote | B58: Séance 4 : élaborer la chaîne d'énergie de la station (schéma-bloc) et justifier le choix des matériaux face au climat martiniquais.
A59: 📋 CAHIER DE TEXTE Travail à faire 👆 CLIC = copier pour Pronote | B59: Terminer l'activité 4 (justification matériau/procédé) en ligne : https://pll-process.github.io/en-ligne-pour-le-cycle-4/theme-2-structure-fonctionnement-comportement/C4-decrire-et-caracteriser-lorganisation/3e/3e_C4.1/sequence_3e_C4.1-C4.2_energie_station.html puis QCM ciblé 3e_C4.2 : https://pll-process.github.io/en-ligne-pour-le-cycle-4/theme-2-structure-fonctionnement-comportement/C4-decrire-et-caracteriser-lorganisation/3e/3e_C4.1/qcm_3e_C4.1-C4.2_energie_station.html ≈ 25 min, faisable sur téléphone.
A60: Suivi enseignant | B60: Fait le : ____________ | C60: Report / aléa / remarques :
A62: ■ Séance 5 — semaine S14 — 🏠 puis 🏫 — Bilan et évaluation
A63: Question directrice | B63: Où en suis-je, code par code ?
A64: Activités & supports | B64: QCM complet à la maison avant la séance ; correction commentée (bilan par compétence) ; évaluation sommative.
A65: Démarche / organisation | B65: Bilan 30 min + évaluation 45 min.
A66: Bilan / trace écrite | B66: Synthèse élève distribuée (1 page A4).
A67: 📋 CAHIER DE TEXTE Contenu de la séance 👆 CLIC = copier pour Pronote | B67: Séance 5 : bilan de la séquence « Station d'alerte cyclonique » et évaluation (chaînes, CAN, données).
A68: 📋 CAHIER DE TEXTE Travail à faire 👆 CLIC = copier pour Pronote | B68: Fait avant la séance : QCM complet (32 q) : https://pll-process.github.io/en-ligne-pour-le-cycle-4/theme-2-structure-fonctionnement-comportement/C4-decrire-et-caracteriser-lorganisation/3e/3e_C4.3/qcm_3e_C4.3-C4.6_station_alerte_cyclonique.html ≈ 30 min, en 2 fois si besoin (reprise automatique).
A69: Suivi enseignant | B69: Fait le : ____________ | C69: Report / aléa / remarques :

Sheet S5
A1: GÉNÉRATEUR DE SÉQUENCE 2024 — S5 · Internet jusqu'à Sainte-Luce : réseaux et routage
A2: Thème 2 · P3 · 3 séances de 1 h 30 · Responsable : Fable (Th. 2) · ✅ Ressources en ligne complètes (LOT 02)
E3: ◀ Progression | F3: ◀ Accueil
A4: Problématique | B4: Comment un message circule-t-il d'un réseau à un autre, et comment s'en protéger ?
A5: Situation déclenchante | B5: Comment un message part-il du collège de Sainte-Luce pour traverser l'Atlantique — et pourquoi Internet résiste-t-il aux pannes de câbles ?
A6: Prérequis | B6: 5e (réseau local, identification) · 4e (adresse IP).
A7: Éléments pour la synthèse (objectifs) | B7: Découpage en paquets, en-têtes, réassemblage · routage de proche en proche · résilience (chemins alternatifs) · protection des échanges.
A8: Piste d'évaluation | B8: Formative : 3 simulateurs (paquets, jeu du routeur, panne de câble — verrous expérientiels) + QCM 30 q → LSU. Sommative courte séance 3.
A9: Domaines du socle mobilisés | B9: D2, D4 (détail par code ci-dessous)
A10: CRCN — compétences numériques (Pix) | B10: 5.1 Résoudre des problèmes techniques (Niv. 3) · 4.1 Sécuriser (Niv. 3 : bonnes pratiques)
A11: Versions 🅰 / 🅱 / 🅲 | B11: 🅰 jeu de rôle routeurs (élèves-routeurs, cartes-paquets) · 🅱 simulateurs intégrés à la page · 🅲 fiches papier.
A12: Liens EPI / parcours | B12: Géographie (câbles sous-marins, mondialisation) · EMC (protection des données).
A13: Cahier Nathan 3e | B13: Cahier Nathan 3e (spécimen) — chapitre réseaux/Internet
A14: Ressources en ligne | B14: ✅ Séquence + QCM 30 q + synthèses (LOT 02 : découpage en paquets, routage, résilience)
A16: Compétences du programme 2024
A17: Code | B17: Intitulé officiel | C17: Domaines du socle | D17: Travaillée en | E17: Évaluation LSU
A18: 3e_C4.7 | B18: Identifier et représenter la circulation d’une information dans le réseau Internet. | C18: D2, D4 | D18: Séances 1-2 | E18: Formative (simulateurs) + QCM → LSU
A19: 3e_C4.8 | B19: Justifier la nécessité d’un protocole de routage pour faire communiquer plusieurs réseaux (activité débranchée, table de routage donnée). | C19: D2, D4 | D19: Séances 2-3 | E19: Formative (jeu du routeur, résilience) + QCM → LSU
A21: Déroulé, séance par séance — avec cahier de texte Pronote prêt à coller
A22: ■ Séance 1 — semaine S16 — 🔁 Hybride — Découper pour envoyer : les paquets (C4.7)
A23: Question directrice | B23: Pourquoi découper un message en morceaux ?
A24: Activités & supports | B24: Simulateur de découpage/réassemblage de paquets (activités 1-2 en ligne) ; lancement en classe, fin à la maison. https://pll-process.github.io/en-ligne-pour-le-cycle-4/theme-2-structure-fonctionnement-comportement/C4-decrire-et-caracteriser-lorganisation/3e/3e_C4.7/sequence_3e_C4.7-C4.8_internet_sainte_luce.html
A25: Démarche / organisation | B25: Investigation ; binômes puis autonomie.
A26: Bilan / trace écrite | B26: Paquets + en-têtes : numéro, source, destination.
A27: 📋 CAHIER DE TEXTE Contenu de la séance 👆 CLIC = copier pour Pronote | B27: Séquence « Internet jusqu'à Sainte-Luce » — Séance 1 : le découpage en paquets (simulateur en ligne).
A28: 📋 CAHIER DE TEXTE Travail à faire 👆 CLIC = copier pour Pronote | B28: Terminer les activités 1-2 : https://pll-process.github.io/en-ligne-pour-le-cycle-4/theme-2-structure-fonctionnement-comportement/C4-decrire-et-caracteriser-lorganisation/3e/3e_C4.7/sequence_3e_C4.7-C4.8_internet_sainte_luce.html ≈ 20 min, sur téléphone possible.
A29: Suivi enseignant | B29: Fait le : ____________ | C29: Report / aléa / remarques :
A31: ■ Séance 2 — semaine S17 — 🏫 En classe — Le jeu du routeur et la panne de câble (C4.8)
A32: Question directrice | B32: Comment le message trouve-t-il son chemin — même quand un câble casse ?
A33: Activités & supports | B33: Jeu du routeur (version 🅰 possible en jeu de rôle) + simulateur de panne : le réseau recalcule un chemin (R1→R3→R5). https://pll-process.github.io/en-ligne-pour-le-cycle-4/theme-2-structure-fonctionnement-comportement/C4-decrire-et-caracteriser-lorganisation/3e/3e_C4.7/sequence_3e_C4.7-C4.8_internet_sainte_luce.html
A34: Démarche / organisation | B34: Jeu collectif + binômes au simulateur.
A35: Bilan / trace écrite | B35: Routage de proche en proche ; résilience = chemins alternatifs.
A36: 📋 CAHIER DE TEXTE Contenu de la séance 👆 CLIC = copier pour Pronote | B36: Séance 2 : le routage et la résilience d'Internet — jeu du routeur et panne de câble simulée.
A37: 📋 CAHIER DE TEXTE Travail à faire 👆 CLIC = copier pour Pronote | B37: QCM mode « Compétence ciblée » 3e_C4.8 : https://pll-process.github.io/en-ligne-pour-le-cycle-4/theme-2-structure-fonctionnement-comportement/C4-decrire-et-caracteriser-lorganisation/3e/3e_C4.7/qcm_3e_C4.7-C4.8_internet_sainte_luce.html ≈ 15 min.
A38: Suivi enseignant | B38: Fait le : ____________ | C38: Report / aléa / remarques :
A40: ■ Séance 3 — semaine S18 — 🏠 puis 🏫 — Bilan réseaux + évaluation
A41: Question directrice | B41: Où en suis-je sur C4.7-C4.8 ?
A42: Activités & supports | B42: QCM complet à la maison ; correction ; évaluation courte (schéma de routage à compléter).
A43: Démarche / organisation | B43: Bilan + évaluation 40 min.
A44: Bilan / trace écrite | B44: Synthèse distribuée.
A45: 📋 CAHIER DE TEXTE Contenu de la séance 👆 CLIC = copier pour Pronote | B45: Séance 3 : bilan de la séquence Internet et évaluation (paquets, routage, résilience).
A46: 📋 CAHIER DE TEXTE Travail à faire 👆 CLIC = copier pour Pronote | B46: Fait avant la séance : QCM complet (30 q) : https://pll-process.github.io/en-ligne-pour-le-cycle-4/theme-2-structure-fonctionnement-comportement/C4-decrire-et-caracteriser-lorganisation/3e/3e_C4.7/qcm_3e_C4.7-C4.8_internet_sainte_luce.html ≈ 25 min.
A47: Suivi enseignant | B47: Fait le : ____________ | C47: Report / aléa / remarques :

Sheet S6
A1: GÉNÉRATEUR DE SÉQUENCE 2024 — S6 · SOS station + Programmer l'alerte : diagnostiquer, réparer, modifier
A2: Thème 2 · P3/P4 · 4 séances de 1 h 30 · Responsable : Fable (Th. 2) · ✅ DEUX séquences complètes en ligne (LOTS 03 + 04) — le générateur les enchaîne en 4 séances denses
E3: ◀ Progression | F3: ◀ Accueil
A4: Problématique | B4: Comment diagnostiquer une panne, la réparer, et modifier le programme sans rien casser ?
A5: Situation déclenchante | B5: La station d'alerte tombe en panne à l'approche d'un cyclone, puis doit recevoir une alerte graduée : réparer, puis modifier le programme — en prouvant chaque étape.
A6: Prérequis | B6: S4 (la station comprise) · S5 (la station connectée) · 4e C6 (compléter un programme).
A7: Éléments pour la synthèse (objectifs) | B7: Hypothèses → mesures ordonnées → diagnostic (2 pannes) · pièce sur mesure (plan coté) · données d'un programme · modifier avec méthode · plan de tests aux frontières · non-régression.
A8: Piste d'évaluation | B8: Formative : simulateur de dépannage (compteur de mesures, verrou) + CodeLab (analyse du code réellement écrit) + 2 QCM (32 q + 30 q) → LSU. Sommatives séances 2 et 4.
A9: Domaines du socle mobilisés | B9: D1.3, D2, D3, D4 (détail par code ci-dessous)
A10: CRCN — compétences numériques (Pix) | B10: 3.4 Programmer (Niv. 3 : modifier, tester, mettre au point) · 5.1 Résoudre des problèmes techniques (Niv. 3)
A11: Versions 🅰 / 🅱 / 🅲 | B11: 🅰 maquettes réelles + multimètre (TBT) / Arduino · 🅱 simulateurs + VittaScience · 🅲 tout dans les pages (CodeLab + plans de tests à la main).
A12: Liens EPI / parcours | B12: EDD (réparer plutôt que jeter) · parcours Avenir (maintenance, développement) · préparation DNB (algorithmique).
A13: Cahier Nathan 3e | B13: Cahier Nathan 3e (spécimen) — chapitres panne/programme
A14: Ressources en ligne | B14: ✅ DEUX séquences complètes : « SOS station » (LOT 03) et « Programmer l'alerte » (LOT 04, CodeLab Techno) + 2 QCM (32 q + 30 q) + synthèses · C6.2 : séquence « Algorigrammes DNB » existante
A16: Compétences du programme 2024
A17: Code | B17: Intitulé officiel | C17: Domaines du socle | D17: Travaillée en | E17: Évaluation LSU
A18: 3e_C5.1 | B18: Formuler des hypothèses expliquant le dysfonctionnement d’un objet technique. | C18: D1.3, D2, D4 | D18: Séance 1 | E18: Formative (simulateur 2 pannes) → LSU
A19: 3e_C5.2 | B19: Proposer un protocole de dépannage puis de réparation. | C19: D1.3, D2, D4 | D19: Séances 1-2 | E19: Protocole suivi → LSU
A20: 3e_C5.3 | B20: Réaliser le dépannage ou la réparation d’un système défectueux. | C20: D2, D3, D4 | D20: Séance 2 | E20: Formative → LSU
A21: 3e_C5.4 | B21: Réaliser une pièce sur mesure pour réparer un objet technique. | C21: D2, D3, D4 | D21: Séance 2 | E21: Pièce sur mesure (plan coté) → LSU
A22: 3e_C6.1 | B22: Déterminer les données utilisées et produites par un programme associé à une fonctionnalité en vue de le modifier. | C22: D1.3, D2, D4 | D22: Séance 3 | E22: Carte d'identité du programme → LSU
A23: 3e_C6.2 | B23: Programmer un algorithme lié à une nouvelle fonctionnalité. | C23: D1.3, D2, D4 | D23: (couvert par « Algorigrammes DNB » existant, lié en révision) | E23: → LSU
A24: 3e_C6.3 | B24: Modifier et tester le programme associé à une nouvelle fonctionnalité d’un OST. | C24: D1.3, D2, D4 | D24: Séances 3-4 | E24: Programme modifié + plan de tests → LSU
A26: Déroulé, séance par séance — avec cahier de texte Pronote prêt à coller
A27: ■ Séance 1 — semaine S19 — 🔁 Hybride — Diagnostiquer la panne (C5.1, C5.2)
A28: Question directrice | B28: La station est muette : où est la panne — et comment le PROUVER ?
A29: Activités & supports | B29: Simulateur de dépannage (2 pannes successives, compteur de mesures) : hypothèses, mesures ordonnées, diagnostic prouvé. https://pll-process.github.io/en-ligne-pour-le-cycle-4/theme-2-structure-fonctionnement-comportement/C5-identifier-un-dysfonctionnement-dun-objet/3e/3e_C5.1/sequence_3e_C5.1-C5.4_sos_station_reparer.html
A30: Démarche / organisation | B30: Binômes ; le simulateur exige de vraies mesures (verrou).
A31: Bilan / trace écrite | B31: Arbre de diagnostic ; une mesure = une hypothèse testée.
A32: 📋 CAHIER DE TEXTE Contenu de la séance 👆 CLIC = copier pour Pronote | B32: Séquence « SOS station » — Séance 1 : diagnostiquer les pannes au simulateur (hypothèses, mesures, preuve).
A33: 📋 CAHIER DE TEXTE Travail à faire 👆 CLIC = copier pour Pronote | B33: Terminer le simulateur de dépannage (2 pannes) : https://pll-process.github.io/en-ligne-pour-le-cycle-4/theme-2-structure-fonctionnement-comportement/C5-identifier-un-dysfonctionnement-dun-objet/3e/3e_C5.1/sequence_3e_C5.1-C5.4_sos_station_reparer.html ≈ 25 min.
A34: Suivi enseignant | B34: Fait le : ____________ | C34: Report / aléa / remarques :
A36: ■ Séance 2 — semaine S21 — 🏫 En classe — Réparer et refabriquer sur mesure (C5.3, C5.4)
A37: Question directrice | B37: La pièce n'existe pas : comment la produire sur mesure ?
A38: Activités & supports | B38: Protocole de réparation + plan coté de la pièce sur mesure (impression 3D) ; évaluation courte. QCM à la maison ensuite. https://pll-process.github.io/en-ligne-pour-le-cycle-4/theme-2-structure-fonctionnement-comportement/C5-identifier-un-dysfonctionnement-dun-objet/3e/3e_C5.1/sequence_3e_C5.1-C5.4_sos_station_reparer.html
A39: Démarche / organisation | B39: Binômes ; plan coté individuel noté.
A40: Bilan / trace écrite | B40: Réparer avec méthode ; concevoir la pièce qui manque.
A41: 📋 CAHIER DE TEXTE Contenu de la séance 👆 CLIC = copier pour Pronote | B41: Séance 2 : réparer la station et produire la pièce sur mesure (plan coté, impression 3D) ; évaluation courte.
A42: 📋 CAHIER DE TEXTE Travail à faire 👆 CLIC = copier pour Pronote | B42: QCM « SOS station » complet (32 q) : https://pll-process.github.io/en-ligne-pour-le-cycle-4/theme-2-structure-fonctionnement-comportement/C5-identifier-un-dysfonctionnement-dun-objet/3e/3e_C5.1/qcm_3e_C5.1-C5.4_sos_station_reparer.html ≈ 25 min.
A43: Suivi enseignant | B43: Fait le : ____________ | C43: Report / aléa / remarques :
A45: ■ Séance 3 — semaine S22 — 🏫 En classe — Lire le programme avant d'y toucher (C6.1)
A46: Question directrice | B46: Quelles données le programme de la station utilise-t-il et produit-il ?
A47: Activités & supports | B47: CodeLab Techno : carte d'identité entrées/sorties du programme Python réel, trace d'exécution, piège des frontières. https://pll-process.github.io/en-ligne-pour-le-cycle-4/theme-2-structure-fonctionnement-comportement/C6-comprendre-et-modifier-un-programme-associe/3e/3e_C6.1/sequence_3e_C6.1-C6.3_programmer_alerte.html
A48: Démarche / organisation | B48: Binômes sur postes ; CodeLab analyse le code réellement écrit.
A49: Bilan / trace écrite | B49: Données utilisées/produites ; > strict aux frontières.
A50: 📋 CAHIER DE TEXTE Contenu de la séance 👆 CLIC = copier pour Pronote | B50: Séquence « Programmer l'alerte » — Séance 3 : la carte d'identité du programme de la station (CodeLab, trace d'exécution).
A51: 📋 CAHIER DE TEXTE Travail à faire 👆 CLIC = copier pour Pronote | B51: Réviser « Algorigrammes DNB » (séquence existante liée) + activité 2 en ligne : https://pll-process.github.io/en-ligne-pour-le-cycle-4/theme-2-structure-fonctionnement-comportement/C6-comprendre-et-modifier-un-programme-associe/3e/3e_C6.1/sequence_3e_C6.1-C6.3_programmer_alerte.html ≈ 20 min.
A52: Suivi enseignant | B52: Fait le : ____________ | C52: Report / aléa / remarques :
A54: ■ Séance 4 — semaine S23 — 🏠 puis 🏫 — Modifier, tester, prouver (C6.3)
A55: Question directrice | B55: Comment ajouter l'alerte graduée SANS rien casser ?
A56: Activités & supports | B56: Implémentation de l'alerte graduée dans CodeLab (vérificateur du code de l'élève) + plan de tests aux frontières + non-régression ; évaluation.
A57: Démarche / organisation | B57: Binômes puis individuel (évaluation).
A58: Bilan / trace écrite | B58: UN test en échec = version refusée ; re-tester l'ancien comportement.
A59: 📋 CAHIER DE TEXTE Contenu de la séance 👆 CLIC = copier pour Pronote | B59: Séance 4 : modifier le programme (alerte graduée) et le prouver par un plan de tests ; évaluation de fin de séquence.
A60: 📋 CAHIER DE TEXTE Travail à faire 👆 CLIC = copier pour Pronote | B60: Fait avant la séance : QCM « Programmer l'alerte » (30 q) : https://pll-process.github.io/en-ligne-pour-le-cycle-4/theme-2-structure-fonctionnement-comportement/C6-comprendre-et-modifier-un-programme-associe/3e/3e_C6.1/qcm_3e_C6.1-C6.3_programmer_alerte.html ≈ 25 min. Après : rien — mode « Uniquement mes erreurs » pour le DNB.
A61: Suivi enseignant | B61: Fait le : ____________ | C61: Report / aléa / remarques :

Sheet S7
A1: GÉNÉRATEUR DE SÉQUENCE 2024 — S7 · Projet fil rouge — Volet 1 : cadrage, besoin et organisation
A2: Thème 3 · P4 · 3 séances de 1 h 30 · Responsable : IA Thème 3 · CANEVAS À REMPLIR par IA Thème 3 (règle : l'IA du thème est seule à modifier)
E3: ◀ Progression | F3: ◀ Accueil
A4: Problématique | B4: Comment bien se préparer et s'organiser pour un projet d'innovation ?
A5: Situation déclenchante | B5: ⚠ À compléter par IA Thème 3 (canevas pré-rempli par Fable — codes, problématique et repères posés).
A6: Prérequis | B6: —
A7: Éléments pour la synthèse (objectifs) | B7: ⚠ À compléter par IA Thème 3 (canevas pré-rempli par Fable — codes, problématique et repères posés).
A8: Piste d'évaluation | B8: Cahier des charges + planning validés
A9: Domaines du socle mobilisés | B9: D1.3, D2, D4, D5 (détail par code ci-dessous)
A10: CRCN — compétences numériques (Pix) | B10: 2.3 Collaborer (Niv. 3)
A11: Versions 🅰 / 🅱 / 🅲 | B11: ⚠ À compléter par IA Thème 3 (canevas pré-rempli par Fable — codes, problématique et repères posés).
A12: Liens EPI / parcours | B12: ⚠ À compléter par IA Thème 3 (canevas pré-rempli par Fable — codes, problématique et repères posés).
A13: Cahier Nathan 3e | B13: Cahier Nathan 3e (spécimen) — démarche de projet
A14: Ressources en ligne | B14: 🔜 À produire (Thème 3)
A16: Compétences du programme 2024
A17: Code | B17: Intitulé officiel | C17: Domaines du socle | D17: Travaillée en | E17: Évaluation LSU
A18: 3e_C7.1 | B18: Élaborer un processus de conception et de réalisation dans une durée, avec des tâches identifiées. | C18: D2, D4, D5 | D18: — | E18: → LSU
A19: 3e_C4.5 | B19: Représenter sous forme de données les informations de diverses natures utilisées par un OST. | C19: D1.3, D2, D4 | D19: (réinvestie — déjà travaillée en S4) | E19: rappel
A21: Déroulé, séance par séance — avec cahier de texte Pronote prêt à coller
A22: ■ Séance 1 — semaine S24 — — — [titre de la séance 1 — à compléter]
A23: Question directrice | B23: [question directrice]
A24: Activités & supports | B24: [activités — repères : Cahier Nathan 3e (spécimen) — démarche de projet]
A25: Démarche / organisation | B25: [démarche]
A26: Bilan / trace écrite | B26: [trace écrite]
A27: 📋 CAHIER DE TEXTE Contenu de la séance 👆 CLIC = copier pour Pronote | B27: [Cahier de texte — contenu de la séance 1 : à rédiger par IA Thème 3.]
A28: 📋 CAHIER DE TEXTE Travail à faire 👆 CLIC = copier pour Pronote | B28: [Cahier de texte — travail à faire : à rédiger — support, durée, « faisable sur téléphone » le cas échéant.]
A29: Suivi enseignant | B29: Fait le : ____________ | C29: Report / aléa / remarques :
A31: ■ Séance 2 — semaine S25 — — — [titre de la séance 2 — à compléter]
A32: Question directrice | B32: [question directrice]
A33: Activités & supports | B33: [activités — repères : Cahier Nathan 3e (spécimen) — démarche de projet]
A34: Démarche / organisation | B34: [démarche]
A35: Bilan / trace écrite | B35: [trace écrite]
A36: 📋 CAHIER DE TEXTE Contenu de la séance 👆 CLIC = copier pour Pronote | B36: [Cahier de texte — contenu de la séance 2 : à rédiger par IA Thème 3.]
A37: 📋 CAHIER DE TEXTE Travail à faire 👆 CLIC = copier pour Pronote | B37: [Cahier de texte — travail à faire : à rédiger — support, durée, « faisable sur téléphone » le cas échéant.]
A38: Suivi enseignant | B38: Fait le : ____________ | C38: Report / aléa / remarques :
A40: ■ Séance 3 — semaine S26 — — — [titre de la séance 3 — à compléter]
A41: Question directrice | B41: [question directrice]
A42: Activités & supports | B42: [activités — repères : Cahier Nathan 3e (spécimen) — démarche de projet]
A43: Démarche / organisation | B43: [démarche]
A44: Bilan / trace écrite | B44: [trace écrite]
A45: 📋 CAHIER DE TEXTE Contenu de la séance 👆 CLIC = copier pour Pronote | B45: [Cahier de texte — contenu de la séance 3 : à rédiger par IA Thème 3.]
A46: 📋 CAHIER DE TEXTE Travail à faire 👆 CLIC = copier pour Pronote | B46: [Cahier de texte — travail à faire : à rédiger — support, durée, « faisable sur téléphone » le cas échéant.]
A47: Suivi enseignant | B47: Fait le : ____________ | C47: Report / aléa / remarques :

Sheet S8
A1: GÉNÉRATEUR DE SÉQUENCE 2024 — S8 · Projet fil rouge — Volet 2 : solutions techniques et prototypage
A2: Thème 3 · P4/P5 · 4 séances de 1 h 30 · Responsable : IA Thème 3 · CANEVAS À REMPLIR par IA Thème 3 (règle : l'IA du thème est seule à modifier)
E3: ◀ Progression | F3: ◀ Accueil
A4: Problématique | B4: Quelles solutions techniques retenir, et comment réaliser le prototype ?
A5: Situation déclenchante | B5: ⚠ À compléter par IA Thème 3 (canevas pré-rempli par Fable — codes, problématique et repères posés).
A6: Prérequis | B6: —
A7: Éléments pour la synthèse (objectifs) | B7: ⚠ À compléter par IA Thème 3 (canevas pré-rempli par Fable — codes, problématique et repères posés).
A8: Piste d'évaluation | B8: Prototype en cours + revue intermédiaire
A9: Domaines du socle mobilisés | B9: D2, D3, D4, D5 (détail par code ci-dessous)
A10: CRCN — compétences numériques (Pix) | B10: 3.4 Programmer (Niv. 3) · 3.2 Documents visuels (Niv. 2-3)
A11: Versions 🅰 / 🅱 / 🅲 | B11: ⚠ À compléter par IA Thème 3 (canevas pré-rempli par Fable — codes, problématique et repères posés).
A12: Liens EPI / parcours | B12: ⚠ À compléter par IA Thème 3 (canevas pré-rempli par Fable — codes, problématique et repères posés).
A13: Cahier Nathan 3e | B13: Cahier Nathan 3e (spécimen)
A14: Ressources en ligne | B14: 🔜 À produire (Thème 3)
A16: Compétences du programme 2024
A17: Code | B17: Intitulé officiel | C17: Domaines du socle | D17: Travaillée en | E17: Évaluation LSU
A18: 3e_C7.2 | B18: Proposer et fabriquer un ensemble de solutions pour produire un nouvel OST (croquis, schéma, graphique, algorithme, modélisation). | C18: D2, D3, D4 | D18: — | E18: → LSU
A19: 3e_C7.3 | B19: Choisir un matériau constitutif d’un objet et/ou système technique. | C19: D3, D4, D5 | D19: — | E19: → LSU
A20: 3e_C7.4 | B20: Choisir une source d’énergie pour un OST. | C20: D3, D4, D5 | D20: — | E20: → LSU
A21: 3e_C7.5 | B21: Choisir les constituants et assembler un prototype. | C21: D2, D3, D4 | D21: — | E21: → LSU
A22: 3e_C7.6 | B22: Modéliser une forme voulue. | C22: D2, D3, D4 | D22: — | E22: → LSU
A23: 3e_C7.7 | B23: Choisir les moyens et produire la forme voulue. | C23: D2, D3, D4 | D23: — | E23: → LSU
A24: 3e_C7.8 | B24: Interfacer deux objets techniques communicants. | C24: D2, D3, D4 | D24: — | E24: → LSU
A26: Déroulé, séance par séance — avec cahier de texte Pronote prêt à coller
A27: ■ Séance 1 — semaine S27 — — — [titre de la séance 1 — à compléter]
A28: Question directrice | B28: [question directrice]
A29: Activités & supports | B29: [activités — repères : Cahier Nathan 3e (spécimen)]
A30: Démarche / organisation | B30: [démarche]
A31: Bilan / trace écrite | B31: [trace écrite]
A32: 📋 CAHIER DE TEXTE Contenu de la séance 👆 CLIC = copier pour Pronote | B32: [Cahier de texte — contenu de la séance 1 : à rédiger par IA Thème 3.]
A33: 📋 CAHIER DE TEXTE Travail à faire 👆 CLIC = copier pour Pronote | B33: [Cahier de texte — travail à faire : à rédiger — support, durée, « faisable sur téléphone » le cas échéant.]
A34: Suivi enseignant | B34: Fait le : ____________ | C34: Report / aléa / remarques :
A36: ■ Séance 2 — semaine S29 — — — [titre de la séance 2 — à compléter]
A37: Question directrice | B37: [question directrice]
A38: Activités & supports | B38: [activités — repères : Cahier Nathan 3e (spécimen)]
A39: Démarche / organisation | B39: [démarche]
A40: Bilan / trace écrite | B40: [trace écrite]
A41: 📋 CAHIER DE TEXTE Contenu de la séance 👆 CLIC = copier pour Pronote | B41: [Cahier de texte — contenu de la séance 2 : à rédiger par IA Thème 3.]
A42: 📋 CAHIER DE TEXTE Travail à faire 👆 CLIC = copier pour Pronote | B42: [Cahier de texte — travail à faire : à rédiger — support, durée, « faisable sur téléphone » le cas échéant.]
A43: Suivi enseignant | B43: Fait le : ____________ | C43: Report / aléa / remarques :
A45: ■ Séance 3 — semaine S30 — — — [titre de la séance 3 — à compléter]
A46: Question directrice | B46: [question directrice]
A47: Activités & supports | B47: [activités — repères : Cahier Nathan 3e (spécimen)]
A48: Démarche / organisation | B48: [démarche]
A49: Bilan / trace écrite | B49: [trace écrite]
A50: 📋 CAHIER DE TEXTE Contenu de la séance 👆 CLIC = copier pour Pronote | B50: [Cahier de texte — contenu de la séance 3 : à rédiger par IA Thème 3.]
A51: 📋 CAHIER DE TEXTE Travail à faire 👆 CLIC = copier pour Pronote | B51: [Cahier de texte — travail à faire : à rédiger — support, durée, « faisable sur téléphone » le cas échéant.]
A52: Suivi enseignant | B52: Fait le : ____________ | C52: Report / aléa / remarques :
A54: ■ Séance 4 — semaine S31 — — — [titre de la séance 4 — à compléter]
A55: Question directrice | B55: [question directrice]
A56: Activités & supports | B56: [activités — repères : Cahier Nathan 3e (spécimen)]
A57: Démarche / organisation | B57: [démarche]
A58: Bilan / trace écrite | B58: [trace écrite]
A59: 📋 CAHIER DE TEXTE Contenu de la séance 👆 CLIC = copier pour Pronote | B59: [Cahier de texte — contenu de la séance 4 : à rédiger par IA Thème 3.]
A60: 📋 CAHIER DE TEXTE Travail à faire 👆 CLIC = copier pour Pronote | B60: [Cahier de texte — travail à faire : à rédiger — support, durée, « faisable sur téléphone » le cas échéant.]
A61: Suivi enseignant | B61: Fait le : ____________ | C61: Report / aléa / remarques :

Sheet S9
A1: GÉNÉRATEUR DE SÉQUENCE 2024 — S9 · Projet fil rouge — Volet 3 : validation et mise au point
A2: Thème 3 · P5 · 3 séances de 1 h 30 · Responsable : IA Thème 3 · CANEVAS À REMPLIR par IA Thème 3 (règle : l'IA du thème est seule à modifier)
E3: ◀ Progression | F3: ◀ Accueil
A4: Problématique | B4: Comment vérifier que le prototype répond au cahier des charges ?
A5: Situation déclenchante | B5: ⚠ À compléter par IA Thème 3 (canevas pré-rempli par Fable — codes, problématique et repères posés).
A6: Prérequis | B6: —
A7: Éléments pour la synthèse (objectifs) | B7: ⚠ À compléter par IA Thème 3 (canevas pré-rempli par Fable — codes, problématique et repères posés).
A8: Piste d'évaluation | B8: Revue de projet finale + prototype validé
A9: Domaines du socle mobilisés | B9: D1.3, D2, D3, D4, D5 (détail par code ci-dessous)
A10: CRCN — compétences numériques (Pix) | B10: 3.4 Programmer (Niv. 3) · 5.1 Résoudre des problèmes techniques (Niv. 3)
A11: Versions 🅰 / 🅱 / 🅲 | B11: ⚠ À compléter par IA Thème 3 (canevas pré-rempli par Fable — codes, problématique et repères posés).
A12: Liens EPI / parcours | B12: ⚠ À compléter par IA Thème 3 (canevas pré-rempli par Fable — codes, problématique et repères posés).
A13: Cahier Nathan 3e | B13: Cahier Nathan 3e (spécimen)
A14: Ressources en ligne | B14: 🔜 À produire (Thème 3)
A16: Compétences du programme 2024
A17: Code | B17: Intitulé officiel | C17: Domaines du socle | D17: Travaillée en | E17: Évaluation LSU
A18: 3e_C8.1 | B18: Mettre en œuvre une simulation pour valider la tenue mécanique d’un matériau. | C18: D1.3, D2, D4 | D18: — | E18: → LSU
A19: 3e_C8.2 | B19: Proposer un protocole de test pour valider la tenue mécanique d’un matériau. | C19: D1.3, D2, D3, D4 | D19: — | E19: → LSU
A20: 3e_C8.3 | B20: Proposer un protocole de test pour valider le comportement et les performances d’un objet technique. | C20: D1.3, D2, D3, D4, D5 | D20: — | E20: → LSU
A21: 3e_C9.1 | B21: Élaborer ou concevoir un algorithme permettant de répondre au besoin visé, puis le traduire en un programme structuré (appel de sous-programmes ou de fonctions), le tester et le mettre au point. | C21: D1.3, D2, D4 | D21: — | E21: → LSU
A22: 3e_C9.2 | B22: Réaliser et mettre au point un programme commandant un système réel incluant une interaction entre un humain et une machine. | C22: D1.3, D2, D4 | D22: — | E22: → LSU
A24: Déroulé, séance par séance — avec cahier de texte Pronote prêt à coller
A25: ■ Séance 1 — semaine S32 — — — [titre de la séance 1 — à compléter]
A26: Question directrice | B26: [question directrice]
A27: Activités & supports | B27: [activités — repères : Cahier Nathan 3e (spécimen)]
A28: Démarche / organisation | B28: [démarche]
A29: Bilan / trace écrite | B29: [trace écrite]
A30: 📋 CAHIER DE TEXTE Contenu de la séance 👆 CLIC = copier pour Pronote | B30: [Cahier de texte — contenu de la séance 1 : à rédiger par IA Thème 3.]
A31: 📋 CAHIER DE TEXTE Travail à faire 👆 CLIC = copier pour Pronote | B31: [Cahier de texte — travail à faire : à rédiger — support, durée, « faisable sur téléphone » le cas échéant.]
A32: Suivi enseignant | B32: Fait le : ____________ | C32: Report / aléa / remarques :
A34: ■ Séance 2 — semaine S33 — — — [titre de la séance 2 — à compléter]
A35: Question directrice | B35: [question directrice]
A36: Activités & supports | B36: [activités — repères : Cahier Nathan 3e (spécimen)]
A37: Démarche / organisation | B37: [démarche]
A38: Bilan / trace écrite | B38: [trace écrite]
A39: 📋 CAHIER DE TEXTE Contenu de la séance 👆 CLIC = copier pour Pronote | B39: [Cahier de texte — contenu de la séance 2 : à rédiger par IA Thème 3.]
A40: 📋 CAHIER DE TEXTE Travail à faire 👆 CLIC = copier pour Pronote | B40: [Cahier de texte — travail à faire : à rédiger — support, durée, « faisable sur téléphone » le cas échéant.]
A41: Suivi enseignant | B41: Fait le : ____________ | C41: Report / aléa / remarques :
A43: ■ Séance 3 — semaine S34 — — — [titre de la séance 3 — à compléter]
A44: Question directrice | B44: [question directrice]
A45: Activités & supports | B45: [activités — repères : Cahier Nathan 3e (spécimen)]
A46: Démarche / organisation | B46: [démarche]
A47: Bilan / trace écrite | B47: [trace écrite]
A48: 📋 CAHIER DE TEXTE Contenu de la séance 👆 CLIC = copier pour Pronote | B48: [Cahier de texte — contenu de la séance 3 : à rédiger par IA Thème 3.]
A49: 📋 CAHIER DE TEXTE Travail à faire 👆 CLIC = copier pour Pronote | B49: [Cahier de texte — travail à faire : à rédiger — support, durée, « faisable sur téléphone » le cas échéant.]
A50: Suivi enseignant | B50: Fait le : ____________ | C50: Report / aléa / remarques :

Sheet ⚙ Moteur
A1: ⚙ MOTEUR DE LA PROGRESSION 3e — 37 créneaux (30 séances + 4 tampons + 3 révisions DNB)
A2: Ne modifier qu'en Conseil. Le Calendrier place ces créneaux, dans l'ordre, sur les semaines sans imprévu.
A4: N° | B4: Créneau
A5: 1 | B5: S1 · séance 1
A6: 2 | B6: S1 · séance 2
A7: 3 | B7: S1 · séance 3
A8: 4 | B8: S2 · séance 1
A9: 5 | B9: S2 · séance 2
A10: 6 | B10: S3 · séance 1
A11: 7 | B11: S3 · séance 2
A12: 8 | B12: ⏳ TAMPON P1 — rattrapage / remédiation
A13: 9 | B13: S3 · séance 3
A14: 10 | B14: S4 · séance 1
A15: 11 | B15: S4 · séance 2
A16: 12 | B16: S4 · séance 3
... A41: 37 | B41: ⏳ 🎓 RÉVISIONS DNB + rattrapages (c)
